Workbook

Sheet Read Me
A1: Advantedge Operations - KPI Catalog v9
A2: Complete redesign. Level-of-care aware. Prepared 2026-09-22 for VMP Systems.
A4: SECTION
A5: What changed | B5: v8 carried 98 KPIs applied more or less uniformly across every care level. v9 rebuilds the set from the ground up so that each measure is scored only where it is valid, and is benchmarked against the source that actually publishes that care level. 108 KPIs across the same nine departments: 72 outside SNF, 36 inside it.
A6: Departments | B6: Unchanged from v8: Operations (OPS), Sales and Marketing (SAL), Nursing (NUR), Skilled Nursing (SNF), Finance (FIN), Human Resources (HR), Plant and Maintenance (PLT), Life Enrichment (LE), Dining Services (DIN).
A7: Concision rule | B7: Every department outside SNF is held to 10 measures or fewer: OPS 8, SAL 9, FIN 10, HR 10, PLT 10, LE 6, DIN 7. Nursing carries 12 because it holds two separate blocks (8 AL/MC clinical measures and 4 SNF-only MDS and PDPM measures). SNF is exempt by design and carries 36, because the brief is to cover every contributing aspect of the CMS Five-Star rating.
A9: HOW CARE LEVEL FILTERING WORKS
A10: Applicability columns | B10: Each KPI carries an X in the IL, AL, MC, SNF and Entity columns where it is valid. When the operator selects care levels on Community Profile (Screen 03, Care Levels Offered), the catalog filters to the union of the selected columns. A KPI with no X in any selected column is suppressed entirely - not scored, not shown, not counted against coverage.
A11: Scope classes | B11: UNIVERSAL - valid at every care level the community operates. These are the yellow rows. Level-specific - valid only at the named levels, usually because the benchmark is published by care level. Care-delivering - AL, MC and SNF only. Excluded from IL because no care is delivered there. SNF only - the measure has no meaning outside a skilled nursing license. Entity - computed once for the organization from the trial balance. Does not decompose by care level. Entity (CCRC) - entity measure whose construct and benchmark are CCRC and Life Plan specific. Suppressed for rental communities and for a standalone SNF.
A12: Yellow highlighting | B12: Yellow rows are the universal measures - they apply to every care level and are therefore always in scope regardless of what the operator selects. 32 of the 108 KPIs are universal. The clearest example is the HR block: all ten HR measures are universal, and the turnover, engagement and training targets come from the RC 2025 CCRC benchmarks.
A13: Entity measures and SNF | B13: Days Cash on Hand, Debt Service Coverage, Days in AR, Entity Operating Margin, Entrance Fee Refund Funding and Average Age of Plant are entity measures. They are computed once from the balance sheet and are not assigned to a care level. A standalone SNF with no entity-level balance sheet in scope does not receive them. Entrance Fee Refund Funding is further restricted to CCRC and Life Plan contracts and is suppressed when no entrance fee contract exists.
A15: BENCHMARK SOURCE BY DOMAIN
A16: IL, AL and MC | B16: State of Seniors Housing 2025 (occupancy, turnover, revenue and expense per occupied unit, labor percent of revenue, dietary cost per resident day).
A17: SNF | B17: CMS only. Five-Star Quality Rating System Technical Users Guide, September 2026, plus the CMS Provider Data Catalog.
A18: CCRC and Life Plan | B18: CARF 2025 Financial Ratios and Trend Analysis (CARF / Ziegler / Baker Tilly, 33rd edition, 2024 medians) and the RC 2025 CCRC Performance Benchmarks.
A19: Sales and Marketing | B19: Aline Sales and Marketing Benchmark Report Q1 2024, which publishes funnel volume and conversion by IL, AL, MC and Life Plan Residential, with urban and rural cuts.
A20: Plant and Maintenance | B20: Siemens / Brightly Senior Living Maintenance Benchmarks, drawn from 1,000+ senior living organizations.
A21: Universal people measures | B21: RC 2025 CCRC Performance Benchmarks supply the turnover, employee satisfaction, training and resident experience targets. These are applied at every care level, which is why the HR block is entirely yellow.
A23: THE SNF BLOCK
A24: Rule applied | B24: The SNF department now contains CMS Five-Star contributors and nothing else. Every measure is tool-fetched from CMS. No operator upload feeds any SNF KPI.
A25: Coverage | B25: All three domains are complete: Health Inspections (9 measures), Staffing (7 PBJ measures), Quality Measures (15 rating measures plus the schizophrenia audit exception), and the 4 composite ratings. See the SNF Five-Star Coverage sheet.
A26: Moved out of SNF | B26: Four v8 SNF measures were not Five-Star contributors and were relocated: Medicare and Skilled Census to FIN-06, PDPM Case Mix Index to NUR-11, Average Medicare Length of Stay to OPS-04, and Skilled Revenue per Patient Day to FIN-03. Life Safety Code survey moved to PLT-08 because CMS states that Life Safety deficiencies are excluded from the Five-Star calculation.
A27: Corrections to v8 | B27: Three material errors were found against the September 2026 CMS guide and are corrected in v9. (1) The health inspection weighting is no longer three cycles at 50/33/17 - as of the July 2025 refresh it is two cycles at 3/4 and 1/4. (2) RN Turnover was missing entirely from the v8 staffing block and is added as SNF-S5. (3) The short-stay self-report moderate-to-severe pain measure was retired by CMS in October 2019 and has been removed.
A29: NURSING SPLIT
A30: AL and MC block | B30: NUR-01 through NUR-08. Clinically focused, covering what CMS does not measure and what AL and MC are actually surveyed on: medication error, falls, unplanned transfers, service plan reassessment timeliness, acuity migration, pressure injury, elopement, antipsychotic use. Benchmarks come from RC 2025, state regulation and the CMS QM distributions used as external reference points.
A31: SNF-only MDS block | B31: NUR-09 through NUR-12. MDS and PDPM measures that are genuinely SNF-only but are not Five-Star contributors, so they cannot sit in the SNF block: MDS transmission timeliness, ARD and late assessment rate, PDPM case mix index by component, care plan timeliness.
A32: Deliberate overlap | B32: NUR-01 Medication Administration Error Rate is the one clinical measure that spans AL, MC and SNF. CMS Five-Star has no medication error measure, so scoring it at SNF as well leaves no gap.
A34: SBC BOUNDARY
A35: Rule applied | B35: The Staffing Base Calculator owns staffing efficiency. No KPI duplicates an SBC output. See the SBC Boundary sheet for the full exclusion list.
A36: The one exception | B36: SNF RN HPRD, total nurse HPRD and weekend HPRD remain in the SNF block. They are CMS Five-Star rating inputs computed from PBJ, not outputs of the SBC staffing model, and they move the star rating. AL and MC HPPD stays with the SBC and is not a KPI.
A37: The PBJ rule | B37: PBJ-derived measures exist only in the SNF block. HR-01 and HR-02 measure turnover from the operator payroll file and apply at every care level, which is what makes them valid for assisted living.
A39: DATA BASIS
A40: Intake grounding | B40: Every KPI is traced to a screen in the Advantedge Onboarding Screen Inventory (v3.0.41). The Intake column names the screen. No KPI depends on data the operator is not already being asked for.
A41: Excluded by design | B41: Policy and procedure alignment, contract analysis, and similar document-review outputs are not KPIs. They remain analysis sections of the report and are not scored.
A42: Data vintage note | B42: Aline figures are Q1 2024 from the attached report. CARF figures are 2024 medians from the 2025 edition. SOSH figures are 2025. CMS methodology is the September 2026 Technical Users Guide, verified 2026-09-22. CMS raises the QM composite thresholds every six months; the next increase is expected at the January 2027 refresh.
A43: Real vs placeholder | B43: Every benchmark value in this catalog is a real published figure traced to a named source. Nothing in the Benchmark and Target column is a placeholder. Where no benchmark exists, the target column says so explicitly and the measure is scored on the community's own trend.

Sheet KPI Catalog
A1: KPI Catalog v9 - 108 measures across nine departments
A2: Yellow rows are UNIVERSAL measures: valid at every care level the community operates. X marks the care levels where a measure is scored.
A4: Code | B4: Department | C4: KPI | D4: What It Measures | E4: Direction | F4: IL | G4: AL | H4: MC | I4: SNF | J4: Entity | K4: Scope Class | L4: Benchmark Source | M4: Benchmark / Target | N4: Intake (Onboarding Screen) | O4: Boundary and Notes | P4: What the Benchmark Reveals | Q4: Primary Benchmark Source Group
A5: OPS-01 | B5: Operations | C5: Occupancy Rate by Care Level | D5: Occupied units or beds / available units or beds, computed separately for each care level | E5: Higher | F5: X | G5: X | H5: X | I5: X | K5: Level-specific | L5: SOSH 2025 Table 2.7 (IL/AL/MC/CCRC); CARF 2025 Occupancy Trends (SNF) | M5: IL 87.8% | AL 89.9% | MC 86.0% | CCRC 90.6% | SNF 79.2% (CARF 2024) | N5: Census / occupancy report (Screen 09) | P5: Below the segment median in a rising market means the problem is local - product, price, reputation or sales execution - not demand. High occupancy paired with weak achieved rate means census is being bought. | Q5: {=IFERROR(INDEX('Benchmark Source Map'!$A$5:$A$13,MATCH(TRUE,(ISNUMBER(SEARCH('Benchmark Source Map'!$E$5:$E$13,$L5))+ISNUMBER(SEARCH('Benchmark Source Map'!$F$5:$F$13,$L5)))>0,0)),"Other named sources")} -> State of Seniors Housing (SOSH) 2025
A6: OPS-02 | B6: Operations | C6: Net Census Change | D6: Move-ins minus move-outs for the period, by care level | E6: Higher | F6: X | G6: X | H6: X | I6: X | K6: UNIVERSAL | L6: Rob Clark - internal standard | M6: Directional. Sector occupancy has risen ~0.5-0.7 pp/qtr for 17+ quarters; net decline against a rising market is the flag | N6: Census / occupancy report (Screen 09) | O6: RE-ATTRIBUTED 22 Sep 2026 by owner instruction: third-party named sources are not carried in this catalog, and removing the previous attribution left no source, so this benchmark is recorded as a Rob Clark internal standard. Previous attribution read: 'NIC MAP Senior Housing Market Fundamentals (quarterly)'. The target value itself was not changed - only the attribution. Treat the figure as an advisor standard with no external publication behind it. | P6: Reads intent rather than condition. Net decline while the sector adds 0.5-0.7 pp a quarter means share is being lost to competitors, not to the market. | Q6: {=IFERROR(INDEX('Benchmark Source Map'!$A$5:$A$13,MATCH(TRUE,(ISNUMBER(SEARCH('Benchmark Source Map'!$E$5:$E$13,$L6))+ISNUMBER(SEARCH('Benchmark Source Map'!$F$5:$F$13,$L6)))>0,0)),"Other named sources")} -> Rob Clark - 2025 CCRC Performance Benchmarks and advisor internal standards
A7: OPS-03 | B7: Operations | C7: Annual Resident Turnover by Care Level | D7: Move-outs / average occupied units, annualized | E7: Lower | F7: X | G7: X | H7: X | K7: Level-specific | L7: SOSH 2025 Table 2.15 | M7: IL 44.3% | AL 48.1% | MC 64.7% | CCRC 15.6% | N7: Census / occupancy report (Screen 09) | O7: Excludes SNF: short-stay turns are by design, not attrition | P7: Turnover above the level median points at expectation-setting at move-in or a care model that cannot hold acuity. IL turnover approaching AL levels usually means residents are leaving to get care the community cannot provide. | Q7: {=IFERROR(INDEX('Benchmark Source Map'!$A$5:$A$13,MATCH(TRUE,(ISNUMBER(SEARCH('Benchmark Source Map'!$E$5:$E$13,$L7))+ISNUMBER(SEARCH('Benchmark Source Map'!$F$5:$F$13,$L7)))>0,0)),"Other named sources")} -> State of Seniors Housing (SOSH) 2025
A8: OPS-04 | B8: Operations | C8: Average Length of Stay by Care Level | D8: Average resident tenure at move-out, by care level; SNF reported separately for short-stay and long-stay | E8: Higher (IL/AL/MC) | F8: X | G8: X | H8: X | I8: X | K8: Level-specific | L8: SOSH 2025 Table 2.15 (inverse of turnover); CMS MDS (SNF) | M8: Derived from SOSH turnover: IL ~2.3 yr | AL ~2.1 yr | MC ~1.5 yr. SNF Medicare LOS on own trend | N8: Census report + clinical / MDS report (Screen 09) | O8: Absorbs retired SNF-1.03 Average Medicare Length of Stay | P8: Short tenure against the level norm is the revenue leak hiding behind a healthy occupancy number: the community is refilling faster than it is retaining. | Q8: {=IFERROR(INDEX('Benchmark Source Map'!$A$5:$A$13,MATCH(TRUE,(ISNUMBER(SEARCH('Benchmark Source Map'!$E$5:$E$13,$L8))+ISNUMBER(SEARCH('Benchmark Source Map'!$F$5:$F$13,$L8)))>0,0)),"Other named sources")} -> State of Seniors Housing (SOSH) 2025
A9: OPS-05 | B9: Operations | C9: Resident Satisfaction Score | D9: As measured by the operator's instrument, normalized to a 0-100 scale, with source and instrument recorded | E9: Higher | F9: X | G9: X | H9: X | I9: X | K9: UNIVERSAL | L9: RC 2025 CCRC Benchmarks | M9: RC 2025 target >= 90%. Reference: J.D. Power 2025 IL 753/1000; Holleran Choice Award > 85th percentile | N9: Manual entry (Screen 10) | O9: Clears the resident-side cultural health red flag SOURCE TRIMMED 22 Sep 2026 by owner instruction - third-party named sources removed from the Benchmark Source column. Original read: 'RC 2025 CCRC Benchmarks; J.D. Power 2025; Holleran'. | P9: The best leading indicator of census risk in the catalog. Scores below target typically surface in turnover and referral volume two to three quarters later. | Q9: {=IFERROR(INDEX('Benchmark Source Map'!$A$5:$A$13,MATCH(TRUE,(ISNUMBER(SEARCH('Benchmark Source Map'!$E$5:$E$13,$L9))+ISNUMBER(SEARCH('Benchmark Source Map'!$F$5:$F$13,$L9)))>0,0)),"Other named sources")} -> Rob Clark - 2025 CCRC Performance Benchmarks and advisor internal standards
A10: OPS-06 | B10: Operations | C10: Family Satisfaction Score | D10: As measured by the operator's instrument, normalized to a 0-100 scale | E10: Higher | F10: X | G10: X | H10: X | I10: X | K10: UNIVERSAL | L10: RC 2025 CCRC Benchmarks | M10: RC 2025 target >= 88%. Reference: J.D. Power 2025 AL/MC 867/1000 | N10: Manual entry (Screen 10) | O10: SOURCE TRIMMED 22 Sep 2026 by owner instruction - third-party named sources removed from the Benchmark Source column. Original read: 'RC 2025 CCRC Benchmarks; J.D. Power 2025; Holleran'. | P10: Families drive both the move-in and the move-out decision. A family score well below the resident score means a communication failure, not a care failure. | Q10: {=IFERROR(INDEX('Benchmark Source Map'!$A$5:$A$13,MATCH(TRUE,(ISNUMBER(SEARCH('Benchmark Source Map'!$E$5:$E$13,$L10))+ISNUMBER(SEARCH('Benchmark Source Map'!$F$5:$F$13,$L10)))>0,0)),"Other named sources")} -> Rob Clark - 2025 CCRC Performance Benchmarks and advisor internal standards
A11: OPS-07 | B11: Operations | C11: Reportable Incident Rate | D11: All reportable incidents / resident days x 1,000 | E11: Lower | F11: X | G11: X | H11: X | I11: X | K11: UNIVERSAL | L11: Rob Clark - internal standard | M11: Scored on the community's own trend. Component reference: falls 3.5-4.0 per 1,000 resident days | N11: Incident and grievance log (Screen 09) | O11: Composite only. Clinical components are scored in NUR (AL/MC) and SNF (CMS QMs) RE-ATTRIBUTED 22 Sep 2026 by owner instruction: third-party named sources are not carried in this catalog, and removing the previous attribution left no source, so this benchmark is recorded as a Rob Clark internal standard. Previous attribution read: 'Component benchmarks only (no published composite)'. The target value itself was not changed - only the attribution. Treat the figure as an advisor standard with no external publication behind it. | P11: Read the trend, not the level. A falling incident count against a rising acuity mix is more often under-reporting than improvement. | Q11: {=IFERROR(INDEX('Benchmark Source Map'!$A$5:$A$13,MATCH(TRUE,(ISNUMBER(SEARCH('Benchmark Source Map'!$E$5:$E$13,$L11))+ISNUMBER(SEARCH('Benchmark Source Map'!$F$5:$F$13,$L11)))>0,0)),"Other named sources")} -> Rob Clark - 2025 CCRC Performance Benchmarks and advisor internal standards
A12: OPS-08 | B12: Operations | C12: Grievance Resolution Time | D12: Average calendar days from grievance receipt to documented resolution, plus grievance volume per 100 residents | E12: Lower | F12: X | G12: X | H12: X | I12: X | K12: UNIVERSAL | L12: CMS 42 CFR 483.10(j); CMS Medicare-plan 30-day grievance standard (reference) | M12: Resolution <= 30 days; acknowledgment <= 5 business days | N12: Incident and grievance log (Screen 09) | P12: Slow resolution with low volume means complaints are being suppressed. Fast resolution with high volume means the process works but something upstream keeps breaking. | Q12: {=IFERROR(INDEX('Benchmark Source Map'!$A$5:$A$13,MATCH(TRUE,(ISNUMBER(SEARCH('Benchmark Source Map'!$E$5:$E$13,$L12))+ISNUMBER(SEARCH('Benchmark Source Map'!$F$5:$F$13,$L12)))>0,0)),"Other named sources")} -> CMS and regulatory requirements (Five-Star Technical Users' Guide, RAI Manual, 42 CFR, Life Safety Code, state regulation)
A13: SAL-01 | B13: Sales and Marketing | C13: Inquiries per 100 Units per Month | D13: Total inquiries / (units / 100) / months in period | E13: Higher | F13: X | G13: X | H13: X | K13: Level-specific | L13: Aline Sales and Marketing Benchmark Report Q1 2024 | M13: IL 37 | AL 45 | MC 41 | Life Plan Residential 30. Urban and rural cuts available | N13: Sales / CRM report (Screen 09) + months in period (Screen 10) | O13: Aline does not benchmark SNF admissions; SNF excluded ALINE VINTAGE 22 Sep 2026: reverted to the Q1 2024 edition, which is the vintage the target figures actually come from. The 2026 report is registration-gated and its figures cannot be obtained by either workbook, so the catalog cites the edition it holds rather than the newest edition it cannot substantiate. | P13: Tests demand generation, not sales skill. Below benchmark means market presence or marketing spend falls short before any sales conversation happens. | Q13: {=IFERROR(INDEX('Benchmark Source Map'!$A$5:$A$13,MATCH(TRUE,(ISNUMBER(SEARCH('Benchmark Source Map'!$E$5:$E$13,$L13))+ISNUMBER(SEARCH('Benchmark Source Map'!$F$5:$F$13,$L13)))>0,0)),"Other named sources")} -> Aline Sales and Marketing Benchmark Report
A14: SAL-02 | B14: Sales and Marketing | C14: Tours per 100 Units per Month | D14: Total tours / (units / 100) / months in period | E14: Higher | F14: X | G14: X | H14: X | K14: Level-specific | L14: Aline Sales and Marketing Benchmark Report Q1 2024 | M14: IL 8 | AL 11 | MC 13 | Life Plan Residential 7 | N14: Sales / CRM report (Screen 09) | O14: ALINE VINTAGE 22 Sep 2026: reverted to the Q1 2024 edition, which is the vintage the target figures actually come from. The 2026 report is registration-gated and its figures cannot be obtained by either workbook, so the catalog cites the edition it holds rather than the newest edition it cannot substantiate. | P14: The bridge measure. Low tours on healthy inquiry volume means inquiries are not being worked. | Q14: {=IFERROR(INDEX('Benchmark Source Map'!$A$5:$A$13,MATCH(TRUE,(ISNUMBER(SEARCH('Benchmark Source Map'!$E$5:$E$13,$L14))+ISNUMBER(SEARCH('Benchmark Source Map'!$F$5:$F$13,$L14)))>0,0)),"Other named sources")} -> Aline Sales and Marketing Benchmark Report
A15: SAL-03 | B15: Sales and Marketing | C15: Move-Ins per 100 Units per Month | D15: Total move-ins / (units / 100) / months in period | E15: Higher | F15: X | G15: X | H15: X | K15: Level-specific | L15: Aline Sales and Marketing Benchmark Report Q1 2024 | M15: IL 3 | AL 5 | MC 7 | Life Plan Residential 2 | N15: Sales / CRM report (Screen 09) | O15: ALINE VINTAGE 22 Sep 2026: reverted to the Q1 2024 edition, which is the vintage the target figures actually come from. The 2026 report is registration-gated and its figures cannot be obtained by either workbook, so the catalog cites the edition it holds rather than the newest edition it cannot substantiate. | P15: The only sales measure that pays. Benchmark inquiries with sub-benchmark move-ins means the funnel is leaking, not starving. | Q15: {=IFERROR(INDEX('Benchmark Source Map'!$A$5:$A$13,MATCH(TRUE,(ISNUMBER(SEARCH('Benchmark Source Map'!$E$5:$E$13,$L15))+ISNUMBER(SEARCH('Benchmark Source Map'!$F$5:$F$13,$L15)))>0,0)),"Other named sources")} -> Aline Sales and Marketing Benchmark Report
A16: SAL-04 | B16: Sales and Marketing | C16: Inquiry-to-Tour Conversion Rate | D16: Tours / inquiries, all channels | E16: Higher | F16: X | G16: X | H16: X | K16: Level-specific | L16: Aline Sales and Marketing Benchmark Report Q1 2024 | M16: IL 28% | AL 29% | MC 36% | Life Plan Residential 29% | N16: Sales / CRM report (Screen 09) | O16: ALINE VINTAGE 22 Sep 2026: reverted to the Q1 2024 edition, which is the vintage the target figures actually come from. The 2026 report is registration-gated and its figures cannot be obtained by either workbook, so the catalog cites the edition it holds rather than the newest edition it cannot substantiate. | P16: Reads lead quality and speed of response together. Below benchmark is usually response time rather than lead quality. | Q16: {=IFERROR(INDEX('Benchmark Source Map'!$A$5:$A$13,MATCH(TRUE,(ISNUMBER(SEARCH('Benchmark Source Map'!$E$5:$E$13,$L16))+ISNUMBER(SEARCH('Benchmark Source Map'!$F$5:$F$13,$L16)))>0,0)),"Other named sources")} -> Aline Sales and Marketing Benchmark Report
A17: SAL-05 | B17: Sales and Marketing | C17: Tour-to-Move-In Conversion Rate | D17: Move-ins / tours | E17: Higher | F17: X | G17: X | H17: X | K17: Level-specific | L17: Aline Sales and Marketing Benchmark Report Q1 2024 | M17: IL 34% | AL 45% | MC 58% | Life Plan Residential 31% | N17: Sales / CRM report (Screen 09) | O17: ALINE VINTAGE 22 Sep 2026: reverted to the Q1 2024 edition, which is the vintage the target figures actually come from. The 2026 report is registration-gated and its figures cannot be obtained by either workbook, so the catalog cites the edition it holds rather than the newest edition it cannot substantiate. | P17: Reads the close and the product. Weak conversion on healthy tour volume points at price, unit condition or the tour experience itself. | Q17: {=IFERROR(INDEX('Benchmark Source Map'!$A$5:$A$13,MATCH(TRUE,(ISNUMBER(SEARCH('Benchmark Source Map'!$E$5:$E$13,$L17))+ISNUMBER(SEARCH('Benchmark Source Map'!$F$5:$F$13,$L17)))>0,0)),"Other named sources")} -> Aline Sales and Marketing Benchmark Report
A18: SAL-06 | B18: Sales and Marketing | C18: Inquiry Channel Mix | D18: Share of inquiries by channel: web, paid, unpaid referral, call-in | E18: Distribution | F18: X | G18: X | H18: X | K18: Level-specific | L18: Aline Sales and Marketing Benchmark Report Q1 2024 | M18: Web IL 40 / AL 43 / MC 35 / LPR 47 | Paid IL 27 / AL 32 / MC 34 / LPR 7 | Call-in IL 24 / AL 14 / MC 14 / LPR 32 | Unpaid IL 9 / AL 11 / MC 17 / LPR 14 (percent) | N18: Sales / CRM report (Screen 09) | O18: ALINE VINTAGE 22 Sep 2026: reverted to the Q1 2024 edition, which is the vintage the target figures actually come from. The 2026 report is registration-gated and its figures cannot be obtained by either workbook, so the catalog cites the edition it holds rather than the newest edition it cannot substantiate. | P18: A paid and aggregator-heavy mix is rented demand: it stops the day spend stops. A high unpaid referral share is the signature of a community with reputation equity. | Q18: {=IFERROR(INDEX('Benchmark Source Map'!$A$5:$A$13,MATCH(TRUE,(ISNUMBER(SEARCH('Benchmark Source Map'!$E$5:$E$13,$L18))+ISNUMBER(SEARCH('Benchmark Source Map'!$F$5:$F$13,$L18)))>0,0)),"Other named sources")} -> Aline Sales and Marketing Benchmark Report
A19: SAL-07 | B19: Sales and Marketing | C19: Inquiry-to-Tour Conversion by Channel | D19: Tours / inquiries computed separately for each acquisition channel | E19: Higher | F19: X | G19: X | H19: X | K19: Level-specific | L19: Aline Sales and Marketing Benchmark Report Q1 2024 | M19: Unpaid referral IL 61 / AL 59 / MC 61 / LPR 51 | Call-in and other IL 50 / AL 55 / MC 56 / LPR 42 | Web IL 28 / AL 28 / MC 37 / LPR 28 | Paid and aggregator IL 22 / AL 27 / MC 36 / LPR 30 (percent) | N19: Sales / CRM report (Screen 09) | O19: This is the spend-allocation measure: it separates channel volume from channel quality ALINE VINTAGE 22 Sep 2026: reverted to the Q1 2024 edition, which is the vintage the target figures actually come from. The 2026 report is registration-gated and its figures cannot be obtained by either workbook, so the catalog cites the edition it holds rather than the newest edition it cannot substantiate. | P19: The spend-allocation test. Unpaid referral converts at roughly double paid, so a paid-heavy mix with weak conversion means money is buying poor leads. | Q19: {=IFERROR(INDEX('Benchmark Source Map'!$A$5:$A$13,MATCH(TRUE,(ISNUMBER(SEARCH('Benchmark Source Map'!$E$5:$E$13,$L19))+ISNUMBER(SEARCH('Benchmark Source Map'!$F$5:$F$13,$L19)))>0,0)),"Other named sources")} -> Aline Sales and Marketing Benchmark Report
A20: SAL-08 | B20: Sales and Marketing | C20: Average Rate Achieved vs Published Rate | D20: Average rate achieved on new move-ins / published street rate for the same unit type | E20: Higher | F20: X | G20: X | H20: X | K20: Level-specific | L20: SOSH 2025; operator rate sheet | M20: Concessions < 3% of gross rent | N20: Rate sheet (Screen 04) + sales / CRM report (Screen 09) + published rate (Screen 10) | P20: Concessions above 3% of gross rent mean census is being purchased. Rising occupancy on a falling achieved rate is not a win. | Q20: {=IFERROR(INDEX('Benchmark Source Map'!$A$5:$A$13,MATCH(TRUE,(ISNUMBER(SEARCH('Benchmark Source Map'!$E$5:$E$13,$L20))+ISNUMBER(SEARCH('Benchmark Source Map'!$F$5:$F$13,$L20)))>0,0)),"Other named sources")} -> State of Seniors Housing (SOSH) 2025
A21: SAL-09 | B21: Sales and Marketing | C21: Online Reputation Score | D21: Average star rating, review volume, and operator response rate, by platform | E21: Higher | F21: X | G21: X | H21: X | I21: X | K21: UNIVERSAL | L21: RC 2025 CCRC Benchmarks | M21: RC 2025 target >= 4.3 stars. Practice standard 4.5+ stars, 50+ reviews, 100% response rate | N21: Manual entry with source platform (Screen 10) | O21: SOURCE TRIMMED 22 Sep 2026 by owner instruction - third-party named sources removed from the Benchmark Source column. Original read: 'RC 2025 CCRC Benchmarks; Caring.com; Senior Housing News'. | P21: The cheapest leading indicator available. Star rating matters less than review volume and response rate - no responses reads to families as an absent operator. | Q21: {=IFERROR(INDEX('Benchmark Source Map'!$A$5:$A$13,MATCH(TRUE,(ISNUMBER(SEARCH('Benchmark Source Map'!$E$5:$E$13,$L21))+ISNUMBER(SEARCH('Benchmark Source Map'!$F$5:$F$13,$L21)))>0,0)),"Other named sources")} -> Rob Clark - 2025 CCRC Performance Benchmarks and advisor internal standards
A22: SAL-10 | B22: Sales and Marketing | C22: Deposit-to-Move-In Conversion Rate | D22: Move-ins originating from deposits / deposits taken | E22: Higher | F22: X | G22: X | H22: X | I22: X | K22: UNIVERSAL | L22: RC 2025 CCRC Performance Benchmarks; Kushant Shah internal standard | M22: 80-90% deposit-to-move-in; target 85% | N22: TO BE MAPPED - added from Gap Matrix v9; intake screen not yet assigned | O22: Sits between SAL-05 tour-to-move-in and the move-in itself. The deposit stage was absent from v9 and is where late-stage fallout concentrates. Added 22 Sep 2026 from the Gap Matrix v9 (Rob Clark, Kushant Shah). | P22: The deepest point in the funnel and the least forgiving. Fallout after a deposit reveals move-in friction - unit readiness, financial qualification or family second-guessing - not sales skill. | Q22: {=IFERROR(INDEX('Benchmark Source Map'!$A$5:$A$13,MATCH(TRUE,(ISNUMBER(SEARCH('Benchmark Source Map'!$E$5:$E$13,$L22))+ISNUMBER(SEARCH('Benchmark Source Map'!$F$5:$F$13,$L22)))>0,0)),"Other named sources")} -> Rob Clark - 2025 CCRC Performance Benchmarks and advisor internal standards
A23: SAL-11 | B23: Sales and Marketing | C23: Cost per Acquired Resident | D23: Total sales and marketing spend / move-ins | E23: Lower | F23: X | G23: X | H23: X | I23: X | K23: UNIVERSAL | L23: RC 2025 CCRC Performance Benchmarks - CDS Best Practice Metrics 2025 (advisor material, derived) | M23: Community-specific ceiling = (marketing spend at 2-3% of operating expenses) / expected annual move-ins | N23: TO BE MAPPED - added from Gap Matrix v9; intake screen not yet assigned | O23: Target is derived, not published - compute the ceiling per community from its own operating expense base. No external per-resident acquisition cost benchmark exists. Added 22 Sep 2026 from the Gap Matrix v9 (Rob Clark). | P23: The only measure that tells you whether census growth was earned or purchased. A community hitting move-in targets at double the acceptable acquisition cost is not performing, it is spending. | Q23: {=IFERROR(INDEX('Benchmark Source Map'!$A$5:$A$13,MATCH(TRUE,(ISNUMBER(SEARCH('Benchmark Source Map'!$E$5:$E$13,$L23))+ISNUMBER(SEARCH('Benchmark Source Map'!$F$5:$F$13,$L23)))>0,0)),"Other named sources")} -> Rob Clark - 2025 CCRC Performance Benchmarks and advisor internal standards
A24: NUR-01 | B24: Nursing | C24: Medication Administration Error Rate | D24: Medication errors / doses administered x 1,000 | E24: Lower | G24: X | H24: X | I24: X | K24: Care-delivering | L24: RC 2025 CCRC Benchmarks | M24: RC 2025: >= 98% administration accuracy, < 2% error rate | N24: Clinical / EHR report (Screen 09) | O24: CMS Five-Star has no medication error measure, so this applies to SNF as well as AL/MC | P24: Accuracy below 98% is a staffing and training signal before it is a clinical one. It tracks closely with agency use and overtime. | Q24: {=IFERROR(INDEX('Benchmark Source Map'!$A$5:$A$13,MATCH(TRUE,(ISNUMBER(SEARCH('Benchmark Source Map'!$E$5:$E$13,$L24))+ISNUMBER(SEARCH('Benchmark Source Map'!$F$5:$F$13,$L24)))>0,0)),"Other named sources")} -> Rob Clark - 2025 CCRC Performance Benchmarks and advisor internal standards
A25: NUR-02 | B25: Nursing | C25: Fall Rate per 1,000 Resident Days | D25: All falls / resident days x 1,000 | E25: Lower | G25: X | H25: X | K25: Level-specific | L25: Rob Clark - internal standard | M25: 3.5-4.0 falls per 1,000 resident days | N25: Clinical / EHR report + incident log (Screen 09) | O25: SNF falls with major injury are scored at SNF-Q6 (CMS QM) RE-ATTRIBUTED 22 Sep 2026 by owner instruction: third-party named sources are not carried in this catalog, and removing the previous attribution left no source, so this benchmark is recorded as a Rob Clark internal standard. Previous attribution read: 'Industry falls benchmark'. The target value itself was not changed - only the attribution. Treat the figure as an advisor standard with no external publication behind it. | P25: The rate alone is ambiguous. A very low fall rate against a high acuity mix usually means falls are not being captured. Read with acuity and injury severity. | Q25: {=IFERROR(INDEX('Benchmark Source Map'!$A$5:$A$13,MATCH(TRUE,(ISNUMBER(SEARCH('Benchmark Source Map'!$E$5:$E$13,$L25))+ISNUMBER(SEARCH('Benchmark Source Map'!$F$5:$F$13,$L25)))>0,0)),"Other named sources")} -> Rob Clark - 2025 CCRC Performance Benchmarks and advisor internal standards
A26: NUR-03 | B26: Nursing | C26: Unplanned Hospital Transfer Rate | D26: Unplanned transfers to acute care / 100 residents / month | E26: Lower | G26: X | H26: X | K26: Level-specific | L26: RC 2025 CCRC Benchmarks (care transition efficiency) | M26: RC 2025: >= 95% timely transitions, < 10% readmission | N26: Clinical / EHR report (Screen 09) | O26: SNF hospitalization and ED rates are scored at SNF-Q8, Q9, Q13, Q14 (CMS QMs) | P26: Measures the ability to manage change in condition in place. High transfer rates erode census, revenue and hospital referral relationships simultaneously. | Q26: {=IFERROR(INDEX('Benchmark Source Map'!$A$5:$A$13,MATCH(TRUE,(ISNUMBER(SEARCH('Benchmark Source Map'!$E$5:$E$13,$L26))+ISNUMBER(SEARCH('Benchmark Source Map'!$F$5:$F$13,$L26)))>0,0)),"Other named sources")} -> Rob Clark - 2025 CCRC Performance Benchmarks and advisor internal standards
A27: NUR-04 | B27: Nursing | C27: Service Plan Reassessment Timeliness | D27: Required AL/MC service plan reassessments completed within the state-mandated interval / reassessments due | E27: Higher | G27: X | H27: X | K27: Level-specific | L27: State regulation (Advantedge State Regulatory Reference) | M27: 100% on time. Interval is state-specific and pulled from the state regulatory dataset | N27: Clinical / EHR report (Screen 09) | O27: This is the AL/MC analogue of MDS timeliness. The MDS measures themselves are SNF only (NUR-09 to NUR-12) | P27: Anything below 100% is regulatory exposure. Chronic lateness means the clinical leadership span of control is too wide. | Q27: {=IFERROR(INDEX('Benchmark Source Map'!$A$5:$A$13,MATCH(TRUE,(ISNUMBER(SEARCH('Benchmark Source Map'!$E$5:$E$13,$L27))+ISNUMBER(SEARCH('Benchmark Source Map'!$F$5:$F$13,$L27)))>0,0)),"Other named sources")} -> CMS and regulatory requirements (Five-Star Technical Users' Guide, RAI Manual, 42 CFR, Life Safety Code, state regulation)
A28: NUR-05 | B28: Nursing | C28: Resident Acuity and Care Tier Mix | D28: Distribution of residents across care tiers or point bands, with period-over-period migration | E28: Trend | G28: X | H28: X | K28: Level-specific | L28: Internal trend, read against SOSH 2025 revenue per occupied unit | M28: Directional. Upward acuity migration without a matching rate or staffing response is the flag | N28: Clinical / EHR report + census report (Screen 09) | O28: SBC consumes census to size staffing; this measures the acuity behind it | P28: Upward acuity migration without a matching rate or staffing response is the most common cause of a margin collapse nobody saw coming. | Q28: {=IFERROR(INDEX('Benchmark Source Map'!$A$5:$A$13,MATCH(TRUE,(ISNUMBER(SEARCH('Benchmark Source Map'!$E$5:$E$13,$L28))+ISNUMBER(SEARCH('Benchmark Source Map'!$F$5:$F$13,$L28)))>0,0)),"Other named sources")} -> State of Seniors Housing (SOSH) 2025
A29: NUR-06 | B29: Nursing | C29: New Pressure Injury Incidence, Stage 2 and Above | E29: Lower | G29: X | H29: X | K29: Level-specific | L29: CMS long-stay pressure ulcer QM distribution used as reference | M29: Trend to zero; CMS SNF long-stay rate as the external reference point | N29: Clinical / EHR report (Screen 09) | O29: SNF is scored at SNF-Q3 (long-stay) and SNF-Q11 (short-stay) | P29: In-house acquired Stage 2+ injuries read repositioning, nutrition and staffing consistency directly. Near-zero is achievable; an upward trend is never benign. | Q29: {=IFERROR(INDEX('Benchmark Source Map'!$A$5:$A$13,MATCH(TRUE,(ISNUMBER(SEARCH('Benchmark Source Map'!$E$5:$E$13,$L29))+ISNUMBER(SEARCH('Benchmark Source Map'!$F$5:$F$13,$L29)))>0,0)),"Other named sources")} -> CMS and regulatory requirements (Five-Star Technical Users' Guide, RAI Manual, 42 CFR, Life Safety Code, state regulation)
A30: NUR-07 | B30: Nursing | C30: Elopement and Exit-Seeking Incidents | D30: Count of elopement and exit-seeking events per 100 MC residents per month | E30: Lower | G30: X | H30: X | K30: Level-specific | L30: State regulation; no published rate benchmark | M30: Zero tolerance. Any event triggers review; trend scored on the community's own baseline | N30: Incident and grievance log (Screen 09) | O30: MC-weighted. No CMS Five-Star equivalent exists | P30: Zero tolerance. Any event is a licensure and litigation event, and the trend reveals whether the MC environment and staffing ratio actually match the resident profile. | Q30: {=IFERROR(INDEX('Benchmark Source Map'!$A$5:$A$13,MATCH(TRUE,(ISNUMBER(SEARCH('Benchmark Source Map'!$E$5:$E$13,$L30))+ISNUMBER(SEARCH('Benchmark Source Map'!$F$5:$F$13,$L30)))>0,0)),"Other named sources")} -> CMS and regulatory requirements (Five-Star Technical Users' Guide, RAI Manual, 42 CFR, Life Safety Code, state regulation)
A31: NUR-08 | B31: Nursing | C31: Antipsychotic Use Rate | D31: Residents receiving an antipsychotic without a supporting diagnosis / total residents | E31: Lower | G31: X | H31: X | K31: Level-specific | L31: CMS long-stay antipsychotic QM distribution used as reference | M31: CMS long-stay QM distribution as the external reference point | N31: Clinical / EHR report (Screen 09) | O31: SNF is scored at SNF-Q7 (long-stay) and SNF-Q12 (short-stay, first-time) | P31: High use without a supporting diagnosis usually substitutes for staffing and behavioral programming. A culture measure disguised as a clinical one - read against LE-06 programming coverage, since unstructured time is what drives behavioural events. | Q31: {=IFERROR(INDEX('Benchmark Source Map'!$A$5:$A$13,MATCH(TRUE,(ISNUMBER(SEARCH('Benchmark Source Map'!$E$5:$E$13,$L31))+ISNUMBER(SEARCH('Benchmark Source Map'!$F$5:$F$13,$L31)))>0,0)),"Other named sources")} -> CMS and regulatory requirements (Five-Star Technical Users' Guide, RAI Manual, 42 CFR, Life Safety Code, state regulation)
A32: NUR-09 | B32: Nursing | C32: MDS Assessment Completion Timeliness | D32: MDS assessments transmitted within the CMS-required window / assessments due | E32: Higher | I32: X | K32: SNF only | L32: CMS RAI Manual | M32: 100% transmitted within the required window | N32: Clinical / EHR MDS report (Screen 09) | O32: MDS-derived and SNF only. Not a Five-Star input, so it lives here rather than in the SNF block | P32: Below 100% costs money. Late transmission hits payment and Five-Star QM inputs at the same time. | Q32: {=IFERROR(INDEX('Benchmark Source Map'!$A$5:$A$13,MATCH(TRUE,(ISNUMBER(SEARCH('Benchmark Source Map'!$E$5:$E$13,$L32))+ISNUMBER(SEARCH('Benchmark Source Map'!$F$5:$F$13,$L32)))>0,0)),"Other named sources")} -> CMS and regulatory requirements (Five-Star Technical Users' Guide, RAI Manual, 42 CFR, Life Safety Code, state regulation)
A33: NUR-10 | B33: Nursing | C33: ARD and Late Assessment Rate | D33: Assessments with a late or defaulted Assessment Reference Date / total assessments | E33: Lower | I33: X | K33: SNF only | L33: CMS RAI Manual; PDPM default rate exposure | M33: Target 0%. Each late ARD defaults the stay to the lowest PDPM rate | N33: Clinical / EHR MDS report (Screen 09) | O33: MDS-derived and SNF only | P33: Pure unforced revenue loss: every late ARD defaults the stay to the lowest PDPM rate. A direct read on MDS staffing capacity. | Q33: {=IFERROR(INDEX('Benchmark Source Map'!$A$5:$A$13,MATCH(TRUE,(ISNUMBER(SEARCH('Benchmark Source Map'!$E$5:$E$13,$L33))+ISNUMBER(SEARCH('Benchmark Source Map'!$F$5:$F$13,$L33)))>0,0)),"Other named sources")} -> CMS and regulatory requirements (Five-Star Technical Users' Guide, RAI Manual, 42 CFR, Life Safety Code, state regulation)
A34: NUR-11 | B34: Nursing | C34: PDPM Case Mix Index by Component | D34: Case mix index computed for each PDPM component: PT, OT, SLP, Nursing, NTA | E34: Trend | I34: X | K34: SNF only | L34: CMS FY2024 SNF PPS Final Rule nursing CMIs (ES3 3.84 down to PA1 0.62) | M34: Compare to national and state PDPM CMI distribution | N34: Clinical / EHR MDS report (Screen 09) | O34: Same nursing CMI set CMS uses to case-mix adjust the Five-Star staffing measures, so it reads directly against SNF-S1 and SNF-S2 | P34: Reveals whether documentation matches the care actually delivered. A CMI well below the state distribution against visibly high acuity means under-documentation, not light residents. | Q34: {=IFERROR(INDEX('Benchmark Source Map'!$A$5:$A$13,MATCH(TRUE,(ISNUMBER(SEARCH('Benchmark Source Map'!$E$5:$E$13,$L34))+ISNUMBER(SEARCH('Benchmark Source Map'!$F$5:$F$13,$L34)))>0,0)),"Other named sources")} -> CMS and regulatory requirements (Five-Star Technical Users' Guide, RAI Manual, 42 CFR, Life Safety Code, state regulation)
A35: NUR-12 | B35: Nursing | C35: Care Plan Completion and Update Timeliness | D35: Comprehensive care plans completed within 7 days of the comprehensive assessment / plans due | E35: Higher | I35: X | K35: SNF only | L35: CMS 42 CFR 483.21 (F656) | M35: 100% | N35: Clinical / EHR report (Screen 09) | O35: SNF only. AL/MC equivalent is NUR-04 | P35: F656 exposure. Below 100% signals that admission volume has outrun clinical capacity. | Q35: {=IFERROR(INDEX('Benchmark Source Map'!$A$5:$A$13,MATCH(TRUE,(ISNUMBER(SEARCH('Benchmark Source Map'!$E$5:$E$13,$L35))+ISNUMBER(SEARCH('Benchmark Source Map'!$F$5:$F$13,$L35)))>0,0)),"Other named sources")} -> CMS and regulatory requirements (Five-Star Technical Users' Guide, RAI Manual, 42 CFR, Life Safety Code, state regulation)
A36: SNF-00 | B36: Skilled Nursing | C36: Overall Five-Star Rating | D36: Health inspection star as the base; +1 if staffing = 5 stars, -1 if staffing = 1 star; +1 if QM = 5 stars, -1 if QM = 1 star. Bounded 1-5 | E36: Higher | I36: X | K36: SNF only | L36: CMS Five-Star Technical Users Guide, September 2026 | M36: Caps: if health inspection = 1 star the overall cannot rise more than one star (max 2). Abuse icon caps health inspection at 2, so overall maxes at 4. Current SFF participants receive no ratings in any domain | N36: Tool-fetched from CMS. No operator upload | P36: The number families and referral sources actually see. One star of movement changes referral volume more than any marketing spend. | Q36: {=IFERROR(INDEX('Benchmark Source Map'!$A$5:$A$13,MATCH(TRUE,(ISNUMBER(SEARCH('Benchmark Source Map'!$E$5:$E$13,$L36))+ISNUMBER(SEARCH('Benchmark Source Map'!$F$5:$F$13,$L36)))>0,0)),"Other named sources")} -> CMS and regulatory requirements (Five-Star Technical Users' Guide, RAI Manual, 42 CFR, Life Safety Code, state regulation)
A37: SNF-01 | B37: Skilled Nursing | C37: Health Inspection Star Rating | D37: State percentile rank of the weighted health inspection score | E37: Higher | I37: X | K37: SNF only | L37: CMS TUG September 2026; state cut-point tables (August 2026) | M37: Top 10% of the state = 5 stars; middle 70% split into three bands of 23.33% = 4, 3, 2 stars; bottom 20% = 1 star. Recalibrated monthly | N37: Tool-fetched from CMS | P37: Relative, not absolute: it is a rank against other facilities in the same state, so standing still while the state improves is a decline. | Q37: {=IFERROR(INDEX('Benchmark Source Map'!$A$5:$A$13,MATCH(TRUE,(ISNUMBER(SEARCH('Benchmark Source Map'!$E$5:$E$13,$L37))+ISNUMBER(SEARCH('Benchmark Source Map'!$F$5:$F$13,$L37)))>0,0)),"Other named sources")} -> CMS and regulatory requirements (Five-Star Technical Users' Guide, RAI Manual, 42 CFR, Life Safety Code, state regulation)
A38: SNF-02 | B38: Skilled Nursing | C38: Staffing Star Rating | D38: Star assigned from the 380-point staffing score | E38: Higher | I38: X | K38: SNF only | L38: CMS TUG September 2026 Table 3 | M38: 1 star < 155 | 2 stars 155-204 | 3 stars 205-254 | 4 stars 255-319 | 5 stars 320-380 | N38: Tool-fetched from CMS PBJ | P38: Almost entirely a function of dollars committed to nursing hours. The most directly controllable of the three domains. | Q38: {=IFERROR(INDEX('Benchmark Source Map'!$A$5:$A$13,MATCH(TRUE,(ISNUMBER(SEARCH('Benchmark Source Map'!$E$5:$E$13,$L38))+ISNUMBER(SEARCH('Benchmark Source Map'!$F$5:$F$13,$L38)))>0,0)),"Other named sources")} -> CMS and regulatory requirements (Five-Star Technical Users' Guide, RAI Manual, 42 CFR, Life Safety Code, state regulation)
A39: SNF-03 | B39: Skilled Nursing | C39: Quality Measure Star Rating | D39: Star assigned from the combined long-stay and short-stay QM score; sub-ratings reported for each stay type | E39: Higher | I39: X | K39: SNF only | L39: CMS TUG September 2026 Table 5 (thresholds raised July 2026) | M39: Overall QM: 1 star 299-927 | 2 stars 928-1120 | 3 stars 1121-1299 | 4 stars 1300-1493 | 5 stars 1494-2300. Thresholds rise every six months by half the observed score gain; next increase expected January 2027 | N39: Tool-fetched from CMS | P39: Thresholds rise every six months by half the observed sector gain, so a flat score loses ground by design. | Q39: {=IFERROR(INDEX('Benchmark Source Map'!$A$5:$A$13,MATCH(TRUE,(ISNUMBER(SEARCH('Benchmark Source Map'!$E$5:$E$13,$L39))+ISNUMBER(SEARCH('Benchmark Source Map'!$F$5:$F$13,$L39)))>0,0)),"Other named sources")} -> CMS and regulatory requirements (Five-Star Technical Users' Guide, RAI Manual, 42 CFR, Life Safety Code, state regulation)
A40: SNF-H1 | B40: Skilled Nursing | C40: Weighted Health Inspection Score | D40: Cycle 1 points x 0.75 + cycle 2 points x 0.25, where each cycle sums standard, complaint, infection control and revisit points | E40: Lower | I40: X | K40: SNF only | L40: CMS TUG September 2026 | M40: Two standard survey cycles only, weighted 3/4 and 1/4. Cycle 3 is still displayed on Care Compare but is no longer scored (changed July 2025 from three cycles at 1/2, 1/3, 1/6) | N40: Tool-fetched from CMS | O40: CORRECTION from v8: the 50/33/17 three-cycle weighting is obsolete as of the July 2025 refresh | P40: Concentrates 75% of the weight on the most recent cycle - one bad recent survey outweighs two clean older ones. | Q40: {=IFERROR(INDEX('Benchmark Source Map'!$A$5:$A$13,MATCH(TRUE,(ISNUMBER(SEARCH('Benchmark Source Map'!$E$5:$E$13,$L40))+ISNUMBER(SEARCH('Benchmark Source Map'!$F$5:$F$13,$L40)))>0,0)),"Other named sources")} -> CMS and regulatory requirements (Five-Star Technical Users' Guide, RAI Manual, 42 CFR, Life Safety Code, state regulation)
A41: SNF-H2 | B41: Skilled Nursing | C41: Standard Survey Deficiency Points by Scope and Severity | D41: Sum of Table 1 point values for every cited deficiency on the two most recent standard surveys | E41: Lower | I41: X | K41: SNF only | L41: CMS TUG September 2026 Table 1 | M41: A/B/C 0 | D 4 | E 8 | F 16 (20 if SQC) | G 20 | H 35 (40) | I 45 (50) | J 50 (75) | K 100 (125) | L 150 (175). Past non-compliance at J/K/L scores at the G value of 20 | N41: Tool-fetched from CMS | P41: Scope and severity drive the score, not the count. Ten D-level tags cost less than a single G. | Q41: {=IFERROR(INDEX('Benchmark Source Map'!$A$5:$A$13,MATCH(TRUE,(ISNUMBER(SEARCH('Benchmark Source Map'!$E$5:$E$13,$L41))+ISNUMBER(SEARCH('Benchmark Source Map'!$F$5:$F$13,$L41)))>0,0)),"Other named sources")} -> CMS and regulatory requirements (Five-Star Technical Users' Guide, RAI Manual, 42 CFR, Life Safety Code, state regulation)
A42: SNF-H3 | B42: Skilled Nursing | C42: Complaint Survey Deficiency Points | D42: Complaint survey deficiency points over the most recent 36 months | E42: Lower | I42: X | K42: SNF only | L42: CMS TUG September 2026 | M42: Months 0-12 weighted 3/4; months 13-36 weighted 1/4 as a single band. Complaint deficiencies within 15 days of a recertification survey are counted once at the higher scope and severity | N42: Tool-fetched from CMS | P42: Complaint volume is the community's relationship with families and staff made visible to the state. | Q42: {=IFERROR(INDEX('Benchmark Source Map'!$A$5:$A$13,MATCH(TRUE,(ISNUMBER(SEARCH('Benchmark Source Map'!$E$5:$E$13,$L42))+ISNUMBER(SEARCH('Benchmark Source Map'!$F$5:$F$13,$L42)))>0,0)),"Other named sources")} -> CMS and regulatory requirements (Five-Star Technical Users' Guide, RAI Manual, 42 CFR, Life Safety Code, state regulation)
A43: SNF-H4 | B43: Skilled Nursing | C43: Focused Infection Control Survey Deficiency Points | D43: Infection control survey deficiency points over the most recent 36 months | E43: Lower | I43: X | K43: SNF only | L43: CMS TUG September 2026 | M43: Same 3/4 and 1/4 weighting as complaint surveys. Where an ICS citation overlaps a recertification or complaint citation within 15 days, only the ICS citation is counted | N43: Tool-fetched from CMS | P43: Infection control findings persist for 36 months, so a single bad cycle shapes the rating for three years. | Q43: {=IFERROR(INDEX('Benchmark Source Map'!$A$5:$A$13,MATCH(TRUE,(ISNUMBER(SEARCH('Benchmark Source Map'!$E$5:$E$13,$L43))+ISNUMBER(SEARCH('Benchmark Source Map'!$F$5:$F$13,$L43)))>0,0)),"Other named sources")} -> CMS and regulatory requirements (Five-Star Technical Users' Guide, RAI Manual, 42 CFR, Life Safety Code, state regulation)
A44: SNF-H5 | B44: Skilled Nursing | C44: Revisit Points | D44: Points added for repeat revisits within a survey cycle | E44: Lower | I44: X | K44: SNF only | L44: CMS TUG September 2026 Table 2 | M44: First revisit 0 | second 50% of the cycle score | third 70% | fourth 85% | N44: Tool-fetched from CMS | P44: Revisits mean the plan of correction did not hold. That is a management credibility problem, not a clinical one. | Q44: {=IFERROR(INDEX('Benchmark Source Map'!$A$5:$A$13,MATCH(TRUE,(ISNUMBER(SEARCH('Benchmark Source Map'!$E$5:$E$13,$L44))+ISNUMBER(SEARCH('Benchmark Source Map'!$F$5:$F$13,$L44)))>0,0)),"Other named sources")} -> CMS and regulatory requirements (Five-Star Technical Users' Guide, RAI Manual, 42 CFR, Life Safety Code, state regulation)
A45: SNF-H6 | B45: Skilled Nursing | C45: Substandard Quality of Care Citations | D45: Count of deficiencies cited as substandard quality of care | E45: Lower | I45: X | K45: SNF only | L45: CMS TUG September 2026 | M45: No separate cap. SQC raises the point value at F, H, I, J, K and L (G has no SQC variant) | N45: Tool-fetched from CMS | P45: SQC raises the point value at nearly every severity level. It is the multiplier that turns a poor survey into a rating collapse. | Q45: {=IFERROR(INDEX('Benchmark Source Map'!$A$5:$A$13,MATCH(TRUE,(ISNUMBER(SEARCH('Benchmark Source Map'!$E$5:$E$13,$L45))+ISNUMBER(SEARCH('Benchmark Source Map'!$F$5:$F$13,$L45)))>0,0)),"Other named sources")} -> CMS and regulatory requirements (Five-Star Technical Users' Guide, RAI Manual, 42 CFR, Life Safety Code, state regulation)
A46: SNF-H7 | B46: Skilled Nursing | C46: Immediate Jeopardy Citations | D46: Count of deficiencies cited at scope and severity J, K or L | E46: Lower | I46: X | K46: SNF only | L46: CMS TUG September 2026 | M46: No separate cap or downgrade. IJ enters the rating only through the J/K/L point values | N46: Tool-fetched from CMS | P46: Immediate jeopardy is the clearest evidence that a system failed rather than a person. | Q46: {=IFERROR(INDEX('Benchmark Source Map'!$A$5:$A$13,MATCH(TRUE,(ISNUMBER(SEARCH('Benchmark Source Map'!$E$5:$E$13,$L46))+ISNUMBER(SEARCH('Benchmark Source Map'!$F$5:$F$13,$L46)))>0,0)),"Other named sources")} -> CMS and regulatory requirements (Five-Star Technical Users' Guide, RAI Manual, 42 CFR, Life Safety Code, state regulation)
A47: SNF-H8 | B47: Skilled Nursing | C47: Abuse Icon Status | D47: Flag set by CMS from abuse citations at F600, F602 and F603 | E47: Lower | I47: X | K47: SNF only | L47: CMS TUG September 2026 | M47: Triggered by an abuse citation at G or above on the most recent standard survey or a complaint/ICS in the past 12 months; or at D or above on both the most recent and second most recent survey windows. Caps the health inspection star at 2 and the overall at 4 | N47: Tool-fetched from CMS | P47: Caps health inspection at 2 stars and the overall at 4 regardless of everything else. A referral-stopping flag. | Q47: {=IFERROR(INDEX('Benchmark Source Map'!$A$5:$A$13,MATCH(TRUE,(ISNUMBER(SEARCH('Benchmark Source Map'!$E$5:$E$13,$L47))+ISNUMBER(SEARCH('Benchmark Source Map'!$F$5:$F$13,$L47)))>0,0)),"Other named sources")} -> CMS and regulatory requirements (Five-Star Technical Users' Guide, RAI Manual, 42 CFR, Life Safety Code, state regulation)
A48: SNF-H9 | B48: Skilled Nursing | C48: Special Focus Facility Status | D48: SFF participant, SFF candidate, or neither | E48: Lower | I48: X | K48: SNF only | L48: CMS TUG September 2026 | M48: Current SFF participants receive no overall and no domain ratings; a warning icon replaces the overall rating. SFF candidates are rated normally | N48: Tool-fetched from CMS | P48: SFF participation suppresses all ratings and in practice removes the facility from managed-care networks. | Q48: {=IFERROR(INDEX('Benchmark Source Map'!$A$5:$A$13,MATCH(TRUE,(ISNUMBER(SEARCH('Benchmark Source Map'!$E$5:$E$13,$L48))+ISNUMBER(SEARCH('Benchmark Source Map'!$F$5:$F$13,$L48)))>0,0)),"Other named sources")} -> CMS and regulatory requirements (Five-Star Technical Users' Guide, RAI Manual, 42 CFR, Life Safety Code, state regulation)
A49: SNF-S1 | B49: Skilled Nursing | C49: Case-Mix Adjusted Total Nurse Staffing HPRD | D49: RN + LPN + nurse aide hours per resident day, case-mix adjusted, quarterly, all days | E49: Higher | I49: X | K49: SNF only | L49: CMS TUG September 2026 Table A2; PDPM nursing CMIs from the FY2024 SNF PPS Final Rule | M49: 100 pts >= 5.070 | 90: 4.499-5.069 | 80: 4.151-4.498 | 70: 3.910-4.150 | 60: 3.692-3.909 | 50: 3.493-3.691 | 40: 3.293-3.492 | 30: 3.051-3.292 | 20: 2.722-3.050 | 10: 0-2.721 | N49: Tool-fetched from CMS PBJ | O49: PBJ-derived and SNF only. There is no PBJ equivalent for AL/MC, which is why HR carries no PBJ measure | P49: Case-mix adjusted, so it answers whether staffing matches the residents actually in the building - not whether the budget was met. | Q49: {=IFERROR(INDEX('Benchmark Source Map'!$A$5:$A$13,MATCH(TRUE,(ISNUMBER(SEARCH('Benchmark Source Map'!$E$5:$E$13,$L49))+ISNUMBER(SEARCH('Benchmark Source Map'!$F$5:$F$13,$L49)))>0,0)),"Other named sources")} -> CMS and regulatory requirements (Five-Star Technical Users' Guide, RAI Manual, 42 CFR, Life Safety Code, state regulation)
A50: SNF-S2 | B50: Skilled Nursing | C50: Case-Mix Adjusted RN HPRD | D50: Registered nurse hours per resident day (job codes 5, 6, 7), case-mix adjusted, quarterly, all days | E50: Higher | I50: X | K50: SNF only | L50: CMS TUG September 2026 Table A2 | M50: 100 pts >= 1.202 | 90: 0.934-1.201 | 80: 0.786-0.933 | 70: 0.678-0.785 | 60: 0.591-0.677 | 50: 0.513-0.590 | 40: 0.440-0.512 | 30: 0.368-0.439 | 20: 0.275-0.367 | 10: 0-0.274 | N50: Tool-fetched from CMS PBJ | O50: PBJ-derived and SNF only | P50: The steepest scoring curve in the staffing domain. RN coverage is where staffing stars are won and lost. | Q50: {=IFERROR(INDEX('Benchmark Source Map'!$A$5:$A$13,MATCH(TRUE,(ISNUMBER(SEARCH('Benchmark Source Map'!$E$5:$E$13,$L50))+ISNUMBER(SEARCH('Benchmark Source Map'!$F$5:$F$13,$L50)))>0,0)),"Other named sources")} -> CMS and regulatory requirements (Five-Star Technical Users' Guide, RAI Manual, 42 CFR, Life Safety Code, state regulation)
A51: SNF-S3 | B51: Skilled Nursing | C51: Case-Mix Adjusted Weekend Total Nurse HPRD | D51: Total nurse staffing hours per resident day on Saturdays and Sundays, case-mix adjusted | E51: Higher | I51: X | K51: SNF only | L51: CMS TUG September 2026 Table A2 | M51: 50 pts >= 4.464 | 45: 3.958-4.463 | 40: 3.668-3.957 | 35: 3.429-3.667 | 30: 3.233-3.428 | 25: 3.044-3.232 | 20: 2.862-3.043 | 15: 2.637-2.861 | 10: 2.354-2.636 | 5: 0-2.353 | N51: Tool-fetched from CMS PBJ | P51: Weekend coverage is where operators quietly under-resource. CMS scores it separately precisely because it diverges from weekday staffing. | Q51: {=IFERROR(INDEX('Benchmark Source Map'!$A$5:$A$13,MATCH(TRUE,(ISNUMBER(SEARCH('Benchmark Source Map'!$E$5:$E$13,$L51))+ISNUMBER(SEARCH('Benchmark Source Map'!$F$5:$F$13,$L51)))>0,0)),"Other named sources")} -> CMS and regulatory requirements (Five-Star Technical Users' Guide, RAI Manual, 42 CFR, Life Safety Code, state regulation)
A52: SNF-S4 | B52: Skilled Nursing | C52: Total Nurse Staffing Turnover | D52: Percentage of nurse staff who left over 12 months, measured on a 90-consecutive-day zero-hours gap | E52: Lower | I52: X | K52: SNF only | L52: CMS TUG September 2026 Table A2 | M52: 50 pts 0-31.126% | 45: 31.127-37.500 | 40: 37.501-41.739 | 35: 41.740-45.679 | 30: 45.680-49.254 | 25: 49.255-53.425 | 20: 53.426-57.692 | 15: 57.693-62.791 | 10: 62.792-69.792 | 5: 69.793-100 | N52: Tool-fetched from CMS PBJ | O52: PBJ-derived. HR-01 and HR-02 measure turnover from the operator payroll file and apply at every care level | P52: Turnover above roughly 50% drops the facility into the bottom scoring bands and is the single best predictor of the next survey result. | Q52: {=IFERROR(INDEX('Benchmark Source Map'!$A$5:$A$13,MATCH(TRUE,(ISNUMBER(SEARCH('Benchmark Source Map'!$E$5:$E$13,$L52))+ISNUMBER(SEARCH('Benchmark Source Map'!$F$5:$F$13,$L52)))>0,0)),"Other named sources")} -> CMS and regulatory requirements (Five-Star Technical Users' Guide, RAI Manual, 42 CFR, Life Safety Code, state regulation)
A53: SNF-S5 | B53: Skilled Nursing | C53: RN Turnover | D53: Percentage of registered nurses who left over 12 months | E53: Lower | I53: X | K53: SNF only | L53: CMS TUG September 2026 Table A2 | M53: 50 pts 0-20.000% | 45: 20.001-28.571 | 40: 28.572-35.714 | 35: 35.715-41.667 | 30: 41.668-44.444 | 25: 44.445-52.941 | 20: 52.942-60.000 | 15: 60.001-66.667 | 10: 66.668-80.000 | 5: 80.001-100 | N53: Tool-fetched from CMS PBJ | O53: ADDED in v9. This measure was missing from the v8 SNF block | P53: RN continuity drives clinical judgement quality. Its absence from v8 hid real risk rather than removing it. | Q53: {=IFERROR(INDEX('Benchmark Source Map'!$A$5:$A$13,MATCH(TRUE,(ISNUMBER(SEARCH('Benchmark Source Map'!$E$5:$E$13,$L53))+ISNUMBER(SEARCH('Benchmark Source Map'!$F$5:$F$13,$L53)))>0,0)),"Other named sources")} -> CMS and regulatory requirements (Five-Star Technical Users' Guide, RAI Manual, 42 CFR, Life Safety Code, state regulation)
A54: SNF-S6 | B54: Skilled Nursing | C54: Administrator Departures | D54: Count of administrator departures over 12 months (job code 1) | E54: Lower | I54: X | K54: SNF only | L54: CMS TUG September 2026 | M54: 0 departures = 30 pts | 1 = 25 pts | 2 or more = 10 pts | N54: Tool-fetched from CMS PBJ | P54: Two or more departures in twelve months signals instability that will show up in the next survey cycle. | Q54: {=IFERROR(INDEX('Benchmark Source Map'!$A$5:$A$13,MATCH(TRUE,(ISNUMBER(SEARCH('Benchmark Source Map'!$E$5:$E$13,$L54))+ISNUMBER(SEARCH('Benchmark Source Map'!$F$5:$F$13,$L54)))>0,0)),"Other named sources")} -> CMS and regulatory requirements (Five-Star Technical Users' Guide, RAI Manual, 42 CFR, Life Safety Code, state regulation)
A55: SNF-S7 | B55: Skilled Nursing | C55: PBJ Submission and RN Coverage Exceptions | D55: Flags that force the staffing star to 1 regardless of score | E55: Lower | I55: X | K55: SNF only | L55: CMS TUG September 2026 scoring exceptions | M55: Automatic 1 star for: failure to submit staffing data by the 45-day deadline; four or more days in the quarter with zero RN hours on days with at least one resident; a failed or unanswered PBJ audit (1 star for three months) | N55: Tool-fetched from CMS PBJ | P55: Forces 1 star regardless of actual staffing. Administrative failures with clinical-grade consequences. | Q55: {=IFERROR(INDEX('Benchmark Source Map'!$A$5:$A$13,MATCH(TRUE,(ISNUMBER(SEARCH('Benchmark Source Map'!$E$5:$E$13,$L55))+ISNUMBER(SEARCH('Benchmark Source Map'!$F$5:$F$13,$L55)))>0,0)),"Other named sources")} -> CMS and regulatory requirements (Five-Star Technical Users' Guide, RAI Manual, 42 CFR, Life Safety Code, state regulation)
A56: SNF-Q1 | B56: Skilled Nursing | C56: Long-Stay: Need for Help with Daily Activities Has Increased | D56: Percentage of long-stay residents whose need for help with daily activities has increased | E56: Lower | I56: X | K56: SNF only | L56: CMS TUG September 2026 (MDS-based) | M56: 150 points, deciles, 15-point increments. Cut points set on 2023Q4-2024Q3 | N56: Tool-fetched from CMS | P56: Long-stay functional decline reads restorative nursing capacity more than resident frailty. | Q56: {=IFERROR(INDEX('Benchmark Source Map'!$A$5:$A$13,MATCH(TRUE,(ISNUMBER(SEARCH('Benchmark Source Map'!$E$5:$E$13,$L56))+ISNUMBER(SEARCH('Benchmark Source Map'!$F$5:$F$13,$L56)))>0,0)),"Other named sources")} -> CMS and regulatory requirements (Five-Star Technical Users' Guide, RAI Manual, 42 CFR, Life Safety Code, state regulation)
A57: SNF-Q2 | B57: Skilled Nursing | C57: Long-Stay: Ability to Walk Independently Worsened | D57: Percentage of long-stay residents whose ability to walk independently worsened | E57: Lower | I57: X | K57: SNF only | L57: CMS TUG September 2026 (MDS-based, risk-adjusted) | M57: 150 points, deciles. Cut points set on 2023Q4-2024Q3 | N57: Tool-fetched from CMS | O57: Respecified January 2025 from the former 'ability to move independently worsened'. Use the current name | P57: Risk-adjusted, so a poor score means the facility underperformed against residents like its own - not that its residents were sicker. | Q57: {=IFERROR(INDEX('Benchmark Source Map'!$A$5:$A$13,MATCH(TRUE,(ISNUMBER(SEARCH('Benchmark Source Map'!$E$5:$E$13,$L57))+ISNUMBER(SEARCH('Benchmark Source Map'!$F$5:$F$13,$L57)))>0,0)),"Other named sources")} -> CMS and regulatory requirements (Five-Star Technical Users' Guide, RAI Manual, 42 CFR, Life Safety Code, state regulation)
A58: SNF-Q3 | B58: Skilled Nursing | C58: Long-Stay: Residents with Pressure Ulcers | D58: Percentage of long-stay residents with pressure ulcers | E58: Lower | I58: X | K58: SNF only | L58: CMS TUG September 2026 (MDS-based, risk-adjusted) | M58: 100 points, quintiles (20/40/60/80/100). Cut points set on 2023Q4-2024Q3 | N58: Tool-fetched from CMS | O58: Respecified January 2025 from the former high-risk-only measure to all residents | P58: Now all-resident rather than high-risk only. Facilities that scored well on the old specification can drop without changing anything they do. | Q58: {=IFERROR(INDEX('Benchmark Source Map'!$A$5:$A$13,MATCH(TRUE,(ISNUMBER(SEARCH('Benchmark Source Map'!$E$5:$E$13,$L58))+ISNUMBER(SEARCH('Benchmark Source Map'!$F$5:$F$13,$L58)))>0,0)),"Other named sources")} -> CMS and regulatory requirements (Five-Star Technical Users' Guide, RAI Manual, 42 CFR, Life Safety Code, state regulation)
A59: SNF-Q4 | B59: Skilled Nursing | C59: Long-Stay: Catheter Inserted and Left in Bladder | D59: Percentage of long-stay residents who have or had a catheter inserted and left in their bladder | E59: Lower | I59: X | K59: SNF only | L59: CMS TUG September 2026 (MDS-based, risk-adjusted) | M59: 100 points, quintiles | N59: Tool-fetched from CMS | P59: Largely a practice-pattern measure. High rates usually reflect convenience rather than clinical necessity. | Q59: {=IFERROR(INDEX('Benchmark Source Map'!$A$5:$A$13,MATCH(TRUE,(ISNUMBER(SEARCH('Benchmark Source Map'!$E$5:$E$13,$L59))+ISNUMBER(SEARCH('Benchmark Source Map'!$F$5:$F$13,$L59)))>0,0)),"Other named sources")} -> CMS and regulatory requirements (Five-Star Technical Users' Guide, RAI Manual, 42 CFR, Life Safety Code, state regulation)
A60: SNF-Q5 | B60: Skilled Nursing | C60: Long-Stay: Urinary Tract Infection | D60: Percentage of long-stay residents with a urinary tract infection | E60: Lower | I60: X | K60: SNF only | L60: CMS TUG September 2026 (MDS-based) | M60: 100 points, quintiles | N60: Tool-fetched from CMS | P60: Reads hydration, toileting and catheter practice together, and moves with staffing consistency. | Q60: {=IFERROR(INDEX('Benchmark Source Map'!$A$5:$A$13,MATCH(TRUE,(ISNUMBER(SEARCH('Benchmark Source Map'!$E$5:$E$13,$L60))+ISNUMBER(SEARCH('Benchmark Source Map'!$F$5:$F$13,$L60)))>0,0)),"Other named sources")} -> CMS and regulatory requirements (Five-Star Technical Users' Guide, RAI Manual, 42 CFR, Life Safety Code, state regulation)
A61: SNF-Q6 | B61: Skilled Nursing | C61: Long-Stay: One or More Falls with Major Injury | D61: Percentage of long-stay residents experiencing one or more falls with major injury | E61: Lower | I61: X | K61: SNF only | L61: CMS TUG September 2026 (MDS-based) | M61: 100 points, quintiles | N61: Tool-fetched from CMS | P61: The injury is scored, not the fall - so this measures the environment and the response, not resident mobility. | Q61: {=IFERROR(INDEX('Benchmark Source Map'!$A$5:$A$13,MATCH(TRUE,(ISNUMBER(SEARCH('Benchmark Source Map'!$E$5:$E$13,$L61))+ISNUMBER(SEARCH('Benchmark Source Map'!$F$5:$F$13,$L61)))>0,0)),"Other named sources")} -> CMS and regulatory requirements (Five-Star Technical Users' Guide, RAI Manual, 42 CFR, Life Safety Code, state regulation)
A62: SNF-Q7 | B62: Skilled Nursing | C62: Long-Stay: Antipsychotic Medication | D62: Percentage of long-stay residents who got an antipsychotic medication | E62: Lower | I62: X | K62: SNF only | L62: CMS TUG September 2026 | M62: 150 points, deciles. Cut points reset to 2024Q4-2025Q3 after the April 2026 schizophrenia-exclusion correction | N62: Tool-fetched from CMS | O62: Respecified January 2026 to add Medicare and Medicaid claims plus Medicare Advantage encounter data alongside MDS | P62: Cut points reset after the April 2026 schizophrenia-exclusion correction, so comparisons to historical performance understate current difficulty. | Q62: {=IFERROR(INDEX('Benchmark Source Map'!$A$5:$A$13,MATCH(TRUE,(ISNUMBER(SEARCH('Benchmark Source Map'!$E$5:$E$13,$L62))+ISNUMBER(SEARCH('Benchmark Source Map'!$F$5:$F$13,$L62)))>0,0)),"Other named sources")} -> CMS and regulatory requirements (Five-Star Technical Users' Guide, RAI Manual, 42 CFR, Life Safety Code, state regulation)
A63: SNF-Q8 | B63: Skilled Nursing | C63: Long-Stay: Hospitalizations per 1,000 Resident Days | D63: Number of hospitalizations per 1,000 long-stay resident days | E63: Lower | I63: X | K63: SNF only | L63: CMS TUG September 2026 (claims-based, risk-adjusted) | M63: 150 points, deciles. Cut points reset July 2025 when Section GG functional variables were added to risk adjustment | N63: Tool-fetched from CMS | P63: Claims-based and invisible in the facility's own records. This is how payers and ACOs judge the building. | Q63: {=IFERROR(INDEX('Benchmark Source Map'!$A$5:$A$13,MATCH(TRUE,(ISNUMBER(SEARCH('Benchmark Source Map'!$E$5:$E$13,$L63))+ISNUMBER(SEARCH('Benchmark Source Map'!$F$5:$F$13,$L63)))>0,0)),"Other named sources")} -> CMS and regulatory requirements (Five-Star Technical Users' Guide, RAI Manual, 42 CFR, Life Safety Code, state regulation)
A64: SNF-Q9 | B64: Skilled Nursing | C64: Long-Stay: Outpatient ED Visits per 1,000 Resident Days | D64: Number of outpatient emergency department visits per 1,000 long-stay resident days | E64: Lower | I64: X | K64: SNF only | L64: CMS TUG September 2026 (claims-based, risk-adjusted) | M64: 150 points, deciles. Cut points reset July 2025 | N64: Tool-fetched from CMS | P64: Catches the transfers that the hospitalization measure misses. High ED volume with low admission means avoidable sends. | Q64: {=IFERROR(INDEX('Benchmark Source Map'!$A$5:$A$13,MATCH(TRUE,(ISNUMBER(SEARCH('Benchmark Source Map'!$E$5:$E$13,$L64))+ISNUMBER(SEARCH('Benchmark Source Map'!$F$5:$F$13,$L64)))>0,0)),"Other named sources")} -> CMS and regulatory requirements (Five-Star Technical Users' Guide, RAI Manual, 42 CFR, Life Safety Code, state regulation)
A65: SNF-Q10 | B65: Skilled Nursing | C65: Short-Stay: Discharge Function Score | D65: Percentage of SNF residents who are at or above an expected ability to care for themselves and move around at discharge | E65: Higher | I65: X | K65: SNF only | L65: CMS TUG September 2026 (MDS-based, risk-adjusted) | M65: 150 points, deciles. Cut points set on 2023Q2-2024Q1 | N65: Tool-fetched from CMS | O65: Entered the rating January 2025, replacing the retired short-stay functional improvement measure | P65: What short-stay referral sources care most about. Effectively the therapy program's report card. | Q65: {=IFERROR(INDEX('Benchmark Source Map'!$A$5:$A$13,MATCH(TRUE,(ISNUMBER(SEARCH('Benchmark Source Map'!$E$5:$E$13,$L65))+ISNUMBER(SEARCH('Benchmark Source Map'!$F$5:$F$13,$L65)))>0,0)),"Other named sources")} -> CMS and regulatory requirements (Five-Star Technical Users' Guide, RAI Manual, 42 CFR, Life Safety Code, state regulation)
A66: SNF-Q11 | B66: Skilled Nursing | C66: Short-Stay: New or Worsened Pressure Ulcers | D66: Percentage of SNF residents with pressure ulcers or pressure injuries that are new or worsened | E66: Lower | I66: X | K66: SNF only | L66: CMS TUG September 2026 (MDS-based, risk-adjusted; PDC measure code S_038_02) | M66: 100 points, quintiles. Cut points set on 2019Q1-2019Q4. Special rule: because more than 20% of facilities score zero, every facility at zero receives the full 100 points | N66: Tool-fetched from CMS | P66: Zero earns full points and more than 20% of facilities achieve it, so anything above zero is a competitive disadvantage rather than an average result. | Q66: {=IFERROR(INDEX('Benchmark Source Map'!$A$5:$A$13,MATCH(TRUE,(ISNUMBER(SEARCH('Benchmark Source Map'!$E$5:$E$13,$L66))+ISNUMBER(SEARCH('Benchmark Source Map'!$F$5:$F$13,$L66)))>0,0)),"Other named sources")} -> CMS and regulatory requirements (Five-Star Technical Users' Guide, RAI Manual, 42 CFR, Life Safety Code, state regulation)
A67: SNF-Q12 | B67: Skilled Nursing | C67: Short-Stay: First-Time Antipsychotic Medication | D67: Percentage of short-stay residents who got antipsychotic medication for the first time | E67: Lower | I67: X | K67: SNF only | L67: CMS TUG September 2026 (MDS-based) | M67: 100 points, quintiles. Special rule: every facility at zero receives the full 100 points | N67: Tool-fetched from CMS | P67: Same zero-scores-full-points rule. Any first-time antipsychotic start in a short stay warrants clinical review. | Q67: {=IFERROR(INDEX('Benchmark Source Map'!$A$5:$A$13,MATCH(TRUE,(ISNUMBER(SEARCH('Benchmark Source Map'!$E$5:$E$13,$L67))+ISNUMBER(SEARCH('Benchmark Source Map'!$F$5:$F$13,$L67)))>0,0)),"Other named sources")} -> CMS and regulatory requirements (Five-Star Technical Users' Guide, RAI Manual, 42 CFR, Life Safety Code, state regulation)
A68: SNF-Q13 | B68: Skilled Nursing | C68: Short-Stay: Re-Hospitalized After Admission | D68: Percentage of short-stay residents who were re-hospitalized after a nursing home admission | E68: Lower | I68: X | K68: SNF only | L68: CMS TUG September 2026 (claims-based, risk-adjusted) | M68: 150 points, deciles. Cut points reset July 2025 | N68: Tool-fetched from CMS | P68: The measure that determines whether hospitals and Medicare Advantage plans keep sending patients. | Q68: {=IFERROR(INDEX('Benchmark Source Map'!$A$5:$A$13,MATCH(TRUE,(ISNUMBER(SEARCH('Benchmark Source Map'!$E$5:$E$13,$L68))+ISNUMBER(SEARCH('Benchmark Source Map'!$F$5:$F$13,$L68)))>0,0)),"Other named sources")} -> CMS and regulatory requirements (Five-Star Technical Users' Guide, RAI Manual, 42 CFR, Life Safety Code, state regulation)
A69: SNF-Q14 | B69: Skilled Nursing | C69: Short-Stay: Outpatient ED Visit | D69: Percentage of short-stay residents who have had an outpatient emergency department visit | E69: Lower | I69: X | K69: SNF only | L69: CMS TUG September 2026 (claims-based, risk-adjusted) | M69: 150 points, deciles. Cut points reset July 2025 | N69: Tool-fetched from CMS | P69: The same network-relationship consequence as re-hospitalization, at lower severity and higher frequency. | Q69: {=IFERROR(INDEX('Benchmark Source Map'!$A$5:$A$13,MATCH(TRUE,(ISNUMBER(SEARCH('Benchmark Source Map'!$E$5:$E$13,$L69))+ISNUMBER(SEARCH('Benchmark Source Map'!$F$5:$F$13,$L69)))>0,0)),"Other named sources")} -> CMS and regulatory requirements (Five-Star Technical Users' Guide, RAI Manual, 42 CFR, Life Safety Code, state regulation)
A70: SNF-Q15 | B70: Skilled Nursing | C70: Short-Stay: Successful Return to Home and Community | D70: Rate of successful return to home and community from a SNF | E70: Higher | I70: X | K70: SNF only | L70: CMS TUG September 2026 (claims-based, risk-adjusted) | M70: 150 points, deciles. Uses a two-year data period; every other QM uses four quarters | N70: Tool-fetched from CMS | P70: Built on two years of data, so it moves slowly and reflects sustained discharge planning rather than recent effort. | Q70: {=IFERROR(INDEX('Benchmark Source Map'!$A$5:$A$13,MATCH(TRUE,(ISNUMBER(SEARCH('Benchmark Source Map'!$E$5:$E$13,$L70))+ISNUMBER(SEARCH('Benchmark Source Map'!$F$5:$F$13,$L70)))>0,0)),"Other named sources")} -> CMS and regulatory requirements (Five-Star Technical Users' Guide, RAI Manual, 42 CFR, Life Safety Code, state regulation)
A71: SNF-Q16 | B71: Skilled Nursing | C71: Schizophrenia Coding Audit Status | D71: Flag set when a CMS audit finds schizophrenia coding inaccuracies | E71: Lower | I71: X | K71: SNF only | L71: CMS TUG September 2026 QM scoring exception | M71: Overall and long-stay QM ratings downgraded to 1 star for 6 months, which drops the overall star by one. Short-stay QM suppressed 6 months; the long-stay antipsychotic QM suppressed 12 months | N71: Tool-fetched from CMS | P71: A coding-integrity flag with a rating consequence. It reads externally as gaming and drops the overall star for six months. | Q71: {=IFERROR(INDEX('Benchmark Source Map'!$A$5:$A$13,MATCH(TRUE,(ISNUMBER(SEARCH('Benchmark Source Map'!$E$5:$E$13,$L71))+ISNUMBER(SEARCH('Benchmark Source Map'!$F$5:$F$13,$L71)))>0,0)),"Other named sources")} -> CMS and regulatory requirements (Five-Star Technical Users' Guide, RAI Manual, 42 CFR, Life Safety Code, state regulation)
A72: FIN-01 | B72: Finance | C72: Community Operating Margin by Care Level | D72: (Revenue - operating expense) / revenue, at the community level before capital cost, computed by care level | E72: Higher | F72: X | G72: X | H72: X | K72: Level-specific | L72: SOSH 2025 Table 3.27 (for-profit) | M72: IL 31.2% | AL 24.5% | MC 21.7% | CCRC 22.8% | N72: T-12 P&L (Screen 07) + GL (Screen 06) + chart of accounts (Screen 05) | O72: This is the NOI-style margin SOSH publishes. It is not the same measure as the CARF entity operating margin in FIN-02 | P72: The margin a buyer underwrites. Below the segment median on benchmark occupancy means the cost structure, not the revenue line, is the problem. | Q72: {=IFERROR(INDEX('Benchmark Source Map'!$A$5:$A$13,MATCH(TRUE,(ISNUMBER(SEARCH('Benchmark Source Map'!$E$5:$E$13,$L72))+ISNUMBER(SEARCH('Benchmark Source Map'!$F$5:$F$13,$L72)))>0,0)),"Other named sources")} -> State of Seniors Housing (SOSH) 2025
A73: FIN-02 | B73: Finance | C73: Entity Operating Margin and Net Operating Margin | D73: CARF definitions. OM = income from operations / total operating revenue. NOM = (resident revenue - resident expense) / resident revenue | E73: Higher | J73: X | K73: Entity (CCRC) | L73: CARF 2025 Financial Ratios and Trend Analysis; RC 2025 | M73: CARF 2024 medians: OM 0.29% single-site / 1.00% multi-site; NOM 6.19% / 5.77%. RC 2025 target >= 3% | N73: Trial balance or balance sheet (Screen 07) + T-12 P&L | O73: Entity-level. Read alongside FIN-01, not instead of it: the two use different denominators | P73: CARF medians are thin - 0.29% single-site - so a small negative swing is normal rather than distressed. Never read without days cash alongside it. | Q73: {=IFERROR(INDEX('Benchmark Source Map'!$A$5:$A$13,MATCH(TRUE,(ISNUMBER(SEARCH('Benchmark Source Map'!$E$5:$E$13,$L73))+ISNUMBER(SEARCH('Benchmark Source Map'!$F$5:$F$13,$L73)))>0,0)),"Other named sources")} -> CARF 2025 Financial Ratios and Trend Analysis
A74: FIN-03 | B74: Finance | C74: Revenue per Occupied Unit by Care Level | D74: Total revenue / occupied units, or revenue per patient day for SNF | E74: Higher | F74: X | G74: X | H74: X | I74: X | K74: Level-specific | L74: SOSH 2025 revenue per occupied unit (CPI-adjusted); CLA 40th Annual SNF (per patient day) | M74: SOSH segment median by care level. CPI toggle applies to all dollar measures | N74: T-12 P&L (Screen 07) + census report (Screen 09) | O74: Absorbs retired SNF-1.04 Skilled Revenue per Patient Day | P74: Tests pricing power. Flat revenue per occupied unit against rising acuity is the clearest sign the rate structure has not kept pace with the care being delivered. | Q74: {=IFERROR(INDEX('Benchmark Source Map'!$A$5:$A$13,MATCH(TRUE,(ISNUMBER(SEARCH('Benchmark Source Map'!$E$5:$E$13,$L74))+ISNUMBER(SEARCH('Benchmark Source Map'!$F$5:$F$13,$L74)))>0,0)),"Other named sources")} -> State of Seniors Housing (SOSH) 2025
A75: FIN-04 | B75: Finance | C75: Operating Expense per Occupied Unit by Care Level | D75: Total operating expense / occupied units, or per patient day for SNF | E75: Lower | F75: X | G75: X | H75: X | I75: X | K75: Level-specific | L75: SOSH 2025 expense per occupied unit (CPI-adjusted); CLA 40th Annual SNF | M75: SOSH segment median by care level. CPI toggle applies | N75: GL (Screen 06) + chart of accounts (Screen 05) + census report | P75: Rising cost per unit on flat census means the expense base is fixed and the community has lost operating leverage. | Q75: {=IFERROR(INDEX('Benchmark Source Map'!$A$5:$A$13,MATCH(TRUE,(ISNUMBER(SEARCH('Benchmark Source Map'!$E$5:$E$13,$L75))+ISNUMBER(SEARCH('Benchmark Source Map'!$F$5:$F$13,$L75)))>0,0)),"Other named sources")} -> State of Seniors Housing (SOSH) 2025
A76: FIN-05 | B76: Finance | C76: Labor Cost as Percent of Revenue | D76: (Wages + payroll taxes + benefits + agency) / total revenue | E76: Lower | F76: X | G76: X | H76: X | I76: X | K76: UNIVERSAL | L76: SOSH 2025 Tables 3.1-3.7 | M76: IL 28% | AL 39% | AL/MC 46% | CCRC 40% | N76: GL (Screen 06) + T-12 P&L (Screen 07) | P76: The largest controllable line. Above the segment band with normal agency use means the staffing model is the issue, not the labor market. | Q76: {=IFERROR(INDEX('Benchmark Source Map'!$A$5:$A$13,MATCH(TRUE,(ISNUMBER(SEARCH('Benchmark Source Map'!$E$5:$E$13,$L76))+ISNUMBER(SEARCH('Benchmark Source Map'!$F$5:$F$13,$L76)))>0,0)),"Other named sources")} -> State of Seniors Housing (SOSH) 2025
A77: FIN-06 | B77: Finance | C77: Payer Mix by Care Level | D77: Share of resident days by payer source, computed by care level | E77: Distribution | F77: X | G77: X | H77: X | I77: X | K77: Level-specific | L77: CLA 40th Annual SNF (approx 11,700 Medicare cost reports); SOSH 2025 | M77: SNF: Medicaid ~62.2%, Medicare FFS ~7.8%, other including Medicare Advantage ~30%. IL and AL predominantly private pay, with state Medicaid waiver share where applicable | N77: Census report (Screen 09) + billing / AR detail | O77: Absorbs retired SNF-1.01 Medicare and Skilled Census SOURCE TRIMMED 22 Sep 2026 by owner instruction - third-party named sources removed from the Benchmark Source column. Original read: 'CLA 40th Annual SNF (approx 11,700 CMS cost reports); SOSH 2025; NIC MAP'. | P77: Determines revenue quality more than volume does. Medicaid concentration above the SNF norm caps achievable margin regardless of occupancy. | Q77: {=IFERROR(INDEX('Benchmark Source Map'!$A$5:$A$13,MATCH(TRUE,(ISNUMBER(SEARCH('Benchmark Source Map'!$E$5:$E$13,$L77))+ISNUMBER(SEARCH('Benchmark Source Map'!$F$5:$F$13,$L77)))>0,0)),"Other named sources")} -> State of Seniors Housing (SOSH) 2025
A78: FIN-07 | B78: Finance | C78: Days in Accounts Receivable | D78: Net accounts receivable / (resident and health care revenue / 365) | E78: Lower | J78: X | K78: Entity | L78: CARF 2025 Financial Ratios and Trend Analysis | M78: CARF 2024 medians: 14 days single-site, 18 days multi-site. Under 30 days desired | N78: Trial balance or balance sheet (Screen 07) + T-12 P&L | O78: Replaces the v8 AR aging percentage. Days in AR is the benchmarked form. Available to any operator that uploads a trial balance; note the CARF median is a CCRC cohort | P78: Above 30 days is a billing-office capacity problem long before it is a collectability problem. | Q78: {=IFERROR(INDEX('Benchmark Source Map'!$A$5:$A$13,MATCH(TRUE,(ISNUMBER(SEARCH('Benchmark Source Map'!$E$5:$E$13,$L78))+ISNUMBER(SEARCH('Benchmark Source Map'!$F$5:$F$13,$L78)))>0,0)),"Other named sources")} -> CARF 2025 Financial Ratios and Trend Analysis
A79: FIN-08 | B79: Finance | C79: Days Cash on Hand | D79: (Unrestricted current + noncurrent cash and investments) / ((operating expense - depreciation - amortization) / 365) | E79: Higher | J79: X | K79: Entity (CCRC) | L79: CARF 2025; RC 2025 | M79: CARF 2024 medians: 437 days single-site, 291 days multi-site. RC 2025 target >= 180 days, 120 minimum | N79: Trial balance or balance sheet (Screen 07) | O79: ENTITY MEASURE. Does not apply to a care level and is not computed for a standalone SNF, which has no balance sheet of its own in this model | P79: The survival measure. Below the 120-day floor every other KPI in this catalog becomes academic. | Q79: {=IFERROR(INDEX('Benchmark Source Map'!$A$5:$A$13,MATCH(TRUE,(ISNUMBER(SEARCH('Benchmark Source Map'!$E$5:$E$13,$L79))+ISNUMBER(SEARCH('Benchmark Source Map'!$F$5:$F$13,$L79)))>0,0)),"Other named sources")} -> CARF 2025 Financial Ratios and Trend Analysis
A80: FIN-09 | B80: Finance | C80: Debt Service Coverage Ratio | D80: (Total excess + interest + depreciation + amortization - deferred revenue amortization + net entrance fee proceeds) / annual debt service | E80: Higher | J80: X | K80: Entity (CCRC) | L80: CARF 2025; RC 2025 | M80: CARF 2024 medians: 3.00x single-site, 2.77x multi-site. RC 2025 target >= 1.25x. Typical bond covenant minimum 1.20x | N80: Debt schedule (Screen 08) + trial balance (Screen 07) | O80: RESTORED in v9. Removed in v8; both CARF and RC 2025 benchmark it and the debt schedule upload now supplies the operand | P80: Covenant proximity is the real read. Anything near 1.20x means the lender, not management, sets next year's priorities. | Q80: {=IFERROR(INDEX('Benchmark Source Map'!$A$5:$A$13,MATCH(TRUE,(ISNUMBER(SEARCH('Benchmark Source Map'!$E$5:$E$13,$L80))+ISNUMBER(SEARCH('Benchmark Source Map'!$F$5:$F$13,$L80)))>0,0)),"Other named sources")} -> CARF 2025 Financial Ratios and Trend Analysis
A81: FIN-10 | B81: Finance | C81: Entrance Fee Refund Liability Funding | D81: Funded refund obligation / total refundable entrance fee liability | E81: Higher | J81: X | K81: Entity (CCRC) | L81: RC 2025 CCRC Benchmarks | M81: RC 2025: >= 90% funded on an actuarial basis, or 100% funded | N81: Trial balance (Screen 07) + residency agreements (Screen 04) | O81: CCRC AND LIFE PLAN ONLY. Suppressed entirely when no entrance fee contract exists | P81: Under-funding a refundable liability transfers risk to future residents. Regulators and rating agencies look here first. | Q81: {=IFERROR(INDEX('Benchmark Source Map'!$A$5:$A$13,MATCH(TRUE,(ISNUMBER(SEARCH('Benchmark Source Map'!$E$5:$E$13,$L81))+ISNUMBER(SEARCH('Benchmark Source Map'!$F$5:$F$13,$L81)))>0,0)),"Other named sources")} -> Rob Clark - 2025 CCRC Performance Benchmarks and advisor internal standards
A82: FIN-11 | B82: Finance | C82: Accounts Receivable Aging (Percent Over 90 Days) | D82: A/R aged over 90 days / total A/R | E82: Lower | F82: X | G82: X | H82: X | I82: X | K82: UNIVERSAL | L82: Kushant Shah internal standard | M82: No more than 15% of total A/R aged over 90 days | N82: TO BE MAPPED - added from Gap Matrix v9; intake screen not yet assigned | O82: Complement to FIN-07 Days in Accounts Receivable, NOT a replacement. FIN-07 reads billing timing; this reads collectability of the aged tail. The v8 AR aging percentage was retired in favour of FIN-07 - this reinstates it in a narrower, targeted form. Added 22 Sep 2026 from the Gap Matrix v9 (Kushant Shah). | P82: The over-90 tail reveals collectability where days in AR reveals timing. A community can hold acceptable average days while a concentrated aged balance quietly becomes bad debt. | Q82: {=IFERROR(INDEX('Benchmark Source Map'!$A$5:$A$13,MATCH(TRUE,(ISNUMBER(SEARCH('Benchmark Source Map'!$E$5:$E$13,$L82))+ISNUMBER(SEARCH('Benchmark Source Map'!$F$5:$F$13,$L82)))>0,0)),"Other named sources")} -> Kushant Shah - internal standard
A83: FIN-12 | B83: Finance | C83: Bad Debt and Write-Off Rate | D83: Write-offs / total operating revenue | E83: Lower | F83: X | G83: X | H83: X | I83: X | K83: UNIVERSAL | L83: RC 2025 CCRC Performance Benchmarks; Kushant Shah internal standard | M83: Write-offs below 1.5% of total operating revenue | N83: TO BE MAPPED - added from Gap Matrix v9; intake screen not yet assigned | O83: Pairs with FIN-11: this measures collection quality where FIN-07 measures timing. Read alongside the admission financial qualification process. Added 22 Sep 2026 from the Gap Matrix v9 (Rob Clark, Kushant Shah). | P83: Reveals the quality of the admission decision as much as the billing function. Rising write-offs usually trace back to financial qualification at move-in, not to collections effort. | Q83: {=IFERROR(INDEX('Benchmark Source Map'!$A$5:$A$13,MATCH(TRUE,(ISNUMBER(SEARCH('Benchmark Source Map'!$E$5:$E$13,$L83))+ISNUMBER(SEARCH('Benchmark Source Map'!$F$5:$F$13,$L83)))>0,0)),"Other named sources")} -> Rob Clark - 2025 CCRC Performance Benchmarks and advisor internal standards
A84: HR-01 | B84: Human Resources | C84: Total Staff Turnover Rate | D84: Separations (voluntary and involuntary) / average headcount, annualized, all departments | E84: Lower | F84: X | G84: X | H84: X | I84: X | K84: UNIVERSAL | L84: RC 2025 CCRC Benchmarks | M84: RC 2025 target < 20% overall. Market reference: HCS 2024 SNF ~53.9% | N84: Payroll / turnover report (Screen 09) | O84: Computed from the operator payroll file, NOT from PBJ. The PBJ turnover measures are SNF-S4 and SNF-S5 and exist only for SNF SOURCE TRIMMED 22 Sep 2026 by owner instruction - third-party named sources removed from the Benchmark Source column. Original read: 'RC 2025 CCRC Benchmarks; HCS Annual Report 2024'. | P84: The root cause behind most clinical and satisfaction misses. Above 20% overall, expect quality measures to deteriorate within two quarters. | Q84: {=IFERROR(INDEX('Benchmark Source Map'!$A$5:$A$13,MATCH(TRUE,(ISNUMBER(SEARCH('Benchmark Source Map'!$E$5:$E$13,$L84))+ISNUMBER(SEARCH('Benchmark Source Map'!$F$5:$F$13,$L84)))>0,0)),"Other named sources")} -> Rob Clark - 2025 CCRC Performance Benchmarks and advisor internal standards
A85: HR-02 | B85: Human Resources | C85: Frontline and Direct Care Turnover Rate | D85: Separations among direct care staff / average direct care headcount, annualized | E85: Lower | F85: X | G85: X | H85: X | I85: X | K85: UNIVERSAL | L85: RC 2025 CCRC Benchmarks | M85: RC 2025 target < 35% frontline. Market reference: HCS 2024 CNA ~40%, AL resident assistant ~44% | N85: Payroll / turnover report (Screen 09) | O85: Payroll-derived, not PBJ-derived SOURCE TRIMMED 22 Sep 2026 by owner instruction - third-party named sources removed from the Benchmark Source column. Original read: 'RC 2025 CCRC Benchmarks; HCS Annual Report 2024'. | P85: What residents actually feel day to day. Frontline turnover predicts falls, medication errors and family complaints better than any clinical measure does. | Q85: {=IFERROR(INDEX('Benchmark Source Map'!$A$5:$A$13,MATCH(TRUE,(ISNUMBER(SEARCH('Benchmark Source Map'!$E$5:$E$13,$L85))+ISNUMBER(SEARCH('Benchmark Source Map'!$F$5:$F$13,$L85)))>0,0)),"Other named sources")} -> Rob Clark - 2025 CCRC Performance Benchmarks and advisor internal standards
A86: HR-03 | B86: Human Resources | C86: 90-Day New Hire Retention Rate | D86: Hires still employed at day 90 / hires in the cohort | E86: Higher | F86: X | G86: X | H86: X | I86: X | K86: UNIVERSAL | L86: Rob Clark - internal standard | M86: > 80% | N86: Payroll / turnover report (Screen 09) | O86: RE-ATTRIBUTED 22 Sep 2026 by owner instruction: third-party named sources are not carried in this catalog, and removing the previous attribution left no source, so this benchmark is recorded as a Rob Clark internal standard. Previous attribution read: 'Activated Insights'. The target value itself was not changed - only the attribution. Treat the figure as an advisor standard with no external publication behind it. | P86: Tests hiring quality and onboarding rather than pay. Below 80% means the community is recruiting people it cannot keep. | Q86: {=IFERROR(INDEX('Benchmark Source Map'!$A$5:$A$13,MATCH(TRUE,(ISNUMBER(SEARCH('Benchmark Source Map'!$E$5:$E$13,$L86))+ISNUMBER(SEARCH('Benchmark Source Map'!$F$5:$F$13,$L86)))>0,0)),"Other named sources")} -> Rob Clark - 2025 CCRC Performance Benchmarks and advisor internal standards
A87: HR-04 | B87: Human Resources | C87: Position Vacancy Rate | D87: Open approved positions / total approved positions | E87: Lower | F87: X | G87: X | H87: X | I87: X | K87: UNIVERSAL | L87: Rob Clark - internal standard | M87: < 5% of approved positions | N87: Payroll report (Screen 09) + org chart (Screen 04) | O87: SBC sets the recommended FTE count. This measures how much of the approved plan is unfilled RE-ATTRIBUTED 22 Sep 2026 by owner instruction: third-party named sources are not carried in this catalog, and removing the previous attribution left no source, so this benchmark is recorded as a Rob Clark internal standard. Previous attribution read: 'Industry practice'. The target value itself was not changed - only the attribution. Treat the figure as an advisor standard with no external publication behind it. | P87: The gap between the approved plan and reality. Persistent vacancy with low agency use means existing staff are absorbing the work - burnout being accrued in advance. | Q87: {=IFERROR(INDEX('Benchmark Source Map'!$A$5:$A$13,MATCH(TRUE,(ISNUMBER(SEARCH('Benchmark Source Map'!$E$5:$E$13,$L87))+ISNUMBER(SEARCH('Benchmark Source Map'!$F$5:$F$13,$L87)))>0,0)),"Other named sources")} -> Rob Clark - 2025 CCRC Performance Benchmarks and advisor internal standards
A88: HR-05 | B88: Human Resources | C88: Agency and Contract Labor as Percent of Labor | D88: Agency labor cost / total labor cost, and agency hours / total hours | E88: Lower | F88: X | G88: X | H88: X | I88: X | K88: UNIVERSAL | L88: SOSH 2025 | M88: < 5% of hours and < 5% of labor cost | N88: Payroll report (Screen 09) + GL (Screen 06) | O88: SBC sizes the FTE requirement. This measures what it cost to cover the gap SOURCE TRIMMED 22 Sep 2026 by owner instruction - third-party named sources removed from the Benchmark Source column. Original read: 'SOSH 2025; industry practice'. | P88: The most expensive symptom of a recruitment failure. Above 5% of labor cost, margin erosion is already locked in. | Q88: {=IFERROR(INDEX('Benchmark Source Map'!$A$5:$A$13,MATCH(TRUE,(ISNUMBER(SEARCH('Benchmark Source Map'!$E$5:$E$13,$L88))+ISNUMBER(SEARCH('Benchmark Source Map'!$F$5:$F$13,$L88)))>0,0)),"Other named sources")} -> State of Seniors Housing (SOSH) 2025
A89: HR-06 | B89: Human Resources | C89: Overtime Rate | D89: Overtime hours / total paid hours | E89: Lower | F89: X | G89: X | H89: X | I89: X | K89: UNIVERSAL | L89: Rob Clark - internal standard | M89: < 5% of total hours | N89: Payroll report (Screen 09) | O89: SBC sets required FTE; overtime is the financial symptom of an unfilled requirement RE-ATTRIBUTED 22 Sep 2026 by owner instruction: third-party named sources are not carried in this catalog, and removing the previous attribution left no source, so this benchmark is recorded as a Rob Clark internal standard. Previous attribution read: 'Industry practice'. The target value itself was not changed - only the attribution. Treat the figure as an advisor standard with no external publication behind it. | P89: The cheaper symptom of the same failure. Overtime and agency rise together; both climbing means the staffing model is broken rather than strained. Benchmark basis is productive hours, not total paid hours. | Q89: {=IFERROR(INDEX('Benchmark Source Map'!$A$5:$A$13,MATCH(TRUE,(ISNUMBER(SEARCH('Benchmark Source Map'!$E$5:$E$13,$L89))+ISNUMBER(SEARCH('Benchmark Source Map'!$F$5:$F$13,$L89)))>0,0)),"Other named sources")} -> Rob Clark - 2025 CCRC Performance Benchmarks and advisor internal standards
A90: HR-07 | B90: Human Resources | C90: Absenteeism and Call-Off Rate | D90: Unscheduled absence hours / scheduled hours | E90: Lower | F90: X | G90: X | H90: X | I90: X | K90: UNIVERSAL | L90: Rob Clark - internal standard | M90: < 3-4% unscheduled absence | N90: Payroll report (Screen 09) | O90: RE-ATTRIBUTED 22 Sep 2026 by owner instruction: third-party named sources are not carried in this catalog, and removing the previous attribution left no source, so this benchmark is recorded as a Rob Clark internal standard. Previous attribution read: 'Industry practice'. The target value itself was not changed - only the attribution. Treat the figure as an advisor standard with no external publication behind it. | P90: A culture measure. Unscheduled absence above 4% usually reflects scheduling practice and supervisor relationships, not workforce reliability. | Q90: {=IFERROR(INDEX('Benchmark Source Map'!$A$5:$A$13,MATCH(TRUE,(ISNUMBER(SEARCH('Benchmark Source Map'!$E$5:$E$13,$L90))+ISNUMBER(SEARCH('Benchmark Source Map'!$F$5:$F$13,$L90)))>0,0)),"Other named sources")} -> Rob Clark - 2025 CCRC Performance Benchmarks and advisor internal standards
A91: HR-08 | B91: Human Resources | C91: Employee Engagement and Satisfaction Score | D91: As measured by the operator's instrument, normalized to a 0-100 scale | E91: Higher | F91: X | G91: X | H91: X | I91: X | K91: UNIVERSAL | L91: RC 2025 CCRC Benchmarks | M91: RC 2025 target >= 85%. Reference: Holleran Choice Award > 85th percentile | N91: Manual entry (Screen 10) | O91: Clears the employee-side cultural health red flag. Covers satisfaction and engagement together SOURCE TRIMMED 22 Sep 2026 by owner instruction - third-party named sources removed from the Benchmark Source column. Original read: 'RC 2025 CCRC Benchmarks; Holleran; Activated Insights'. | P91: Leads turnover by roughly two quarters. Below target, assume the turnover number is about to get worse. | Q91: {=IFERROR(INDEX('Benchmark Source Map'!$A$5:$A$13,MATCH(TRUE,(ISNUMBER(SEARCH('Benchmark Source Map'!$E$5:$E$13,$L91))+ISNUMBER(SEARCH('Benchmark Source Map'!$F$5:$F$13,$L91)))>0,0)),"Other named sources")} -> Rob Clark - 2025 CCRC Performance Benchmarks and advisor internal standards
A92: HR-09 | B92: Human Resources | C92: Mandatory Training Completion Rate and Hours | D92: Required training completed on time / required training due; plus training hours per employee, clinical and non-clinical | E92: Higher | F92: X | G92: X | H92: X | I92: X | K92: UNIVERSAL | L92: RC 2025 CCRC Benchmarks; state and federal regulation | M92: 100% on-time completion. RC 2025: >= 24 hours clinical, >= 16 hours non-clinical per year | N92: Payroll / LMS report (Screen 09) | P92: Below 100% is regulatory exposure. Chronic lateness means staffing is too thin to release people from the floor. | Q92: {=IFERROR(INDEX('Benchmark Source Map'!$A$5:$A$13,MATCH(TRUE,(ISNUMBER(SEARCH('Benchmark Source Map'!$E$5:$E$13,$L92))+ISNUMBER(SEARCH('Benchmark Source Map'!$F$5:$F$13,$L92)))>0,0)),"Other named sources")} -> Rob Clark - 2025 CCRC Performance Benchmarks and advisor internal standards
A93: HR-10 | B93: Human Resources | C93: Workers Compensation Cost as Percent of Wages | D93: (Workers compensation premium + claims cost) / total wages | E93: Lower | F93: X | G93: X | H93: X | I93: X | K93: UNIVERSAL | L93: SOSH 2025 Tables 3.20-3.21 | M93: Average 2.2% of wages (published range 0.1-13.1%) | N93: GL (Screen 06) + payroll report (Screen 09) | O93: Replaces the v8 claim frequency measure, which had no published benchmark | P93: Above the 2.2% average points at lifting practice, staffing ratios and return-to-work discipline rather than at premium pricing. | Q93: {=IFERROR(INDEX('Benchmark Source Map'!$A$5:$A$13,MATCH(TRUE,(ISNUMBER(SEARCH('Benchmark Source Map'!$E$5:$E$13,$L93))+ISNUMBER(SEARCH('Benchmark Source Map'!$F$5:$F$13,$L93)))>0,0)),"Other named sources")} -> State of Seniors Housing (SOSH) 2025
A94: HR-11 | B94: Human Resources | C94: Time to Fill | D94: Sum of days to fill / positions filled | E94: Lower | F94: X | G94: X | H94: X | I94: X | K94: UNIVERSAL | L94: RC 2025 CCRC Performance Benchmarks (advisor internal standard) | M94: 30-45 days to fill clinical roles; target 45; flag above 60 | N94: TO BE MAPPED - added from Gap Matrix v9; intake screen not yet assigned | O94: Speed measure. HR-04 Position Vacancy Rate is the stock equivalent and the two are not interchangeable. Benchmark band applies to clinical roles; non-clinical roles are not benchmarked. Added 22 Sep 2026 from the Gap Matrix v9 (Rob Clark). | P94: Reveals recruiting capacity and market wage position. Long fill times are the upstream cause of the agency, overtime and vacancy numbers reported elsewhere - fix here and HR-04, HR-05 and HR-06 all move. | Q94: {=IFERROR(INDEX('Benchmark Source Map'!$A$5:$A$13,MATCH(TRUE,(ISNUMBER(SEARCH('Benchmark Source Map'!$E$5:$E$13,$L94))+ISNUMBER(SEARCH('Benchmark Source Map'!$F$5:$F$13,$L94)))>0,0)),"Other named sources")} -> Rob Clark - 2025 CCRC Performance Benchmarks and advisor internal standards
A95: PLT-01 | B95: Plant and Maintenance | C95: Work Orders per Resident Unit | D95: Total work orders / resident units, reported split between ad hoc and preventive maintenance | E95: Trend | F95: X | G95: X | H95: X | I95: X | K95: UNIVERSAL | L95: Siemens / Brightly Senior Living Maintenance Benchmarks (1,000+ organizations) | M95: 18 total per resident unit: 13 ad hoc, 5 preventive | N95: Plant / maintenance report (Screen 09) | P95: Volume above 18 per unit means the physical plant is consuming labor - usually deferred capital resurfacing as maintenance. | Q95: {=IFERROR(INDEX('Benchmark Source Map'!$A$5:$A$13,MATCH(TRUE,(ISNUMBER(SEARCH('Benchmark Source Map'!$E$5:$E$13,$L95))+ISNUMBER(SEARCH('Benchmark Source Map'!$F$5:$F$13,$L95)))>0,0)),"Other named sources")} -> Siemens / Brightly Senior Living Maintenance Benchmarks
A96: PLT-02 | B96: Plant and Maintenance | C96: Work Order On-Time Completion Rate | D96: Work orders completed on time / total work orders | E96: Higher | F96: X | G96: X | H96: X | I96: X | K96: UNIVERSAL | L96: Siemens / Brightly Senior Living Maintenance Benchmarks | M96: 76% completed on time | N96: Plant / maintenance report (Screen 09) | O96: Replaces the v8 completion-rate measure, which carried no published benchmark | P96: The sector standard is only 76%, so the bar is low. Materially below it means residents are waiting. | Q96: {=IFERROR(INDEX('Benchmark Source Map'!$A$5:$A$13,MATCH(TRUE,(ISNUMBER(SEARCH('Benchmark Source Map'!$E$5:$E$13,$L96))+ISNUMBER(SEARCH('Benchmark Source Map'!$F$5:$F$13,$L96)))>0,0)),"Other named sources")} -> Siemens / Brightly Senior Living Maintenance Benchmarks
A97: PLT-03 | B97: Plant and Maintenance | C97: Maintenance Labor Hours per Resident Unit | D97: Total tracked labor hours / resident units, split ad hoc and preventive | E97: Trend | F97: X | G97: X | H97: X | I97: X | K97: UNIVERSAL | L97: Siemens / Brightly Senior Living Maintenance Benchmarks | M97: 14 hours per resident unit: 9 ad hoc, 5 preventive | N97: Plant / maintenance report (Screen 09) | O97: Labor hours, not FTE count. SBC sets the plant ops FTE at campus square footage / 50,000 | P97: Read against work order volume. High hours on normal volume means the work is harder than it should be, which points at aging systems. | Q97: {=IFERROR(INDEX('Benchmark Source Map'!$A$5:$A$13,MATCH(TRUE,(ISNUMBER(SEARCH('Benchmark Source Map'!$E$5:$E$13,$L97))+ISNUMBER(SEARCH('Benchmark Source Map'!$F$5:$F$13,$L97)))>0,0)),"Other named sources")} -> Siemens / Brightly Senior Living Maintenance Benchmarks
A98: PLT-04 | B98: Plant and Maintenance | C98: Average Days Overdue | D98: Total days overdue / number of overdue work orders, reported for PM and ad hoc separately | E98: Lower | F98: X | G98: X | H98: X | I98: X | K98: UNIVERSAL | L98: Siemens / Brightly Senior Living Maintenance Benchmarks | M98: 3.4 days overall: PM 5.6 days, ad hoc 2.4 days | N98: Plant / maintenance report (Screen 09) | P98: Preventive work overdue by more than 5.6 days is how equipment failures are manufactured. | Q98: {=IFERROR(INDEX('Benchmark Source Map'!$A$5:$A$13,MATCH(TRUE,(ISNUMBER(SEARCH('Benchmark Source Map'!$E$5:$E$13,$L98))+ISNUMBER(SEARCH('Benchmark Source Map'!$F$5:$F$13,$L98)))>0,0)),"Other named sources")} -> Siemens / Brightly Senior Living Maintenance Benchmarks
A99: PLT-05 | B99: Plant and Maintenance | C99: Average Days Open per Work Order | D99: Average calendar days from request date to completion date | E99: Lower | F99: X | G99: X | H99: X | I99: X | K99: UNIVERSAL | L99: Siemens / Brightly Senior Living Maintenance Benchmarks | M99: 3.8 days open | N99: Plant / maintenance report (Screen 09) | O99: This is the resident-facing responsiveness measure | P99: The resident-facing responsiveness measure and a direct input into satisfaction scores. | Q99: {=IFERROR(INDEX('Benchmark Source Map'!$A$5:$A$13,MATCH(TRUE,(ISNUMBER(SEARCH('Benchmark Source Map'!$E$5:$E$13,$L99))+ISNUMBER(SEARCH('Benchmark Source Map'!$F$5:$F$13,$L99)))>0,0)),"Other named sources")} -> Siemens / Brightly Senior Living Maintenance Benchmarks
A100: PLT-06 | B100: Plant and Maintenance | C100: Resident Billings per Resident Unit | D100: Resident billing dollars logged against work orders / resident units | E100: Trend | F100: X | G100: X | H100: X | I100: X | K100: UNIVERSAL | L100: Siemens / Brightly Senior Living Maintenance Benchmarks | M100: $18 per resident unit | N100: Plant / maintenance report (Screen 09) + GL (Screen 06) | O100: Recovery measure. Low billing against high ad hoc volume means chargeable work is being absorbed | P100: Low billing against high ad hoc volume means chargeable work is being absorbed - lost revenue hiding inside the maintenance department. | Q100: {=IFERROR(INDEX('Benchmark Source Map'!$A$5:$A$13,MATCH(TRUE,(ISNUMBER(SEARCH('Benchmark Source Map'!$E$5:$E$13,$L100))+ISNUMBER(SEARCH('Benchmark Source Map'!$F$5:$F$13,$L100)))>0,0)),"Other named sources")} -> Siemens / Brightly Senior Living Maintenance Benchmarks
A101: PLT-07 | B101: Plant and Maintenance | C101: Preventive Maintenance Completion Rate | D101: PM work orders completed on time / PM work orders scheduled | E101: Higher | F101: X | G101: X | H101: X | I101: X | K101: UNIVERSAL | L101: Siemens / Brightly (PM = 5 of 18 work orders, about 28% of volume) | M101: > 90% on-time. PM should hold about 28% of total work order volume | N101: Plant / maintenance report (Screen 09) | O101: Absorbs the v8 vehicle PM measure, which had no separate benchmark SOURCE TRIMMED 22 Sep 2026 by owner instruction - third-party named sources removed from the Benchmark Source column. Original read: 'Siemens / Brightly (PM = 5 of 18 work orders, about 28% of volume); industry practice'. | P101: PM should hold about 28% of volume. Below that the department has gone fully reactive, and ad hoc volume will rise next quarter. | Q101: {=IFERROR(INDEX('Benchmark Source Map'!$A$5:$A$13,MATCH(TRUE,(ISNUMBER(SEARCH('Benchmark Source Map'!$E$5:$E$13,$L101))+ISNUMBER(SEARCH('Benchmark Source Map'!$F$5:$F$13,$L101)))>0,0)),"Other named sources")} -> Siemens / Brightly Senior Living Maintenance Benchmarks
...

Sheet SNF Five-Star Coverage
A1: CMS Five-Star Coverage Check
A2: Verified against the CMS Five-Star Quality Rating System Technical Users Guide, September 2026 (retrieved 2026-09-22). Every contributing component is mapped to a v9 code.
A4: Domain | B4: Contributing Component | C4: v9 Code | D4: Weight or Points | E4: Note
A5: Overall | B5: Composite of the three domain stars | C5: SNF-00 | D5: Health inspection base, +/-1 for staffing, +/-1 for QM | E5: If health inspection is 1 star the overall cannot rise above 2. Abuse icon caps the overall at 4.
A6: Domain 1 Health Inspection | B6: Domain star rating | C6: SNF-01 | D6: State percentile: top 10% = 5 stars, bottom 20% = 1 star | E6: Middle 70% split into three bands of 23.33%. Recalibrated monthly.
A7: Domain 1 Health Inspection | B7: Weighted health inspection score | C7: SNF-H1 | D7: Cycle 1 x 3/4 + cycle 2 x 1/4 | E7: Two cycles only since the July 2025 refresh. Cycle 3 is displayed but not scored.
A8: Domain 1 Health Inspection | B8: Standard survey deficiency points | C8: SNF-H2 | D8: Table 1 scale, D=4 through L=150 (175 with SQC) | E8: Past non-compliance at J/K/L scores at the G value of 20.
A9: Domain 1 Health Inspection | B9: Complaint survey deficiency points | C9: SNF-H3 | D9: 36 months, 0-12 mo at 3/4 and 13-36 mo at 1/4 | E9: Deduplicated against recertification citations within 15 days.
A10: Domain 1 Health Inspection | B10: Focused infection control survey points | C10: SNF-H4 | D10: 36 months, same 3/4 and 1/4 weighting | E10: Where an ICS citation overlaps another within 15 days, only the ICS citation counts.
A11: Domain 1 Health Inspection | B11: Revisit points | C11: SNF-H5 | D11: 1st 0, 2nd 50%, 3rd 70%, 4th 85% of cycle score
A12: Domain 1 Health Inspection | B12: Substandard quality of care citations | C12: SNF-H6 | D12: Raises point values at F, H, I, J, K, L | E12: No separate cap. G has no SQC variant.
A13: Domain 1 Health Inspection | B13: Immediate jeopardy citations | C13: SNF-H7 | D13: Enters only through J, K, L point values | E13: No separate cap or downgrade.
A14: Domain 1 Health Inspection | B14: Abuse icon | C14: SNF-H8 | D14: Caps health inspection at 2 stars | E14: Set from F600, F602, F603 citations. Caps overall at 4 stars.
A15: Domain 1 Health Inspection | B15: Special Focus Facility status | C15: SNF-H9 | D15: SFF participants receive no ratings at all | E15: SFF candidates are rated normally.
A16: Domain 2 Staffing | B16: Domain star rating | C16: SNF-02 | D16: 380-point scale: 5 stars at 320-380, 1 star below 155
A17: Domain 2 Staffing | B17: Case-mix adjusted total nurse HPRD | C17: SNF-S1 | D17: 100 points, deciles | E17: Case-mix adjusted on PDPM nursing CMIs from the FY2024 SNF PPS Final Rule, not RUG-IV.
A18: Domain 2 Staffing | B18: Case-mix adjusted RN HPRD | C18: SNF-S2 | D18: 100 points, deciles | E18: Job codes 5, 6, 7.
A19: Domain 2 Staffing | B19: Case-mix adjusted weekend total nurse HPRD | C19: SNF-S3 | D19: 50 points, deciles | E19: Saturdays and Sundays.
A20: Domain 2 Staffing | B20: Total nurse staffing turnover | C20: SNF-S4 | D20: 50 points, deciles | E20: Requires six consecutive quarters of PBJ. 90-day zero-hours gap definition.
A21: Domain 2 Staffing | B21: RN turnover | C21: SNF-S5 | D21: 50 points, deciles | E21: ADDED in v9. This measure was absent from the v8 catalog.
A22: Domain 2 Staffing | B22: Administrator departures | C22: SNF-S6 | D22: 30 points: 0 departures = 30, 1 = 25, 2+ = 10 | E22: Job code 1.
A23: Domain 2 Staffing | B23: Scoring exceptions | C23: SNF-S7 | D23: Automatic 1 star | E23: Non-submission by the 45-day deadline; 4+ days with zero RN hours; failed or unanswered PBJ audit.
A24: Domain 3 QM | B24: Domain star rating | C24: SNF-03 | D24: Overall QM 299-2,300; 5 stars at 1,494+ | E24: Long-stay 155-1,150; short-stay rescaled by 1,150/800 to 144-1,150.
A25: Domain 3 QM Long-Stay | B25: Need for help with daily activities has increased | C25: SNF-Q1 | D25: 150 points, deciles | E25: MDS-based.
A26: Domain 3 QM Long-Stay | B26: Ability to walk independently worsened | C26: SNF-Q2 | D26: 150 points, deciles | E26: MDS, risk-adjusted. Respecified January 2025 from 'move independently'.
A27: Domain 3 QM Long-Stay | B27: Residents with pressure ulcers | C27: SNF-Q3 | D27: 100 points, quintiles | E27: MDS, risk-adjusted. Respecified January 2025 from high-risk-only to all residents.
A28: Domain 3 QM Long-Stay | B28: Catheter inserted and left in bladder | C28: SNF-Q4 | D28: 100 points, quintiles | E28: MDS, risk-adjusted.
... A45: REMOVED from v8 | B45: Short-stay self-report moderate to severe pain | C45: none | D45: Retired by CMS October 2019 | E45: Was carried in the v8 catalog as SNF-5.04. Must be removed.

Sheet SBC Boundary
A1: Staffing Base Calculator Boundary
A2: The SBC owns staffing efficiency at every level of care. No KPI duplicates an SBC output. One deliberate exception is noted at the bottom.
A4: SBC Output (excluded from the KPI set) | B4: Why the SBC owns it | C4: What the KPI set measures instead
A5: FTEs per occupied unit, by department | B5: SBC computes recommended FTE by level of care and reports variance to current | C5: No KPI
A6: CNA and nurse HPPD for AL and MC | B6: SBC derives AL/MC HPPD from the three-shift ratio model (AL 12/15/20, MC 8/8/12) | C6: No KPI
A7: Meals per labor hour (MPLH) | B7: SBC dining model, target MPLH IL 2.2 / AL 2.5 / MC 3.0 / SNF 3.5 | C7: DIN-01 and DIN-02 measure cost, not productivity
A8: Housekeeping square feet per FTE | B8: SBC housekeeping model: IL 25,000 / AL 20,000 / MC 8,000 / SNF 8,000 sq ft per FTE | C8: No KPI
A9: Laundry pounds per labor hour | B9: SBC laundry model at 50 lbs/hr processing rate | C9: No KPI
A10: Security coverage hours | B10: SBC coverage schedule model, gated on CCRC registration or optional security | C10: No KPI
A11: Plant ops FTE per square foot | B11: SBC plant model: campus square footage / 50,000 | C11: PLT-03 measures labor hours per resident unit, which is work volume rather than headcount
A12: Variance of current staffing to recommended | B12: SBC variance columns for rental and entrance fee scenarios | C12: No KPI
A13: SNF RN HPRD, total nurse HPRD, weekend HPRD | B13: EXCEPTION. These stay in the SNF block as SNF-S1, SNF-S2 and SNF-S3 | C13: These are CMS Five-Star rating inputs computed from PBJ, not outputs of the SBC staffing model. They are scored because they move the star rating

Sheet Care Level Filter
A1: Care Level Filter - what an operator actually gets
A2: KPI counts by department for the care level combinations an operator can select on Community Profile (Screen 03).
A4: Care Levels Selected | B4: Operations | C4: Sales and Marketing | D4: Nursing | E4: Skilled Nursing | F4: Finance | G4: Human Resources | H4: Plant and Maintenance | I4: Life Enrichment | J4: Dining Services | K4: TOTAL
A5: IL only | B5: 8 | C5: 9 | D5: 0 | E5: 0 | F5: 6 | G5: 10 | H5: 10 | I5: 5 | J5: 5 | K5: 53
A6: AL only | B6: 8 | C6: 9 | D6: 8 | E6: 0 | F6: 6 | G6: 10 | H6: 10 | I6: 5 | J6: 7 | K6: 63
A7: MC only | B7: 8 | C7: 9 | D7: 8 | E7: 0 | F7: 6 | G7: 10 | H7: 10 | I7: 6 | J7: 7 | K7: 64
A8: SNF only | B8: 7 | C8: 1 | D8: 5 | E8: 36 | F8: 4 | G8: 10 | H8: 9 | I8: 4 | J8: 6 | K8: 82
A9: AL + MC | B9: 8 | C9: 9 | D9: 8 | E9: 0 | F9: 6 | G9: 10 | H9: 10 | I9: 6 | J9: 7 | K9: 64
A10: IL + AL + MC | B10: 8 | C10: 9 | D10: 8 | E10: 0 | F10: 6 | G10: 10 | H10: 10 | I10: 6 | J10: 7 | K10: 64
A11: AL + MC + SNF | B11: 8 | C11: 9 | D11: 12 | E11: 36 | F11: 6 | G11: 10 | H11: 10 | I11: 6 | J11: 7 | K11: 104
A12: IL + AL + MC + SNF | B12: 8 | C12: 9 | D12: 12 | E12: 36 | F12: 6 | G12: 10 | H12: 10 | I12: 6 | J12: 7 | K12: 104
A13: CCRC (all + entity) | B13: 8 | C13: 9 | D13: 12 | E13: 36 | F13: 10 | G13: 10 | H13: 10 | I13: 6 | J13: 7 | K13: 108
A15: A standalone SNF scores 36 CMS measures plus the universal people, plant, life enrichment and dining measures, plus the SNF-only MDS block. It does NOT receive Days Cash on Hand, Debt Service Coverage or any other entity balance-sheet measure, and it does not receive the Aline sales funnel.
A16: An IL-only community scores no nursing measures at all and no care-delivering dining measures. The AL/MC clinical block is fully suppressed.
A17: General entity measures (Days in AR, Average Age of Plant) switch on whenever a trial balance or balance sheet is uploaded (Screen 07). The four CCRC-gated entity measures - Entity Operating Margin, Days Cash on Hand, Debt Service Coverage and Entrance Fee Refund Funding - stay suppressed unless a CCRC or Life Plan entity is designated, because both their construct and their CARF / RC 2025 benchmarks are CCRC specific.
A18: Universal (yellow) measures are in scope for every combination above. There are 32 of them.

Sheet Retired from v8
A1: Retired, Merged and Relocated from v8
A2: 37 v8 entries are removed, merged or moved. Codes below are v8 codes and do not correspond to v9 codes of the same name.
A4: v8 Code | B4: v8 KPI | C4: Disposition in v9
A5: OPS-05 | B5: Resident Engagement Index | C5: Folded into LE-01 weekly participation and OPS-05 resident satisfaction. A composite index is not a measured data point
A6: OPS-10 | B6: Move-Out Reason Distribution | C6: No benchmark exists for the reason breakdown. Belongs in the report narrative as analysis, not in the KPI set
A7: SAL-01 | B7: Lead Volume by Source | C7: Split into SAL-01 (volume, Aline-benchmarked) and SAL-06 (channel mix, Aline-benchmarked)
A8: SAL-04 | B8: Deposit-to-Move-In Conversion Rate | C8: Aline does not benchmark this step. The funnel is fully covered by SAL-04 and SAL-05 || SUPERSEDED 22 Sep 2026: reinstated in the live catalog as SAL-10 Deposit-to-Move-In Conversion Rate, benchmarked to Rob Clark and Kushant Shah at 80-90% rather than to Aline, so the original rationale no longer applies. The Gap Matrix v9 workbook never retired this measure - it carries the same Aline observation as the reason to use an internal standard. Do not read this entry as excluding the measure.
A9: SAL-05 | B9: Inquiry-to-Move-In Conversion Rate | C9: Arithmetic product of SAL-04 and SAL-05. Redundant
A10: SAL-06 | B10: Active Pipeline Depth by Stage | C10: No published benchmark. Operator target only
A11: SAL-07 | B11: Referral Source Mix and Conversion | C11: Replaced by SAL-06 (mix) and SAL-07 (conversion by channel), both on Aline data
A12: NUR-01 | B12: MDS Assessment Completion Timeliness | C12: Retained but rescoped to SNF only as NUR-09
A13: NUR-02 | B13: ARD Accuracy Rate | C13: Retained but rescoped to SNF only as NUR-10
A14: NUR-03 | B14: Care Plan Completion and Update Timeliness | C14: Retained but rescoped to SNF only as NUR-12
A15: NUR-07 | B15: 30-Day Hospital Readmission Rate | C15: AL/MC replaced by NUR-03 unplanned transfer rate. SNF is covered by CMS QMs SNF-Q8, Q9, Q13, Q14
... A41: DIN-10 | B41: Cost per Meal Served | C41: Derived from DIN-01 and DIN-02, and brushes the SBC meals-per-labor-hour model
A43: Removed after v9 publication
A44: v9 Code | B44: v9 KPI | C44: Disposition
A45: LE-03 | B45: Memory Care Structured Engagement Hours per Resident per Day | C45: DELETED 22 Sep 2026. The 4-6 hour target could not be sourced: the row cited the Alzheimer's Association with no title, year or page, and no link existed in this workbook or in the Gap Matrix v9. The Gap Matrix recorded the same measure as 4-6 hours per WEEK on a Rob Clark internal standard and noted that the Alzheimer's Association publishes dementia care practice recommendations, not an hours-per-resident benchmark - a 7x ambiguity with no documented basis either way. The owner already holds a life enrichment staffing coverage expectation, now carried as LE-06 Life Enrichment Programming Coverage (minimum 8 hours per day, 7 days per week, Rob Clark). LE-04 to LE-07 were renumbered to LE-03 to LE-06. Consequence to note: no per-resident engagement INTENSITY measure now exists - LE-06 measures availability, LE-01 measures attendance. If an intensity measure is wanted later it needs a real citation first.

Sheet Benchmark Source Map
A1: Benchmark Source Map
A2: Which published source sets the target for which department and care level.
A4: Source | B4: Applies To | C4: Supplies | D4: Vintage / Note | E4: Match Key | F4: Alt Match Key | G4: KPIs Mapped | H4: KPI Codes | I4: Where the Data Is Found (Gap Matrix v9)
A5: State of Seniors Housing (SOSH) 2025 | B5: IL, AL, MC, CCRC | C5: Occupancy, annual turnover, revenue and expense per occupied unit, labor percent of revenue, community operating margin, dietary cost per resident day, workers compensation percent of wages | D5: 2025 edition. All dollar measures pass through the CPI toggle. | E5: SOSH | F5: State of Seniors | G5: {=SUMPRODUCT(--((ISNUMBER(SEARCH($E5,'KPI Catalog'!$L$5:$L$119))+ISNUMBER(SEARCH($F5,'KPI Catalog'!$L$5:$L$119)))>0))} -> 14 | H5: {=_xlfn.TEXTJOIN(", ",TRUE,IF((ISNUMBER(SEARCH($E5,'KPI Catalog'!$L$5:$L$119))+ISNUMBER(SEARCH($F5,'KPI Catalog'!$L$5:$L$119)))>0,'KPI Catalog'!$A$5:$A$119,""))} -> OPS-01, OPS-03, OPS-04, SAL-08, NUR-05, FIN-01, FIN-03, FIN-04, FIN-05, FIN-06, HR-05, HR-10, DIN-01, DIN-02 | I5: Gap Matrix v9: 'Benchmark Sources' row 6 (name A6, link I6). Link: https://ashaliving.org/research-and-analytics/ - publisher landing page, NOT a deep link; report is purchasable (ASHA member or paid). Locations cited: Tables 2.7, 2.15, 2.18-2.19, 3.1-3.7, 3.20-3.21, 3.22-3.24, 3.27, 4.1. URL verified 22 Sep 2026. Matrix does not hold the PDF.
A6: CMS and regulatory requirements (Five-Star Technical Users' Guide, RAI Manual, 42 CFR, Life Safety Code, state regulation) | B6: SNF only | C6: All 36 SNF Five-Star measures and their cut-points, plus the regulatory requirements behind assessment timeliness, care plan timeliness, grievance response, life safety, food safety, therapeutic diets and unplanned weight loss | D6: September 2026 for the Five-Star Technical Users' Guide (decision recorded below). Regulatory citations carry no edition - 42 CFR, F-tags, RAI Manual and state regulation are requirements, not benchmark vintages. | E6: CMS | F6: State regulat | G6: {=SUMPRODUCT(--((ISNUMBER(SEARCH($E6,'KPI Catalog'!$L$5:$L$119))+ISNUMBER(SEARCH($F6,'KPI Catalog'!$L$5:$L$119)))>0))} -> 50 | H6: {=_xlfn.TEXTJOIN(", ",TRUE,IF((ISNUMBER(SEARCH($E6,'KPI Catalog'!$L$5:$L$119))+ISNUMBER(SEARCH($F6,'KPI Catalog'!$L$5:$L$119)))>0,'KPI Catalog'!$A$5:$A$119,""))} -> OPS-04, OPS-08, NUR-04, NUR-06, NUR-07, NUR-08, NUR-09, NUR-10, NUR-11, NUR-12, SNF-00, SNF-01, SNF-02, SNF-03, SNF-H1, SNF-H2, SNF-H3, SNF-H4, SNF-H5, SNF-H6, SNF-H7, SNF-H8, SNF-H9, SNF-S1, SNF-S2, SNF-S3, SNF-S4, SNF-S5, SNF-S6, SNF-S7, SNF-Q1, SNF-Q2, SNF-Q3, SNF-Q4, SNF-Q5, SNF-Q6, SNF-Q7, SNF-Q8, SNF-Q9, SNF-Q10, SNF-Q11, SNF-Q12, SNF-Q13, SNF-Q14, SNF-Q15, SNF-Q16, PLT-08, DIN-05, DIN-06, DIN-07 | I6: Gap Matrix v9: 'Benchmark Sources' row 5 (name A5, link I5, which also holds 4 sub-URLs). Link: https://www.cms.gov/medicare/health-safety-standards/certification-compliance/five-star-quality-rating-system - URL pre-existing and not independently verified, though it matches the official CMS page. Locations cited: Table 3 (staffing cut-points), Table A2 (staffing point ranges), Table 5 (QM points). EDITION UNSETTLED - see note in row 22.
A7: CARF 2025 Financial Ratios and Trend Analysis | B7: CCRC and Life Plan, entity level | C7: Days Cash on Hand, Debt Service Coverage, Days in AR, Net Operating Margin, Operating Margin, Average Age of Plant, occupancy trend by care level | D7: CARF / Ziegler / Baker Tilly, 33rd edition. 2024 medians, single-site and multi-site, with Type A/B/C contract cuts available. | E7: CARF | F7: CARF 2025 | G7: {=SUMPRODUCT(--((ISNUMBER(SEARCH($E7,'KPI Catalog'!$L$5:$L$119))+ISNUMBER(SEARCH($F7,'KPI Catalog'!$L$5:$L$119)))>0))} -> 6 | H7: {=_xlfn.TEXTJOIN(", ",TRUE,IF((ISNUMBER(SEARCH($E7,'KPI Catalog'!$L$5:$L$119))+ISNUMBER(SEARCH($F7,'KPI Catalog'!$L$5:$L$119)))>0,'KPI Catalog'!$A$5:$A$119,""))} -> OPS-01, FIN-02, FIN-07, FIN-08, FIN-09, PLT-09 | I7: Gap Matrix v9: 'Benchmark Sources' row 8 (name A8, access note E8, link I8). Link: https://carf.org/wp-content/uploads/2025/10/2025FinancialRatiosTrendAnalysis.pdf - free, no login or payment gate, downloaded and verified 22 Sep 2026 (90pp). Locations: Ratio Summary p.10 (2024 medians, single-site n=71 / multi-site n=26); Section 3 Liquidity pp.41-44 with the Days Cash quartile table p.44; Appendices A and B for account-level inclusions.
A8: Rob Clark - 2025 CCRC Performance Benchmarks and advisor internal standards | B8: CCRC, and universal people measures at every care level | C8: Resident and family satisfaction, online review rating, staff turnover (overall and frontline), employee satisfaction, training hours, medication accuracy, care transition, days cash, DSC, entrance fee refund funding, resident technology use | D8: 2025 for the CCRC Performance Benchmarks; advisor internal standards carry no publication date. Row covers both because neither is externally published - the LE-06 programming coverage floor was set by owner ruling on 22 Sep 2026. | E8: RC 2025 | F8: Rob Clark | G8: {=SUMPRODUCT(--((ISNUMBER(SEARCH($E8,'KPI Catalog'!$L$5:$L$119))+ISNUMBER(SEARCH($F8,'KPI Catalog'!$L$5:$L$119)))>0))} -> 33 | H8: {=_xlfn.TEXTJOIN(", ",TRUE,IF((ISNUMBER(SEARCH($E8,'KPI Catalog'!$L$5:$L$119))+ISNUMBER(SEARCH($F8,'KPI Catalog'!$L$5:$L$119)))>0,'KPI Catalog'!$A$5:$A$119,""))} -> OPS-02, OPS-05, OPS-06, OPS-07, SAL-09, SAL-10, SAL-11, NUR-01, NUR-02, NUR-03, FIN-02, FIN-08, FIN-09, FIN-10, FIN-12, HR-01, HR-02, HR-03, HR-04, HR-06, HR-07, HR-08, HR-09, HR-11, LE-01, LE-02, LE-03, LE-04, LE-05, LE-06, DIN-03, DIN-04, DIN-08 | I8: Gap Matrix v9: 'Benchmark Sources' row 7 (name A7, I7 states no public link). No URL exists - advisor material, not published. Not documented at table or page level in either workbook, so these targets cannot be externally verified by a third party.
A9: Aline Sales and Marketing Benchmark Report | B9: IL, AL, MC, Life Plan Residential | C9: Inquiries, tours and move-ins per 100 units per month; inquiry-to-tour and tour-to-move-in conversion; inquiry channel mix; conversion by channel | D9: Q1 2024 edition as held. The 2026 Senior Living Sales and Marketing Benchmark Report is the current publication but is registration-gated and its figures could not be obtained, so the catalog cites Q1 2024 to match its own numbers. | E9: Aline | F9: Aline Benchmark | G9: {=SUMPRODUCT(--((ISNUMBER(SEARCH($E9,'KPI Catalog'!$L$5:$L$119))+ISNUMBER(SEARCH($F9,'KPI Catalog'!$L$5:$L$119)))>0))} -> 7 | H9: {=_xlfn.TEXTJOIN(", ",TRUE,IF((ISNUMBER(SEARCH($E9,'KPI Catalog'!$L$5:$L$119))+ISNUMBER(SEARCH($F9,'KPI Catalog'!$L$5:$L$119)))>0,'KPI Catalog'!$A$5:$A$119,""))} -> SAL-01, SAL-02, SAL-03, SAL-04, SAL-05, SAL-06, SAL-07 | I9: Gap Matrix v9: 'Benchmark Sources' row 15 (name A15, link I15). Link: https://alineops.com/senior-living-sales-marketing-benchmark-report-2026/ - verified 22 Sep 2026. EDITION MISMATCH: the matrix holds the 2026 Senior Living Sales & Marketing Benchmark Report, not the Q1 2024 edition recorded in column D of this row. Not recorded at table or exhibit level.
A10: Siemens / Brightly Senior Living Maintenance Benchmarks | B10: All care levels, campus wide | C10: Work orders per resident unit, on-time completion, labor hours per resident unit, average days overdue, average days open, resident billings per resident unit | D10: Drawn from 1,000+ senior living organizations. Entire Plant block except Average Age of Plant and Energy Use Intensity. | E10: Brightly | F10: Siemens | G10: {=SUMPRODUCT(--((ISNUMBER(SEARCH($E10,'KPI Catalog'!$L$5:$L$119))+ISNUMBER(SEARCH($F10,'KPI Catalog'!$L$5:$L$119)))>0))} -> 7 | H10: {=_xlfn.TEXTJOIN(", ",TRUE,IF((ISNUMBER(SEARCH($E10,'KPI Catalog'!$L$5:$L$119))+ISNUMBER(SEARCH($F10,'KPI Catalog'!$L$5:$L$119)))>0,'KPI Catalog'!$A$5:$A$119,""))} -> PLT-01, PLT-02, PLT-03, PLT-04, PLT-05, PLT-06, PLT-07 | I10: Gap Matrix v9: 'Benchmark Sources' row 9 (name A9, basis H9, link I9). Link: https://www.assetmanagement.siemens.com/use-cases/senior-living - verified 22 Sep 2026. 2026 edition, (c) Brightly Software Inc 2026, 1,000+ senior living organisations. Locations: KPI #2 on-time (76%), KPI #4 overdue severity (3.4 days avg; PM 5.6, ad hoc 2.4). NAMING: the matrix records this source as Siemens throughout (Brightly was acquired by Siemens).
A11: CLA 40th Annual SNF Report | B11: SNF, financial only | C11: SNF payer mix, revenue and expense per patient day | D11: Approximately 11,700 CMS cost reports. Used for SNF financial comparison, which sits in Finance, not in the SNF Five-Star block. | E11: CLA 40th | F11: CLA | G11: {=SUMPRODUCT(--((ISNUMBER(SEARCH($E11,'KPI Catalog'!$L$5:$L$119))+ISNUMBER(SEARCH($F11,'KPI Catalog'!$L$5:$L$119)))>0))} -> 3 | H11: {=_xlfn.TEXTJOIN(", ",TRUE,IF((ISNUMBER(SEARCH($E11,'KPI Catalog'!$L$5:$L$119))+ISNUMBER(SEARCH($F11,'KPI Catalog'!$L$5:$L$119)))>0,'KPI Catalog'!$A$5:$A$119,""))} -> FIN-03, FIN-04, FIN-06 | I11: Gap Matrix v9: 'Benchmark Sources' row 13 (name A13, link I13). Link: https://www.claconnect.com/en/resources/white-papers/snf-cost-comparison-industry-trends-report - verified 22 Sep 2026. 40th edition, 2025 release on FY2024 data. Locations: skilled revenue per patient day by payer; payer mix derived from approximately 11,700 CMS SNF cost reports.
A12: EPA ENERGY STAR Portfolio Manager | B12: All care levels | C12: Energy Use Intensity for senior care communities | D12: Senior Care Communities DataTrends. Median site EUI approximately 214 kBtu per square foot. | E12: ENERGY STAR | F12: Portfolio Manager | G12: {=SUMPRODUCT(--((ISNUMBER(SEARCH($E12,'KPI Catalog'!$L$5:$L$119))+ISNUMBER(SEARCH($F12,'KPI Catalog'!$L$5:$L$119)))>0))} -> 1 | H12: {=_xlfn.TEXTJOIN(", ",TRUE,IF((ISNUMBER(SEARCH($E12,'KPI Catalog'!$L$5:$L$119))+ISNUMBER(SEARCH($F12,'KPI Catalog'!$L$5:$L$119)))>0,'KPI Catalog'!$A$5:$A$119,""))} -> PLT-10 | I12: NOT HELD - DO NOT WRITE A LINK. The Gap Matrix v9 workbook has no row, no link and no KPI citing ENERGY STAR. Its utility benchmark comes from SOSH 2025 Tables 3.22-3.24 instead. PLT-10 in this catalog is therefore the only place ENERGY STAR is used across the two workbooks and must be sourced independently.
A13: Kushant Shah - internal standard | B13: IL, AL, MC, SNF | C13: A/R aged over 90 days, bad debt and write-off rate, food waste rate, deposit-to-move-in conversion (joint with Rob Clark) | D13: No published edition or date - advisor internal standard, no external benchmark exists. Added 22 Sep 2026 with the Gap Matrix v9 measures. | E13: Kushant Shah | F13: KS internal | G13: {=SUMPRODUCT(--((ISNUMBER(SEARCH($E13,'KPI Catalog'!$L$5:$L$119))+ISNUMBER(SEARCH($F13,'KPI Catalog'!$L$5:$L$119)))>0))} -> 4 | H13: {=_xlfn.TEXTJOIN(", ",TRUE,IF((ISNUMBER(SEARCH($E13,'KPI Catalog'!$L$5:$L$119))+ISNUMBER(SEARCH($F13,'KPI Catalog'!$L$5:$L$119)))>0,'KPI Catalog'!$A$5:$A$119,""))} -> SAL-10, FIN-11, FIN-12, DIN-09 | I13: Gap Matrix v9: no dedicated 'Benchmark Sources' row - recorded there as 'Internal standard (Kushant Shah)' on the KPI rows themselves. No URL exists; advisor material, not published.
A14: Other named sources - RETIRED 22 Sep 2026, should read zero | B14: Varies | C14: Emptied by owner instruction: third-party named sources are no longer carried in the Benchmark Source column. Benchmarks that lost their attribution were re-recorded as Rob Clark internal standards; CMS and state regulatory citations were folded into the CMS and regulatory row above rather than re-attributed, because a regulatory requirement is not an advisor standard. | D14: If this count is ever above zero, a new unapproved source has entered the catalog - investigate rather than add a row. | E14: (no key - catch-all) | F14: (no key - catch-all) | G14: =COUNTIF('KPI Catalog'!$Q$5:$Q$119,$A14) -> 0 | H14: {=_xlfn.TEXTJOIN(", ",TRUE,IF('KPI Catalog'!$Q$5:$Q$119=$A14,'KPI Catalog'!$A$5:$A$119,""))} | I14: Not applicable - no source. This row is a control check, not a source.
A16: How these counts are built
A17: Counts and codes are formulas over the Benchmark Source column on the KPI Catalog tab, matched on the Match Key and Alt Match Key in columns E and F. Edit a key and the count and code list update. Nothing is typed in.
A18: Other named sources' is the exclusive remainder - KPIs matching none of the nine keys - taken from the Primary Benchmark Source Group helper in column Q of the KPI Catalog. Matching elsewhere is non-exclusive, so a KPI citing two sources is counted under both.
A19: Sum of rows 5-13 (with overlap): | D19: =SUM(G5:G13) -> 125
A20: Distinct KPIs in the catalog: | D20: =COUNTA('KPI Catalog'!$A$5:$A$119) -> 115
A21: Dual-source KPIs (the difference): | D21: =SUM(G5:G13)+G14-COUNTA('KPI Catalog'!$A$5:$A$119) -> 10
A22: Source discrepancies raised by the Gap Matrix v9 workbook (22 Sep 2026)
A23: CMS Five-Star Technical Users' Guide edition - DECIDED 22 Sep 2026: this catalog keeps September 2026. The Gap Matrix holds April 2026 on some SNF rows and July 2026 on others and is internally inconsistent by its own account; ours is the later edition and stands. The 36 SNF measures and their QM cut-points remain on the September 2026 basis. If the Gap Matrix re-bases to September 2026 the two will align; until then expect its SNF cut-points to differ from ours.
A24: Aline edition - CLOSED 22 Sep 2026: the catalog stays on the Q1 2024 edition, which is the vintage the SAL-01 to SAL-07 target figures actually come from. The 2026 report is the newer publication but is registration-gated and neither workbook can obtain its figures, so citing 2026 would put a label on numbers that did not come from it. Citing the edition we hold is the defensible position. Yellow flags on the target cells have been cleared - the source and the figures now agree. Revisit only if someone with Aline report access supplies the 2026 values.
A25: Siemens / Brightly naming: the Gap Matrix records this source as Siemens throughout, since Siemens acquired Brightly, and asks that the catalog do the same. The seven Plant rows here cite Brightly. The match keys in columns E and F accept both spellings, so counts are unaffected either way - renaming the citations is a one-line change on request.
A26: EPA ENERGY STAR Portfolio Manager: not held by the Gap Matrix at all. PLT-10 is the only measure across both workbooks using it, and the matrix benchmarks utilities from SOSH 2025 instead. PLT-10's 214 kBtu target needs an independent source or should move to SOSH.
A27: Alzheimer's Association attribution - CLOSED 22 Sep 2026 by deletion. The former LE-03 memory care structured engagement hours cited the Alzheimer's Association for 4-6 hours per resident per day with no title, year or page, and no link existed in either workbook. The Gap Matrix recorded the same measure as 4-6 hours per WEEK on a Rob Clark internal standard and noted that the Alzheimer's Association publishes dementia care practice recommendations, not an hours-per-resident benchmark. Rather than carry an unsourceable 7x ambiguity, the owner deleted the measure on 22 Sep 2026 and the LE codes were renumbered. The Alzheimer's Association is no longer cited anywhere in this catalog. The remaining life enrichment coverage expectation is LE-06, attributed to Rob Clark.
A28: Sources held by the Gap Matrix v9 workbook but not cited in this catalog
A29: Third-party named sources removed from the catalog - 22 Sep 2026, owner instruction
A30: The Benchmark Source column no longer names any third-party organisation outside the approved list. Eleven rows kept a valid source and simply had the extra names trimmed: OPS-05, OPS-06, SAL-09, FIN-06, HR-01, HR-02, HR-05, HR-08, PLT-07, DIN-04, DIN-05. Eleven rows were left with no source and are now Rob Clark internal standards: OPS-02, OPS-07, NUR-02, HR-03, HR-04, HR-06, HR-07, LE-01, LE-02, LE-05, DIN-03. Removed names included NIC MAP, LeadingAge, Argentum, ICAA, Activated Insights, ANFP, Holleran, J.D. Power, Caring.com, Senior Housing News, Pinnacle Quality Insight, HCS Annual Report 2024 and unattributed 'industry practice'. Every original attribution is preserved verbatim in that row's Boundary and Notes column - nothing was silently discarded.
A31: EXCEPTION applied deliberately: CMS and state regulatory citations were NOT re-attributed to Rob Clark. 42 CFR, F-tags, the RAI Manual, the Life Safety Code, MDS Section K and state regulation are legal requirements, not advisor benchmarks, and re-labelling them would have destroyed survey-relevant traceability on 13 measures (OPS-08, NUR-04, NUR-06 to NUR-12, PLT-08, DIN-05, DIN-06, DIN-07). They were folded into the CMS and regulatory row instead, which is why its count rose from 36 to 50. Raise this if the intent was to strip them too.
A32: Creating Results - https://creatingresults.com/marketing-research-strategy/ (verified 22 Sep 2026)
A33: State health department / fire marshal inspections - no single national link, varies by state
... A35: Rob Clark internal standard, and Kushant Shah internal standard - no external publication, no link.

Sheet RC-KS KPI Comparison
A1: Rob Clark - Kushant Shah KPIs - Gap Matrix v9 vs. this KPI Catalog
A2: Source: Advantedge_KPI_Benchmark_Onboarding_Gap_Matrix_v9.xlsx, sheet 'KPI Matrix Updated'. 26 KPIs attributed to Rob Clark and/or Kushant Shah. Compared against the 108 measures on the KPI Catalog tab. Gap Matrix internal codes intentionally excluded.
A4: Added to catalog: | B4: =COUNTIF($J$8:$J$37,"Added to catalog") -> 7 | C4: Already covered: | D4: =COUNTIF($J$8:$J$37,"Already covered") -> 13 | E4: Partial overlap: | G4: =COUNTIF($J$8:$J$37,"Partial overlap") -> 4 | H4: Total RC / KS KPIs: | J4: =COUNTA($C$8:$C$37) -> 26
A5: Eliminated by owner: | B5: =COUNTIF($J$8:$J$37,"Eliminated by owner") -> 1 | C5: Removed from catalog: | D5: =COUNTIF($J$8:$J$37,"Removed from catalog") -> 1
A6: Owner | B6: Department (Gap Matrix) | C6: KPI (Gap Matrix v9) | D6: What It Measures | E6: Direction | F6: Benchmark / Target | G6: Benchmark Basis | H6: Scope | I6: Closest Match in KPI Catalog v9 | J6: Status | K6: Assessment / Recommendation | L6: What the Benchmark Reveals
A7: ADDED TO THE KPI CATALOG - 22 Sep 2026, attributed to Rob Clark / Kushant Shah | B7: ="(" & COUNTIF($J$8:$J$37,"Added to catalog") & " KPI" & IF(COUNTIF($J$8:$J$37,"Added to catalog")=1,"","s") & ")" -> (7 KPIs)
A8: Rob Clark; Kushant Shah | B8: Sales & Marketing | C8: Deposit-to-Move-In Conversion Rate | D8: (moveInsFromDeposits / deposits) * 100 | E8: higher is better | F8: higher - target 85; band 80-90; Deposit-to-move-in 80-90%. | G8: Internal - no external benchmark | H8: All levels of living | I8: SAL-10 (new) | J8: Added to catalog | K8: ADDED 22 Sep 2026 as SAL-10, using the Gap Matrix measure and target and attributed to the advisor rather than a new external source. ADD. Catalog funnel runs inquiry > tour > move-in; the deposit stage is a separate step and is where fallout is usually hiding. | L8: The deepest point in the funnel and the least forgiving. Fallout after a deposit reveals move-in friction - unit readiness, financial qualification or family second-guessing - not sales skill.
A9: Rob Clark | B9: Sales / Marketing | C9: Cost per Acquired Resident | D9: totalSalesMarketingSpend / moveIns | E9: lower is better | F9: lower - target = (CDS marketing 2-3% of operating expenses) / expected annual move-ins. Community-specific - compute the ceiling per community. | G9: Industry - CDS (derived) / internal | H9: All levels of living | I9: SAL-11 (new) | J9: Added to catalog | K9: ADDED 22 Sep 2026 as SAL-11, using the Gap Matrix measure and target and attributed to the advisor rather than a new external source. ADD. No acquisition-cost measure exists. SAL-07 splits channel quality but never divides spend by move-ins. | L9: The only measure that tells you whether census growth was earned or purchased. A community hitting move-in targets at double the acceptable acquisition cost is not performing, it is spending.
A10: Kushant Shah | B10: Finance / Accounting | C10: Accounts Receivable Aging (% > 90 days) | D10: (arOver90 / totalAR) * 100 {unit: percent} | E10: lower is better | F10: lower - target 15; no more than 15% of total A/R aged over 90 days. Internal standard (Kushant Shah). | G10: Internal - no external benchmark | H10: All levels of living | I10: FIN-11 (new) | J10: Added to catalog | K10: ADDED 22 Sep 2026 as FIN-11, using the Gap Matrix measure and target and attributed to the advisor rather than a new external source. ADD as a complement to FIN-07, not a reversal of it. Days in AR reads billing timing; the over-90 tail reads collectability. A community can hold acceptable average days while a concentrated aged balance turns into bad debt. Adding the accepted Bad Debt and Write-Off Rate without this leading indicator is a half-fix. | L10: The over-90 tail reveals collectability, where days in AR reveals timing. A community can hold acceptable average days while a concentrated aged balance quietly becomes bad debt.
A11: Rob Clark; Kushant Shah | B11: Finance / Accounting | C11: Bad Debt and Write-Off Rate | D11: (writeOffs / totalRevenue) * 100 | E11: lower is better | F11: lower - target 1.5; write-offs below 1.5% of total operating revenue. Internal standard (Rob Clark, Kushant Shah). | G11: Internal - no external benchmark | H11: All levels of living | I11: FIN-12 (new) | J11: Added to catalog | K11: ADDED 22 Sep 2026 as FIN-12, using the Gap Matrix measure and target and attributed to the advisor rather than a new external source. ADD. FIN-07 measures collection timing only; nothing measures collection quality or write-offs. | L11: Reveals the quality of the admission decision as much as the billing function. Rising write-offs usually trace back to financial qualification at move-in, not to collections effort.
A12: Rob Clark | B12: Human Resources | C12: Time to Fill | D12: sumDaysToFill / positionsFilled | E12: lower is better | F12: lower - target 45; band 30-45; time to fill clinical roles 30-45 days, flag above 60. Internal standard (Rob Clark). | G12: Internal - no external benchmark | H12: All levels of living | I12: HR-11 (new) | J12: Added to catalog | K12: ADDED 22 Sep 2026 as HR-11, using the Gap Matrix measure and target and attributed to the advisor rather than a new external source. ADD. HR-04 counts how many approved positions are open, not how long they take to fill. | L12: Reveals recruiting capacity and market wage position. Long fill times are the upstream cause of the agency, overtime and vacancy numbers reported elsewhere - fix here and three other KPIs move.
A13: Rob Clark | B13: Dining Services | C13: Nutritional Assessment Completion Rate | D13: (nutAssessmentsCompleted / nutAssessmentsDue) * 100 | E13: higher is better | F13: higher - target 100; Nutritional assessment 100% on-time. | G13: CMS regulatory; Rob Clark - internal standard | H13: SNF only | I13: DIN-08 (new) | J13: Added to catalog | K13: ADDED 22 Sep 2026 as DIN-08, using the Gap Matrix measure and target and attributed to the advisor rather than a new external source. ADD. Dietitian nutritional assessment timeliness is not covered; DIN-06 catches the weight-loss outcome only, after the fact. Scope the CMS F-tag benchmark to SNF/NF while applying the practice at all care levels. | L13: Reveals whether nutrition risk is being caught prospectively or discovered after weight loss. Late assessments mean the community is managing outcomes instead of preventing them.
A14: Kushant Shah | B14: Dining Services | C14: Food Waste Rate | D14: (foodWasteCost / foodPurchases) * 100 | E14: lower is better | F14: lower - target 6; food waste as % of food purchases. Internal standard (Kushant Shah); no published benchmark available. | G14: Internal standard - Kushant Shah | H14: All levels of living | I14: DIN-09 (new) | J14: Added to catalog | K14: ADDED 22 Sep 2026 as DIN-09, using the Gap Matrix measure and target and attributed to the advisor rather than a new external source. ADD. DIN-01 and DIN-02 measure cost only; waste is the controllable driver behind both. | L14: The controllable driver behind food cost. High waste against acceptable cost per resident day reveals menu fit and production forecasting problems that a cost measure alone will never surface.
A15: ALREADY COVERED BY THE KPI CATALOG - no action required | B15: ="(" & COUNTIF($J$8:$J$37,"Already covered") & " KPI" & IF(COUNTIF($J$8:$J$37,"Already covered")=1,"","s") & ")" -> (13 KPIs)
A16: Rob Clark | B16: Operations | C16: Resident Satisfaction Score | D16: DIRECT - single reported/keyed figure (no calculation). {source: MANUAL ENTRY; red-flag resident pair} | E16: higher is better | F16: higher - target 90; resident satisfaction 90%. Internal standard (Rob Clark). | G16: Internal - no external benchmark | H16: All levels of living | I16: OPS-05 Resident Satisfaction Score | J16: Already covered | K16: Catalog target >= 90% already reflects the Rob Clark internal standard. | L16: An internal 90% standard with no external comparator, so it only reveals trend against the community's own history. Its real value is as a leading indicator: it moves two to three quarters ahead of turnover and referral volume.
A17: Rob Clark | B17: Operations | C17: Family Satisfaction Score | D17: DIRECT - single reported/keyed figure (no calculation). {source: MANUAL ENTRY} | E17: higher is better | F17: higher - target 90; family satisfaction 90%. Internal standard (Rob Clark). | G17: Internal - no external benchmark | H17: All levels of living | I17: OPS-06 Family Satisfaction Score | J17: Already covered | K17: Catalog target >= 88% (RC 2025). | L17: Families make both the move-in and the move-out decision. A family score materially below the resident score reveals a communication gap, not a care gap.
A18: Rob Clark | B18: Sales & Marketing | C18: Online Reputation Score | D18: DIRECT - single reported/keyed figure (no calculation). {source: MANUAL ENTRY} | E18: higher is better | F18: higher - target 4.3; CCRC 2025 Google review rating 4.3. | G18: Rob Clark - CCRC 2025 | H18: All levels of living | I18: SAL-09 Online Reputation Score | J18: Already covered | K18: Catalog target >= 4.3 stars (RC 2025). | L18: Reveals reputation equity, which is what determines whether demand is owned or rented. Response rate says more about the operator than the star rating does.
A19: Rob Clark | B19: Human Resources | C19: Voluntary and Involuntary Turnover Rate | D19: (separations / avgHeadcount) * 100 | E19: lower is better | F19: lower - target 35; CCRC 2025 <35% frontline, <20% overall. | G19: Rob Clark - CCRC 2025 | H19: All levels of living | I19: HR-01 Total Staff Turnover Rate | J19: Already covered | K19: HR-01 definition already spans voluntary and involuntary separations. | L19: The root cause behind most clinical and satisfaction misses. The voluntary and involuntary split matters: high involuntary turnover reveals hiring quality, high voluntary reveals management.
A20: Rob Clark | B20: Human Resources | C20: 90-Day New Hire Retention Rate | D20: (newHiresRetained90 / newHires) * 100 | E20: higher is better | F20: higher - target 80; 90-day new hire retention above 80%. Internal standard (Rob Clark). | G20: Internal - no external benchmark | H20: All levels of living | I20: HR-03 90-Day New Hire Retention Rate | J20: Already covered | K20: Identical measure. | L20: Isolates onboarding and hiring quality from everything that happens later. Below 80% the community is recruiting people it was never going to keep.
A21: Rob Clark | B21: Human Resources | C21: Agency and Contract Labor Utilization Rate (as % of labor expense) | D21: (agencyHours / totalHours) * 100 | E21: lower is better | F21: lower - target 120000; CDS nurse agency spend ceiling $120K/yr (2026-adj); % utilization threshold remains internal. | G21: Industry - CDS (Rob Clark), 2026-adjusted | H21: All levels of living | I21: HR-05 Agency and Contract Labor as Percent of Labor | J21: Already covered | K21: Catalog measures both cost share and hours share. | L21: The most expensive symptom of a recruitment failure and the clearest evidence that the staffing model has stopped working. Above 5% of labor cost, margin erosion is already locked in.
A22: Rob Clark | B22: Human Resources | C22: Absenteeism and Call-Off Rate | D22: (unscheduledAbsenceHours / scheduledHours) * 100 | E22: lower is better | F22: lower - target 10; CDS non-productive time 8-10% of productive (proxy - absenteeism is a subset). | G22: Industry - CDS (Rob Clark), 2026-adjusted | H22: All levels of living | I22: HR-07 Absenteeism and Call-Off Rate | J22: Already covered | K22: Identical measure. | L22: A culture measure more than a reliability one. Call-off rates above the band usually reveal scheduling practice and supervisor relationships.
A23: Rob Clark | B23: Human Resources | C23: Employee Engagement Score | D23: DIRECT - single reported/keyed figure (no calculation). {source: MANUAL ENTRY; red-flag employee pair} | E23: higher is better | F23: higher - target 85; CCRC 2025 employee satisfaction 85%. | G23: Rob Clark - CCRC 2025 | H23: All levels of living | I23: HR-08 Employee Engagement and Satisfaction Score | J23: Already covered | K23: Catalog covers engagement and satisfaction together. | L23: Leads turnover by roughly two quarters, which makes it the earliest actionable warning in the workforce set. A low score with acceptable turnover means the turnover is still coming.
A24: Rob Clark | B24: Plant / Maintenance | C24: Preventive Maintenance Completion Rate | D24: (pmCompletedOnTime / pmScheduled) * 100 | E24: higher is better | F24: higher - target 90; PM completed on time above 90%. Internal standard (Rob Clark). | G24: Internal - no external benchmark | H24: All levels of living | I24: PLT-07 Preventive Maintenance Completion Rate | J24: Already covered | K24: Identical measure. | L24: Reveals whether the plant department is running the building or reacting to it. Falling PM completion reliably produces higher ad hoc volume and higher capital spend later.
A25: Rob Clark | B25: Life Enrichment | C25: Overall Activity Participation Rate | D25: (participatingResidents / totalResidents) * 100 {source: MANUAL ENTRY} | E25: higher is better | F25: higher - target 80; weekly activity participation above 80%. Internal standard (Rob Clark); absorbs retired OPS-05. | G25: Internal - no external benchmark | H25: All levels of living | I25: LE-01 Weekly Resident Participation Rate | J25: Already covered | K25: Catalog target > 80% weekly. | L25: The quietest early signal of cultural decline in the building. It falls before satisfaction scores do and well before turnover reflects it.
A26: Rob Clark | B26: Life Enrichment | C26: Resident Satisfaction - Programming | D26: DIRECT - single reported/keyed figure (no calculation). {source: MANUAL ENTRY} | E26: higher is better | F26: higher - target 85; programming satisfaction above 85%. Internal standard (Rob Clark). | G26: Internal - no external benchmark | H26: All levels of living | I26: LE-03 Programming Satisfaction Score (renumbered from LE-04 on 22 Sep 2026) | J26: Already covered | K26: Identical measure. | L26: Separates programming fit from programming volume. High offering counts with low programming satisfaction reveal a calendar built for the department rather than the residents.
A27: Rob Clark | B27: Dining Services | C27: Resident Meal Satisfaction Score | D27: DIRECT - single reported/keyed figure (no calculation). {source: MANUAL ENTRY} | E27: higher is better | F27: higher - target 85; meal satisfaction above 85%, top quartile above 90%. Internal standard (Rob Clark). | G27: Internal - no external benchmark | H27: All levels of living | I27: DIN-04 Resident Meal Satisfaction Score | J27: Already covered | K27: Identical measure. | L27: Dining is the most frequently experienced service in the building and the most cited source of dissatisfaction, so this measure carries more weight with families than its subject matter suggests.
A28: Rob Clark | B28: Dining Services | C28: Therapeutic Diet Compliance Rate | D28: (therapeuticDietsCorrect / therapeuticDietsTotal) * 100 | E28: higher is better | F28: higher - target 98; Therapeutic diet >98%. | G28: CMS regulatory; Rob Clark - internal standard | H28: SNF only | I28: DIN-05 Therapeutic and Modified Diet Accuracy Rate | J28: Already covered | K28: Practice scope and benchmark scope differ. DIN-05 correctly applies the practice to AL/MC/SNF, but the cited authority is CMS F-812 / F-692, which is SNF/NF scoped - do not carry the F-tag benchmark to IL/AL/MC. Record benchmark scope separately from practice scope. | L28: Reveals the handoff between clinical orders and the kitchen. Failures here are clinical events, not service complaints, and the CMS F-tag exposure makes them survey-relevant in SNF.
A29: PARTIAL OVERLAP - same ground, different definition or scope; reconcile rather than add | B29: ="(" & COUNTIF($J$8:$J$37,"Partial overlap") & " KPI" & IF(COUNTIF($J$8:$J$37,"Partial overlap")=1,"","s") & ")" -> (4 KPIs)
A30: Rob Clark | B30: Human Resources | C30: Overtime Rate (as % of productive labor) | D30: (overtimeHours / totalHours) * 100 | E30: lower is better | F30: lower - target 4; CDS overtime 0-4% of productive time. | G30: Industry - CDS (Rob Clark), 2026-adjusted | H30: All levels of living | I30: HR-06 Overtime Rate (denominator conflict) | J30: Partial overlap | K30: CATALOG SHOULD CHANGE. Gap Matrix basis is correct: the CDS Best Practice band is 0-4% of PRODUCTIVE time, so PTO, holiday and sick hours must be excluded. HR-06's total-paid-hours denominator understates the rate and can show false compliance. Restate HR-06 to productive hours, or carry both with the benchmark attached only to the productive version. | L30: The cheaper symptom of the same failure. Measured on productive hours it reveals true reliance on existing staff to cover an unfilled plan; on total paid hours it flatters the community.
A31: Kushant Shah | B31: Plant / Maintenance | C31: Planned vs. Reactive Maintenance Ratio | D31: (plannedWorkOrders / totalWorkOrders) * 100 | E31: higher is better | F31: higher - target 65; 65% of work orders planned. Internal standard (Kushant Shah). | G31: Internal - no external benchmark | H31: All levels of living | I31: PLT-01 Work Orders per Resident Unit / PLT-07 | J31: Partial overlap | K31: PLT-01 already reports ad hoc vs preventive volume (13 vs 5) and PLT-07 notes PM ~28% of volume. Derivable - add as a computed field, not a new measure. | L31: The clearest single read on plant discipline. A ratio tilting reactive reveals a department that has lost control of its own schedule, and it precedes equipment failure and capital surprises.
A32: Rob Clark | B32: Dining Services | C32: Special Diet Error Rate | D32: (specialDietErrors / specialDietMealsServed) * 100 | E32: lower is better | F32: lower - target 2; special diet error rate below 2%; zero allergen errors. Internal standard (Rob Clark). | G32: Internal - no external benchmark | H32: All levels of living | I32: DIN-05 Therapeutic and Modified Diet Accuracy Rate | J32: Partial overlap | K32: Inverse of DIN-05 accuracy. No new measure needed - report as 1 minus accuracy. | L32: The inverse view of diet accuracy, and the more useful one operationally: it counts events rather than averaging them away. Allergen errors are never an acceptable rate.
A33: Rob Clark | B33: Dining Services | C33: Dining Room Attendance Rate | D33: (diningRoomAttendees / totalResidents) * 100 {source: MANUAL ENTRY} | E33: higher is better | F33: higher - target 80; by care level IL:90, AL:80, MC:67; dining attendance IL>90 / AL 75-85 / MC 60-75. Internal standard (Rob Clark). | G33: Internal - no external benchmark | H33: All levels of living | I33: DIN-03 Meal Participation Rate | J33: Partial overlap | K33: DIN-03 counts meals served including room trays; dining-room attendance is narrower. Best as a sub-field of DIN-03. | L33: A proxy for social engagement as much as for food quality. Residents eating in their rooms reveal isolation, mobility decline or dining room experience problems that satisfaction surveys often miss.
A34: ELIMINATED BY THE BENCHMARK OWNER (Gap Matrix v8.3) - do not add, do not re-propose | B34: ="(" & COUNTIF($J$8:$J$37,"Eliminated by owner") & " KPI" & IF(COUNTIF($J$8:$J$37,"Eliminated by owner")=1,"","s") & ")" -> (1 KPI)
A35: Kushant Shah | B35: Plant / Maintenance | C35: Unit Turnover Time | D35: ELIMINATED v8.3 - removed per Rob (per-event cost multiplier, not a frequency target). | F35: ELIMINATED v8.3 - removed per Rob (per-event cost multiplier, not a frequency target). | H35: All levels of living | I35: None - eliminated in Gap Matrix v8.3 (10 Jun 2026) | J35: Eliminated by owner | K35: DO NOT ADD. Confirmed a genuine elimination, not a corrupted record. The KPI computed days from move-out to rent-ready, but the only available benchmark expressed a per-event cost multiplier - the two measured different quantities. v8.2 yellow-flagged this as one of eight scope mismatches; v8.3 resolved seven and eliminated this one rather than re-specify it, taking the matrix from 98 to 97 measures. The 15-day IL/AL/MC figure that circulated is dead - it predates the elimination and was never reconciled to a source. The underlying operational gap is real (unit turn time constrains OPS-01 occupancy and SAL-03 move-ins) but it needs a benchmark that measures duration, not cost per event, before it can enter the catalog. | L35: Converts maintenance performance into revenue terms. Every extra day between move-out and rent-ready is lost revenue on an otherwise sold unit, and it reveals coordination between plant, housekeeping and sales.
A36: REMOVED FROM THE CATALOG - benchmark could not be sourced; do not reinstate without a citation | B36: ="(" & COUNTIF($J$8:$J$37,"Removed from catalog") & " KPI" & IF(COUNTIF($J$8:$J$37,"Removed from catalog")=1,"","s") & ")" -> (1 KPI)
A37: Rob Clark | B37: Life Enrichment | C37: Memory Care Resident Engagement Hours per Resident per Week | D37: structuredEngagementHours / mcResidents | E37: higher is better | F37: higher - target 4; band 4-6; MC structured engagement 4-6 hrs/day. | G37: Internal - no external benchmark | H37: All levels of living | I37: None - the catalog measure was deleted; LE-06 coverage floor is a different denominator | J37: Removed from catalog | K37: REMOVED 22 Sep 2026 by owner decision. Rather than carry an unsourceable 7x ambiguity, the catalog measure was deleted outright: the 4-6 hour figure cited the Alzheimer's Association with no title, year or page, no link existed in either workbook, and the Gap Matrix recorded the same measure as per WEEK on a Rob Clark internal standard while noting the Alzheimer's Association publishes practice recommendations, not an hours-per-resident benchmark. The owner already holds a life enrichment staffing coverage expectation, now LE-06 Life Enrichment Programming Coverage (minimum 8 hours per day, 7 days per week, Rob Clark). LE-04 to LE-07 renumbered to LE-03 to LE-06; logged on the 'Retired from v8' tab. Consequence: no per-resident engagement INTENSITY measure exists in the catalog - LE-06 measures availability, LE-01 measures attendance. An intensity measure needs a real citation before it can return. | L37: Structured engagement is the non-pharmacological alternative to antipsychotic use, so this reveals the MC programming model's real capacity. Interpretation is currently blocked by the unresolved per-day versus per-week conflict.
A39: Catalog additions made 22 Sep 2026
A40: Catalog Code | B40: KPI | C40: Benchmark Source as Recorded in the Catalog
A41: =I8 -> SAL-10 (new) | B41: =C8 -> Deposit-to-Move-In Conversion Rate | C41: =IFERROR(INDEX('KPI Catalog'!$L$5:$L$119,MATCH(TRIM(SUBSTITUTE($A41," (new)","")),'KPI Catalog'!$A$5:$A$119,0)),"") -> RC 2025 CCRC Performance Benchmarks; Kushant Shah internal standard
A42: =I9 -> SAL-11 (new) | B42: =C9 -> Cost per Acquired Resident | C42: =IFERROR(INDEX('KPI Catalog'!$L$5:$L$119,MATCH(TRIM(SUBSTITUTE($A42," (new)","")),'KPI Catalog'!$A$5:$A$119,0)),"") -> RC 2025 CCRC Performance Benchmarks - CDS Best Practice Metrics 2025 (advisor material, derived)
A43: =I10 -> FIN-11 (new) | B43: =C10 -> Accounts Receivable Aging (% > 90 days) | C43: =IFERROR(INDEX('KPI Catalog'!$L$5:$L$119,MATCH(TRIM(SUBSTITUTE($A43," (new)","")),'KPI Catalog'!$A$5:$A$119,0)),"") -> Kushant Shah internal standard
A44: =I11 -> FIN-12 (new) | B44: =C11 -> Bad Debt and Write-Off Rate | C44: =IFERROR(INDEX('KPI Catalog'!$L$5:$L$119,MATCH(TRIM(SUBSTITUTE($A44," (new)","")),'KPI Catalog'!$A$5:$A$119,0)),"") -> RC 2025 CCRC Performance Benchmarks; Kushant Shah internal standard
A45: =I12 -> HR-11 (new) | B45: =C12 -> Time to Fill | C45: =IFERROR(INDEX('KPI Catalog'!$L$5:$L$119,MATCH(TRIM(SUBSTITUTE($A45," (new)","")),'KPI Catalog'!$A$5:$A$119,0)),"") -> RC 2025 CCRC Performance Benchmarks (advisor internal standard)
A46: =I13 -> DIN-08 (new) | B46: =C13 -> Nutritional Assessment Completion Rate | C46: =IFERROR(INDEX('KPI Catalog'!$L$5:$L$119,MATCH(TRIM(SUBSTITUTE($A46," (new)","")),'KPI Catalog'!$A$5:$A$119,0)),"") -> RC 2025 CCRC Performance Benchmarks (advisor internal standard)
A47: =I14 -> DIN-09 (new) | B47: =C14 -> Food Waste Rate | C47: =IFERROR(INDEX('KPI Catalog'!$L$5:$L$119,MATCH(TRIM(SUBSTITUTE($A47," (new)","")),'KPI Catalog'!$A$5:$A$119,0)),"") -> Kushant Shah internal standard
A49: Note from the Gap Matrix v9 export: Days Cash on Hand was previously attributed to Rob Clark's 2025 CCRC Performance Benchmarks but has been re-sourced to CARF 2025, so it is not in this list. It is already in the catalog as FIN-08. Only the canonical 'KPI Matrix Updated' sheet was exported; the superseded 'KPI Matrix Old Version' and 'v5 Source Backfill' tabs also carry Rob Clark attributions and were excluded as archive.
A51: Reconciliation notes (agreed with the Gap Matrix v9 workbook, 22 Sep 2026)
A52: 1. Overtime Rate: the Gap Matrix basis wins. Benchmark is 0-4% of productive time (CDS Best Practice), so HR-06 needs restating to a productive-hours denominator. Its operand was renamed there from 'totalHours' to 'productiveHours' with an explicit PTO / holiday / sick exclusion list.
A53: 2. Memory care engagement hours - CLOSED ON THIS SIDE ONLY, 22 Sep 2026, by deleting the measure. Neither reading was sourceable: the catalog cited the Alzheimer's Association with no title, year or page, and the Gap Matrix recorded a Rob Clark internal standard per week while noting the Alzheimer's Association publishes practice recommendations, not an hours-per-resident benchmark. NOT CLOSED IN THE GAP MATRIX: that row carries its own internal contradiction - name and benchmark text say per week, structured target says per day, compute formula carries no period - which predates this catalog's involvement and survives the deletion. It cannot compute and must not be cited until Rob Clark rules. If he confirms a figure the intensity measure can return here properly attributed as an advisor standard.
A54: 3. Therapeutic diet and nutritional assessment: not a conflict. 'SNF only' in the Gap Matrix is BENCHMARK scope (CMS F-812 / F-692 is SNF/NF scoped); the practice itself is cross-level. Catalog DIN-05 applying to AL/MC/SNF is correct for the practice - the F-tag benchmark must not travel with it.
A55: 4. LE-02: not a mismatch. Code numbering is not aligned between the two workbooks. Gap Matrix LE-02 is the memory care engagement measure; in this catalog LE-02 is Programs Offered per Resident per Week (universal) and the memory care measure is LE-03, already scoped memory care only.
A57: Kushant Shah attribution check: six KPIs on this tab carry his name (four solo, two joint with Rob Clark). Five are now in the catalog - SAL-10, FIN-11, FIN-12 and DIN-09 as additions, plus AR aging promoted from 'already covered' on 22 Sep 2026. Planned vs. Reactive Maintenance Ratio remains deliberately excluded as derivable from PLT-01 and PLT-07.
A59: How the additions were sourced: each new catalog row uses the Gap Matrix v9 measure definition and target verbatim and attributes the benchmark to Rob Clark or Kushant Shah, so no new external source was introduced. A 'Kushant Shah - internal standard' row was added to the Benchmark Source Map (row 13) because his standards previously fell into the catch-all. Intake column N is flagged yellow on all seven new rows - no intake screen has been assigned yet.
A61: Unit Turnover Time - closed 22 Sep 2026. Confirmed by the Gap Matrix v9 workbook as eliminated in v8.3, not a data defect: 'ELIMINATED' appears on exactly one row of its 111 (PLT-08) and nowhere else, corroborated by the v8 Change Log. The parenthetical 'per-event cost multiplier, not a frequency target' describes the rejected BENCHMARK, not the KPI - context that was missing from the export. The row was marked rather than deleted, so its name, source and intake fields still read as active while the elimination marker sits in later columns, which is why the export looked contradictory. The owner has since marked the name and benchmark cells and added the background in cell notes.
A62: Count reconciliation: this catalog holds 115 measures and the Gap Matrix v9 holds 111 rows, 110 active after the eliminated measure. The two totals are not meant to agree - the code sequences are not aligned (see note 4 above), the catalog carries 36 SNF Five-Star measures the matrix does not break out individually, and the matrix carries sources and measures outside this catalog's scope. Do not reconcile the two counts against each other.
A63: LE-06 Life Enrichment Programming Coverage - added 22 Sep 2026 from an owner ruling rather than from the Gap Matrix. Minimum 8 hours per day, 7 days per week, universal across care levels, attributed to Rob Clark because no published source carries a coverage floor. Originally written as LE-07; renumbered to LE-06 when the unsourceable memory care engagement measure was deleted. Catalog is now 115 measures. The Benchmark Source Map's Rob Clark row covers both the 2025 CCRC Performance Benchmarks and advisor internal standards, with the match key widened to 'Rob Clark' so future advisor standards map automatically.
A65: SAL-10 reinstatement - CLEARED 22 Sep 2026. The 'Retired from v8' tab retired v8 SAL-04 Deposit-to-Move-In Conversion Rate on the grounds that 'Aline does not benchmark this step'. The Gap Matrix confirms it never retired the measure: it is a live row there on a Rob Clark and Kushant Shah internal standard at 80-90%, and the same Aline observation is recorded there as the reason to use an internal standard rather than a reason to drop the measure. Our SAL-10 reinstatement therefore agrees with their record; the v8 retirement entry has been annotated rather than left to read as a contradiction.
A67: LE code renumbering - 22 Sep 2026. Life Enrichment codes shifted when the unsourceable memory care measure was deleted: former LE-04 to LE-07 became LE-03 to LE-06. Any LE code cited by number in a record written before that date is ambiguous, including the Gap Matrix v9 export and this tab's own earlier entries - one stale reference (Programming Satisfaction, cited as LE-04) was found and corrected. LE codes are not aligned between the two workbooks either: the Gap Matrix LE-03 is a satisfaction measure unrelated to any LE-03 here. Cite LE measures by name, or by code with the date, never by code alone.
