Workbook

Sheet KPI_Master
A1: Sr. No. | B1: KPI ID | C1: Department | D1: KPI Name | E1: Formula | F1: Source System | G1: Source Documents / Records | H1: Frequency | I1: Direction | J1: Dashboard Tier | K1: Adoption Priority | L1: Priority Rationale | M1: Found in Other Files
A2: 1 | B2: DINF-01 | C2: Dining / Food Service | D2: Raw Food Cost per Resident Day (PRD) | E2: Total Raw Food Purchase Cost / Total Resident Days | F2: Dining/Food service system, Finance GL | G2: Vendor invoices; Inventory count sheets; Daily census report | H2: Monthly | I2: Lower is better | J2: Executive | K2: 1 - Core | L2: Largest controllable non-labour cost | M2: Both files
A3: 2 | B3: DINF-02 | C3: Dining / Food Service | D3: Total Dining Cost per Resident Day | E3: (Food Cost + Dining Labor + Supplies) / Total Resident Days | F3: Finance GL, Payroll | G3: GL department expense report; Payroll register; Census report | H3: Monthly | I3: Lower is better | J3: Executive | K3: 2 - Standard | L3: Explains movement in a Tier 1 KPI - add in phase 2 | M3: Both files
A4: 3 | B4: DINF-03 | C4: Dining / Food Service | D4: Dining Labor as % of Dining Expense | E4: (Dining Labor Cost / Total Dining Department Cost) * 100 | F4: Payroll, Finance GL | G4: Payroll register; Department P&L | H4: Monthly | I4: Lower is better | J4: Operational | K4: 2 - Standard | L4: Explains movement in a Tier 1 KPI - add in phase 2 | M4: Cross-Source only
A5: 4 | B5: DINF-04 | C5: Dining / Food Service | D5: Meal Participation Rate | E5: (Meals Actually Served / Meals Forecast for Census) * 100 | F5: Dining POS / meal tracking system | G5: Meal count sheets; POS transaction log; Census report | H5: Weekly | I5: Higher is better | J5: Operational | K5: 2 - Standard | L5: Explains movement in a Tier 1 KPI - add in phase 2 | M5: Advantedge only
A6: 5 | B6: DINF-06 | C6: Dining / Food Service | D6: Resident Dining Satisfaction Score | E6: Sum of Dining Satisfaction Ratings / Number of Responses | F6: Survey platform, Resident engagement system | G6: Resident satisfaction survey; Food committee minutes; Comment cards | H6: Quarterly | I6: Higher is better | J6: Executive | K6: 1 - Core | L6: Drives referrals and retention | M6: Advantedge only
A7: 6 | B7: DINF-07 | C7: Dining / Food Service | D7: Therapeutic Diet Accuracy Rate | E7: (Trays Matching Prescribed Diet Order / Total Trays Audited) * 100 | F7: PCC (diet orders), Dining system | G7: Diet order report; Tray line audit sheet; Dietitian audit log | H7: Monthly | I7: Higher is better | J7: Operational | K7: 2 - Standard | L7: Explains movement in a Tier 1 KPI - add in phase 2 | M7: Advantedge only
A8: 7 | B8: DINF-08 | C8: Dining / Food Service | D8: Food Safety / Sanitation Audit Score | E8: (Points Earned on Sanitation Audit / Total Possible Points) * 100 | F8: Compliance/QAPI system | G8: Health department inspection report; Internal sanitation audit; Temperature logs | H8: Monthly | I8: Higher is better | J8: Operational | K8: 2 - Standard | L8: Explains movement in a Tier 1 KPI - add in phase 2 | M8: Advantedge only
A9: 8 | B9: DINF-12 | C9: Dining / Food Service | D9: Nutritional Assessment Completion Rate | E9: (Nutritional Assessments Completed On Time / Nutritional Assessments Due) * 100 | F9: PCC (dietitian assessments), Dining system | G9: Dietitian assessment records; MDS Section K; Admission nutrition screen | H9: Monthly | I9: Higher is better | J9: Operational | K9: 2 - Standard | L9: Regulatory - survey exposure (F-692) | M9: Advantedge KPI Matrix v8
A10: 9 | B10: DINF-13 | C10: Dining / Food Service | D10: Hydration Monitoring Compliance Rate | E10: (At-Risk Residents Monitored per Protocol / Residents Requiring Hydration Monitoring) * 100 | F10: PCC, Dining system | G10: Intake & output records; Hydration risk list; Care plans | H10: Monthly | I10: Higher is better | J10: Operational | K10: 2 - Standard | L10: Regulatory - survey exposure (F-692) | M10: Advantedge KPI Matrix v8
A11: 10 | B11: DINF-14 | C11: Dining / Food Service | D11: Raw Food Cost per Meal | E11: Total Raw Food Purchase Cost / Total Meals Served | F11: Dining/Food service system, Finance GL | G11: Food purchase invoices; Meal count / POS report | H11: Monthly | I11: Target range | J11: Operational | K11: 2 - Standard | L11: Largest controllable non-labour cost (per-meal view of DINF-01) | M11: Cross-Source Benchmark 2025
A12: 11 | B12: DINF-15 | C12: Dining / Food Service | D12: Meals per Labor Hour | E12: Total Meals Served / Total Dining Labor Hours | F12: Payroll / Time & Attendance, Dining POS | G12: Dining timecards; Meal count / POS report | H12: Monthly | I12: Higher is better | J12: Operational | K12: 2 - Standard | L12: Explains movement in a Tier 1 KPI - add in phase 2 (DINF-03) | M12: Cross-Source Benchmark 2025
A13: 12 | B13: FINA-01 | C13: Finance / Accounting | D13: Occupancy Rate | E13: (Occupied Units / Total Available Units) * 100 | F13: CRM, Finance / Billing system | G13: Daily census report; Unit inventory schedule; Rent roll | H13: Daily | I13: Higher is better | J13: Executive | K13: 1 - Core | L13: The single number the business runs on | M13: Both files
... A172: 171 | B172: TRA-07 | C172: Transportation | D172: Vehicle Preventive Maintenance Compliance | E172: (Vehicle PM Services Completed On Time / PM Services Due) * 100 | F172: MicroMain CMMS, Fleet records | G172: Vehicle service records; Fleet PM schedule | H172: Quarterly | I172: Higher is better | J172: Operational | K172: 2 - Standard | L172: Explains movement in a Tier 1 KPI - add in phase 2 | M172: Advantedge only

Sheet Common_Formula_Elements
A1: Common Formula Elements - which formula inputs are shared, and by which Sr. Nos.
A2: Each row is one input that appears in KPI formulas. "Used in Sr. No." lists the KPI_Master serial numbers that use it. Each element is fed by ONE document (column G, blue = editable). Change a Doc ID here and the map, matrix and document counts all update. Click any Sr. No. in columns J onward to jump straight to that KPI's row (formula, sources, documents) in KPI_Master.
A4: Element ID | B4: Common Data Element (formula input) | C4: Standard Definition (use the same everywhere) | D4: Used in Sr. No. | E4: No. of KPIs Using It | F4: Of which Tier 1 - Core | G4: Doc ID | H4: Single Source Document | J4: Go to KPI_Master - click a Sr. No. to jump to that KPI row
A5: E01 | B5: Total Resident Days | C5: Sum of daily (midnight) census over the period | D5: {=_xlfn.TEXTJOIN(", ",TRUE(),IF(KPI_Element_Map!$E$2:$E$287=$A5,KPI_Element_Map!$A$2:$A$287,""))} -> 1, 2, 4, 22, 52, 81, 84, 87, 88, 89, 95, 98, 115, 144, 169 | E5: =COUNTIF(KPI_Element_Map!$E$2:$E$287,$A5) -> 15 | F5: =COUNTIFS(KPI_Element_Map!$E$2:$E$287,$A5,KPI_Element_Map!$D$2:$D$287,"1 - Core") -> 3 | G5: D01 | H5: =INDEX(Minimum_Documents!$B:$B,MATCH($G5,Minimum_Documents!$A:$A,0)) -> Census & ADT Register | J5: {=IFERROR(HYPERLINK("#KPI_Master!A"&MATCH(SMALL(IF(KPI_Element_Map!$E$2:$E$287=$A5,KPI_Element_Map!$A$2:$A$287),COLUMNS($J5:J5)),KPI_Master!$A:$A,0)&":P"&MATCH(SMALL(IF(KPI_Element_Map!$E$2:$E$287=$A5,KPI_Element_Map!$A$2:$A$287),COLUMNS($J5:J5)),KPI_Master!$A:$A,0),SMALL(IF(KPI_Element_Map!$E$2:$E$287=$A5,KPI_Element_Map!$A$2:$A$287),COLUMNS($J5:J5))),"")} -> 1 | K5: {=IFERROR(HYPERLINK("#KPI_Master!A"&MATCH(SMALL(IF(KPI_Element_Map!$E$2:$E$287=$A5,KPI_Element_Map!$A$2:$A$287),COLUMNS($J5:K5)),KPI_Master!$A:$A,0)&":P"&MATCH(SMALL(IF(KPI_Element_Map!$E$2:$E$287=$A5,KPI_Element_Map!$A$2:$A$287),COLUMNS($J5:K5)),KPI_Master!$A:$A,0),SMALL(IF(KPI_Element_Map!$E$2:$E$287=$A5,KPI_Element_Map!$A$2:$A$287),COLUMNS($J5:K5))),"")} -> 2 | L5: {=IFERROR(HYPERLINK("#KPI_Master!A"&MATCH(SMALL(IF(KPI_Element_Map!$E$2:$E$287=$A5,KPI_Element_Map!$A$2:$A$287),COLUMNS($J5:L5)),KPI_Master!$A:$A,0)&":P"&MATCH(SMALL(IF(KPI_Element_Map!$E$2:$E$287=$A5,KPI_Element_Map!$A$2:$A$287),COLUMNS($J5:L5)),KPI_Master!$A:$A,0),SMALL(IF(KPI_Element_Map!$E$2:$E$287=$A5,KPI_Element_Map!$A$2:$A$287),COLUMNS($J5:L5))),"")} -> 4 | M5: {=IFERROR(HYPERLINK("#KPI_Master!A"&MATCH(SMALL(IF(KPI_Element_Map!$E$2:$E$287=$A5,KPI_Element_Map!$A$2:$A$287),COLUMNS($J5:M5)),KPI_Master!$A:$A,0)&":P"&MATCH(SMALL(IF(KPI_Element_Map!$E$2:$E$287=$A5,KPI_Element_Map!$A$2:$A$287),COLUMNS($J5:M5)),KPI_Master!$A:$A,0),SMALL(IF(KPI_Element_Map!$E$2:$E$287=$A5,KPI_Element_Map!$A$2:$A$287),COLUMNS($J5:M5))),"")} -> 22 | N5: {=IFERROR(HYPERLINK("#KPI_Master!A"&MATCH(SMALL(IF(KPI_Element_Map!$E$2:$E$287=$A5,KPI_Element_Map!$A$2:$A$287),COLUMNS($J5:N5)),KPI_Master!$A:$A,0)&":P"&MATCH(SMALL(IF(KPI_Element_Map!$E$2:$E$287=$A5,KPI_Element_Map!$A$2:$A$287),COLUMNS($J5:N5)),KPI_Master!$A:$A,0),SMALL(IF(KPI_Element_Map!$E$2:$E$287=$A5,KPI_Element_Map!$A$2:$A$287),COLUMNS($J5:N5))),"")} -> 52 | O5: {=IFERROR(HYPERLINK("#KPI_Master!A"&MATCH(SMALL(IF(KPI_Element_Map!$E$2:$E$287=$A5,KPI_Element_Map!$A$2:$A$287),COLUMNS($J5:O5)),KPI_Master!$A:$A,0)&":P"&MATCH(SMALL(IF(KPI_Element_Map!$E$2:$E$287=$A5,KPI_Element_Map!$A$2:$A$287),COLUMNS($J5:O5)),KPI_Master!$A:$A,0),SMALL(IF(KPI_Element_Map!$E$2:$E$287=$A5,KPI_Element_Map!$A$2:$A$287),COLUMNS($J5:O5))),"")} -> 81 | P5: {=IFERROR(HYPERLINK("#KPI_Master!A"&MATCH(SMALL(IF(KPI_Element_Map!$E$2:$E$287=$A5,KPI_Element_Map!$A$2:$A$287),COLUMNS($J5:P5)),KPI_Master!$A:$A,0)&":P"&MATCH(SMALL(IF(KPI_Element_Map!$E$2:$E$287=$A5,KPI_Element_Map!$A$2:$A$287),COLUMNS($J5:P5)),KPI_Master!$A:$A,0),SMALL(IF(KPI_Element_Map!$E$2:$E$287=$A5,KPI_Element_Map!$A$2:$A$287),COLUMNS($J5:P5))),"")} -> 84 | Q5: {=IFERROR(HYPERLINK("#KPI_Master!A"&MATCH(SMALL(IF(KPI_Element_Map!$E$2:$E$287=$A5,KPI_Element_Map!$A$2:$A$287),COLUMNS($J5:Q5)),KPI_Master!$A:$A,0)&":P"&MATCH(SMALL(IF(KPI_Element_Map!$E$2:$E$287=$A5,KPI_Element_Map!$A$2:$A$287),COLUMNS($J5:Q5)),KPI_Master!$A:$A,0),SMALL(IF(KPI_Element_Map!$E$2:$E$287=$A5,KPI_Element_Map!$A$2:$A$287),COLUMNS($J5:Q5))),"")} -> 87 | ... AH5: {=IFERROR(HYPERLINK("#KPI_Master!A"&MATCH(SMALL(IF(KPI_Element_Map!$E$2:$E$287=$A5,KPI_Element_Map!$A$2:$A$287),COLUMNS($J5:AH5)),KPI_Master!$A:$A,0)&":P"&MATCH(SMALL(IF(KPI_Element_Map!$E$2:$E$287=$A5,KPI_Element_Map!$A$2:$A$287),COLUMNS($J5:AH5)),KPI_Master!$A:$A,0),SMALL(IF(KPI_Element_Map!$E$2:$E$287=$A5,KPI_Element_Map!$A$2:$A$287),COLUMNS($J5:AH5))),"")}
A6: E02 | B6: Occupied Units / Beds | C6: Average occupied units (or beds) for the period, from daily census | D6: {=_xlfn.TEXTJOIN(", ",TRUE(),IF(KPI_Element_Map!$E$2:$E$287=$A6,KPI_Element_Map!$A$2:$A$287,""))} -> 12, 13, 24, 25, 78, 113, 153, 159, 160 | E6: =COUNTIF(KPI_Element_Map!$E$2:$E$287,$A6) -> 9 | F6: =COUNTIFS(KPI_Element_Map!$E$2:$E$287,$A6,KPI_Element_Map!$D$2:$D$287,"1 - Core") -> 3 | G6: D01 | H6: =INDEX(Minimum_Documents!$B:$B,MATCH($G6,Minimum_Documents!$A:$A,0)) -> Census & ADT Register | J6: {=IFERROR(HYPERLINK("#KPI_Master!A"&MATCH(SMALL(IF(KPI_Element_Map!$E$2:$E$287=$A6,KPI_Element_Map!$A$2:$A$287),COLUMNS($J6:J6)),KPI_Master!$A:$A,0)&":P"&MATCH(SMALL(IF(KPI_Element_Map!$E$2:$E$287=$A6,KPI_Element_Map!$A$2:$A$287),COLUMNS($J6:J6)),KPI_Master!$A:$A,0),SMALL(IF(KPI_Element_Map!$E$2:$E$287=$A6,KPI_Element_Map!$A$2:$A$287),COLUMNS($J6:J6))),"")} -> 12 | K6: {=IFERROR(HYPERLINK("#KPI_Master!A"&MATCH(SMALL(IF(KPI_Element_Map!$E$2:$E$287=$A6,KPI_Element_Map!$A$2:$A$287),COLUMNS($J6:K6)),KPI_Master!$A:$A,0)&":P"&MATCH(SMALL(IF(KPI_Element_Map!$E$2:$E$287=$A6,KPI_Element_Map!$A$2:$A$287),COLUMNS($J6:K6)),KPI_Master!$A:$A,0),SMALL(IF(KPI_Element_Map!$E$2:$E$287=$A6,KPI_Element_Map!$A$2:$A$287),COLUMNS($J6:K6))),"")} -> 13 | L6: {=IFERROR(HYPERLINK("#KPI_Master!A"&MATCH(SMALL(IF(KPI_Element_Map!$E$2:$E$287=$A6,KPI_Element_Map!$A$2:$A$287),COLUMNS($J6:L6)),KPI_Master!$A:$A,0)&":P"&MATCH(SMALL(IF(KPI_Element_Map!$E$2:$E$287=$A6,KPI_Element_Map!$A$2:$A$287),COLUMNS($J6:L6)),KPI_Master!$A:$A,0),SMALL(IF(KPI_Element_Map!$E$2:$E$287=$A6,KPI_Element_Map!$A$2:$A$287),COLUMNS($J6:L6))),"")} -> 24 | M6: {=IFERROR(HYPERLINK("#KPI_Master!A"&MATCH(SMALL(IF(KPI_Element_Map!$E$2:$E$287=$A6,KPI_Element_Map!$A$2:$A$287),COLUMNS($J6:M6)),KPI_Master!$A:$A,0)&":P"&MATCH(SMALL(IF(KPI_Element_Map!$E$2:$E$287=$A6,KPI_Element_Map!$A$2:$A$287),COLUMNS($J6:M6)),KPI_Master!$A:$A,0),SMALL(IF(KPI_Element_Map!$E$2:$E$287=$A6,KPI_Element_Map!$A$2:$A$287),COLUMNS($J6:M6))),"")} -> 25 | N6: {=IFERROR(HYPERLINK("#KPI_Master!A"&MATCH(SMALL(IF(KPI_Element_Map!$E$2:$E$287=$A6,KPI_Element_Map!$A$2:$A$287),COLUMNS($J6:N6)),KPI_Master!$A:$A,0)&":P"&MATCH(SMALL(IF(KPI_Element_Map!$E$2:$E$287=$A6,KPI_Element_Map!$A$2:$A$287),COLUMNS($J6:N6)),KPI_Master!$A:$A,0),SMALL(IF(KPI_Element_Map!$E$2:$E$287=$A6,KPI_Element_Map!$A$2:$A$287),COLUMNS($J6:N6))),"")} -> 78 | O6: {=IFERROR(HYPERLINK("#KPI_Master!A"&MATCH(SMALL(IF(KPI_Element_Map!$E$2:$E$287=$A6,KPI_Element_Map!$A$2:$A$287),COLUMNS($J6:O6)),KPI_Master!$A:$A,0)&":P"&MATCH(SMALL(IF(KPI_Element_Map!$E$2:$E$287=$A6,KPI_Element_Map!$A$2:$A$287),COLUMNS($J6:O6)),KPI_Master!$A:$A,0),SMALL(IF(KPI_Element_Map!$E$2:$E$287=$A6,KPI_Element_Map!$A$2:$A$287),COLUMNS($J6:O6))),"")} -> 113 | P6: {=IFERROR(HYPERLINK("#KPI_Master!A"&MATCH(SMALL(IF(KPI_Element_Map!$E$2:$E$287=$A6,KPI_Element_Map!$A$2:$A$287),COLUMNS($J6:P6)),KPI_Master!$A:$A,0)&":P"&MATCH(SMALL(IF(KPI_Element_Map!$E$2:$E$287=$A6,KPI_Element_Map!$A$2:$A$287),COLUMNS($J6:P6)),KPI_Master!$A:$A,0),SMALL(IF(KPI_Element_Map!$E$2:$E$287=$A6,KPI_Element_Map!$A$2:$A$287),COLUMNS($J6:P6))),"")} -> 153 | Q6: {=IFERROR(HYPERLINK("#KPI_Master!A"&MATCH(SMALL(IF(KPI_Element_Map!$E$2:$E$287=$A6,KPI_Element_Map!$A$2:$A$287),COLUMNS($J6:Q6)),KPI_Master!$A:$A,0)&":P"&MATCH(SMALL(IF(KPI_Element_Map!$E$2:$E$287=$A6,KPI_Element_Map!$A$2:$A$287),COLUMNS($J6:Q6)),KPI_Master!$A:$A,0),SMALL(IF(KPI_Element_Map!$E$2:$E$287=$A6,KPI_Element_Map!$A$2:$A$287),COLUMNS($J6:Q6))),"")} -> 159 | ... AH6: {=IFERROR(HYPERLINK("#KPI_Master!A"&MATCH(SMALL(IF(KPI_Element_Map!$E$2:$E$287=$A6,KPI_Element_Map!$A$2:$A$287),COLUMNS($J6:AH6)),KPI_Master!$A:$A,0)&":P"&MATCH(SMALL(IF(KPI_Element_Map!$E$2:$E$287=$A6,KPI_Element_Map!$A$2:$A$287),COLUMNS($J6:AH6)),KPI_Master!$A:$A,0),SMALL(IF(KPI_Element_Map!$E$2:$E$287=$A6,KPI_Element_Map!$A$2:$A$287),COLUMNS($J6:AH6))),"")}
A7: E03 | B7: Total Residents (headcount) | C7: Residents in house (average or point-in-time, state which) | D7: {=_xlfn.TEXTJOIN(", ",TRUE(),IF(KPI_Element_Map!$E$2:$E$287=$A7,KPI_Element_Map!$A$2:$A$287,""))} -> 74, 75, 91, 94, 97, 110 | E7: =COUNTIF(KPI_Element_Map!$E$2:$E$287,$A7) -> 6 | F7: =COUNTIFS(KPI_Element_Map!$E$2:$E$287,$A7,KPI_Element_Map!$D$2:$D$287,"1 - Core") -> 1 | G7: D01 | H7: =INDEX(Minimum_Documents!$B:$B,MATCH($G7,Minimum_Documents!$A:$A,0)) -> Census & ADT Register | J7: {=IFERROR(HYPERLINK("#KPI_Master!A"&MATCH(SMALL(IF(KPI_Element_Map!$E$2:$E$287=$A7,KPI_Element_Map!$A$2:$A$287),COLUMNS($J7:J7)),KPI_Master!$A:$A,0)&":P"&MATCH(SMALL(IF(KPI_Element_Map!$E$2:$E$287=$A7,KPI_Element_Map!$A$2:$A$287),COLUMNS($J7:J7)),KPI_Master!$A:$A,0),SMALL(IF(KPI_Element_Map!$E$2:$E$287=$A7,KPI_Element_Map!$A$2:$A$287),COLUMNS($J7:J7))),"")} -> 74 | K7: {=IFERROR(HYPERLINK("#KPI_Master!A"&MATCH(SMALL(IF(KPI_Element_Map!$E$2:$E$287=$A7,KPI_Element_Map!$A$2:$A$287),COLUMNS($J7:K7)),KPI_Master!$A:$A,0)&":P"&MATCH(SMALL(IF(KPI_Element_Map!$E$2:$E$287=$A7,KPI_Element_Map!$A$2:$A$287),COLUMNS($J7:K7)),KPI_Master!$A:$A,0),SMALL(IF(KPI_Element_Map!$E$2:$E$287=$A7,KPI_Element_Map!$A$2:$A$287),COLUMNS($J7:K7))),"")} -> 75 | L7: {=IFERROR(HYPERLINK("#KPI_Master!A"&MATCH(SMALL(IF(KPI_Element_Map!$E$2:$E$287=$A7,KPI_Element_Map!$A$2:$A$287),COLUMNS($J7:L7)),KPI_Master!$A:$A,0)&":P"&MATCH(SMALL(IF(KPI_Element_Map!$E$2:$E$287=$A7,KPI_Element_Map!$A$2:$A$287),COLUMNS($J7:L7)),KPI_Master!$A:$A,0),SMALL(IF(KPI_Element_Map!$E$2:$E$287=$A7,KPI_Element_Map!$A$2:$A$287),COLUMNS($J7:L7))),"")} -> 91 | M7: {=IFERROR(HYPERLINK("#KPI_Master!A"&MATCH(SMALL(IF(KPI_Element_Map!$E$2:$E$287=$A7,KPI_Element_Map!$A$2:$A$287),COLUMNS($J7:M7)),KPI_Master!$A:$A,0)&":P"&MATCH(SMALL(IF(KPI_Element_Map!$E$2:$E$287=$A7,KPI_Element_Map!$A$2:$A$287),COLUMNS($J7:M7)),KPI_Master!$A:$A,0),SMALL(IF(KPI_Element_Map!$E$2:$E$287=$A7,KPI_Element_Map!$A$2:$A$287),COLUMNS($J7:M7))),"")} -> 94 | N7: {=IFERROR(HYPERLINK("#KPI_Master!A"&MATCH(SMALL(IF(KPI_Element_Map!$E$2:$E$287=$A7,KPI_Element_Map!$A$2:$A$287),COLUMNS($J7:N7)),KPI_Master!$A:$A,0)&":P"&MATCH(SMALL(IF(KPI_Element_Map!$E$2:$E$287=$A7,KPI_Element_Map!$A$2:$A$287),COLUMNS($J7:N7)),KPI_Master!$A:$A,0),SMALL(IF(KPI_Element_Map!$E$2:$E$287=$A7,KPI_Element_Map!$A$2:$A$287),COLUMNS($J7:N7))),"")} -> 97 | O7: {=IFERROR(HYPERLINK("#KPI_Master!A"&MATCH(SMALL(IF(KPI_Element_Map!$E$2:$E$287=$A7,KPI_Element_Map!$A$2:$A$287),COLUMNS($J7:O7)),KPI_Master!$A:$A,0)&":P"&MATCH(SMALL(IF(KPI_Element_Map!$E$2:$E$287=$A7,KPI_Element_Map!$A$2:$A$287),COLUMNS($J7:O7)),KPI_Master!$A:$A,0),SMALL(IF(KPI_Element_Map!$E$2:$E$287=$A7,KPI_Element_Map!$A$2:$A$287),COLUMNS($J7:O7))),"")} -> 110 | P7: {=IFERROR(HYPERLINK("#KPI_Master!A"&MATCH(SMALL(IF(KPI_Element_Map!$E$2:$E$287=$A7,KPI_Element_Map!$A$2:$A$287),COLUMNS($J7:P7)),KPI_Master!$A:$A,0)&":P"&MATCH(SMALL(IF(KPI_Element_Map!$E$2:$E$287=$A7,KPI_Element_Map!$A$2:$A$287),COLUMNS($J7:P7)),KPI_Master!$A:$A,0),SMALL(IF(KPI_Element_Map!$E$2:$E$287=$A7,KPI_Element_Map!$A$2:$A$287),COLUMNS($J7:P7))),"")} | Q7: {=IFERROR(HYPERLINK("#KPI_Master!A"&MATCH(SMALL(IF(KPI_Element_Map!$E$2:$E$287=$A7,KPI_Element_Map!$A$2:$A$287),COLUMNS($J7:Q7)),KPI_Master!$A:$A,0)&":P"&MATCH(SMALL(IF(KPI_Element_Map!$E$2:$E$287=$A7,KPI_Element_Map!$A$2:$A$287),COLUMNS($J7:Q7)),KPI_Master!$A:$A,0),SMALL(IF(KPI_Element_Map!$E$2:$E$287=$A7,KPI_Element_Map!$A$2:$A$287),COLUMNS($J7:Q7))),"")} | ... AH7: {=IFERROR(HYPERLINK("#KPI_Master!A"&MATCH(SMALL(IF(KPI_Element_Map!$E$2:$E$287=$A7,KPI_Element_Map!$A$2:$A$287),COLUMNS($J7:AH7)),KPI_Master!$A:$A,0)&":P"&MATCH(SMALL(IF(KPI_Element_Map!$E$2:$E$287=$A7,KPI_Element_Map!$A$2:$A$287),COLUMNS($J7:AH7)),KPI_Master!$A:$A,0),SMALL(IF(KPI_Element_Map!$E$2:$E$287=$A7,KPI_Element_Map!$A$2:$A$287),COLUMNS($J7:AH7))),"")}
A8: E04 | B8: Resident Days by Payer | C8: Resident days split by payer type | D8: {=_xlfn.TEXTJOIN(", ",TRUE(),IF(KPI_Element_Map!$E$2:$E$287=$A8,KPI_Element_Map!$A$2:$A$287,""))} -> 22 | E8: =COUNTIF(KPI_Element_Map!$E$2:$E$287,$A8) -> 1 | F8: =COUNTIFS(KPI_Element_Map!$E$2:$E$287,$A8,KPI_Element_Map!$D$2:$D$287,"1 - Core") -> 0 | G8: D01 | H8: =INDEX(Minimum_Documents!$B:$B,MATCH($G8,Minimum_Documents!$A:$A,0)) -> Census & ADT Register | J8: {=IFERROR(HYPERLINK("#KPI_Master!A"&MATCH(SMALL(IF(KPI_Element_Map!$E$2:$E$287=$A8,KPI_Element_Map!$A$2:$A$287),COLUMNS($J8:J8)),KPI_Master!$A:$A,0)&":P"&MATCH(SMALL(IF(KPI_Element_Map!$E$2:$E$287=$A8,KPI_Element_Map!$A$2:$A$287),COLUMNS($J8:J8)),KPI_Master!$A:$A,0),SMALL(IF(KPI_Element_Map!$E$2:$E$287=$A8,KPI_Element_Map!$A$2:$A$287),COLUMNS($J8:J8))),"")} -> 22 | K8: {=IFERROR(HYPERLINK("#KPI_Master!A"&MATCH(SMALL(IF(KPI_Element_Map!$E$2:$E$287=$A8,KPI_Element_Map!$A$2:$A$287),COLUMNS($J8:K8)),KPI_Master!$A:$A,0)&":P"&MATCH(SMALL(IF(KPI_Element_Map!$E$2:$E$287=$A8,KPI_Element_Map!$A$2:$A$287),COLUMNS($J8:K8)),KPI_Master!$A:$A,0),SMALL(IF(KPI_Element_Map!$E$2:$E$287=$A8,KPI_Element_Map!$A$2:$A$287),COLUMNS($J8:K8))),"")} | L8: {=IFERROR(HYPERLINK("#KPI_Master!A"&MATCH(SMALL(IF(KPI_Element_Map!$E$2:$E$287=$A8,KPI_Element_Map!$A$2:$A$287),COLUMNS($J8:L8)),KPI_Master!$A:$A,0)&":P"&MATCH(SMALL(IF(KPI_Element_Map!$E$2:$E$287=$A8,KPI_Element_Map!$A$2:$A$287),COLUMNS($J8:L8)),KPI_Master!$A:$A,0),SMALL(IF(KPI_Element_Map!$E$2:$E$287=$A8,KPI_Element_Map!$A$2:$A$287),COLUMNS($J8:L8))),"")} | M8: {=IFERROR(HYPERLINK("#KPI_Master!A"&MATCH(SMALL(IF(KPI_Element_Map!$E$2:$E$287=$A8,KPI_Element_Map!$A$2:$A$287),COLUMNS($J8:M8)),KPI_Master!$A:$A,0)&":P"&MATCH(SMALL(IF(KPI_Element_Map!$E$2:$E$287=$A8,KPI_Element_Map!$A$2:$A$287),COLUMNS($J8:M8)),KPI_Master!$A:$A,0),SMALL(IF(KPI_Element_Map!$E$2:$E$287=$A8,KPI_Element_Map!$A$2:$A$287),COLUMNS($J8:M8))),"")} | N8: {=IFERROR(HYPERLINK("#KPI_Master!A"&MATCH(SMALL(IF(KPI_Element_Map!$E$2:$E$287=$A8,KPI_Element_Map!$A$2:$A$287),COLUMNS($J8:N8)),KPI_Master!$A:$A,0)&":P"&MATCH(SMALL(IF(KPI_Element_Map!$E$2:$E$287=$A8,KPI_Element_Map!$A$2:$A$287),COLUMNS($J8:N8)),KPI_Master!$A:$A,0),SMALL(IF(KPI_Element_Map!$E$2:$E$287=$A8,KPI_Element_Map!$A$2:$A$287),COLUMNS($J8:N8))),"")} | O8: {=IFERROR(HYPERLINK("#KPI_Master!A"&MATCH(SMALL(IF(KPI_Element_Map!$E$2:$E$287=$A8,KPI_Element_Map!$A$2:$A$287),COLUMNS($J8:O8)),KPI_Master!$A:$A,0)&":P"&MATCH(SMALL(IF(KPI_Element_Map!$E$2:$E$287=$A8,KPI_Element_Map!$A$2:$A$287),COLUMNS($J8:O8)),KPI_Master!$A:$A,0),SMALL(IF(KPI_Element_Map!$E$2:$E$287=$A8,KPI_Element_Map!$A$2:$A$287),COLUMNS($J8:O8))),"")} | P8: {=IFERROR(HYPERLINK("#KPI_Master!A"&MATCH(SMALL(IF(KPI_Element_Map!$E$2:$E$287=$A8,KPI_Element_Map!$A$2:$A$287),COLUMNS($J8:P8)),KPI_Master!$A:$A,0)&":P"&MATCH(SMALL(IF(KPI_Element_Map!$E$2:$E$287=$A8,KPI_Element_Map!$A$2:$A$287),COLUMNS($J8:P8)),KPI_Master!$A:$A,0),SMALL(IF(KPI_Element_Map!$E$2:$E$287=$A8,KPI_Element_Map!$A$2:$A$287),COLUMNS($J8:P8))),"")} | Q8: {=IFERROR(HYPERLINK("#KPI_Master!A"&MATCH(SMALL(IF(KPI_Element_Map!$E$2:$E$287=$A8,KPI_Element_Map!$A$2:$A$287),COLUMNS($J8:Q8)),KPI_Master!$A:$A,0)&":P"&MATCH(SMALL(IF(KPI_Element_Map!$E$2:$E$287=$A8,KPI_Element_Map!$A$2:$A$287),COLUMNS($J8:Q8)),KPI_Master!$A:$A,0),SMALL(IF(KPI_Element_Map!$E$2:$E$287=$A8,KPI_Element_Map!$A$2:$A$287),COLUMNS($J8:Q8))),"")} | ... AH8: {=IFERROR(HYPERLINK("#KPI_Master!A"&MATCH(SMALL(IF(KPI_Element_Map!$E$2:$E$287=$A8,KPI_Element_Map!$A$2:$A$287),COLUMNS($J8:AH8)),KPI_Master!$A:$A,0)&":P"&MATCH(SMALL(IF(KPI_Element_Map!$E$2:$E$287=$A8,KPI_Element_Map!$A$2:$A$287),COLUMNS($J8:AH8)),KPI_Master!$A:$A,0),SMALL(IF(KPI_Element_Map!$E$2:$E$287=$A8,KPI_Element_Map!$A$2:$A$287),COLUMNS($J8:AH8))),"")}
A9: E05 | B9: Skilled / Medicare Part A Days & Census | C9: Skilled patient days and Part A census | D9: {=_xlfn.TEXTJOIN(", ",TRUE(),IF(KPI_Element_Map!$E$2:$E$287=$A9,KPI_Element_Map!$A$2:$A$287,""))} -> 23, 104 | E9: =COUNTIF(KPI_Element_Map!$E$2:$E$287,$A9) -> 2 | F9: =COUNTIFS(KPI_Element_Map!$E$2:$E$287,$A9,KPI_Element_Map!$D$2:$D$287,"1 - Core") -> 1 | G9: D01 | H9: =INDEX(Minimum_Documents!$B:$B,MATCH($G9,Minimum_Documents!$A:$A,0)) -> Census & ADT Register | J9: {=IFERROR(HYPERLINK("#KPI_Master!A"&MATCH(SMALL(IF(KPI_Element_Map!$E$2:$E$287=$A9,KPI_Element_Map!$A$2:$A$287),COLUMNS($J9:J9)),KPI_Master!$A:$A,0)&":P"&MATCH(SMALL(IF(KPI_Element_Map!$E$2:$E$287=$A9,KPI_Element_Map!$A$2:$A$287),COLUMNS($J9:J9)),KPI_Master!$A:$A,0),SMALL(IF(KPI_Element_Map!$E$2:$E$287=$A9,KPI_Element_Map!$A$2:$A$287),COLUMNS($J9:J9))),"")} -> 23 | K9: {=IFERROR(HYPERLINK("#KPI_Master!A"&MATCH(SMALL(IF(KPI_Element_Map!$E$2:$E$287=$A9,KPI_Element_Map!$A$2:$A$287),COLUMNS($J9:K9)),KPI_Master!$A:$A,0)&":P"&MATCH(SMALL(IF(KPI_Element_Map!$E$2:$E$287=$A9,KPI_Element_Map!$A$2:$A$287),COLUMNS($J9:K9)),KPI_Master!$A:$A,0),SMALL(IF(KPI_Element_Map!$E$2:$E$287=$A9,KPI_Element_Map!$A$2:$A$287),COLUMNS($J9:K9))),"")} -> 104 | L9: {=IFERROR(HYPERLINK("#KPI_Master!A"&MATCH(SMALL(IF(KPI_Element_Map!$E$2:$E$287=$A9,KPI_Element_Map!$A$2:$A$287),COLUMNS($J9:L9)),KPI_Master!$A:$A,0)&":P"&MATCH(SMALL(IF(KPI_Element_Map!$E$2:$E$287=$A9,KPI_Element_Map!$A$2:$A$287),COLUMNS($J9:L9)),KPI_Master!$A:$A,0),SMALL(IF(KPI_Element_Map!$E$2:$E$287=$A9,KPI_Element_Map!$A$2:$A$287),COLUMNS($J9:L9))),"")} | M9: {=IFERROR(HYPERLINK("#KPI_Master!A"&MATCH(SMALL(IF(KPI_Element_Map!$E$2:$E$287=$A9,KPI_Element_Map!$A$2:$A$287),COLUMNS($J9:M9)),KPI_Master!$A:$A,0)&":P"&MATCH(SMALL(IF(KPI_Element_Map!$E$2:$E$287=$A9,KPI_Element_Map!$A$2:$A$287),COLUMNS($J9:M9)),KPI_Master!$A:$A,0),SMALL(IF(KPI_Element_Map!$E$2:$E$287=$A9,KPI_Element_Map!$A$2:$A$287),COLUMNS($J9:M9))),"")} | N9: {=IFERROR(HYPERLINK("#KPI_Master!A"&MATCH(SMALL(IF(KPI_Element_Map!$E$2:$E$287=$A9,KPI_Element_Map!$A$2:$A$287),COLUMNS($J9:N9)),KPI_Master!$A:$A,0)&":P"&MATCH(SMALL(IF(KPI_Element_Map!$E$2:$E$287=$A9,KPI_Element_Map!$A$2:$A$287),COLUMNS($J9:N9)),KPI_Master!$A:$A,0),SMALL(IF(KPI_Element_Map!$E$2:$E$287=$A9,KPI_Element_Map!$A$2:$A$287),COLUMNS($J9:N9))),"")} | O9: {=IFERROR(HYPERLINK("#KPI_Master!A"&MATCH(SMALL(IF(KPI_Element_Map!$E$2:$E$287=$A9,KPI_Element_Map!$A$2:$A$287),COLUMNS($J9:O9)),KPI_Master!$A:$A,0)&":P"&MATCH(SMALL(IF(KPI_Element_Map!$E$2:$E$287=$A9,KPI_Element_Map!$A$2:$A$287),COLUMNS($J9:O9)),KPI_Master!$A:$A,0),SMALL(IF(KPI_Element_Map!$E$2:$E$287=$A9,KPI_Element_Map!$A$2:$A$287),COLUMNS($J9:O9))),"")} | P9: {=IFERROR(HYPERLINK("#KPI_Master!A"&MATCH(SMALL(IF(KPI_Element_Map!$E$2:$E$287=$A9,KPI_Element_Map!$A$2:$A$287),COLUMNS($J9:P9)),KPI_Master!$A:$A,0)&":P"&MATCH(SMALL(IF(KPI_Element_Map!$E$2:$E$287=$A9,KPI_Element_Map!$A$2:$A$287),COLUMNS($J9:P9)),KPI_Master!$A:$A,0),SMALL(IF(KPI_Element_Map!$E$2:$E$287=$A9,KPI_Element_Map!$A$2:$A$287),COLUMNS($J9:P9))),"")} | Q9: {=IFERROR(HYPERLINK("#KPI_Master!A"&MATCH(SMALL(IF(KPI_Element_Map!$E$2:$E$287=$A9,KPI_Element_Map!$A$2:$A$287),COLUMNS($J9:Q9)),KPI_Master!$A:$A,0)&":P"&MATCH(SMALL(IF(KPI_Element_Map!$E$2:$E$287=$A9,KPI_Element_Map!$A$2:$A$287),COLUMNS($J9:Q9)),KPI_Master!$A:$A,0),SMALL(IF(KPI_Element_Map!$E$2:$E$287=$A9,KPI_Element_Map!$A$2:$A$287),COLUMNS($J9:Q9))),"")} | ... AH9: {=IFERROR(HYPERLINK("#KPI_Master!A"&MATCH(SMALL(IF(KPI_Element_Map!$E$2:$E$287=$A9,KPI_Element_Map!$A$2:$A$287),COLUMNS($J9:AH9)),KPI_Master!$A:$A,0)&":P"&MATCH(SMALL(IF(KPI_Element_Map!$E$2:$E$287=$A9,KPI_Element_Map!$A$2:$A$287),COLUMNS($J9:AH9)),KPI_Master!$A:$A,0),SMALL(IF(KPI_Element_Map!$E$2:$E$287=$A9,KPI_Element_Map!$A$2:$A$287),COLUMNS($J9:AH9))),"")}
A10: E06 | B10: Census by Level of Care (AL / MC / SNF) | C10: Occupied units and resident days by care level | D10: {=_xlfn.TEXTJOIN(", ",TRUE(),IF(KPI_Element_Map!$E$2:$E$287=$A10,KPI_Element_Map!$A$2:$A$287,""))} -> 41, 77 | E10: =COUNTIF(KPI_Element_Map!$E$2:$E$287,$A10) -> 2 | F10: =COUNTIFS(KPI_Element_Map!$E$2:$E$287,$A10,KPI_Element_Map!$D$2:$D$287,"1 - Core") -> 0 | G10: D01 | H10: =INDEX(Minimum_Documents!$B:$B,MATCH($G10,Minimum_Documents!$A:$A,0)) -> Census & ADT Register | J10: {=IFERROR(HYPERLINK("#KPI_Master!A"&MATCH(SMALL(IF(KPI_Element_Map!$E$2:$E$287=$A10,KPI_Element_Map!$A$2:$A$287),COLUMNS($J10:J10)),KPI_Master!$A:$A,0)&":P"&MATCH(SMALL(IF(KPI_Element_Map!$E$2:$E$287=$A10,KPI_Element_Map!$A$2:$A$287),COLUMNS($J10:J10)),KPI_Master!$A:$A,0),SMALL(IF(KPI_Element_Map!$E$2:$E$287=$A10,KPI_Element_Map!$A$2:$A$287),COLUMNS($J10:J10))),"")} -> 41 | K10: {=IFERROR(HYPERLINK("#KPI_Master!A"&MATCH(SMALL(IF(KPI_Element_Map!$E$2:$E$287=$A10,KPI_Element_Map!$A$2:$A$287),COLUMNS($J10:K10)),KPI_Master!$A:$A,0)&":P"&MATCH(SMALL(IF(KPI_Element_Map!$E$2:$E$287=$A10,KPI_Element_Map!$A$2:$A$287),COLUMNS($J10:K10)),KPI_Master!$A:$A,0),SMALL(IF(KPI_Element_Map!$E$2:$E$287=$A10,KPI_Element_Map!$A$2:$A$287),COLUMNS($J10:K10))),"")} -> 77 | L10: {=IFERROR(HYPERLINK("#KPI_Master!A"&MATCH(SMALL(IF(KPI_Element_Map!$E$2:$E$287=$A10,KPI_Element_Map!$A$2:$A$287),COLUMNS($J10:L10)),KPI_Master!$A:$A,0)&":P"&MATCH(SMALL(IF(KPI_Element_Map!$E$2:$E$287=$A10,KPI_Element_Map!$A$2:$A$287),COLUMNS($J10:L10)),KPI_Master!$A:$A,0),SMALL(IF(KPI_Element_Map!$E$2:$E$287=$A10,KPI_Element_Map!$A$2:$A$287),COLUMNS($J10:L10))),"")} | M10: {=IFERROR(HYPERLINK("#KPI_Master!A"&MATCH(SMALL(IF(KPI_Element_Map!$E$2:$E$287=$A10,KPI_Element_Map!$A$2:$A$287),COLUMNS($J10:M10)),KPI_Master!$A:$A,0)&":P"&MATCH(SMALL(IF(KPI_Element_Map!$E$2:$E$287=$A10,KPI_Element_Map!$A$2:$A$287),COLUMNS($J10:M10)),KPI_Master!$A:$A,0),SMALL(IF(KPI_Element_Map!$E$2:$E$287=$A10,KPI_Element_Map!$A$2:$A$287),COLUMNS($J10:M10))),"")} | N10: {=IFERROR(HYPERLINK("#KPI_Master!A"&MATCH(SMALL(IF(KPI_Element_Map!$E$2:$E$287=$A10,KPI_Element_Map!$A$2:$A$287),COLUMNS($J10:N10)),KPI_Master!$A:$A,0)&":P"&MATCH(SMALL(IF(KPI_Element_Map!$E$2:$E$287=$A10,KPI_Element_Map!$A$2:$A$287),COLUMNS($J10:N10)),KPI_Master!$A:$A,0),SMALL(IF(KPI_Element_Map!$E$2:$E$287=$A10,KPI_Element_Map!$A$2:$A$287),COLUMNS($J10:N10))),"")} | O10: {=IFERROR(HYPERLINK("#KPI_Master!A"&MATCH(SMALL(IF(KPI_Element_Map!$E$2:$E$287=$A10,KPI_Element_Map!$A$2:$A$287),COLUMNS($J10:O10)),KPI_Master!$A:$A,0)&":P"&MATCH(SMALL(IF(KPI_Element_Map!$E$2:$E$287=$A10,KPI_Element_Map!$A$2:$A$287),COLUMNS($J10:O10)),KPI_Master!$A:$A,0),SMALL(IF(KPI_Element_Map!$E$2:$E$287=$A10,KPI_Element_Map!$A$2:$A$287),COLUMNS($J10:O10))),"")} | P10: {=IFERROR(HYPERLINK("#KPI_Master!A"&MATCH(SMALL(IF(KPI_Element_Map!$E$2:$E$287=$A10,KPI_Element_Map!$A$2:$A$287),COLUMNS($J10:P10)),KPI_Master!$A:$A,0)&":P"&MATCH(SMALL(IF(KPI_Element_Map!$E$2:$E$287=$A10,KPI_Element_Map!$A$2:$A$287),COLUMNS($J10:P10)),KPI_Master!$A:$A,0),SMALL(IF(KPI_Element_Map!$E$2:$E$287=$A10,KPI_Element_Map!$A$2:$A$287),COLUMNS($J10:P10))),"")} | Q10: {=IFERROR(HYPERLINK("#KPI_Master!A"&MATCH(SMALL(IF(KPI_Element_Map!$E$2:$E$287=$A10,KPI_Element_Map!$A$2:$A$287),COLUMNS($J10:Q10)),KPI_Master!$A:$A,0)&":P"&MATCH(SMALL(IF(KPI_Element_Map!$E$2:$E$287=$A10,KPI_Element_Map!$A$2:$A$287),COLUMNS($J10:Q10)),KPI_Master!$A:$A,0),SMALL(IF(KPI_Element_Map!$E$2:$E$287=$A10,KPI_Element_Map!$A$2:$A$287),COLUMNS($J10:Q10))),"")} | ... AH10: {=IFERROR(HYPERLINK("#KPI_Master!A"&MATCH(SMALL(IF(KPI_Element_Map!$E$2:$E$287=$A10,KPI_Element_Map!$A$2:$A$287),COLUMNS($J10:AH10)),KPI_Master!$A:$A,0)&":P"&MATCH(SMALL(IF(KPI_Element_Map!$E$2:$E$287=$A10,KPI_Element_Map!$A$2:$A$287),COLUMNS($J10:AH10)),KPI_Master!$A:$A,0),SMALL(IF(KPI_Element_Map!$E$2:$E$287=$A10,KPI_Element_Map!$A$2:$A$287),COLUMNS($J10:AH10))),"")}
A11: E07 | B11: Move-Ins / Admissions | C11: Count and dates of move-ins / admissions (incl. admission source) | D11: {=_xlfn.TEXTJOIN(", ",TRUE(),IF(KPI_Element_Map!$E$2:$E$287=$A11,KPI_Element_Map!$A$2:$A$287,""))} -> 86, 103, 151, 157, 158, 161, 167 | E11: =COUNTIF(KPI_Element_Map!$E$2:$E$287,$A11) -> 7 | F11: =COUNTIFS(KPI_Element_Map!$E$2:$E$287,$A11,KPI_Element_Map!$D$2:$D$287,"1 - Core") -> 2 | G11: D01 | H11: =INDEX(Minimum_Documents!$B:$B,MATCH($G11,Minimum_Documents!$A:$A,0)) -> Census & ADT Register | J11: {=IFERROR(HYPERLINK("#KPI_Master!A"&MATCH(SMALL(IF(KPI_Element_Map!$E$2:$E$287=$A11,KPI_Element_Map!$A$2:$A$287),COLUMNS($J11:J11)),KPI_Master!$A:$A,0)&":P"&MATCH(SMALL(IF(KPI_Element_Map!$E$2:$E$287=$A11,KPI_Element_Map!$A$2:$A$287),COLUMNS($J11:J11)),KPI_Master!$A:$A,0),SMALL(IF(KPI_Element_Map!$E$2:$E$287=$A11,KPI_Element_Map!$A$2:$A$287),COLUMNS($J11:J11))),"")} -> 86 | K11: {=IFERROR(HYPERLINK("#KPI_Master!A"&MATCH(SMALL(IF(KPI_Element_Map!$E$2:$E$287=$A11,KPI_Element_Map!$A$2:$A$287),COLUMNS($J11:K11)),KPI_Master!$A:$A,0)&":P"&MATCH(SMALL(IF(KPI_Element_Map!$E$2:$E$287=$A11,KPI_Element_Map!$A$2:$A$287),COLUMNS($J11:K11)),KPI_Master!$A:$A,0),SMALL(IF(KPI_Element_Map!$E$2:$E$287=$A11,KPI_Element_Map!$A$2:$A$287),COLUMNS($J11:K11))),"")} -> 103 | L11: {=IFERROR(HYPERLINK("#KPI_Master!A"&MATCH(SMALL(IF(KPI_Element_Map!$E$2:$E$287=$A11,KPI_Element_Map!$A$2:$A$287),COLUMNS($J11:L11)),KPI_Master!$A:$A,0)&":P"&MATCH(SMALL(IF(KPI_Element_Map!$E$2:$E$287=$A11,KPI_Element_Map!$A$2:$A$287),COLUMNS($J11:L11)),KPI_Master!$A:$A,0),SMALL(IF(KPI_Element_Map!$E$2:$E$287=$A11,KPI_Element_Map!$A$2:$A$287),COLUMNS($J11:L11))),"")} -> 151 | M11: {=IFERROR(HYPERLINK("#KPI_Master!A"&MATCH(SMALL(IF(KPI_Element_Map!$E$2:$E$287=$A11,KPI_Element_Map!$A$2:$A$287),COLUMNS($J11:M11)),KPI_Master!$A:$A,0)&":P"&MATCH(SMALL(IF(KPI_Element_Map!$E$2:$E$287=$A11,KPI_Element_Map!$A$2:$A$287),COLUMNS($J11:M11)),KPI_Master!$A:$A,0),SMALL(IF(KPI_Element_Map!$E$2:$E$287=$A11,KPI_Element_Map!$A$2:$A$287),COLUMNS($J11:M11))),"")} -> 157 | N11: {=IFERROR(HYPERLINK("#KPI_Master!A"&MATCH(SMALL(IF(KPI_Element_Map!$E$2:$E$287=$A11,KPI_Element_Map!$A$2:$A$287),COLUMNS($J11:N11)),KPI_Master!$A:$A,0)&":P"&MATCH(SMALL(IF(KPI_Element_Map!$E$2:$E$287=$A11,KPI_Element_Map!$A$2:$A$287),COLUMNS($J11:N11)),KPI_Master!$A:$A,0),SMALL(IF(KPI_Element_Map!$E$2:$E$287=$A11,KPI_Element_Map!$A$2:$A$287),COLUMNS($J11:N11))),"")} -> 158 | O11: {=IFERROR(HYPERLINK("#KPI_Master!A"&MATCH(SMALL(IF(KPI_Element_Map!$E$2:$E$287=$A11,KPI_Element_Map!$A$2:$A$287),COLUMNS($J11:O11)),KPI_Master!$A:$A,0)&":P"&MATCH(SMALL(IF(KPI_Element_Map!$E$2:$E$287=$A11,KPI_Element_Map!$A$2:$A$287),COLUMNS($J11:O11)),KPI_Master!$A:$A,0),SMALL(IF(KPI_Element_Map!$E$2:$E$287=$A11,KPI_Element_Map!$A$2:$A$287),COLUMNS($J11:O11))),"")} -> 161 | P11: {=IFERROR(HYPERLINK("#KPI_Master!A"&MATCH(SMALL(IF(KPI_Element_Map!$E$2:$E$287=$A11,KPI_Element_Map!$A$2:$A$287),COLUMNS($J11:P11)),KPI_Master!$A:$A,0)&":P"&MATCH(SMALL(IF(KPI_Element_Map!$E$2:$E$287=$A11,KPI_Element_Map!$A$2:$A$287),COLUMNS($J11:P11)),KPI_Master!$A:$A,0),SMALL(IF(KPI_Element_Map!$E$2:$E$287=$A11,KPI_Element_Map!$A$2:$A$287),COLUMNS($J11:P11))),"")} -> 167 | Q11: {=IFERROR(HYPERLINK("#KPI_Master!A"&MATCH(SMALL(IF(KPI_Element_Map!$E$2:$E$287=$A11,KPI_Element_Map!$A$2:$A$287),COLUMNS($J11:Q11)),KPI_Master!$A:$A,0)&":P"&MATCH(SMALL(IF(KPI_Element_Map!$E$2:$E$287=$A11,KPI_Element_Map!$A$2:$A$287),COLUMNS($J11:Q11)),KPI_Master!$A:$A,0),SMALL(IF(KPI_Element_Map!$E$2:$E$287=$A11,KPI_Element_Map!$A$2:$A$287),COLUMNS($J11:Q11))),"")} | ... AH11: {=IFERROR(HYPERLINK("#KPI_Master!A"&MATCH(SMALL(IF(KPI_Element_Map!$E$2:$E$287=$A11,KPI_Element_Map!$A$2:$A$287),COLUMNS($J11:AH11)),KPI_Master!$A:$A,0)&":P"&MATCH(SMALL(IF(KPI_Element_Map!$E$2:$E$287=$A11,KPI_Element_Map!$A$2:$A$287),COLUMNS($J11:AH11)),KPI_Master!$A:$A,0),SMALL(IF(KPI_Element_Map!$E$2:$E$287=$A11,KPI_Element_Map!$A$2:$A$287),COLUMNS($J11:AH11))),"")}
A12: E08 | B12: Move-Outs / Discharges | C12: Count, dates, reason code, destination and payer of each departure | D12: {=_xlfn.TEXTJOIN(", ",TRUE(),IF(KPI_Element_Map!$E$2:$E$287=$A12,KPI_Element_Map!$A$2:$A$287,""))} -> 151, 152, 158, 159, 162 | E12: =COUNTIF(KPI_Element_Map!$E$2:$E$287,$A12) -> 5 | F12: =COUNTIFS(KPI_Element_Map!$E$2:$E$287,$A12,KPI_Element_Map!$D$2:$D$287,"1 - Core") -> 2 | G12: D01 | H12: =INDEX(Minimum_Documents!$B:$B,MATCH($G12,Minimum_Documents!$A:$A,0)) -> Census & ADT Register | J12: {=IFERROR(HYPERLINK("#KPI_Master!A"&MATCH(SMALL(IF(KPI_Element_Map!$E$2:$E$287=$A12,KPI_Element_Map!$A$2:$A$287),COLUMNS($J12:J12)),KPI_Master!$A:$A,0)&":P"&MATCH(SMALL(IF(KPI_Element_Map!$E$2:$E$287=$A12,KPI_Element_Map!$A$2:$A$287),COLUMNS($J12:J12)),KPI_Master!$A:$A,0),SMALL(IF(KPI_Element_Map!$E$2:$E$287=$A12,KPI_Element_Map!$A$2:$A$287),COLUMNS($J12:J12))),"")} -> 151 | K12: {=IFERROR(HYPERLINK("#KPI_Master!A"&MATCH(SMALL(IF(KPI_Element_Map!$E$2:$E$287=$A12,KPI_Element_Map!$A$2:$A$287),COLUMNS($J12:K12)),KPI_Master!$A:$A,0)&":P"&MATCH(SMALL(IF(KPI_Element_Map!$E$2:$E$287=$A12,KPI_Element_Map!$A$2:$A$287),COLUMNS($J12:K12)),KPI_Master!$A:$A,0),SMALL(IF(KPI_Element_Map!$E$2:$E$287=$A12,KPI_Element_Map!$A$2:$A$287),COLUMNS($J12:K12))),"")} -> 152 | L12: {=IFERROR(HYPERLINK("#KPI_Master!A"&MATCH(SMALL(IF(KPI_Element_Map!$E$2:$E$287=$A12,KPI_Element_Map!$A$2:$A$287),COLUMNS($J12:L12)),KPI_Master!$A:$A,0)&":P"&MATCH(SMALL(IF(KPI_Element_Map!$E$2:$E$287=$A12,KPI_Element_Map!$A$2:$A$287),COLUMNS($J12:L12)),KPI_Master!$A:$A,0),SMALL(IF(KPI_Element_Map!$E$2:$E$287=$A12,KPI_Element_Map!$A$2:$A$287),COLUMNS($J12:L12))),"")} -> 158 | M12: {=IFERROR(HYPERLINK("#KPI_Master!A"&MATCH(SMALL(IF(KPI_Element_Map!$E$2:$E$287=$A12,KPI_Element_Map!$A$2:$A$287),COLUMNS($J12:M12)),KPI_Master!$A:$A,0)&":P"&MATCH(SMALL(IF(KPI_Element_Map!$E$2:$E$287=$A12,KPI_Element_Map!$A$2:$A$287),COLUMNS($J12:M12)),KPI_Master!$A:$A,0),SMALL(IF(KPI_Element_Map!$E$2:$E$287=$A12,KPI_Element_Map!$A$2:$A$287),COLUMNS($J12:M12))),"")} -> 159 | N12: {=IFERROR(HYPERLINK("#KPI_Master!A"&MATCH(SMALL(IF(KPI_Element_Map!$E$2:$E$287=$A12,KPI_Element_Map!$A$2:$A$287),COLUMNS($J12:N12)),KPI_Master!$A:$A,0)&":P"&MATCH(SMALL(IF(KPI_Element_Map!$E$2:$E$287=$A12,KPI_Element_Map!$A$2:$A$287),COLUMNS($J12:N12)),KPI_Master!$A:$A,0),SMALL(IF(KPI_Element_Map!$E$2:$E$287=$A12,KPI_Element_Map!$A$2:$A$287),COLUMNS($J12:N12))),"")} -> 162 | O12: {=IFERROR(HYPERLINK("#KPI_Master!A"&MATCH(SMALL(IF(KPI_Element_Map!$E$2:$E$287=$A12,KPI_Element_Map!$A$2:$A$287),COLUMNS($J12:O12)),KPI_Master!$A:$A,0)&":P"&MATCH(SMALL(IF(KPI_Element_Map!$E$2:$E$287=$A12,KPI_Element_Map!$A$2:$A$287),COLUMNS($J12:O12)),KPI_Master!$A:$A,0),SMALL(IF(KPI_Element_Map!$E$2:$E$287=$A12,KPI_Element_Map!$A$2:$A$287),COLUMNS($J12:O12))),"")} | P12: {=IFERROR(HYPERLINK("#KPI_Master!A"&MATCH(SMALL(IF(KPI_Element_Map!$E$2:$E$287=$A12,KPI_Element_Map!$A$2:$A$287),COLUMNS($J12:P12)),KPI_Master!$A:$A,0)&":P"&MATCH(SMALL(IF(KPI_Element_Map!$E$2:$E$287=$A12,KPI_Element_Map!$A$2:$A$287),COLUMNS($J12:P12)),KPI_Master!$A:$A,0),SMALL(IF(KPI_Element_Map!$E$2:$E$287=$A12,KPI_Element_Map!$A$2:$A$287),COLUMNS($J12:P12))),"")} | Q12: {=IFERROR(HYPERLINK("#KPI_Master!A"&MATCH(SMALL(IF(KPI_Element_Map!$E$2:$E$287=$A12,KPI_Element_Map!$A$2:$A$287),COLUMNS($J12:Q12)),KPI_Master!$A:$A,0)&":P"&MATCH(SMALL(IF(KPI_Element_Map!$E$2:$E$287=$A12,KPI_Element_Map!$A$2:$A$287),COLUMNS($J12:Q12)),KPI_Master!$A:$A,0),SMALL(IF(KPI_Element_Map!$E$2:$E$287=$A12,KPI_Element_Map!$A$2:$A$287),COLUMNS($J12:Q12))),"")} | ... AH12: {=IFERROR(HYPERLINK("#KPI_Master!A"&MATCH(SMALL(IF(KPI_Element_Map!$E$2:$E$287=$A12,KPI_Element_Map!$A$2:$A$287),COLUMNS($J12:AH12)),KPI_Master!$A:$A,0)&":P"&MATCH(SMALL(IF(KPI_Element_Map!$E$2:$E$287=$A12,KPI_Element_Map!$A$2:$A$287),COLUMNS($J12:AH12)),KPI_Master!$A:$A,0),SMALL(IF(KPI_Element_Map!$E$2:$E$287=$A12,KPI_Element_Map!$A$2:$A$287),COLUMNS($J12:AH12))),"")}
A13: E09 | B13: Hospital Transfers & Readmissions | C13: Transfer-to-hospital events with date, planned / unplanned flag and return | D13: {=_xlfn.TEXTJOIN(", ",TRUE(),IF(KPI_Element_Map!$E$2:$E$287=$A13,KPI_Element_Map!$A$2:$A$287,""))} -> 86, 87 | E13: =COUNTIF(KPI_Element_Map!$E$2:$E$287,$A13) -> 2 | F13: =COUNTIFS(KPI_Element_Map!$E$2:$E$287,$A13,KPI_Element_Map!$D$2:$D$287,"1 - Core") -> 1 | G13: D01 | H13: =INDEX(Minimum_Documents!$B:$B,MATCH($G13,Minimum_Documents!$A:$A,0)) -> Census & ADT Register | J13: {=IFERROR(HYPERLINK("#KPI_Master!A"&MATCH(SMALL(IF(KPI_Element_Map!$E$2:$E$287=$A13,KPI_Element_Map!$A$2:$A$287),COLUMNS($J13:J13)),KPI_Master!$A:$A,0)&":P"&MATCH(SMALL(IF(KPI_Element_Map!$E$2:$E$287=$A13,KPI_Element_Map!$A$2:$A$287),COLUMNS($J13:J13)),KPI_Master!$A:$A,0),SMALL(IF(KPI_Element_Map!$E$2:$E$287=$A13,KPI_Element_Map!$A$2:$A$287),COLUMNS($J13:J13))),"")} -> 86 | K13: {=IFERROR(HYPERLINK("#KPI_Master!A"&MATCH(SMALL(IF(KPI_Element_Map!$E$2:$E$287=$A13,KPI_Element_Map!$A$2:$A$287),COLUMNS($J13:K13)),KPI_Master!$A:$A,0)&":P"&MATCH(SMALL(IF(KPI_Element_Map!$E$2:$E$287=$A13,KPI_Element_Map!$A$2:$A$287),COLUMNS($J13:K13)),KPI_Master!$A:$A,0),SMALL(IF(KPI_Element_Map!$E$2:$E$287=$A13,KPI_Element_Map!$A$2:$A$287),COLUMNS($J13:K13))),"")} -> 87 | L13: {=IFERROR(HYPERLINK("#KPI_Master!A"&MATCH(SMALL(IF(KPI_Element_Map!$E$2:$E$287=$A13,KPI_Element_Map!$A$2:$A$287),COLUMNS($J13:L13)),KPI_Master!$A:$A,0)&":P"&MATCH(SMALL(IF(KPI_Element_Map!$E$2:$E$287=$A13,KPI_Element_Map!$A$2:$A$287),COLUMNS($J13:L13)),KPI_Master!$A:$A,0),SMALL(IF(KPI_Element_Map!$E$2:$E$287=$A13,KPI_Element_Map!$A$2:$A$287),COLUMNS($J13:L13))),"")} | M13: {=IFERROR(HYPERLINK("#KPI_Master!A"&MATCH(SMALL(IF(KPI_Element_Map!$E$2:$E$287=$A13,KPI_Element_Map!$A$2:$A$287),COLUMNS($J13:M13)),KPI_Master!$A:$A,0)&":P"&MATCH(SMALL(IF(KPI_Element_Map!$E$2:$E$287=$A13,KPI_Element_Map!$A$2:$A$287),COLUMNS($J13:M13)),KPI_Master!$A:$A,0),SMALL(IF(KPI_Element_Map!$E$2:$E$287=$A13,KPI_Element_Map!$A$2:$A$287),COLUMNS($J13:M13))),"")} | N13: {=IFERROR(HYPERLINK("#KPI_Master!A"&MATCH(SMALL(IF(KPI_Element_Map!$E$2:$E$287=$A13,KPI_Element_Map!$A$2:$A$287),COLUMNS($J13:N13)),KPI_Master!$A:$A,0)&":P"&MATCH(SMALL(IF(KPI_Element_Map!$E$2:$E$287=$A13,KPI_Element_Map!$A$2:$A$287),COLUMNS($J13:N13)),KPI_Master!$A:$A,0),SMALL(IF(KPI_Element_Map!$E$2:$E$287=$A13,KPI_Element_Map!$A$2:$A$287),COLUMNS($J13:N13))),"")} | O13: {=IFERROR(HYPERLINK("#KPI_Master!A"&MATCH(SMALL(IF(KPI_Element_Map!$E$2:$E$287=$A13,KPI_Element_Map!$A$2:$A$287),COLUMNS($J13:O13)),KPI_Master!$A:$A,0)&":P"&MATCH(SMALL(IF(KPI_Element_Map!$E$2:$E$287=$A13,KPI_Element_Map!$A$2:$A$287),COLUMNS($J13:O13)),KPI_Master!$A:$A,0),SMALL(IF(KPI_Element_Map!$E$2:$E$287=$A13,KPI_Element_Map!$A$2:$A$287),COLUMNS($J13:O13))),"")} | P13: {=IFERROR(HYPERLINK("#KPI_Master!A"&MATCH(SMALL(IF(KPI_Element_Map!$E$2:$E$287=$A13,KPI_Element_Map!$A$2:$A$287),COLUMNS($J13:P13)),KPI_Master!$A:$A,0)&":P"&MATCH(SMALL(IF(KPI_Element_Map!$E$2:$E$287=$A13,KPI_Element_Map!$A$2:$A$287),COLUMNS($J13:P13)),KPI_Master!$A:$A,0),SMALL(IF(KPI_Element_Map!$E$2:$E$287=$A13,KPI_Element_Map!$A$2:$A$287),COLUMNS($J13:P13))),"")} | Q13: {=IFERROR(HYPERLINK("#KPI_Master!A"&MATCH(SMALL(IF(KPI_Element_Map!$E$2:$E$287=$A13,KPI_Element_Map!$A$2:$A$287),COLUMNS($J13:Q13)),KPI_Master!$A:$A,0)&":P"&MATCH(SMALL(IF(KPI_Element_Map!$E$2:$E$287=$A13,KPI_Element_Map!$A$2:$A$287),COLUMNS($J13:Q13)),KPI_Master!$A:$A,0),SMALL(IF(KPI_Element_Map!$E$2:$E$287=$A13,KPI_Element_Map!$A$2:$A$287),COLUMNS($J13:Q13))),"")} | ... AH13: {=IFERROR(HYPERLINK("#KPI_Master!A"&MATCH(SMALL(IF(KPI_Element_Map!$E$2:$E$287=$A13,KPI_Element_Map!$A$2:$A$287),COLUMNS($J13:AH13)),KPI_Master!$A:$A,0)&":P"&MATCH(SMALL(IF(KPI_Element_Map!$E$2:$E$287=$A13,KPI_Element_Map!$A$2:$A$287),COLUMNS($J13:AH13)),KPI_Master!$A:$A,0),SMALL(IF(KPI_Element_Map!$E$2:$E$287=$A13,KPI_Element_Map!$A$2:$A$287),COLUMNS($J13:AH13))),"")}
A14: E10 | B14: Prior Hospital Stay Dates | C14: Hospital admit / discharge dates captured on the admission record | D14: {=_xlfn.TEXTJOIN(", ",TRUE(),IF(KPI_Element_Map!$E$2:$E$287=$A14,KPI_Element_Map!$A$2:$A$287,""))} -> 103 | E14: =COUNTIF(KPI_Element_Map!$E$2:$E$287,$A14) -> 1 | F14: =COUNTIFS(KPI_Element_Map!$E$2:$E$287,$A14,KPI_Element_Map!$D$2:$D$287,"1 - Core") -> 0 | G14: D01 | H14: =INDEX(Minimum_Documents!$B:$B,MATCH($G14,Minimum_Documents!$A:$A,0)) -> Census & ADT Register | J14: {=IFERROR(HYPERLINK("#KPI_Master!A"&MATCH(SMALL(IF(KPI_Element_Map!$E$2:$E$287=$A14,KPI_Element_Map!$A$2:$A$287),COLUMNS($J14:J14)),KPI_Master!$A:$A,0)&":P"&MATCH(SMALL(IF(KPI_Element_Map!$E$2:$E$287=$A14,KPI_Element_Map!$A$2:$A$287),COLUMNS($J14:J14)),KPI_Master!$A:$A,0),SMALL(IF(KPI_Element_Map!$E$2:$E$287=$A14,KPI_Element_Map!$A$2:$A$287),COLUMNS($J14:J14))),"")} -> 103 | K14: {=IFERROR(HYPERLINK("#KPI_Master!A"&MATCH(SMALL(IF(KPI_Element_Map!$E$2:$E$287=$A14,KPI_Element_Map!$A$2:$A$287),COLUMNS($J14:K14)),KPI_Master!$A:$A,0)&":P"&MATCH(SMALL(IF(KPI_Element_Map!$E$2:$E$287=$A14,KPI_Element_Map!$A$2:$A$287),COLUMNS($J14:K14)),KPI_Master!$A:$A,0),SMALL(IF(KPI_Element_Map!$E$2:$E$287=$A14,KPI_Element_Map!$A$2:$A$287),COLUMNS($J14:K14))),"")} | L14: {=IFERROR(HYPERLINK("#KPI_Master!A"&MATCH(SMALL(IF(KPI_Element_Map!$E$2:$E$287=$A14,KPI_Element_Map!$A$2:$A$287),COLUMNS($J14:L14)),KPI_Master!$A:$A,0)&":P"&MATCH(SMALL(IF(KPI_Element_Map!$E$2:$E$287=$A14,KPI_Element_Map!$A$2:$A$287),COLUMNS($J14:L14)),KPI_Master!$A:$A,0),SMALL(IF(KPI_Element_Map!$E$2:$E$287=$A14,KPI_Element_Map!$A$2:$A$287),COLUMNS($J14:L14))),"")} | M14: {=IFERROR(HYPERLINK("#KPI_Master!A"&MATCH(SMALL(IF(KPI_Element_Map!$E$2:$E$287=$A14,KPI_Element_Map!$A$2:$A$287),COLUMNS($J14:M14)),KPI_Master!$A:$A,0)&":P"&MATCH(SMALL(IF(KPI_Element_Map!$E$2:$E$287=$A14,KPI_Element_Map!$A$2:$A$287),COLUMNS($J14:M14)),KPI_Master!$A:$A,0),SMALL(IF(KPI_Element_Map!$E$2:$E$287=$A14,KPI_Element_Map!$A$2:$A$287),COLUMNS($J14:M14))),"")} | N14: {=IFERROR(HYPERLINK("#KPI_Master!A"&MATCH(SMALL(IF(KPI_Element_Map!$E$2:$E$287=$A14,KPI_Element_Map!$A$2:$A$287),COLUMNS($J14:N14)),KPI_Master!$A:$A,0)&":P"&MATCH(SMALL(IF(KPI_Element_Map!$E$2:$E$287=$A14,KPI_Element_Map!$A$2:$A$287),COLUMNS($J14:N14)),KPI_Master!$A:$A,0),SMALL(IF(KPI_Element_Map!$E$2:$E$287=$A14,KPI_Element_Map!$A$2:$A$287),COLUMNS($J14:N14))),"")} | O14: {=IFERROR(HYPERLINK("#KPI_Master!A"&MATCH(SMALL(IF(KPI_Element_Map!$E$2:$E$287=$A14,KPI_Element_Map!$A$2:$A$287),COLUMNS($J14:O14)),KPI_Master!$A:$A,0)&":P"&MATCH(SMALL(IF(KPI_Element_Map!$E$2:$E$287=$A14,KPI_Element_Map!$A$2:$A$287),COLUMNS($J14:O14)),KPI_Master!$A:$A,0),SMALL(IF(KPI_Element_Map!$E$2:$E$287=$A14,KPI_Element_Map!$A$2:$A$287),COLUMNS($J14:O14))),"")} | P14: {=IFERROR(HYPERLINK("#KPI_Master!A"&MATCH(SMALL(IF(KPI_Element_Map!$E$2:$E$287=$A14,KPI_Element_Map!$A$2:$A$287),COLUMNS($J14:P14)),KPI_Master!$A:$A,0)&":P"&MATCH(SMALL(IF(KPI_Element_Map!$E$2:$E$287=$A14,KPI_Element_Map!$A$2:$A$287),COLUMNS($J14:P14)),KPI_Master!$A:$A,0),SMALL(IF(KPI_Element_Map!$E$2:$E$287=$A14,KPI_Element_Map!$A$2:$A$287),COLUMNS($J14:P14))),"")} | Q14: {=IFERROR(HYPERLINK("#KPI_Master!A"&MATCH(SMALL(IF(KPI_Element_Map!$E$2:$E$287=$A14,KPI_Element_Map!$A$2:$A$287),COLUMNS($J14:Q14)),KPI_Master!$A:$A,0)&":P"&MATCH(SMALL(IF(KPI_Element_Map!$E$2:$E$287=$A14,KPI_Element_Map!$A$2:$A$287),COLUMNS($J14:Q14)),KPI_Master!$A:$A,0),SMALL(IF(KPI_Element_Map!$E$2:$E$287=$A14,KPI_Element_Map!$A$2:$A$287),COLUMNS($J14:Q14))),"")} | ... AH14: {=IFERROR(HYPERLINK("#KPI_Master!A"&MATCH(SMALL(IF(KPI_Element_Map!$E$2:$E$287=$A14,KPI_Element_Map!$A$2:$A$287),COLUMNS($J14:AH14)),KPI_Master!$A:$A,0)&":P"&MATCH(SMALL(IF(KPI_Element_Map!$E$2:$E$287=$A14,KPI_Element_Map!$A$2:$A$287),COLUMNS($J14:AH14)),KPI_Master!$A:$A,0),SMALL(IF(KPI_Element_Map!$E$2:$E$287=$A14,KPI_Element_Map!$A$2:$A$287),COLUMNS($J14:AH14))),"")}
A15: E11 | B15: Total Available Units / Licensed Beds | C15: Units (or licensed beds) available to occupy | D15: {=_xlfn.TEXTJOIN(", ",TRUE(),IF(KPI_Element_Map!$E$2:$E$287=$A15,KPI_Element_Map!$A$2:$A$287,""))} -> 12, 24, 25, 32, 39, 40, 121, 123, 126, 160, 166, 167 | E15: =COUNTIF(KPI_Element_Map!$E$2:$E$287,$A15) -> 12 | F15: =COUNTIFS(KPI_Element_Map!$E$2:$E$287,$A15,KPI_Element_Map!$D$2:$D$287,"1 - Core") -> 1 | G15: D02 | H15: =INDEX(Minimum_Documents!$B:$B,MATCH($G15,Minimum_Documents!$A:$A,0)) -> Property & Unit Master Schedule | J15: {=IFERROR(HYPERLINK("#KPI_Master!A"&MATCH(SMALL(IF(KPI_Element_Map!$E$2:$E$287=$A15,KPI_Element_Map!$A$2:$A$287),COLUMNS($J15:J15)),KPI_Master!$A:$A,0)&":P"&MATCH(SMALL(IF(KPI_Element_Map!$E$2:$E$287=$A15,KPI_Element_Map!$A$2:$A$287),COLUMNS($J15:J15)),KPI_Master!$A:$A,0),SMALL(IF(KPI_Element_Map!$E$2:$E$287=$A15,KPI_Element_Map!$A$2:$A$287),COLUMNS($J15:J15))),"")} -> 12 | K15: {=IFERROR(HYPERLINK("#KPI_Master!A"&MATCH(SMALL(IF(KPI_Element_Map!$E$2:$E$287=$A15,KPI_Element_Map!$A$2:$A$287),COLUMNS($J15:K15)),KPI_Master!$A:$A,0)&":P"&MATCH(SMALL(IF(KPI_Element_Map!$E$2:$E$287=$A15,KPI_Element_Map!$A$2:$A$287),COLUMNS($J15:K15)),KPI_Master!$A:$A,0),SMALL(IF(KPI_Element_Map!$E$2:$E$287=$A15,KPI_Element_Map!$A$2:$A$287),COLUMNS($J15:K15))),"")} -> 24 | L15: {=IFERROR(HYPERLINK("#KPI_Master!A"&MATCH(SMALL(IF(KPI_Element_Map!$E$2:$E$287=$A15,KPI_Element_Map!$A$2:$A$287),COLUMNS($J15:L15)),KPI_Master!$A:$A,0)&":P"&MATCH(SMALL(IF(KPI_Element_Map!$E$2:$E$287=$A15,KPI_Element_Map!$A$2:$A$287),COLUMNS($J15:L15)),KPI_Master!$A:$A,0),SMALL(IF(KPI_Element_Map!$E$2:$E$287=$A15,KPI_Element_Map!$A$2:$A$287),COLUMNS($J15:L15))),"")} -> 25 | M15: {=IFERROR(HYPERLINK("#KPI_Master!A"&MATCH(SMALL(IF(KPI_Element_Map!$E$2:$E$287=$A15,KPI_Element_Map!$A$2:$A$287),COLUMNS($J15:M15)),KPI_Master!$A:$A,0)&":P"&MATCH(SMALL(IF(KPI_Element_Map!$E$2:$E$287=$A15,KPI_Element_Map!$A$2:$A$287),COLUMNS($J15:M15)),KPI_Master!$A:$A,0),SMALL(IF(KPI_Element_Map!$E$2:$E$287=$A15,KPI_Element_Map!$A$2:$A$287),COLUMNS($J15:M15))),"")} -> 32 | N15: {=IFERROR(HYPERLINK("#KPI_Master!A"&MATCH(SMALL(IF(KPI_Element_Map!$E$2:$E$287=$A15,KPI_Element_Map!$A$2:$A$287),COLUMNS($J15:N15)),KPI_Master!$A:$A,0)&":P"&MATCH(SMALL(IF(KPI_Element_Map!$E$2:$E$287=$A15,KPI_Element_Map!$A$2:$A$287),COLUMNS($J15:N15)),KPI_Master!$A:$A,0),SMALL(IF(KPI_Element_Map!$E$2:$E$287=$A15,KPI_Element_Map!$A$2:$A$287),COLUMNS($J15:N15))),"")} -> 39 | O15: {=IFERROR(HYPERLINK("#KPI_Master!A"&MATCH(SMALL(IF(KPI_Element_Map!$E$2:$E$287=$A15,KPI_Element_Map!$A$2:$A$287),COLUMNS($J15:O15)),KPI_Master!$A:$A,0)&":P"&MATCH(SMALL(IF(KPI_Element_Map!$E$2:$E$287=$A15,KPI_Element_Map!$A$2:$A$287),COLUMNS($J15:O15)),KPI_Master!$A:$A,0),SMALL(IF(KPI_Element_Map!$E$2:$E$287=$A15,KPI_Element_Map!$A$2:$A$287),COLUMNS($J15:O15))),"")} -> 40 | P15: {=IFERROR(HYPERLINK("#KPI_Master!A"&MATCH(SMALL(IF(KPI_Element_Map!$E$2:$E$287=$A15,KPI_Element_Map!$A$2:$A$287),COLUMNS($J15:P15)),KPI_Master!$A:$A,0)&":P"&MATCH(SMALL(IF(KPI_Element_Map!$E$2:$E$287=$A15,KPI_Element_Map!$A$2:$A$287),COLUMNS($J15:P15)),KPI_Master!$A:$A,0),SMALL(IF(KPI_Element_Map!$E$2:$E$287=$A15,KPI_Element_Map!$A$2:$A$287),COLUMNS($J15:P15))),"")} -> 121 | Q15: {=IFERROR(HYPERLINK("#KPI_Master!A"&MATCH(SMALL(IF(KPI_Element_Map!$E$2:$E$287=$A15,KPI_Element_Map!$A$2:$A$287),COLUMNS($J15:Q15)),KPI_Master!$A:$A,0)&":P"&MATCH(SMALL(IF(KPI_Element_Map!$E$2:$E$287=$A15,KPI_Element_Map!$A$2:$A$287),COLUMNS($J15:Q15)),KPI_Master!$A:$A,0),SMALL(IF(KPI_Element_Map!$E$2:$E$287=$A15,KPI_Element_Map!$A$2:$A$287),COLUMNS($J15:Q15))),"")} -> 123 | ... AH15: {=IFERROR(HYPERLINK("#KPI_Master!A"&MATCH(SMALL(IF(KPI_Element_Map!$E$2:$E$287=$A15,KPI_Element_Map!$A$2:$A$287),COLUMNS($J15:AH15)),KPI_Master!$A:$A,0)&":P"&MATCH(SMALL(IF(KPI_Element_Map!$E$2:$E$287=$A15,KPI_Element_Map!$A$2:$A$287),COLUMNS($J15:AH15)),KPI_Master!$A:$A,0),SMALL(IF(KPI_Element_Map!$E$2:$E$287=$A15,KPI_Element_Map!$A$2:$A$287),COLUMNS($J15:AH15))),"")}
A16: E12 | B16: Square Footage (building / cleanable) | C16: Gross building and cleanable square feet | D16: {=_xlfn.TEXTJOIN(", ",TRUE(),IF(KPI_Element_Map!$E$2:$E$287=$A16,KPI_Element_Map!$A$2:$A$287,""))} -> 42, 114, 119 | E16: =COUNTIF(KPI_Element_Map!$E$2:$E$287,$A16) -> 3 | F16: =COUNTIFS(KPI_Element_Map!$E$2:$E$287,$A16,KPI_Element_Map!$D$2:$D$287,"1 - Core") -> 0 | G16: D02 | H16: =INDEX(Minimum_Documents!$B:$B,MATCH($G16,Minimum_Documents!$A:$A,0)) -> Property & Unit Master Schedule | J16: {=IFERROR(HYPERLINK("#KPI_Master!A"&MATCH(SMALL(IF(KPI_Element_Map!$E$2:$E$287=$A16,KPI_Element_Map!$A$2:$A$287),COLUMNS($J16:J16)),KPI_Master!$A:$A,0)&":P"&MATCH(SMALL(IF(KPI_Element_Map!$E$2:$E$287=$A16,KPI_Element_Map!$A$2:$A$287),COLUMNS($J16:J16)),KPI_Master!$A:$A,0),SMALL(IF(KPI_Element_Map!$E$2:$E$287=$A16,KPI_Element_Map!$A$2:$A$287),COLUMNS($J16:J16))),"")} -> 42 | K16: {=IFERROR(HYPERLINK("#KPI_Master!A"&MATCH(SMALL(IF(KPI_Element_Map!$E$2:$E$287=$A16,KPI_Element_Map!$A$2:$A$287),COLUMNS($J16:K16)),KPI_Master!$A:$A,0)&":P"&MATCH(SMALL(IF(KPI_Element_Map!$E$2:$E$287=$A16,KPI_Element_Map!$A$2:$A$287),COLUMNS($J16:K16)),KPI_Master!$A:$A,0),SMALL(IF(KPI_Element_Map!$E$2:$E$287=$A16,KPI_Element_Map!$A$2:$A$287),COLUMNS($J16:K16))),"")} -> 114 | L16: {=IFERROR(HYPERLINK("#KPI_Master!A"&MATCH(SMALL(IF(KPI_Element_Map!$E$2:$E$287=$A16,KPI_Element_Map!$A$2:$A$287),COLUMNS($J16:L16)),KPI_Master!$A:$A,0)&":P"&MATCH(SMALL(IF(KPI_Element_Map!$E$2:$E$287=$A16,KPI_Element_Map!$A$2:$A$287),COLUMNS($J16:L16)),KPI_Master!$A:$A,0),SMALL(IF(KPI_Element_Map!$E$2:$E$287=$A16,KPI_Element_Map!$A$2:$A$287),COLUMNS($J16:L16))),"")} -> 119 | M16: {=IFERROR(HYPERLINK("#KPI_Master!A"&MATCH(SMALL(IF(KPI_Element_Map!$E$2:$E$287=$A16,KPI_Element_Map!$A$2:$A$287),COLUMNS($J16:M16)),KPI_Master!$A:$A,0)&":P"&MATCH(SMALL(IF(KPI_Element_Map!$E$2:$E$287=$A16,KPI_Element_Map!$A$2:$A$287),COLUMNS($J16:M16)),KPI_Master!$A:$A,0),SMALL(IF(KPI_Element_Map!$E$2:$E$287=$A16,KPI_Element_Map!$A$2:$A$287),COLUMNS($J16:M16))),"")} | N16: {=IFERROR(HYPERLINK("#KPI_Master!A"&MATCH(SMALL(IF(KPI_Element_Map!$E$2:$E$287=$A16,KPI_Element_Map!$A$2:$A$287),COLUMNS($J16:N16)),KPI_Master!$A:$A,0)&":P"&MATCH(SMALL(IF(KPI_Element_Map!$E$2:$E$287=$A16,KPI_Element_Map!$A$2:$A$287),COLUMNS($J16:N16)),KPI_Master!$A:$A,0),SMALL(IF(KPI_Element_Map!$E$2:$E$287=$A16,KPI_Element_Map!$A$2:$A$287),COLUMNS($J16:N16))),"")} | O16: {=IFERROR(HYPERLINK("#KPI_Master!A"&MATCH(SMALL(IF(KPI_Element_Map!$E$2:$E$287=$A16,KPI_Element_Map!$A$2:$A$287),COLUMNS($J16:O16)),KPI_Master!$A:$A,0)&":P"&MATCH(SMALL(IF(KPI_Element_Map!$E$2:$E$287=$A16,KPI_Element_Map!$A$2:$A$287),COLUMNS($J16:O16)),KPI_Master!$A:$A,0),SMALL(IF(KPI_Element_Map!$E$2:$E$287=$A16,KPI_Element_Map!$A$2:$A$287),COLUMNS($J16:O16))),"")} | P16: {=IFERROR(HYPERLINK("#KPI_Master!A"&MATCH(SMALL(IF(KPI_Element_Map!$E$2:$E$287=$A16,KPI_Element_Map!$A$2:$A$287),COLUMNS($J16:P16)),KPI_Master!$A:$A,0)&":P"&MATCH(SMALL(IF(KPI_Element_Map!$E$2:$E$287=$A16,KPI_Element_Map!$A$2:$A$287),COLUMNS($J16:P16)),KPI_Master!$A:$A,0),SMALL(IF(KPI_Element_Map!$E$2:$E$287=$A16,KPI_Element_Map!$A$2:$A$287),COLUMNS($J16:P16))),"")} | Q16: {=IFERROR(HYPERLINK("#KPI_Master!A"&MATCH(SMALL(IF(KPI_Element_Map!$E$2:$E$287=$A16,KPI_Element_Map!$A$2:$A$287),COLUMNS($J16:Q16)),KPI_Master!$A:$A,0)&":P"&MATCH(SMALL(IF(KPI_Element_Map!$E$2:$E$287=$A16,KPI_Element_Map!$A$2:$A$287),COLUMNS($J16:Q16)),KPI_Master!$A:$A,0),SMALL(IF(KPI_Element_Map!$E$2:$E$287=$A16,KPI_Element_Map!$A$2:$A$287),COLUMNS($J16:Q16))),"")} | ... AH16: {=IFERROR(HYPERLINK("#KPI_Master!A"&MATCH(SMALL(IF(KPI_Element_Map!$E$2:$E$287=$A16,KPI_Element_Map!$A$2:$A$287),COLUMNS($J16:AH16)),KPI_Master!$A:$A,0)&":P"&MATCH(SMALL(IF(KPI_Element_Map!$E$2:$E$287=$A16,KPI_Element_Map!$A$2:$A$287),COLUMNS($J16:AH16)),KPI_Master!$A:$A,0),SMALL(IF(KPI_Element_Map!$E$2:$E$287=$A16,KPI_Element_Map!$A$2:$A$287),COLUMNS($J16:AH16))),"")}
... A62: E58 | B62: Food Purchase Cost | C62: Raw food purchases. Kept on D03 because food is normally its own P&L account; if it is not, change this Doc ID to D31 | D62: {=_xlfn.TEXTJOIN(", ",TRUE(),IF(KPI_Element_Map!$E$2:$E$287=$A62,KPI_Element_Map!$A$2:$A$287,""))} -> 1, 2, 3, 10 | E62: =COUNTIF(KPI_Element_Map!$E$2:$E$287,$A62) -> 4 | F62: =COUNTIFS(KPI_Element_Map!$E$2:$E$287,$A62,KPI_Element_Map!$D$2:$D$287,"1 - Core") -> 1 | G62: D03 | H62: =INDEX(Minimum_Documents!$B:$B,MATCH($G62,Minimum_Documents!$A:$A,0)) -> Monthly Financial Statement Package - consolidated (P&L with budget, balance sheet, cash flow, trial balance; no department split needed) | J62: {=IFERROR(HYPERLINK("#KPI_Master!A"&MATCH(SMALL(IF(KPI_Element_Map!$E$2:$E$287=$A62,KPI_Element_Map!$A$2:$A$287),COLUMNS($J62:J62)),KPI_Master!$A:$A,0)&":P"&MATCH(SMALL(IF(KPI_Element_Map!$E$2:$E$287=$A62,KPI_Element_Map!$A$2:$A$287),COLUMNS($J62:J62)),KPI_Master!$A:$A,0),SMALL(IF(KPI_Element_Map!$E$2:$E$287=$A62,KPI_Element_Map!$A$2:$A$287),COLUMNS($J62:J62))),"")} -> 1 | K62: {=IFERROR(HYPERLINK("#KPI_Master!A"&MATCH(SMALL(IF(KPI_Element_Map!$E$2:$E$287=$A62,KPI_Element_Map!$A$2:$A$287),COLUMNS($J62:K62)),KPI_Master!$A:$A,0)&":P"&MATCH(SMALL(IF(KPI_Element_Map!$E$2:$E$287=$A62,KPI_Element_Map!$A$2:$A$287),COLUMNS($J62:K62)),KPI_Master!$A:$A,0),SMALL(IF(KPI_Element_Map!$E$2:$E$287=$A62,KPI_Element_Map!$A$2:$A$287),COLUMNS($J62:K62))),"")} -> 2 | L62: {=IFERROR(HYPERLINK("#KPI_Master!A"&MATCH(SMALL(IF(KPI_Element_Map!$E$2:$E$287=$A62,KPI_Element_Map!$A$2:$A$287),COLUMNS($J62:L62)),KPI_Master!$A:$A,0)&":P"&MATCH(SMALL(IF(KPI_Element_Map!$E$2:$E$287=$A62,KPI_Element_Map!$A$2:$A$287),COLUMNS($J62:L62)),KPI_Master!$A:$A,0),SMALL(IF(KPI_Element_Map!$E$2:$E$287=$A62,KPI_Element_Map!$A$2:$A$287),COLUMNS($J62:L62))),"")} -> 3 | M62: {=IFERROR(HYPERLINK("#KPI_Master!A"&MATCH(SMALL(IF(KPI_Element_Map!$E$2:$E$287=$A62,KPI_Element_Map!$A$2:$A$287),COLUMNS($J62:M62)),KPI_Master!$A:$A,0)&":P"&MATCH(SMALL(IF(KPI_Element_Map!$E$2:$E$287=$A62,KPI_Element_Map!$A$2:$A$287),COLUMNS($J62:M62)),KPI_Master!$A:$A,0),SMALL(IF(KPI_Element_Map!$E$2:$E$287=$A62,KPI_Element_Map!$A$2:$A$287),COLUMNS($J62:M62))),"")} -> 10 | N62: {=IFERROR(HYPERLINK("#KPI_Master!A"&MATCH(SMALL(IF(KPI_Element_Map!$E$2:$E$287=$A62,KPI_Element_Map!$A$2:$A$287),COLUMNS($J62:N62)),KPI_Master!$A:$A,0)&":P"&MATCH(SMALL(IF(KPI_Element_Map!$E$2:$E$287=$A62,KPI_Element_Map!$A$2:$A$287),COLUMNS($J62:N62)),KPI_Master!$A:$A,0),SMALL(IF(KPI_Element_Map!$E$2:$E$287=$A62,KPI_Element_Map!$A$2:$A$287),COLUMNS($J62:N62))),"")} | O62: {=IFERROR(HYPERLINK("#KPI_Master!A"&MATCH(SMALL(IF(KPI_Element_Map!$E$2:$E$287=$A62,KPI_Element_Map!$A$2:$A$287),COLUMNS($J62:O62)),KPI_Master!$A:$A,0)&":P"&MATCH(SMALL(IF(KPI_Element_Map!$E$2:$E$287=$A62,KPI_Element_Map!$A$2:$A$287),COLUMNS($J62:O62)),KPI_Master!$A:$A,0),SMALL(IF(KPI_Element_Map!$E$2:$E$287=$A62,KPI_Element_Map!$A$2:$A$287),COLUMNS($J62:O62))),"")} | P62: {=IFERROR(HYPERLINK("#KPI_Master!A"&MATCH(SMALL(IF(KPI_Element_Map!$E$2:$E$287=$A62,KPI_Element_Map!$A$2:$A$287),COLUMNS($J62:P62)),KPI_Master!$A:$A,0)&":P"&MATCH(SMALL(IF(KPI_Element_Map!$E$2:$E$287=$A62,KPI_Element_Map!$A$2:$A$287),COLUMNS($J62:P62)),KPI_Master!$A:$A,0),SMALL(IF(KPI_Element_Map!$E$2:$E$287=$A62,KPI_Element_Map!$A$2:$A$287),COLUMNS($J62:P62))),"")} | Q62: {=IFERROR(HYPERLINK("#KPI_Master!A"&MATCH(SMALL(IF(KPI_Element_Map!$E$2:$E$287=$A62,KPI_Element_Map!$A$2:$A$287),COLUMNS($J62:Q62)),KPI_Master!$A:$A,0)&":P"&MATCH(SMALL(IF(KPI_Element_Map!$E$2:$E$287=$A62,KPI_Element_Map!$A$2:$A$287),COLUMNS($J62:Q62)),KPI_Master!$A:$A,0),SMALL(IF(KPI_Element_Map!$E$2:$E$287=$A62,KPI_Element_Map!$A$2:$A$287),COLUMNS($J62:Q62))),"")} | ... AH62: {=IFERROR(HYPERLINK("#KPI_Master!A"&MATCH(SMALL(IF(KPI_Element_Map!$E$2:$E$287=$A62,KPI_Element_Map!$A$2:$A$287),COLUMNS($J62:AH62)),KPI_Master!$A:$A,0)&":P"&MATCH(SMALL(IF(KPI_Element_Map!$E$2:$E$287=$A62,KPI_Element_Map!$A$2:$A$287),COLUMNS($J62:AH62)),KPI_Master!$A:$A,0),SMALL(IF(KPI_Element_Map!$E$2:$E$287=$A62,KPI_Element_Map!$A$2:$A$287),COLUMNS($J62:AH62))),"")}

Sheet Minimum_Documents
A1: Minimum Source Document Set - one document per data element, covering all 171 KPIs
A2: Distinct documents named in KPI_Master (Source Documents column) | F2: 281 | G2: Counted from KPI_Master column G at build time (split on ";", de-duplicated, case-insensitive)
A3: Minimum documents in this set | F3: =COUNTA(A7:A37) -> 31 | G3: KPIs not covered by any document (should be 0) | I3: =COUNTIF(KPI_Doc_Matrix!F2:F172,0) -> 0
A4: Of which needed to launch Tier 1 - Core KPIs | F4: =COUNTIF(H7:H37,"Yes") -> 19
A6: Doc ID | B6: Minimum Source Document | C6: Source System | D6: Data Elements It Supplies | E6: Replaces / Consolidates (from KPI_Master) | F6: KPIs Using It | G6: Tier 1 KPIs Using It | H6: Needed for Tier 1 Launch? | I6: Sr. Nos. Using It
A7: D01 | B7: Census & ADT Register | C7: EHR (PCC / MatrixCare / AL Advantage / Eldermark) | D7: E01 Total Resident Days; E02 Occupied Units / Beds; E03 Total Residents (headcount); E04 Resident Days by Payer; E05 Skilled / Medicare Part A Days & Census; E06 Census by Level of Care (AL / MC / SNF); E07 Move-Ins / Admissions; E08 Move-Outs / Discharges; E09 Hospital Transfers & Readmissions; E10 Prior Hospital Stay Dates | E7: Daily census report; Census register; Census by payer; Skilled census register; MC census; Occupancy report; Move-in / move-out logs; Discharge records; Transfer / discharge log; Admission face sheets; Discharge register by payer; Midnight census | F7: =KPI_Doc_Matrix!G174 -> 43 | G7: =KPI_Doc_Matrix!G175 -> 10 | H7: =IF(G7>0,"Yes","No - phase 2+") -> Yes | I7: {=_xlfn.TEXTJOIN(", ",TRUE(),IF(KPI_Doc_Matrix!G2:G172=1,KPI_Doc_Matrix!$A$2:$A$172,""))} -> 1, 2, 4, 12, 13, 22, 23, 24, 25, 41, 52, 74, 75, 77, 78, 81, 84, 86, 87, 88, 89, 91, 94, 95, 97, 98, 103, 104, 110, 113, 115, 144, 151, 152, 153, 157, 158, 159, 160, 161, 162, 167, 169
A8: D02 | B8: Property & Unit Master Schedule | C8: Property management / Finance | D8: E11 Total Available Units / Licensed Beds; E12 Square Footage (building / cleanable); E13 Developed Acreage; E14 Published Street Rates | E8: Unit inventory schedule; Licensed bed count; Building floor plan / area schedule; Cleanable square-footage schedule; Site plan (developed acreage); Published rate sheet | F8: =KPI_Doc_Matrix!H174 -> 17 | G8: =KPI_Doc_Matrix!H175 -> 1 | H8: =IF(G8>0,"Yes","No - phase 2+") -> Yes | I8: {=_xlfn.TEXTJOIN(", ",TRUE(),IF(KPI_Doc_Matrix!H2:H172=1,KPI_Doc_Matrix!$A$2:$A$172,""))} -> 12, 24, 25, 32, 39, 40, 42, 114, 119, 120, 121, 123, 126, 160, 165, 166, 167
A9: D03 | B9: Monthly Financial Statement Package - consolidated (P&L with budget, balance sheet, cash flow, trial balance; no department split needed) | C9: Finance GL | D9: E15 Total Revenue / Operating Revenue; E16 Total Operating Expense; E17 Account-Level Expense Lines; E18 Depreciation & Amortisation; E19 Net / Operating Income Items; E20 Budgeted Amounts; E21 Balance Sheet Balances; E22 Capital Expenditure & Debt Service; E23 Labor Cost $ (wages, benefits, agency, WC premium); E58 Food Purchase Cost | E9: Monthly P&L; Income statement; Trial balance; Balance sheet; Cash-flow statement; Budget file; Audited financial statements; Revenue GL; Food purchase invoices ($); Utility invoices ($); Insurance invoices; Benefits invoices; Agency invoices; Loan amortisation schedule; Fixed-asset register; Management agreement; Write-off approval forms | F9: =KPI_Doc_Matrix!I174 -> 33 | G9: =KPI_Doc_Matrix!I175 -> 6 | H9: =IF(G9>0,"Yes","No - phase 2+") -> Yes | I9: {=_xlfn.TEXTJOIN(", ",TRUE(),IF(KPI_Doc_Matrix!I2:I172=1,KPI_Doc_Matrix!$A$2:$A$172,""))} -> 1, 2, 3, 10, 14, 17, 18, 19, 20, 21, 26, 27, 28, 29, 30, 31, 32, 33, 34, 35, 36, 37, 38, 39, 40, 50, 62, 63, 66, 72, 114, 117, 164
A10: D04 | B10: Resident Billing Register / Rent Roll (by resident, payer and charge code) | C10: Billing (EHR billing module) | D10: E24 Resident Revenue Detail | E10: Rent roll; Billing revenue by payer; Monthly billing by charge code; Move-in contracts; Concession log | F10: =KPI_Doc_Matrix!J174 -> 5 | G10: =KPI_Doc_Matrix!J175 -> 3 | H10: =IF(G10>0,"Yes","No - phase 2+") -> Yes | I10: {=_xlfn.TEXTJOIN(", ",TRUE(),IF(KPI_Doc_Matrix!J2:J172=1,KPI_Doc_Matrix!$A$2:$A$172,""))} -> 13, 15, 23, 41, 165
A11: D05 | B11: AR Aging Report | C11: Billing / Finance | D11: E25 AR Balance & Aging Buckets | E11: AR aging report; Collection notes; Payer remittance advices | F11: =KPI_Doc_Matrix!K174 -> 2 | G11: =KPI_Doc_Matrix!K175 -> 1 | H11: =IF(G11>0,"Yes","No - phase 2+") -> Yes | I11: {=_xlfn.TEXTJOIN(", ",TRUE(),IF(KPI_Doc_Matrix!K2:K172=1,KPI_Doc_Matrix!$A$2:$A$172,""))} -> 15, 16
A12: D06 | B12: Payroll Register (hours and wages by employee, job class and department) | C12: Payroll | D12: E26 Hours Worked (regular / OT, by department & job class); E27 Wages by Job Class / Department; E28 FTEs by Department | E12: Payroll register; Payroll register by job class / department; Payroll hours report; Payroll FTE report; Dining / laundry timecards; Timecards; PBJ file (hours) | F12: =KPI_Doc_Matrix!L174 -> 26 | G12: =KPI_Doc_Matrix!L175 -> 2 | H12: =IF(G12>0,"Yes","No - phase 2+") -> Yes | I12: {=_xlfn.TEXTJOIN(", ",TRUE(),IF(KPI_Doc_Matrix!L2:L172=1,KPI_Doc_Matrix!$A$2:$A$172,""))} -> 2, 3, 11, 34, 42, 43, 49, 52, 56, 57, 58, 59, 60, 61, 63, 64, 67, 68, 69, 70, 71, 72, 95, 113, 119, 164
A13: D07 | B13: Time & Attendance / Scheduling Report (scheduled vs worked, by day and shift) | C13: Time & Attendance | D13: E29 Scheduled vs Worked by Day & Shift | E13: Schedule; Attendance records; Call-out log; Daily staffing sheets; Shift schedules; Time & attendance by day of week; Daily RN coverage report | F13: =KPI_Doc_Matrix!M174 -> 4 | G13: =KPI_Doc_Matrix!M175 -> 0 | H13: =IF(G13>0,"Yes","No - phase 2+") -> No - phase 2+ | I13: {=_xlfn.TEXTJOIN(", ",TRUE(),IF(KPI_Doc_Matrix!M2:M172=1,KPI_Doc_Matrix!$A$2:$A$172,""))} -> 51, 98, 110, 142
A14: D08 | B14: HRIS Employee Roster & Movement Report (headcount, hires, separations) | C14: HRIS | D14: E30 Employee Headcount; E31 Separations; E32 New Hires | E14: Headcount report; Termination / separation records; Separation records by job class; New hire roster; HR department roster; Exit interview forms; PBJ administrator job-class data | F14: =KPI_Doc_Matrix!N174 -> 7 | G14: =KPI_Doc_Matrix!N175 -> 2 | H14: =IF(G14>0,"Yes","No - phase 2+") -> Yes | I14: {=_xlfn.TEXTJOIN(", ",TRUE(),IF(KPI_Doc_Matrix!N2:N172=1,KPI_Doc_Matrix!$A$2:$A$172,""))} -> 44, 45, 46, 53, 55, 64, 65
A15: D09 | B15: Position Control & Requisition Report (budgeted positions, recommended FTE, open requisitions) | C15: HRIS / ATS | D15: E33 Budgeted Positions / Requisitions | E15: Approved staffing plan; Requisition log; Job requisition records; Offer letters; SBC recommended FTE by position | F15: =KPI_Doc_Matrix!O174 -> 3 | G15: =KPI_Doc_Matrix!O175 -> 0 | H15: =IF(G15>0,"Yes","No - phase 2+") -> No - phase 2+ | I15: {=_xlfn.TEXTJOIN(", ",TRUE(),IF(KPI_Doc_Matrix!O2:O172=1,KPI_Doc_Matrix!$A$2:$A$172,""))} -> 47, 48, 67
A16: D10 | B16: Workers' Compensation Loss Run | C16: Insurance carrier / broker | D16: E34 Workers' Comp Claims | E16: Claims loss runs; Insurance claim records; OSHA 300 log; WC incident reports | F16: =KPI_Doc_Matrix!P174 -> 2 | G16: =KPI_Doc_Matrix!P175 -> 0 | H16: =IF(G16>0,"Yes","No - phase 2+") -> No - phase 2+ | I16: {=_xlfn.TEXTJOIN(", ",TRUE(),IF(KPI_Doc_Matrix!P2:P172=1,KPI_Doc_Matrix!$A$2:$A$172,""))} -> 53, 66
A17: D11 | B17: LMS Training Completion Report | C17: LMS | D17: E35 Training Assignments & Completions | E17: LMS assignment and completion report; Course transcripts | F17: =KPI_Doc_Matrix!Q174 -> 1 | G17: =KPI_Doc_Matrix!Q175 -> 1 | H17: =IF(G17>0,"Yes","No - phase 2+") -> Yes | I17: {=_xlfn.TEXTJOIN(", ",TRUE(),IF(KPI_Doc_Matrix!Q2:Q172=1,KPI_Doc_Matrix!$A$2:$A$172,""))} -> 73
A18: D12 | B18: Satisfaction & Engagement Survey Results (resident, family, employee) | C18: Survey platform | D18: E36 Survey Ratings & Response Counts | E18: Resident satisfaction survey; Family survey results; Employee engagement survey; Pulse survey exports; Program feedback forms; Comment cards; Food committee / family council minutes | F18: =KPI_Doc_Matrix!R174 -> 5 | G18: =KPI_Doc_Matrix!R175 -> 3 | H18: =IF(G18>0,"Yes","No - phase 2+") -> Yes | I18: {=_xlfn.TEXTJOIN(", ",TRUE(),IF(KPI_Doc_Matrix!R2:R172=1,KPI_Doc_Matrix!$A$2:$A$172,""))} -> 5, 54, 76, 146, 147
A19: D13 | B19: Incident & Accident Log (falls, med errors, reportable, security, elopement) | C19: EHR risk / incident module | D19: E37 Incidents by Type | E19: Incident / accident reports; eINTERACT fall logs; Medication error incident forms; State reportable incident log; Security incident reports; Elopement reports; Door alarm / WanderGuard logs; Shift logs | F19: =KPI_Doc_Matrix!S174 -> 6 | G19: =KPI_Doc_Matrix!S175 -> 3 | H19: =IF(G19>0,"Yes","No - phase 2+") -> Yes | I19: {=_xlfn.TEXTJOIN(", ",TRUE(),IF(KPI_Doc_Matrix!S2:S172=1,KPI_Doc_Matrix!$A$2:$A$172,""))} -> 81, 82, 85, 144, 169, 170
A20: D14 | B20: eMAR Administration Report | C20: EHR eMAR | D20: E38 Medication Administrations | E20: eMAR exception report; Medication administration record; eMAR PRN log; Pharmacy consultant report; GDR documentation | F20: =KPI_Doc_Matrix!T174 -> 3 | G20: =KPI_Doc_Matrix!T175 -> 1 | H20: =IF(G20>0,"Yes","No - phase 2+") -> Yes | I20: {=_xlfn.TEXTJOIN(", ",TRUE(),IF(KPI_Doc_Matrix!T2:T172=1,KPI_Doc_Matrix!$A$2:$A$172,""))} -> 85, 91, 97
A21: D15 | B21: EHR Clinical Assessment & Care Plan Report | C21: EHR | D21: E39 Clinical Assessment Results; E40 Care Plan & Assessment Schedule | E21: Skin & wound assessments; Braden scores; Wound rounds; Monthly weight record; Intake & output; Hydration risk list; Dietitian / nutrition assessments; Diagnosis list; Acuity / level-of-care assessments; Care plan due-date report; Assessment due report; Service plan records | F21: =KPI_Doc_Matrix!U174 -> 9 | G21: =KPI_Doc_Matrix!U175 -> 1 | H21: =IF(G21>0,"Yes","No - phase 2+") -> Yes | I21: {=_xlfn.TEXTJOIN(", ",TRUE(),IF(KPI_Doc_Matrix!U2:U172=1,KPI_Doc_Matrix!$A$2:$A$172,""))} -> 8, 9, 83, 84, 90, 91, 92, 93, 94
A22: D16 | B22: MDS 3.0 Assessment Export (SNF only) | C22: EHR MDS module | D22: E41 MDS Data (ARD, PDPM CMI) | E22: MDS submission log; MDS ARD field; MDS audit log; PDPM HIPPS codes; MDS Sections GG/H/I/J/K/N | F22: =KPI_Doc_Matrix!V174 -> 2 | G22: =KPI_Doc_Matrix!V175 -> 0 | H22: =IF(G22>0,"Yes","No - phase 2+") -> No - phase 2+ | I22: {=_xlfn.TEXTJOIN(", ",TRUE(),IF(KPI_Doc_Matrix!V2:V172=1,KPI_Doc_Matrix!$A$2:$A$172,""))} -> 96, 104
A23: D17 | B23: CMS Care Compare Provider Data Download (monthly) | C23: CMS (public data) | D23: E42 CMS-Published Measures & Ratings | E23: Care Compare star ratings; QM file; Staffing file; Health inspection file; Provider information (abuse icon, SFF status); Medicare claims-based QMs; PBJ audit outcomes | F23: =KPI_Doc_Matrix!W174 -> 21 | G23: =KPI_Doc_Matrix!W175 -> 2 | H23: =IF(G23>0,"Yes","No - phase 2+") -> Yes | I23: {=_xlfn.TEXTJOIN(", ",TRUE(),IF(KPI_Doc_Matrix!W2:W172=1,KPI_Doc_Matrix!$A$2:$A$172,""))} -> 99, 100, 101, 102, 105, 106, 107, 108, 109, 130, 131, 132, 133, 134, 135, 136, 137, 140, 141, 142, 143
A24: D18 | B24: Regulatory Survey Report (CMS-2567 / State survey, incl. Life Safety) | C24: Regulator | D24: E43 Survey Deficiencies | E24: CMS-2567; Statement of deficiencies; LSC survey; Fire marshal inspection reports | F24: =KPI_Doc_Matrix!X174 -> 4 | G24: =KPI_Doc_Matrix!X175 -> 3 | H24: =IF(G24>0,"Yes","No - phase 2+") -> Yes | I24: {=_xlfn.TEXTJOIN(", ",TRUE(),IF(KPI_Doc_Matrix!X2:X172=1,KPI_Doc_Matrix!$A$2:$A$172,""))} -> 127, 129, 138, 139
A25: D19 | B25: Infection Surveillance Line Listing | C25: EHR infection module / IP log | D25: E44 Confirmed Infections | E25: Infection line listing; Lab culture reports; Urine culture results; McGeer worksheet; Antibiotic start log | F25: =KPI_Doc_Matrix!Y174 -> 2 | G25: =KPI_Doc_Matrix!Y175 -> 0 | H25: =IF(G25>0,"Yes","No - phase 2+") -> No - phase 2+ | I25: {=_xlfn.TEXTJOIN(", ",TRUE(),IF(KPI_Doc_Matrix!Y2:Y172=1,KPI_Doc_Matrix!$A$2:$A$172,""))} -> 88, 89
A26: D20 | B26: Quality Audit Tool Export (IP, sanitation, tray-line audits) | C26: Digital audit / rounding tool | D26: E45 Audit Points Earned / Possible | E26: Hand hygiene / PPE audits; IP rounding logs; Internal sanitation audit; Temperature logs; Tray line audit sheet; Dietitian audit log; Health department inspection | F26: =KPI_Doc_Matrix!Z174 -> 3 | G26: =KPI_Doc_Matrix!Z175 -> 0 | H26: =IF(G26>0,"Yes","No - phase 2+") -> No - phase 2+ | I26: {=_xlfn.TEXTJOIN(", ",TRUE(),IF(KPI_Doc_Matrix!Z2:Z172=1,KPI_Doc_Matrix!$A$2:$A$172,""))} -> 6, 7, 128
A27: D21 | B27: Therapy Discharge / Functional Outcomes Report | C27: Rehab / therapy system | D27: E46 Therapy Functional Outcomes | E27: Initial and discharge functional assessments; Section GG scores; Therapy discharge summaries | F27: =KPI_Doc_Matrix!AA174 -> 1 | G27: =KPI_Doc_Matrix!AA175 -> 1 | H27: =IF(G27>0,"Yes","No - phase 2+") -> Yes | I27: {=_xlfn.TEXTJOIN(", ",TRUE(),IF(KPI_Doc_Matrix!AA2:AA172=1,KPI_Doc_Matrix!$A$2:$A$172,""))} -> 145
A28: D22 | B28: Meal Count / POS Report | C28: Dining / POS system | D28: E47 Meals Served | E28: Meal count sheets; POS transaction log | F28: =KPI_Doc_Matrix!AB174 -> 3 | G28: =KPI_Doc_Matrix!AB175 -> 0 | H28: =IF(G28>0,"Yes","No - phase 2+") -> No - phase 2+ | I28: {=_xlfn.TEXTJOIN(", ",TRUE(),IF(KPI_Doc_Matrix!AB2:AB172=1,KPI_Doc_Matrix!$A$2:$A$172,""))} -> 4, 10, 11
A29: D23 | B29: Laundry Weight Log | C29: Housekeeping (manual) | D29: E48 Laundry Pounds Processed | E29: Laundry weight log | F29: =KPI_Doc_Matrix!AC174 -> 1 | G29: =KPI_Doc_Matrix!AC175 -> 0 | H29: =IF(G29>0,"Yes","No - phase 2+") -> No - phase 2+ | I29: {=_xlfn.TEXTJOIN(", ",TRUE(),IF(KPI_Doc_Matrix!AC2:AC172=1,KPI_Doc_Matrix!$A$2:$A$172,""))} -> 43
A30: D24 | B30: Activity Calendar & Attendance Report | C30: Life enrichment system | D30: E49 Activity Programs Offered; E50 Activity Attendance | E30: Activity attendance sheets; Program calendar; Calendar tagged by wellness dimension; MC activity logs; Weekend / evening schedule | F30: =KPI_Doc_Matrix!AD174 -> 6 | G30: =KPI_Doc_Matrix!AD175 -> 1 | H30: =IF(G30>0,"Yes","No - phase 2+") -> Yes | I30: {=_xlfn.TEXTJOIN(", ",TRUE(),IF(KPI_Doc_Matrix!AD2:AD172=1,KPI_Doc_Matrix!$A$2:$A$172,""))} -> 74, 75, 77, 78, 79, 80
A31: D25 | B31: Grievance Log (filed and resolved dates) | C31: Resident services / CRM | D31: E51 Grievances | E31: Grievance forms; Grievance log; Resolution letters; Resident council minutes | F31: =KPI_Doc_Matrix!AE174 -> 3 | G31: =KPI_Doc_Matrix!AE175 -> 1 | H31: =IF(G31>0,"Yes","No - phase 2+") -> Yes | I31: {=_xlfn.TEXTJOIN(", ",TRUE(),IF(KPI_Doc_Matrix!AE2:AE172=1,KPI_Doc_Matrix!$A$2:$A$172,""))} -> 148, 149, 150
A32: D26 | B32: Resident Engagement Platform Usage Report | C32: Resident engagement platform | D32: E52 Platform Active Users | E32: Platform active-user report | F32: =KPI_Doc_Matrix!AF174 -> 1 | G32: =KPI_Doc_Matrix!AF175 -> 0 | H32: =IF(G32>0,"Yes","No - phase 2+") -> No - phase 2+ | I32: {=_xlfn.TEXTJOIN(", ",TRUE(),IF(KPI_Doc_Matrix!AF2:AF172=1,KPI_Doc_Matrix!$A$2:$A$172,""))} -> 153
A33: D27 | B33: CRM Sales Pipeline Report | C33: Sales CRM | D33: E53 Sales Pipeline Events | E33: Inquiry records; Call tracking log; Web forms; Lead records; Tour log; Deposit agreements / log; Reservation records; Referral source field; Deposit refund log | F33: =KPI_Doc_Matrix!AG174 -> 8 | G33: =KPI_Doc_Matrix!AG175 -> 2 | H33: =IF(G33>0,"Yes","No - phase 2+") -> Yes | I33: {=_xlfn.TEXTJOIN(", ",TRUE(),IF(KPI_Doc_Matrix!AG2:AG172=1,KPI_Doc_Matrix!$A$2:$A$172,""))} -> 154, 155, 156, 157, 160, 161, 166, 168
A34: D28 | B34: Online Review Platform Export | C34: Review platforms | D34: E54 Online Review Ratings | E34: Review platform exports; Review response log | F34: =KPI_Doc_Matrix!AH174 -> 1 | G34: =KPI_Doc_Matrix!AH175 -> 0 | H34: =IF(G34>0,"Yes","No - phase 2+") -> No - phase 2+ | I34: {=_xlfn.TEXTJOIN(", ",TRUE(),IF(KPI_Doc_Matrix!AH2:AH172=1,KPI_Doc_Matrix!$A$2:$A$172,""))} -> 163
A35: D29 | B35: CMMS Work Order & PM Report (incl. life-safety and vehicle PM tasks) | C35: MicroMain CMMS | D35: E55 Work Orders & PM Tasks | E35: Work order log; PM schedule; Open work order aging; Emergency work orders; Chargeable work orders; Life safety inspection certificates / binder; Vehicle service records; Fleet PM schedule | F35: =KPI_Doc_Matrix!AI174 -> 11 | G35: =KPI_Doc_Matrix!AI175 -> 3 | H35: =IF(G35>0,"Yes","No - phase 2+") -> Yes | I35: {=_xlfn.TEXTJOIN(", ",TRUE(),IF(KPI_Doc_Matrix!AI2:AI172=1,KPI_Doc_Matrix!$A$2:$A$172,""))} -> 111, 112, 116, 118, 121, 122, 123, 124, 125, 126, 171
A36: D30 | B36: Utility Bills (consumption: kWh, therms, water) | C36: Utility providers | D36: E56 Utility Consumption | E36: Utility bills; Meter readings | F36: =KPI_Doc_Matrix!AJ174 -> 1 | G36: =KPI_Doc_Matrix!AJ175 -> 0 | H36: =IF(G36>0,"Yes","No - phase 2+") -> No - phase 2+ | I36: {=_xlfn.TEXTJOIN(", ",TRUE(),IF(KPI_Doc_Matrix!AJ2:AJ172=1,KPI_Doc_Matrix!$A$2:$A$172,""))} -> 115
A37: D31 | B37: AP Invoice Register coded by Department / Cost Centre | C37: AP / Purchasing (Finance) | D37: E57 Department Non-Labor Expense | E37: Department P&L; GL department expense report; Dining supplies invoices; Parts and labor cost report; Grounds contract invoices; IT cost centre; Marketing cost centre | F37: =KPI_Doc_Matrix!AK174 -> 6 | G37: =KPI_Doc_Matrix!AK175 -> 0 | H37: =IF(G37>0,"Yes","No - phase 2+") -> No - phase 2+ | I37: {=_xlfn.TEXTJOIN(", ",TRUE(),IF(KPI_Doc_Matrix!AK2:AK172=1,KPI_Doc_Matrix!$A$2:$A$172,""))} -> 2, 3, 34, 113, 120, 164

Sheet KPI_Doc_Matrix
A1: Sr. No. | B1: KPI ID | C1: KPI Name | D1: Adoption Priority | E1: Common Elements Used | F1: No. of Documents Needed | G1: D01 | H1: D02 | I1: D03 | J1: D04 | K1: D05 | L1: D06 | M1: D07 | N1: D08 | O1: D09 | P1: D10 | Q1: D11 | R1: D12 | S1: D13 | T1: D14 | U1: D15 | V1: D16 | W1: D17 | X1: D18 | Y1: D19 | Z1: D20 | AA1: D21 | AB1: D22 | AC1: D23 | AD1: D24 | AE1: D25 | AF1: D26 | AG1: D27 | AH1: D28 | AI1: D29 | AJ1: D30 | AK1: D31
A2: 1 | B2: =INDEX(KPI_Master!$B:$B,MATCH($A2,KPI_Master!$A:$A,0)) -> DINF-01 | C2: =INDEX(KPI_Master!$D:$D,MATCH($A2,KPI_Master!$A:$A,0)) -> Raw Food Cost per Resident Day (PRD) | D2: =INDEX(KPI_Master!$K:$K,MATCH($A2,KPI_Master!$A:$A,0)) -> 1 - Core | E2: {=_xlfn.TEXTJOIN(", ",TRUE(),IF(KPI_Element_Map!$A$2:$A$287=$A2,KPI_Element_Map!$E$2:$E$287,""))} -> E58, E01 | F2: =SUM(G2:AK2) -> 2 | G2: =IF(COUNTIFS(KPI_Element_Map!$A$2:$A$287,$A2,KPI_Element_Map!$G$2:$G$287,G$1)>0,1,"") -> 1 | H2: =IF(COUNTIFS(KPI_Element_Map!$A$2:$A$287,$A2,KPI_Element_Map!$G$2:$G$287,H$1)>0,1,"") | I2: =IF(COUNTIFS(KPI_Element_Map!$A$2:$A$287,$A2,KPI_Element_Map!$G$2:$G$287,I$1)>0,1,"") -> 1 | J2: =IF(COUNTIFS(KPI_Element_Map!$A$2:$A$287,$A2,KPI_Element_Map!$G$2:$G$287,J$1)>0,1,"") | K2: =IF(COUNTIFS(KPI_Element_Map!$A$2:$A$287,$A2,KPI_Element_Map!$G$2:$G$287,K$1)>0,1,"") | L2: =IF(COUNTIFS(KPI_Element_Map!$A$2:$A$287,$A2,KPI_Element_Map!$G$2:$G$287,L$1)>0,1,"") | M2: =IF(COUNTIFS(KPI_Element_Map!$A$2:$A$287,$A2,KPI_Element_Map!$G$2:$G$287,M$1)>0,1,"") | N2: =IF(COUNTIFS(KPI_Element_Map!$A$2:$A$287,$A2,KPI_Element_Map!$G$2:$G$287,N$1)>0,1,"") | ... AK2: =IF(COUNTIFS(KPI_Element_Map!$A$2:$A$287,$A2,KPI_Element_Map!$G$2:$G$287,AK$1)>0,1,"")
A3: 2 | B3: =INDEX(KPI_Master!$B:$B,MATCH($A3,KPI_Master!$A:$A,0)) -> DINF-02 | C3: =INDEX(KPI_Master!$D:$D,MATCH($A3,KPI_Master!$A:$A,0)) -> Total Dining Cost per Resident Day | D3: =INDEX(KPI_Master!$K:$K,MATCH($A3,KPI_Master!$A:$A,0)) -> 2 - Standard | E3: {=_xlfn.TEXTJOIN(", ",TRUE(),IF(KPI_Element_Map!$A$2:$A$287=$A3,KPI_Element_Map!$E$2:$E$287,""))} -> E58, E27, E57, E01 | F3: =SUM(G3:AK3) -> 4 | G3: =IF(COUNTIFS(KPI_Element_Map!$A$2:$A$287,$A3,KPI_Element_Map!$G$2:$G$287,G$1)>0,1,"") -> 1 | H3: =IF(COUNTIFS(KPI_Element_Map!$A$2:$A$287,$A3,KPI_Element_Map!$G$2:$G$287,H$1)>0,1,"") | I3: =IF(COUNTIFS(KPI_Element_Map!$A$2:$A$287,$A3,KPI_Element_Map!$G$2:$G$287,I$1)>0,1,"") -> 1 | J3: =IF(COUNTIFS(KPI_Element_Map!$A$2:$A$287,$A3,KPI_Element_Map!$G$2:$G$287,J$1)>0,1,"") | K3: =IF(COUNTIFS(KPI_Element_Map!$A$2:$A$287,$A3,KPI_Element_Map!$G$2:$G$287,K$1)>0,1,"") | L3: =IF(COUNTIFS(KPI_Element_Map!$A$2:$A$287,$A3,KPI_Element_Map!$G$2:$G$287,L$1)>0,1,"") -> 1 | M3: =IF(COUNTIFS(KPI_Element_Map!$A$2:$A$287,$A3,KPI_Element_Map!$G$2:$G$287,M$1)>0,1,"") | N3: =IF(COUNTIFS(KPI_Element_Map!$A$2:$A$287,$A3,KPI_Element_Map!$G$2:$G$287,N$1)>0,1,"") | ... AK3: =IF(COUNTIFS(KPI_Element_Map!$A$2:$A$287,$A3,KPI_Element_Map!$G$2:$G$287,AK$1)>0,1,"") -> 1
A4: 3 | B4: =INDEX(KPI_Master!$B:$B,MATCH($A4,KPI_Master!$A:$A,0)) -> DINF-03 | C4: =INDEX(KPI_Master!$D:$D,MATCH($A4,KPI_Master!$A:$A,0)) -> Dining Labor as % of Dining Expense | D4: =INDEX(KPI_Master!$K:$K,MATCH($A4,KPI_Master!$A:$A,0)) -> 2 - Standard | E4: {=_xlfn.TEXTJOIN(", ",TRUE(),IF(KPI_Element_Map!$A$2:$A$287=$A4,KPI_Element_Map!$E$2:$E$287,""))} -> E27, E58, E57 | F4: =SUM(G4:AK4) -> 3 | G4: =IF(COUNTIFS(KPI_Element_Map!$A$2:$A$287,$A4,KPI_Element_Map!$G$2:$G$287,G$1)>0,1,"") | H4: =IF(COUNTIFS(KPI_Element_Map!$A$2:$A$287,$A4,KPI_Element_Map!$G$2:$G$287,H$1)>0,1,"") | I4: =IF(COUNTIFS(KPI_Element_Map!$A$2:$A$287,$A4,KPI_Element_Map!$G$2:$G$287,I$1)>0,1,"") -> 1 | J4: =IF(COUNTIFS(KPI_Element_Map!$A$2:$A$287,$A4,KPI_Element_Map!$G$2:$G$287,J$1)>0,1,"") | K4: =IF(COUNTIFS(KPI_Element_Map!$A$2:$A$287,$A4,KPI_Element_Map!$G$2:$G$287,K$1)>0,1,"") | L4: =IF(COUNTIFS(KPI_Element_Map!$A$2:$A$287,$A4,KPI_Element_Map!$G$2:$G$287,L$1)>0,1,"") -> 1 | M4: =IF(COUNTIFS(KPI_Element_Map!$A$2:$A$287,$A4,KPI_Element_Map!$G$2:$G$287,M$1)>0,1,"") | N4: =IF(COUNTIFS(KPI_Element_Map!$A$2:$A$287,$A4,KPI_Element_Map!$G$2:$G$287,N$1)>0,1,"") | ... AK4: =IF(COUNTIFS(KPI_Element_Map!$A$2:$A$287,$A4,KPI_Element_Map!$G$2:$G$287,AK$1)>0,1,"") -> 1
A5: 4 | B5: =INDEX(KPI_Master!$B:$B,MATCH($A5,KPI_Master!$A:$A,0)) -> DINF-04 | C5: =INDEX(KPI_Master!$D:$D,MATCH($A5,KPI_Master!$A:$A,0)) -> Meal Participation Rate | D5: =INDEX(KPI_Master!$K:$K,MATCH($A5,KPI_Master!$A:$A,0)) -> 2 - Standard | E5: {=_xlfn.TEXTJOIN(", ",TRUE(),IF(KPI_Element_Map!$A$2:$A$287=$A5,KPI_Element_Map!$E$2:$E$287,""))} -> E47, E01 | F5: =SUM(G5:AK5) -> 2 | G5: =IF(COUNTIFS(KPI_Element_Map!$A$2:$A$287,$A5,KPI_Element_Map!$G$2:$G$287,G$1)>0,1,"") -> 1 | H5: =IF(COUNTIFS(KPI_Element_Map!$A$2:$A$287,$A5,KPI_Element_Map!$G$2:$G$287,H$1)>0,1,"") | I5: =IF(COUNTIFS(KPI_Element_Map!$A$2:$A$287,$A5,KPI_Element_Map!$G$2:$G$287,I$1)>0,1,"") | J5: =IF(COUNTIFS(KPI_Element_Map!$A$2:$A$287,$A5,KPI_Element_Map!$G$2:$G$287,J$1)>0,1,"") | K5: =IF(COUNTIFS(KPI_Element_Map!$A$2:$A$287,$A5,KPI_Element_Map!$G$2:$G$287,K$1)>0,1,"") | L5: =IF(COUNTIFS(KPI_Element_Map!$A$2:$A$287,$A5,KPI_Element_Map!$G$2:$G$287,L$1)>0,1,"") | M5: =IF(COUNTIFS(KPI_Element_Map!$A$2:$A$287,$A5,KPI_Element_Map!$G$2:$G$287,M$1)>0,1,"") | N5: =IF(COUNTIFS(KPI_Element_Map!$A$2:$A$287,$A5,KPI_Element_Map!$G$2:$G$287,N$1)>0,1,"") | ... AK5: =IF(COUNTIFS(KPI_Element_Map!$A$2:$A$287,$A5,KPI_Element_Map!$G$2:$G$287,AK$1)>0,1,"")
A6: 5 | B6: =INDEX(KPI_Master!$B:$B,MATCH($A6,KPI_Master!$A:$A,0)) -> DINF-06 | C6: =INDEX(KPI_Master!$D:$D,MATCH($A6,KPI_Master!$A:$A,0)) -> Resident Dining Satisfaction Score | D6: =INDEX(KPI_Master!$K:$K,MATCH($A6,KPI_Master!$A:$A,0)) -> 1 - Core | E6: {=_xlfn.TEXTJOIN(", ",TRUE(),IF(KPI_Element_Map!$A$2:$A$287=$A6,KPI_Element_Map!$E$2:$E$287,""))} -> E36 | F6: =SUM(G6:AK6) -> 1 | G6: =IF(COUNTIFS(KPI_Element_Map!$A$2:$A$287,$A6,KPI_Element_Map!$G$2:$G$287,G$1)>0,1,"") | H6: =IF(COUNTIFS(KPI_Element_Map!$A$2:$A$287,$A6,KPI_Element_Map!$G$2:$G$287,H$1)>0,1,"") | I6: =IF(COUNTIFS(KPI_Element_Map!$A$2:$A$287,$A6,KPI_Element_Map!$G$2:$G$287,I$1)>0,1,"") | J6: =IF(COUNTIFS(KPI_Element_Map!$A$2:$A$287,$A6,KPI_Element_Map!$G$2:$G$287,J$1)>0,1,"") | K6: =IF(COUNTIFS(KPI_Element_Map!$A$2:$A$287,$A6,KPI_Element_Map!$G$2:$G$287,K$1)>0,1,"") | L6: =IF(COUNTIFS(KPI_Element_Map!$A$2:$A$287,$A6,KPI_Element_Map!$G$2:$G$287,L$1)>0,1,"") | M6: =IF(COUNTIFS(KPI_Element_Map!$A$2:$A$287,$A6,KPI_Element_Map!$G$2:$G$287,M$1)>0,1,"") | N6: =IF(COUNTIFS(KPI_Element_Map!$A$2:$A$287,$A6,KPI_Element_Map!$G$2:$G$287,N$1)>0,1,"") | ... AK6: =IF(COUNTIFS(KPI_Element_Map!$A$2:$A$287,$A6,KPI_Element_Map!$G$2:$G$287,AK$1)>0,1,"")
A7: 6 | B7: =INDEX(KPI_Master!$B:$B,MATCH($A7,KPI_Master!$A:$A,0)) -> DINF-07 | C7: =INDEX(KPI_Master!$D:$D,MATCH($A7,KPI_Master!$A:$A,0)) -> Therapeutic Diet Accuracy Rate | D7: =INDEX(KPI_Master!$K:$K,MATCH($A7,KPI_Master!$A:$A,0)) -> 2 - Standard | E7: {=_xlfn.TEXTJOIN(", ",TRUE(),IF(KPI_Element_Map!$A$2:$A$287=$A7,KPI_Element_Map!$E$2:$E$287,""))} -> E45 | F7: =SUM(G7:AK7) -> 1 | G7: =IF(COUNTIFS(KPI_Element_Map!$A$2:$A$287,$A7,KPI_Element_Map!$G$2:$G$287,G$1)>0,1,"") | H7: =IF(COUNTIFS(KPI_Element_Map!$A$2:$A$287,$A7,KPI_Element_Map!$G$2:$G$287,H$1)>0,1,"") | I7: =IF(COUNTIFS(KPI_Element_Map!$A$2:$A$287,$A7,KPI_Element_Map!$G$2:$G$287,I$1)>0,1,"") | J7: =IF(COUNTIFS(KPI_Element_Map!$A$2:$A$287,$A7,KPI_Element_Map!$G$2:$G$287,J$1)>0,1,"") | K7: =IF(COUNTIFS(KPI_Element_Map!$A$2:$A$287,$A7,KPI_Element_Map!$G$2:$G$287,K$1)>0,1,"") | L7: =IF(COUNTIFS(KPI_Element_Map!$A$2:$A$287,$A7,KPI_Element_Map!$G$2:$G$287,L$1)>0,1,"") | M7: =IF(COUNTIFS(KPI_Element_Map!$A$2:$A$287,$A7,KPI_Element_Map!$G$2:$G$287,M$1)>0,1,"") | N7: =IF(COUNTIFS(KPI_Element_Map!$A$2:$A$287,$A7,KPI_Element_Map!$G$2:$G$287,N$1)>0,1,"") | ... AK7: =IF(COUNTIFS(KPI_Element_Map!$A$2:$A$287,$A7,KPI_Element_Map!$G$2:$G$287,AK$1)>0,1,"")
A8: 7 | B8: =INDEX(KPI_Master!$B:$B,MATCH($A8,KPI_Master!$A:$A,0)) -> DINF-08 | C8: =INDEX(KPI_Master!$D:$D,MATCH($A8,KPI_Master!$A:$A,0)) -> Food Safety / Sanitation Audit Score | D8: =INDEX(KPI_Master!$K:$K,MATCH($A8,KPI_Master!$A:$A,0)) -> 2 - Standard | E8: {=_xlfn.TEXTJOIN(", ",TRUE(),IF(KPI_Element_Map!$A$2:$A$287=$A8,KPI_Element_Map!$E$2:$E$287,""))} -> E45 | F8: =SUM(G8:AK8) -> 1 | G8: =IF(COUNTIFS(KPI_Element_Map!$A$2:$A$287,$A8,KPI_Element_Map!$G$2:$G$287,G$1)>0,1,"") | H8: =IF(COUNTIFS(KPI_Element_Map!$A$2:$A$287,$A8,KPI_Element_Map!$G$2:$G$287,H$1)>0,1,"") | I8: =IF(COUNTIFS(KPI_Element_Map!$A$2:$A$287,$A8,KPI_Element_Map!$G$2:$G$287,I$1)>0,1,"") | J8: =IF(COUNTIFS(KPI_Element_Map!$A$2:$A$287,$A8,KPI_Element_Map!$G$2:$G$287,J$1)>0,1,"") | K8: =IF(COUNTIFS(KPI_Element_Map!$A$2:$A$287,$A8,KPI_Element_Map!$G$2:$G$287,K$1)>0,1,"") | L8: =IF(COUNTIFS(KPI_Element_Map!$A$2:$A$287,$A8,KPI_Element_Map!$G$2:$G$287,L$1)>0,1,"") | M8: =IF(COUNTIFS(KPI_Element_Map!$A$2:$A$287,$A8,KPI_Element_Map!$G$2:$G$287,M$1)>0,1,"") | N8: =IF(COUNTIFS(KPI_Element_Map!$A$2:$A$287,$A8,KPI_Element_Map!$G$2:$G$287,N$1)>0,1,"") | ... AK8: =IF(COUNTIFS(KPI_Element_Map!$A$2:$A$287,$A8,KPI_Element_Map!$G$2:$G$287,AK$1)>0,1,"")
A9: 8 | B9: =INDEX(KPI_Master!$B:$B,MATCH($A9,KPI_Master!$A:$A,0)) -> DINF-12 | C9: =INDEX(KPI_Master!$D:$D,MATCH($A9,KPI_Master!$A:$A,0)) -> Nutritional Assessment Completion Rate | D9: =INDEX(KPI_Master!$K:$K,MATCH($A9,KPI_Master!$A:$A,0)) -> 2 - Standard | E9: {=_xlfn.TEXTJOIN(", ",TRUE(),IF(KPI_Element_Map!$A$2:$A$287=$A9,KPI_Element_Map!$E$2:$E$287,""))} -> E40 | F9: =SUM(G9:AK9) -> 1 | G9: =IF(COUNTIFS(KPI_Element_Map!$A$2:$A$287,$A9,KPI_Element_Map!$G$2:$G$287,G$1)>0,1,"") | H9: =IF(COUNTIFS(KPI_Element_Map!$A$2:$A$287,$A9,KPI_Element_Map!$G$2:$G$287,H$1)>0,1,"") | I9: =IF(COUNTIFS(KPI_Element_Map!$A$2:$A$287,$A9,KPI_Element_Map!$G$2:$G$287,I$1)>0,1,"") | J9: =IF(COUNTIFS(KPI_Element_Map!$A$2:$A$287,$A9,KPI_Element_Map!$G$2:$G$287,J$1)>0,1,"") | K9: =IF(COUNTIFS(KPI_Element_Map!$A$2:$A$287,$A9,KPI_Element_Map!$G$2:$G$287,K$1)>0,1,"") | L9: =IF(COUNTIFS(KPI_Element_Map!$A$2:$A$287,$A9,KPI_Element_Map!$G$2:$G$287,L$1)>0,1,"") | M9: =IF(COUNTIFS(KPI_Element_Map!$A$2:$A$287,$A9,KPI_Element_Map!$G$2:$G$287,M$1)>0,1,"") | N9: =IF(COUNTIFS(KPI_Element_Map!$A$2:$A$287,$A9,KPI_Element_Map!$G$2:$G$287,N$1)>0,1,"") | ... AK9: =IF(COUNTIFS(KPI_Element_Map!$A$2:$A$287,$A9,KPI_Element_Map!$G$2:$G$287,AK$1)>0,1,"")
A10: 9 | B10: =INDEX(KPI_Master!$B:$B,MATCH($A10,KPI_Master!$A:$A,0)) -> DINF-13 | C10: =INDEX(KPI_Master!$D:$D,MATCH($A10,KPI_Master!$A:$A,0)) -> Hydration Monitoring Compliance Rate | D10: =INDEX(KPI_Master!$K:$K,MATCH($A10,KPI_Master!$A:$A,0)) -> 2 - Standard | E10: {=_xlfn.TEXTJOIN(", ",TRUE(),IF(KPI_Element_Map!$A$2:$A$287=$A10,KPI_Element_Map!$E$2:$E$287,""))} -> E39 | F10: =SUM(G10:AK10) -> 1 | G10: =IF(COUNTIFS(KPI_Element_Map!$A$2:$A$287,$A10,KPI_Element_Map!$G$2:$G$287,G$1)>0,1,"") | H10: =IF(COUNTIFS(KPI_Element_Map!$A$2:$A$287,$A10,KPI_Element_Map!$G$2:$G$287,H$1)>0,1,"") | I10: =IF(COUNTIFS(KPI_Element_Map!$A$2:$A$287,$A10,KPI_Element_Map!$G$2:$G$287,I$1)>0,1,"") | J10: =IF(COUNTIFS(KPI_Element_Map!$A$2:$A$287,$A10,KPI_Element_Map!$G$2:$G$287,J$1)>0,1,"") | K10: =IF(COUNTIFS(KPI_Element_Map!$A$2:$A$287,$A10,KPI_Element_Map!$G$2:$G$287,K$1)>0,1,"") | L10: =IF(COUNTIFS(KPI_Element_Map!$A$2:$A$287,$A10,KPI_Element_Map!$G$2:$G$287,L$1)>0,1,"") | M10: =IF(COUNTIFS(KPI_Element_Map!$A$2:$A$287,$A10,KPI_Element_Map!$G$2:$G$287,M$1)>0,1,"") | N10: =IF(COUNTIFS(KPI_Element_Map!$A$2:$A$287,$A10,KPI_Element_Map!$G$2:$G$287,N$1)>0,1,"") | ... AK10: =IF(COUNTIFS(KPI_Element_Map!$A$2:$A$287,$A10,KPI_Element_Map!$G$2:$G$287,AK$1)>0,1,"")
A11: 10 | B11: =INDEX(KPI_Master!$B:$B,MATCH($A11,KPI_Master!$A:$A,0)) -> DINF-14 | C11: =INDEX(KPI_Master!$D:$D,MATCH($A11,KPI_Master!$A:$A,0)) -> Raw Food Cost per Meal | D11: =INDEX(KPI_Master!$K:$K,MATCH($A11,KPI_Master!$A:$A,0)) -> 2 - Standard | E11: {=_xlfn.TEXTJOIN(", ",TRUE(),IF(KPI_Element_Map!$A$2:$A$287=$A11,KPI_Element_Map!$E$2:$E$287,""))} -> E58, E47 | F11: =SUM(G11:AK11) -> 2 | G11: =IF(COUNTIFS(KPI_Element_Map!$A$2:$A$287,$A11,KPI_Element_Map!$G$2:$G$287,G$1)>0,1,"") | H11: =IF(COUNTIFS(KPI_Element_Map!$A$2:$A$287,$A11,KPI_Element_Map!$G$2:$G$287,H$1)>0,1,"") | I11: =IF(COUNTIFS(KPI_Element_Map!$A$2:$A$287,$A11,KPI_Element_Map!$G$2:$G$287,I$1)>0,1,"") -> 1 | J11: =IF(COUNTIFS(KPI_Element_Map!$A$2:$A$287,$A11,KPI_Element_Map!$G$2:$G$287,J$1)>0,1,"") | K11: =IF(COUNTIFS(KPI_Element_Map!$A$2:$A$287,$A11,KPI_Element_Map!$G$2:$G$287,K$1)>0,1,"") | L11: =IF(COUNTIFS(KPI_Element_Map!$A$2:$A$287,$A11,KPI_Element_Map!$G$2:$G$287,L$1)>0,1,"") | M11: =IF(COUNTIFS(KPI_Element_Map!$A$2:$A$287,$A11,KPI_Element_Map!$G$2:$G$287,M$1)>0,1,"") | N11: =IF(COUNTIFS(KPI_Element_Map!$A$2:$A$287,$A11,KPI_Element_Map!$G$2:$G$287,N$1)>0,1,"") | ... AK11: =IF(COUNTIFS(KPI_Element_Map!$A$2:$A$287,$A11,KPI_Element_Map!$G$2:$G$287,AK$1)>0,1,"")
A12: 11 | B12: =INDEX(KPI_Master!$B:$B,MATCH($A12,KPI_Master!$A:$A,0)) -> DINF-15 | C12: =INDEX(KPI_Master!$D:$D,MATCH($A12,KPI_Master!$A:$A,0)) -> Meals per Labor Hour | D12: =INDEX(KPI_Master!$K:$K,MATCH($A12,KPI_Master!$A:$A,0)) -> 2 - Standard | E12: {=_xlfn.TEXTJOIN(", ",TRUE(),IF(KPI_Element_Map!$A$2:$A$287=$A12,KPI_Element_Map!$E$2:$E$287,""))} -> E47, E26 | F12: =SUM(G12:AK12) -> 2 | G12: =IF(COUNTIFS(KPI_Element_Map!$A$2:$A$287,$A12,KPI_Element_Map!$G$2:$G$287,G$1)>0,1,"") | H12: =IF(COUNTIFS(KPI_Element_Map!$A$2:$A$287,$A12,KPI_Element_Map!$G$2:$G$287,H$1)>0,1,"") | I12: =IF(COUNTIFS(KPI_Element_Map!$A$2:$A$287,$A12,KPI_Element_Map!$G$2:$G$287,I$1)>0,1,"") | J12: =IF(COUNTIFS(KPI_Element_Map!$A$2:$A$287,$A12,KPI_Element_Map!$G$2:$G$287,J$1)>0,1,"") | K12: =IF(COUNTIFS(KPI_Element_Map!$A$2:$A$287,$A12,KPI_Element_Map!$G$2:$G$287,K$1)>0,1,"") | L12: =IF(COUNTIFS(KPI_Element_Map!$A$2:$A$287,$A12,KPI_Element_Map!$G$2:$G$287,L$1)>0,1,"") -> 1 | M12: =IF(COUNTIFS(KPI_Element_Map!$A$2:$A$287,$A12,KPI_Element_Map!$G$2:$G$287,M$1)>0,1,"") | N12: =IF(COUNTIFS(KPI_Element_Map!$A$2:$A$287,$A12,KPI_Element_Map!$G$2:$G$287,N$1)>0,1,"") | ... AK12: =IF(COUNTIFS(KPI_Element_Map!$A$2:$A$287,$A12,KPI_Element_Map!$G$2:$G$287,AK$1)>0,1,"")
A13: 12 | B13: =INDEX(KPI_Master!$B:$B,MATCH($A13,KPI_Master!$A:$A,0)) -> FINA-01 | C13: =INDEX(KPI_Master!$D:$D,MATCH($A13,KPI_Master!$A:$A,0)) -> Occupancy Rate | D13: =INDEX(KPI_Master!$K:$K,MATCH($A13,KPI_Master!$A:$A,0)) -> 1 - Core | E13: {=_xlfn.TEXTJOIN(", ",TRUE(),IF(KPI_Element_Map!$A$2:$A$287=$A13,KPI_Element_Map!$E$2:$E$287,""))} -> E02, E11 | F13: =SUM(G13:AK13) -> 2 | G13: =IF(COUNTIFS(KPI_Element_Map!$A$2:$A$287,$A13,KPI_Element_Map!$G$2:$G$287,G$1)>0,1,"") -> 1 | H13: =IF(COUNTIFS(KPI_Element_Map!$A$2:$A$287,$A13,KPI_Element_Map!$G$2:$G$287,H$1)>0,1,"") -> 1 | I13: =IF(COUNTIFS(KPI_Element_Map!$A$2:$A$287,$A13,KPI_Element_Map!$G$2:$G$287,I$1)>0,1,"") | J13: =IF(COUNTIFS(KPI_Element_Map!$A$2:$A$287,$A13,KPI_Element_Map!$G$2:$G$287,J$1)>0,1,"") | K13: =IF(COUNTIFS(KPI_Element_Map!$A$2:$A$287,$A13,KPI_Element_Map!$G$2:$G$287,K$1)>0,1,"") | L13: =IF(COUNTIFS(KPI_Element_Map!$A$2:$A$287,$A13,KPI_Element_Map!$G$2:$G$287,L$1)>0,1,"") | M13: =IF(COUNTIFS(KPI_Element_Map!$A$2:$A$287,$A13,KPI_Element_Map!$G$2:$G$287,M$1)>0,1,"") | N13: =IF(COUNTIFS(KPI_Element_Map!$A$2:$A$287,$A13,KPI_Element_Map!$G$2:$G$287,N$1)>0,1,"") | ... AK13: =IF(COUNTIFS(KPI_Element_Map!$A$2:$A$287,$A13,KPI_Element_Map!$G$2:$G$287,AK$1)>0,1,"")
... A172: 171 | B172: =INDEX(KPI_Master!$B:$B,MATCH($A172,KPI_Master!$A:$A,0)) -> TRA-07 | C172: =INDEX(KPI_Master!$D:$D,MATCH($A172,KPI_Master!$A:$A,0)) -> Vehicle Preventive Maintenance Compliance | D172: =INDEX(KPI_Master!$K:$K,MATCH($A172,KPI_Master!$A:$A,0)) -> 2 - Standard | E172: {=_xlfn.TEXTJOIN(", ",TRUE(),IF(KPI_Element_Map!$A$2:$A$287=$A172,KPI_Element_Map!$E$2:$E$287,""))} -> E55 | F172: =SUM(G172:AK172) -> 1 | G172: =IF(COUNTIFS(KPI_Element_Map!$A$2:$A$287,$A172,KPI_Element_Map!$G$2:$G$287,G$1)>0,1,"") | H172: =IF(COUNTIFS(KPI_Element_Map!$A$2:$A$287,$A172,KPI_Element_Map!$G$2:$G$287,H$1)>0,1,"") | I172: =IF(COUNTIFS(KPI_Element_Map!$A$2:$A$287,$A172,KPI_Element_Map!$G$2:$G$287,I$1)>0,1,"") | J172: =IF(COUNTIFS(KPI_Element_Map!$A$2:$A$287,$A172,KPI_Element_Map!$G$2:$G$287,J$1)>0,1,"") | K172: =IF(COUNTIFS(KPI_Element_Map!$A$2:$A$287,$A172,KPI_Element_Map!$G$2:$G$287,K$1)>0,1,"") | L172: =IF(COUNTIFS(KPI_Element_Map!$A$2:$A$287,$A172,KPI_Element_Map!$G$2:$G$287,L$1)>0,1,"") | M172: =IF(COUNTIFS(KPI_Element_Map!$A$2:$A$287,$A172,KPI_Element_Map!$G$2:$G$287,M$1)>0,1,"") | N172: =IF(COUNTIFS(KPI_Element_Map!$A$2:$A$287,$A172,KPI_Element_Map!$G$2:$G$287,N$1)>0,1,"") | ... AK172: =IF(COUNTIFS(KPI_Element_Map!$A$2:$A$287,$A172,KPI_Element_Map!$G$2:$G$287,AK$1)>0,1,"")
C174: KPIs using this document (all tiers) | G174: =SUM(G2:G172) -> 43 | H174: =SUM(H2:H172) -> 17 | I174: =SUM(I2:I172) -> 33 | J174: =SUM(J2:J172) -> 5 | K174: =SUM(K2:K172) -> 2 | L174: =SUM(L2:L172) -> 26 | M174: =SUM(M2:M172) -> 4 | N174: =SUM(N2:N172) -> 7 | ... AK174: =SUM(AK2:AK172) -> 6
C175: KPIs using this document (Tier 1 - Core) | G175: =COUNTIFS(G2:G172,1,$D$2:$D$172,"1 - Core") -> 10 | H175: =COUNTIFS(H2:H172,1,$D$2:$D$172,"1 - Core") -> 1 | I175: =COUNTIFS(I2:I172,1,$D$2:$D$172,"1 - Core") -> 6 | J175: =COUNTIFS(J2:J172,1,$D$2:$D$172,"1 - Core") -> 3 | K175: =COUNTIFS(K2:K172,1,$D$2:$D$172,"1 - Core") -> 1 | L175: =COUNTIFS(L2:L172,1,$D$2:$D$172,"1 - Core") -> 2 | M175: =COUNTIFS(M2:M172,1,$D$2:$D$172,"1 - Core") -> 0 | N175: =COUNTIFS(N2:N172,1,$D$2:$D$172,"1 - Core") -> 2 | ... AK175: =COUNTIFS(AK2:AK172,1,$D$2:$D$172,"1 - Core") -> 0

Sheet KPI_Element_Map
A1: Sr. No. | B1: KPI ID | C1: KPI Name | D1: Adoption Priority | E1: Element ID | F1: Common Data Element | G1: Doc ID | H1: Single Source Document
A2: 1 | B2: =INDEX(KPI_Master!$B:$B,MATCH($A2,KPI_Master!$A:$A,0)) -> DINF-01 | C2: =INDEX(KPI_Master!$D:$D,MATCH($A2,KPI_Master!$A:$A,0)) -> Raw Food Cost per Resident Day (PRD) | D2: =INDEX(KPI_Master!$K:$K,MATCH($A2,KPI_Master!$A:$A,0)) -> 1 - Core | E2: E58 | F2: =INDEX(Common_Formula_Elements!$B:$B,MATCH($E2,Common_Formula_Elements!$A:$A,0)) -> Food Purchase Cost | G2: =INDEX(Common_Formula_Elements!$G:$G,MATCH($E2,Common_Formula_Elements!$A:$A,0)) -> D03 | H2: =INDEX(Minimum_Documents!$B:$B,MATCH($G2,Minimum_Documents!$A:$A,0)) -> Monthly Financial Statement Package - consolidated (P&L with budget, balance sheet, cash flow, trial balance; no department split needed)
A3: 1 | B3: =INDEX(KPI_Master!$B:$B,MATCH($A3,KPI_Master!$A:$A,0)) -> DINF-01 | C3: =INDEX(KPI_Master!$D:$D,MATCH($A3,KPI_Master!$A:$A,0)) -> Raw Food Cost per Resident Day (PRD) | D3: =INDEX(KPI_Master!$K:$K,MATCH($A3,KPI_Master!$A:$A,0)) -> 1 - Core | E3: E01 | F3: =INDEX(Common_Formula_Elements!$B:$B,MATCH($E3,Common_Formula_Elements!$A:$A,0)) -> Total Resident Days | G3: =INDEX(Common_Formula_Elements!$G:$G,MATCH($E3,Common_Formula_Elements!$A:$A,0)) -> D01 | H3: =INDEX(Minimum_Documents!$B:$B,MATCH($G3,Minimum_Documents!$A:$A,0)) -> Census & ADT Register
A4: 2 | B4: =INDEX(KPI_Master!$B:$B,MATCH($A4,KPI_Master!$A:$A,0)) -> DINF-02 | C4: =INDEX(KPI_Master!$D:$D,MATCH($A4,KPI_Master!$A:$A,0)) -> Total Dining Cost per Resident Day | D4: =INDEX(KPI_Master!$K:$K,MATCH($A4,KPI_Master!$A:$A,0)) -> 2 - Standard | E4: E58 | F4: =INDEX(Common_Formula_Elements!$B:$B,MATCH($E4,Common_Formula_Elements!$A:$A,0)) -> Food Purchase Cost | G4: =INDEX(Common_Formula_Elements!$G:$G,MATCH($E4,Common_Formula_Elements!$A:$A,0)) -> D03 | H4: =INDEX(Minimum_Documents!$B:$B,MATCH($G4,Minimum_Documents!$A:$A,0)) -> Monthly Financial Statement Package - consolidated (P&L with budget, balance sheet, cash flow, trial balance; no department split needed)
A5: 2 | B5: =INDEX(KPI_Master!$B:$B,MATCH($A5,KPI_Master!$A:$A,0)) -> DINF-02 | C5: =INDEX(KPI_Master!$D:$D,MATCH($A5,KPI_Master!$A:$A,0)) -> Total Dining Cost per Resident Day | D5: =INDEX(KPI_Master!$K:$K,MATCH($A5,KPI_Master!$A:$A,0)) -> 2 - Standard | E5: E27 | F5: =INDEX(Common_Formula_Elements!$B:$B,MATCH($E5,Common_Formula_Elements!$A:$A,0)) -> Wages by Job Class / Department | G5: =INDEX(Common_Formula_Elements!$G:$G,MATCH($E5,Common_Formula_Elements!$A:$A,0)) -> D06 | H5: =INDEX(Minimum_Documents!$B:$B,MATCH($G5,Minimum_Documents!$A:$A,0)) -> Payroll Register (hours and wages by employee, job class and department)
A6: 2 | B6: =INDEX(KPI_Master!$B:$B,MATCH($A6,KPI_Master!$A:$A,0)) -> DINF-02 | C6: =INDEX(KPI_Master!$D:$D,MATCH($A6,KPI_Master!$A:$A,0)) -> Total Dining Cost per Resident Day | D6: =INDEX(KPI_Master!$K:$K,MATCH($A6,KPI_Master!$A:$A,0)) -> 2 - Standard | E6: E57 | F6: =INDEX(Common_Formula_Elements!$B:$B,MATCH($E6,Common_Formula_Elements!$A:$A,0)) -> Department Non-Labor Expense | G6: =INDEX(Common_Formula_Elements!$G:$G,MATCH($E6,Common_Formula_Elements!$A:$A,0)) -> D31 | H6: =INDEX(Minimum_Documents!$B:$B,MATCH($G6,Minimum_Documents!$A:$A,0)) -> AP Invoice Register coded by Department / Cost Centre
A7: 2 | B7: =INDEX(KPI_Master!$B:$B,MATCH($A7,KPI_Master!$A:$A,0)) -> DINF-02 | C7: =INDEX(KPI_Master!$D:$D,MATCH($A7,KPI_Master!$A:$A,0)) -> Total Dining Cost per Resident Day | D7: =INDEX(KPI_Master!$K:$K,MATCH($A7,KPI_Master!$A:$A,0)) -> 2 - Standard | E7: E01 | F7: =INDEX(Common_Formula_Elements!$B:$B,MATCH($E7,Common_Formula_Elements!$A:$A,0)) -> Total Resident Days | G7: =INDEX(Common_Formula_Elements!$G:$G,MATCH($E7,Common_Formula_Elements!$A:$A,0)) -> D01 | H7: =INDEX(Minimum_Documents!$B:$B,MATCH($G7,Minimum_Documents!$A:$A,0)) -> Census & ADT Register
A8: 3 | B8: =INDEX(KPI_Master!$B:$B,MATCH($A8,KPI_Master!$A:$A,0)) -> DINF-03 | C8: =INDEX(KPI_Master!$D:$D,MATCH($A8,KPI_Master!$A:$A,0)) -> Dining Labor as % of Dining Expense | D8: =INDEX(KPI_Master!$K:$K,MATCH($A8,KPI_Master!$A:$A,0)) -> 2 - Standard | E8: E27 | F8: =INDEX(Common_Formula_Elements!$B:$B,MATCH($E8,Common_Formula_Elements!$A:$A,0)) -> Wages by Job Class / Department | G8: =INDEX(Common_Formula_Elements!$G:$G,MATCH($E8,Common_Formula_Elements!$A:$A,0)) -> D06 | H8: =INDEX(Minimum_Documents!$B:$B,MATCH($G8,Minimum_Documents!$A:$A,0)) -> Payroll Register (hours and wages by employee, job class and department)
A9: 3 | B9: =INDEX(KPI_Master!$B:$B,MATCH($A9,KPI_Master!$A:$A,0)) -> DINF-03 | C9: =INDEX(KPI_Master!$D:$D,MATCH($A9,KPI_Master!$A:$A,0)) -> Dining Labor as % of Dining Expense | D9: =INDEX(KPI_Master!$K:$K,MATCH($A9,KPI_Master!$A:$A,0)) -> 2 - Standard | E9: E58 | F9: =INDEX(Common_Formula_Elements!$B:$B,MATCH($E9,Common_Formula_Elements!$A:$A,0)) -> Food Purchase Cost | G9: =INDEX(Common_Formula_Elements!$G:$G,MATCH($E9,Common_Formula_Elements!$A:$A,0)) -> D03 | H9: =INDEX(Minimum_Documents!$B:$B,MATCH($G9,Minimum_Documents!$A:$A,0)) -> Monthly Financial Statement Package - consolidated (P&L with budget, balance sheet, cash flow, trial balance; no department split needed)
A10: 3 | B10: =INDEX(KPI_Master!$B:$B,MATCH($A10,KPI_Master!$A:$A,0)) -> DINF-03 | C10: =INDEX(KPI_Master!$D:$D,MATCH($A10,KPI_Master!$A:$A,0)) -> Dining Labor as % of Dining Expense | D10: =INDEX(KPI_Master!$K:$K,MATCH($A10,KPI_Master!$A:$A,0)) -> 2 - Standard | E10: E57 | F10: =INDEX(Common_Formula_Elements!$B:$B,MATCH($E10,Common_Formula_Elements!$A:$A,0)) -> Department Non-Labor Expense | G10: =INDEX(Common_Formula_Elements!$G:$G,MATCH($E10,Common_Formula_Elements!$A:$A,0)) -> D31 | H10: =INDEX(Minimum_Documents!$B:$B,MATCH($G10,Minimum_Documents!$A:$A,0)) -> AP Invoice Register coded by Department / Cost Centre
A11: 4 | B11: =INDEX(KPI_Master!$B:$B,MATCH($A11,KPI_Master!$A:$A,0)) -> DINF-04 | C11: =INDEX(KPI_Master!$D:$D,MATCH($A11,KPI_Master!$A:$A,0)) -> Meal Participation Rate | D11: =INDEX(KPI_Master!$K:$K,MATCH($A11,KPI_Master!$A:$A,0)) -> 2 - Standard | E11: E47 | F11: =INDEX(Common_Formula_Elements!$B:$B,MATCH($E11,Common_Formula_Elements!$A:$A,0)) -> Meals Served | G11: =INDEX(Common_Formula_Elements!$G:$G,MATCH($E11,Common_Formula_Elements!$A:$A,0)) -> D22 | H11: =INDEX(Minimum_Documents!$B:$B,MATCH($G11,Minimum_Documents!$A:$A,0)) -> Meal Count / POS Report
A12: 4 | B12: =INDEX(KPI_Master!$B:$B,MATCH($A12,KPI_Master!$A:$A,0)) -> DINF-04 | C12: =INDEX(KPI_Master!$D:$D,MATCH($A12,KPI_Master!$A:$A,0)) -> Meal Participation Rate | D12: =INDEX(KPI_Master!$K:$K,MATCH($A12,KPI_Master!$A:$A,0)) -> 2 - Standard | E12: E01 | F12: =INDEX(Common_Formula_Elements!$B:$B,MATCH($E12,Common_Formula_Elements!$A:$A,0)) -> Total Resident Days | G12: =INDEX(Common_Formula_Elements!$G:$G,MATCH($E12,Common_Formula_Elements!$A:$A,0)) -> D01 | H12: =INDEX(Minimum_Documents!$B:$B,MATCH($G12,Minimum_Documents!$A:$A,0)) -> Census & ADT Register
A13: 5 | B13: =INDEX(KPI_Master!$B:$B,MATCH($A13,KPI_Master!$A:$A,0)) -> DINF-06 | C13: =INDEX(KPI_Master!$D:$D,MATCH($A13,KPI_Master!$A:$A,0)) -> Resident Dining Satisfaction Score | D13: =INDEX(KPI_Master!$K:$K,MATCH($A13,KPI_Master!$A:$A,0)) -> 1 - Core | E13: E36 | F13: =INDEX(Common_Formula_Elements!$B:$B,MATCH($E13,Common_Formula_Elements!$A:$A,0)) -> Survey Ratings & Response Counts | G13: =INDEX(Common_Formula_Elements!$G:$G,MATCH($E13,Common_Formula_Elements!$A:$A,0)) -> D12 | H13: =INDEX(Minimum_Documents!$B:$B,MATCH($G13,Minimum_Documents!$A:$A,0)) -> Satisfaction & Engagement Survey Results (resident, family, employee)
... A287: 171 | B287: =INDEX(KPI_Master!$B:$B,MATCH($A287,KPI_Master!$A:$A,0)) -> TRA-07 | C287: =INDEX(KPI_Master!$D:$D,MATCH($A287,KPI_Master!$A:$A,0)) -> Vehicle Preventive Maintenance Compliance | D287: =INDEX(KPI_Master!$K:$K,MATCH($A287,KPI_Master!$A:$A,0)) -> 2 - Standard | E287: E55 | F287: =INDEX(Common_Formula_Elements!$B:$B,MATCH($E287,Common_Formula_Elements!$A:$A,0)) -> Work Orders & PM Tasks | G287: =INDEX(Common_Formula_Elements!$G:$G,MATCH($E287,Common_Formula_Elements!$A:$A,0)) -> D29 | H287: =INDEX(Minimum_Documents!$B:$B,MATCH($G287,Minimum_Documents!$A:$A,0)) -> CMMS Work Order & PM Report (incl. life-safety and vehicle PM tasks)

Sheet v9_Gap_List
A1: v9 KPIs Not Fully Covered by This File
A2: v9 measures with no equivalent in KPI_Master (Not in file) or only a similar in-house version (Partial match). Grey cells are proposed Frequency / Tier / Priority - edit as needed.
A3: Not in file | B3: =COUNTIF($F$6:$F$30,"Not in file") -> 5 | C3: Partial match | D3: =COUNTIF($F$6:$F$30,"Partial match") -> 20 | E3: Total | F3: =COUNTA($A$6:$A$30) -> 25
A5: v9 Code | B5: v9 KPI | C5: v9 Department | D5: What It Measures (v9) | E5: Care Levels (v9) | F5: Status | G5: Closest KPI ID (this file) | H5: Closest KPI Name (this file) | I5: Gap vs Closest KPI | J5: v9 Data Source (Intake) | K5: Additional Report Needed? | L5: Frequency | M5: Dashboard Tier | N5: Adoption Priority | O5: Basis for Assignment
A6: SAL-01 | B6: Inquiries per 100 Units per Month | C6: Sales and Marketing | D6: Total inquiries / (units / 100) / months in period | E6: IL, AL, MC | F6: Partial match | G6: SALM-01 | H6: =IFERROR(INDEX(KPI_Master!$D:$D,MATCH(G6,KPI_Master!$B:$B,0)),"Not found") -> Lead Volume (New Inquiries) | I6: SALM-01 is a raw lead count; v9 normalizes per 100 units per month | J6: Sales / CRM report (Screen 09) + months in period (Screen 10) | K6: No - SALM-01 data plus unit count | L6: Monthly | M6: Executive | N6: 1 - Core | O6: Normalized version of a Core KPI (SALM-01); monthly per v9 definition
A7: SAL-05 | B7: Tour-to-Move-In Conversion Rate | C7: Sales and Marketing | D7: Move-ins / tours | E7: IL, AL, MC | F7: Partial match | G7: SALM-03 | H7: =IFERROR(INDEX(KPI_Master!$D:$D,MATCH(G7,KPI_Master!$B:$B,0)),"Not found") -> Tour to Deposit Conversion Rate | I7: This file has Tour-to-Deposit (SALM-03) and Deposit-to-Move-In (SALM-22), but not Tour-to-Move-In | J7: Sales / CRM report (Screen 09) | K7: No - same CRM report as SALM-03 / SALM-22 | L7: Monthly | M7: Executive | N7: 1 - Core | O7: Matches SALM-03 (Core, Executive)
A8: SAL-06 | B8: Inquiry Channel Mix | C8: Sales and Marketing | D8: Share of inquiries by channel: web, paid, unpaid referral, call-in | E8: IL, AL, MC | F8: Partial match | G8: SALM-14 | H8: =IFERROR(INDEX(KPI_Master!$D:$D,MATCH(G8,KPI_Master!$B:$B,0)),"Not found") -> Referral Source Contribution | I8: SALM-14 measures referral source contribution; v9 wants share of all inquiries by channel | J8: Sales / CRM report (Screen 09) | K8: Maybe - needs channel field on the CRM inquiry report | L8: Monthly | M8: Operational | N8: 2 - Standard | O8: Matches SALM-14
A9: SAL-07 | B9: Inquiry-to-Tour Conversion by Channel | C9: Sales and Marketing | D9: Tours / inquiries computed separately for each acquisition channel | E9: IL, AL, MC | F9: Not in file | G9: SALM-02 | H9: =IFERROR(INDEX(KPI_Master!$D:$D,MATCH(G9,KPI_Master!$B:$B,0)),"Not found") -> Lead to Tour Conversion Rate | I9: No channel-level conversion in this file; SALM-02 is total lead-to-tour only | J9: Sales / CRM report (Screen 09) | K9: Maybe - needs channel field on the CRM inquiry report | L9: Monthly | M9: Operational | N9: 3 - Optional | O9: Diagnostic breakdown of SALM-02
A10: SAL-11 | B10: Cost per Acquired Resident | C10: Sales and Marketing | D10: Total sales and marketing spend / move-ins | E10: IL, AL, MC, SNF | F10: Not in file | G10: SALM-18 | H10: =IFERROR(INDEX(KPI_Master!$D:$D,MATCH(G10,KPI_Master!$B:$B,0)),"Not found") -> Marketing Cost as % of Operating Expense | I10: SALM-18 is marketing cost as % of opex; no cost per move-in | J10: TO BE MAPPED - added from Gap Matrix v9; intake screen not yet assigned | K10: No - GL marketing spend plus move-ins from CRM | L10: Monthly | M10: Executive | N10: 2 - Standard | O10: Efficiency measure paired with SALM-18 and move-ins
A11: NUR-05 | B11: Resident Acuity and Care Tier Mix | C11: Nursing | D11: Distribution of residents across care tiers or point bands, with period-over-period migration | E11: AL, MC | F11: Partial match | G11: NURC-16 | H11: =IFERROR(INDEX(KPI_Master!$D:$D,MATCH(G11,KPI_Master!$B:$B,0)),"Not found") -> Average Acuity Score per Resident | I11: NURC-16 is an average acuity score; v9 wants distribution across care tiers plus migration | J11: Clinical / EHR report + census report (Screen 09) | K11: No - same EHR / census report as NURC-16 | L11: Monthly | M11: Operational | N11: 2 - Standard | O11: Raised from NURC-16 (Optional) because v9 uses it for AL / MC level-of-care pricing
A12: SNF-H2 | B12: Standard Survey Deficiency Points by Scope and Severity | C12: Skilled Nursing | D12: Sum of Table 1 point values for every cited deficiency on the two most recent standard surveys | E12: SNF | F12: Partial match | G12: QUAC-01 | H12: =IFERROR(INDEX(KPI_Master!$D:$D,MATCH(G12,KPI_Master!$B:$B,0)),"Not found") -> Survey Deficiency Count | I12: QUAC-01 counts deficiencies; v9 applies CMS scope/severity point values | J12: Tool-fetched from CMS | K12: No - CMS survey data already fetched for QUAC-20 | L12: Per survey | M12: Operational | N12: 2 - Standard | O12: Component of QUAC-17, same as QUAC-20
A13: SNF-S1 | B13: Case-Mix Adjusted Total Nurse Staffing HPRD | C13: Skilled Nursing | D13: RN + LPN + nurse aide hours per resident day, case-mix adjusted, quarterly, all days | E13: SNF | F13: Partial match | G13: NURC-17 | H13: =IFERROR(INDEX(KPI_Master!$D:$D,MATCH(G13,KPI_Master!$B:$B,0)),"Not found") -> Nursing Hours per Resident Day (HPRD) | I13: NURC-17 is facility-calculated and not case-mix adjusted | J13: Tool-fetched from CMS PBJ | K13: No - fetch from CMS PBJ / Care Compare with NURC-28 | L13: Quarterly | M13: Operational | N13: 2 - Standard | O13: Matches NURC-28 (CMS staffing input)
A14: SNF-S3 | B14: Case-Mix Adjusted Weekend Total Nurse HPRD | C14: Skilled Nursing | D14: Total nurse staffing hours per resident day on Saturdays and Sundays, case-mix adjusted | E14: SNF | F14: Partial match | G14: NURC-21 | H14: =IFERROR(INDEX(KPI_Master!$D:$D,MATCH(G14,KPI_Master!$B:$B,0)),"Not found") -> Weekend Staffing Ratio | I14: NURC-21 is a weekend/weekday ratio, not case-mix adjusted weekend HPRD | J14: Tool-fetched from CMS PBJ | K14: No - fetch from CMS PBJ / Care Compare with NURC-28 | L14: Quarterly | M14: Operational | N14: 2 - Standard | O14: Matches NURC-28 (CMS staffing input)
A15: SNF-S4 | B15: Total Nurse Staffing Turnover | C15: Skilled Nursing | D15: Percentage of nurse staff who left over 12 months, measured on a 90-consecutive-day zero-hours gap | E15: SNF | F15: Partial match | G15: HRP-02 | H15: =IFERROR(INDEX(KPI_Master!$D:$D,MATCH(G15,KPI_Master!$B:$B,0)),"Not found") -> Total Turnover Rate | I15: HRP-02 covers all staff from HRIS; CMS measures nurse staff only from PBJ (90-day gap rule) | J15: Tool-fetched from CMS PBJ | K15: No - fetch from CMS PBJ / Care Compare with NURC-28 | L15: Quarterly | M15: Operational | N15: 2 - Standard | O15: Matches NURC-28 (CMS staffing input)
A16: SNF-S5 | B16: RN Turnover | C16: Skilled Nursing | D16: Percentage of registered nurses who left over 12 months | E16: SNF | F16: Partial match | G16: HRP-27 | H16: =IFERROR(INDEX(KPI_Master!$D:$D,MATCH(G16,KPI_Master!$B:$B,0)),"Not found") -> RN Turnover Rate | I16: HRP-27 uses HRIS headcount; CMS uses PBJ with the 90-day gap rule | J16: Tool-fetched from CMS PBJ | K16: No - fetch from CMS PBJ / Care Compare with NURC-28 | L16: Quarterly | M16: Operational | N16: 2 - Standard | O16: Matches HRP-27
A17: SNF-Q3 | B17: Long-Stay: Residents with Pressure Ulcers | C17: Skilled Nursing | D17: Percentage of long-stay residents with pressure ulcers | E17: SNF | F17: Partial match | G17: NURC-03 | H17: =IFERROR(INDEX(KPI_Master!$D:$D,MATCH(G17,KPI_Master!$B:$B,0)),"Not found") -> Pressure Injury Prevalence Rate | I17: NURC-03 is facility-calculated prevalence, not the CMS risk-adjusted long-stay QM | J17: Tool-fetched from CMS | K17: No - fetch from CMS Care Compare with the other CMS QMs already in this file | L17: Quarterly | M17: Operational | N17: 2 - Standard | O17: Matches other CMS QMs in this file (e.g., NURC-22, NURC-29)
... A30: DIN-09 | B30: Food Waste Rate | C30: Dining Services | D30: Food waste cost / food purchases | E30: IL, AL, MC, SNF | F30: Not in file | G30: DINF-01 | H30: =IFERROR(INDEX(KPI_Master!$D:$D,MATCH(G30,KPI_Master!$B:$B,0)),"Not found") -> Raw Food Cost per Resident Day (PRD) | I30: No food waste measure in this file | J30: TO BE MAPPED - added from Gap Matrix v9; intake screen not yet assigned | K30: Yes - food waste log or waste tracking system | L30: Monthly | M30: Operational | N30: 3 - Optional | O30: New tracking required; v9 has no intake screen assigned yet
