Workbook

Sheet Cover
B7: Operations Intelligence Report
B8: Occupancy-driven model - change occupancy, staffing and the scorecard follow
B10: Whitefield Commons
B11: Lakeshore Senior Living Group - Ada, Michigan
B12: Type B (Modified) Life Plan Community / CCRC
B13: 142 IL - 58 AL - 28 MC - 52 SNF - 280 units and beds
B14: MI LARA: Home for the Aged (AL+MC) - Nursing Home (SNF) - CCRC registration
B16: Reporting period | C16: Trailing 12 months ended 2026-08-31
B17: Prepared | C17: 2026-09-22
B18: KPI catalog | C18: Operations KPI Catalog v9 (2026-09-22) - 115 measures
B19: In scope for this community | C19: 115 of 115 - full continuum plus CCRC entity measures
B20: Staffing model | C20: Staffing Base Calculator rules, driven live off occupancy
B21: Screen grounding | C21: Onboarding Screen Analysis Catalog (2026-09-22)
A23: How to use this workbook
B24: 1. Open Inputs | C24: Every shaded cell on the Inputs sheet is editable. Occupancy is the headline driver.
B25: 2. Change occupancy | C25: Staffing Model, Financials, the KPI Scorecard and the Action Plan all recalculate.
B26: 3. Read Sensitivity | C26: Shows staffing and margin at seven occupancy levels side by side without touching Inputs.
B27: 4. Everything else | C27: Reported KPIs come from the uploaded operating reports and do not move with occupancy. Each row on the scorecard says which it is.
A29: MOCKUP - ILLUSTRATIVE OUTPUT. Whitefield Commons is a fictional community and every community-specific value in this workbook is fabricated sample data. The KPI set, benchmark targets and their published sources, the Michigan LARA and CMS regulatory references, the staffing rules and the report structure are all real.
B32: Advantedge Operations - A VMP Systems product - Prepared by Rob Clark

Sheet Executive Summary
A1: Executive Summary
A3: Whitefield Commons - trailing twelve months ended 2026-08-31. Every required report and manual entry was received. Figures marked model-linked below move with the occupancy set on Inputs; everything else is the reported trailing-twelve-month result.
A5: Campus occupancy | B5: Recommended FTE | C5: Staffing variance | D5: Operating margin | E5: Labour % of revenue | F5: Measures below
A6: =Inputs!F19 -> 0.91785714 | B6: ='Staffing Model'!G34 -> 173.36252 | C6: ='Staffing Model'!I34 -> -13.862522 | D6: =Financials!E20 -> 0.21472239 | E6: =Financials!E21 -> 0.48993492 | F6: =COUNTIF('KPI Scorecard'!$F$7:$F$140,"Below") -> 18
A7: of 280 units and beds | B7: at this occupancy | C7: vs current headcount | D7: CCRC benchmark 22.8% | E7: CCRC benchmark 40% | F7: of 115 in scope
A9: What the model says
A10: 1 | B10: The community is staffed for roughly 80% occupancy and running at 92%.
B11: Current headcount of 159.5 FTE is almost exactly what the model recommends at 80% occupancy. At the occupancy actually being run it is about 15 FTE short, and the shortfall is concentrated in direct care. That is the cleanest explanation available for agency at 9.4% and overtime at 7.2%: the building is carrying 92% census on an 80% staffing plan, and buying the difference at premium rates.
A13: 2 | B13: Occupancy is the lever, and the model prices it.
B14: The Sensitivity sheet runs the same model from 75% to 100%. Recommended FTE moves about 32 positions across that range while operating margin moves roughly nine points, because fixed campus expense and the occupancy-invariant roles do not follow census. Filling units is worth considerably more than trimming staff.
A16: 3 | B16: Labour is above benchmark at every occupancy the model runs.
B17: Labour lands near 49% of revenue at recommended staffing and does not reach the 40% CCRC benchmark even at full occupancy. That is a structural consequence of a 52-bed skilled centre inside a 280-unit campus, not a scheduling failure - but agency at 9.4% and overtime at 7.2% are the controllable part of it.
A19: 4 | B19: Seventeen open positions are the root of four separate findings.
B20: Vacancy 8.9%, time to fill 58 days, agency 9.4%, overtime 7.2%, frontline turnover 58.9%. The same gap drives the CMS staffing domain, the labour percentage, and the direct-care variance in the staffing model.
A22: 5 | B22: The skilled centre sits at three stars with the fixable domain underperforming.
B23: Health inspection is two stars and lags by survey cycle. Staffing is three. Weekend HPRD at 2.714 against a weekday 3.452 is the single largest recoverable gap, and it needs scheduling rather than hiring.
A25: 6 | B25: Preventive maintenance is being deferred into capital.
B26: PM completion 81.2% against a 90% standard, 19 days average overdue, on a 1994 campus with average age of plant at 14.8 years. Life safety is clean, so this is economics rather than compliance - for now.
A29: Scorecard rollup - live
A30: Result | B30: Count | C30: Share of scored
A31: On benchmark | B31: =COUNTIF('KPI Scorecard'!$F$7:$F$140,"On benchmark") -> 22 | C31: =IFERROR(B31/(COUNTIF('KPI Scorecard'!$F$7:$F$140,"On benchmark")+COUNTIF('KPI Scorecard'!$F$7:$F$140,"Watch")+COUNTIF('KPI Scorecard'!$F$7:$F$140,"Below")),0) -> 0.30985915
A32: Watch | B32: =COUNTIF('KPI Scorecard'!$F$7:$F$140,"Watch") -> 31 | C32: =IFERROR(B32/(COUNTIF('KPI Scorecard'!$F$7:$F$140,"On benchmark")+COUNTIF('KPI Scorecard'!$F$7:$F$140,"Watch")+COUNTIF('KPI Scorecard'!$F$7:$F$140,"Below")),0) -> 0.43661972
A33: Below benchmark | B33: =COUNTIF('KPI Scorecard'!$F$7:$F$140,"Below") -> 18 | C33: =IFERROR(B33/(COUNTIF('KPI Scorecard'!$F$7:$F$140,"On benchmark")+COUNTIF('KPI Scorecard'!$F$7:$F$140,"Watch")+COUNTIF('KPI Scorecard'!$F$7:$F$140,"Below")),0) -> 0.25352113
A34: Informational | B34: =COUNTIF('KPI Scorecard'!$F$7:$F$140,"Informational") -> 8 | C34: n/a
A35: CMS-fetched | B35: =COUNTIF('KPI Scorecard'!$F$7:$F$140,"CMS-fetched") -> 36 | C35: n/a
A36: Total measures in scope | B36: =COUNTA('KPI Scorecard'!$J$7:$J$140) -> 115
A38: Counts recompute from the scorecard, so the model-linked financial measures move the rollup when occupancy changes.

Sheet Inputs
A1: Inputs - the control panel
A3: Every shaded cell is editable. Nothing else in this workbook is typed in; the rest is formula. Occupancy on row 12 is the headline driver.
A5: Care levels and capacity
C6: IL | D6: AL | E6: MC | F6: SNF | G6: Note
A7: Care level offered? | C7: Yes | D7: Yes | E7: Yes | F7: Yes | G7: Set to No to drop a level. Scorecard scope follows.
A8: Capacity (units / beds) | C8: 142 | D8: 58 | E8: 28 | F8: 52 | G8: Licensed or built capacity
A9: Gross square feet | C9: 168000 | D9: 46400 | E9: 19600 | F9: 41600 | G9: Drives housekeeping and plant
A11: Occupancy - the driver
C12: IL | D12: AL | E12: MC | F12: SNF | G12: Note
A13: OCCUPANCY % | C13: 0.923 | D13: 0.914 | E13: 0.929 | F13: 0.904 | G13: CHANGE THESE. Everything downstream follows.
A14: Occupied units / census | C14: =ROUND(C8*C13,0) -> 131 | D14: =ROUND(D8*D13,0) -> 53 | E14: =ROUND(E8*E13,0) -> 26 | F14: =ROUND(F8*F13,0) -> 47 | G14: Computed - rounded to whole residents
A15: SNF short-stay share of census | C15: n/a | D15: n/a | E15: n/a | F15: 0.3 | G15: Splits SNF census into rehab and long-term care
A16: SNF short-stay census | F16: =ROUND(F14*F15,0) -> 14 | G16: Computed
A17: SNF long-term-care census | F17: =F14-F16 -> 33 | G17: Computed
A19: Total capacity | C19: =SUM(C8:F8) -> 280 | D19: Total occupied | E19: =SUM(C14:F14) -> 257 | F19: =IFERROR(E19/C19,0) -> 0.91785714 | G19: Campus occupancy
A21: Campus structure
A22: CCRC / Life Plan registered? | C22: Yes | G22: Turns on entity measures, security post and foundation role
A23: Ownership model | C23: Standalone | G23: System centralises HR off-site
A24: Tax status | C24: Nonprofit | G24: Drives the foundation / giving role
A25: Campus configuration | C25: Single | G25: Single or Multi-building
A26: Optional security (non-CCRC) | C26: No | G26: Only applies when not CCRC registered
A27: Total employees (headcount) | C27: 196 | G27: Drives HR ratio and employee dining
A29: Revenue and expense assumptions
C30: IL | D30: AL | E30: MC | F30: SNF | G30: Note
A31: Rate (IL/AL/MC per month, SNF per day) | C31: 4150 | D31: 7100 | E31: 8750 | F31: 398 | G31: Blended achieved rate net of concessions
A32: Non-labour opex per occupied unit (mo) / per patient day | C32: 340 | D32: 780 | E32: 980 | F32: 96 | G32: Dining food, supplies, variable utilities
A33: Fixed campus opex (annual) | C33: 3100000 | G33: Insurance, property, admin, base utilities - does not move with census
A34: Benefit / tax burden on wages | C34: 0.22 | G34: Applied to every wage below
A36: Staffing drivers - direct care
A37: Three-shift ratios (residents per caregiver) | C37: IL | D37: AL | E37: MC | F37: SNF | G37: Note
A38: CNA / aide - day shift | C38: n/a | D38: 12 | E38: 8 | F38: 8 | G38: SBC default AL 12 / MC 8 / SNF 8
A39: CNA / aide - evening shift | C39: n/a | D39: 15 | E39: 8 | F39: 8
A40: CNA / aide - night shift | C40: n/a | D40: 20 | E40: 12 | F40: 12
A41: Nurse / med aide - day shift | C41: n/a | D41: 30 | E41: 30 | F41: 20 | G41: SBC default AL/MC 30 / SNF 20
A42: Nurse / med aide - evening shift | C42: n/a | D42: 30 | E42: 30 | F42: 20
A43: Nurse / med aide - night shift | C43: n/a | D43: 30 | E43: 30 | F43: 20
A44: Minimum staff on night shift | C44: n/a | D44: 2 | E44: 2 | F44: 0 | G44: Michigan HFA requires awake staff 24/7. Set 0 to remove the floor.
A46: Staffing drivers - support services
C47: IL | D47: AL | E47: MC | F47: SNF | G47: Note
A48: Meals per resident per day | C48: 1 | D48: 3 | E48: 3 | F48: 3 | G48: IL 1.0 for a Type B one-meal plan. Set 3.0 for a full plan.
A49: Target meals per labour hour | C49: 2.2 | D49: 2.5 | E49: 3 | F49: 3.5 | G49: Lower MPLH = more labour-intensive service
A50: Housekeeping square feet per FTE | C50: 25000 | D50: 20000 | E50: 8000 | F50: 8000
A51: Laundry lbs per resident per week | C51: 6.4 | D51: 18.9 | E51: 18.9 | F51: 66 | G51: SNF blended short-stay and long-term care
A52: Laundry processing rate (lbs per hour) | C52: 50 | G52: SBC constant
A53: Plant ops square feet per FTE | C53: 50000 | G53: Grounds are outsourced and excluded
A55: Wages - loaded cost is wage x 2,080 x (1 + burden)
A56: Position | C56: Hourly wage | D56: Loaded / yr | G56: Note
A57: Executive Director / NHA | C57: 62 | D57: =C57*2080*(1+$C$34) -> 157331.2 | G57: BLS OEWS, Grand Rapids-Kentwood MSA
A58: Associate ED | C58: 44 | D58: =C58*2080*(1+$C$34) -> 111654.4
A59: Business office | C59: 27 | D59: =C59*2080*(1+$C$34) -> 68515.2
A60: Concierge / front desk | C60: 17 | D60: =C60*2080*(1+$C$34) -> 43139.2
A61: Sales / marketing | C61: 34 | D61: =C61*2080*(1+$C$34) -> 86278.4
A62: Program director | C62: 34 | D62: =C62*2080*(1+$C$34) -> 86278.4
A63: Dining | C63: 17.2 | D63: =C63*2080*(1+$C$34) -> 43646.72
A64: Plant operations | C64: 26.5 | D64: =C64*2080*(1+$C$34) -> 67246.4
A65: DON / care manager | C65: 42 | D65: =C65*2080*(1+$C$34) -> 106579.2
A66: Human resources | C66: 30 | D66: =C66*2080*(1+$C$34) -> 76128
A67: Activities / life enrichment | C67: 19 | D67: =C67*2080*(1+$C$34) -> 48214.4
A68: Social services | C68: 24 | D68: =C68*2080*(1+$C$34) -> 60902.4
A69: Housekeeping | C69: 16.4 | D69: =C69*2080*(1+$C$34) -> 41616.64
... A77: MDS coordinator | C77: 36 | D77: =C77*2080*(1+$C$34) -> 91353.6
A79: Wage medians benchmark to BLS OEWS for the community's MSA. Replace them with the community's own average hourly rate by role from the payroll report for a precise cost read.
A81: Other model constants
A82: Security coverage FTE when staffed | C82: 5.12 | G82: Coverage schedule / 2,080. Gated on CCRC registration or optional security.
A83: Employee meals per employee per day | C83: 0.25 | G83: Drives the employee dining role
A84: Employee dining MPLH | C84: 3
A85: Hours per FTE per year | C85: 2080
A86: Raw food share of non-labour variable expense | C86: 0.18 | G86: Splits out raw food so dining cost per resident day can be scored
A88: Current staffing - from the payroll report
A89: Position | C89: Current FTE | G89: Note
A90: Executive Director / SNF Administrator (NHA) | C90: 1
A91: Associate ED | C91: 1
A92: Business office / billing | C92: 3
A93: Concierge / front desk | C93: 7
A94: Sales / marketing / admissions | C94: 5
A95: Program director | C95: 1
A96: Dining | C96: 30
A97: Plant operations | C97: 5
A98: DON / head nurse / care manager | C98: 2
A99: Human resources | C99: 2
A100: Activities / life enrichment | C100: 5.4
A101: Social services | C101: 2
... A112: MDS coordinator | C112: 1.4
A113: Total current FTE | C113: =SUM(C90:C112) -> 159.5
A115: Current FTE comes from the payroll / turnover report on Screen 09. The staffing model compares its own recommendation against these figures and prices the gap at the wages above.

Sheet Sensitivity
A1: Occupancy Sensitivity
A3: The same staffing and financial model run at seven occupancy levels. Row 6 is the only input on this sheet - change any percentage and that column recalculates. Occupancy is applied uniformly to every care level here; the Inputs sheet lets you set each level separately.
A5: Occupancy applied to every care level | B5: 0.75 | C5: 0.8 | D5: 0.85 | E5: 0.9 | F5: 0.95 | G5: 0.98 | H5: 1 | I5: Editable
A6: Census at each occupancy
A7: IL occupied | B7: =ROUND(Inputs!$C$8*B$5,0) -> 107 | C7: =ROUND(Inputs!$C$8*C$5,0) -> 114 | D7: =ROUND(Inputs!$C$8*D$5,0) -> 121 | E7: =ROUND(Inputs!$C$8*E$5,0) -> 128 | F7: =ROUND(Inputs!$C$8*F$5,0) -> 135 | G7: =ROUND(Inputs!$C$8*G$5,0) -> 139 | H7: =ROUND(Inputs!$C$8*H$5,0) -> 142
A8: AL occupied | B8: =ROUND(Inputs!$D$8*B$5,0) -> 44 | C8: =ROUND(Inputs!$D$8*C$5,0) -> 46 | D8: =ROUND(Inputs!$D$8*D$5,0) -> 49 | E8: =ROUND(Inputs!$D$8*E$5,0) -> 52 | F8: =ROUND(Inputs!$D$8*F$5,0) -> 55 | G8: =ROUND(Inputs!$D$8*G$5,0) -> 57 | H8: =ROUND(Inputs!$D$8*H$5,0) -> 58
A9: MC occupied | B9: =ROUND(Inputs!$E$8*B$5,0) -> 21 | C9: =ROUND(Inputs!$E$8*C$5,0) -> 22 | D9: =ROUND(Inputs!$E$8*D$5,0) -> 24 | E9: =ROUND(Inputs!$E$8*E$5,0) -> 25 | F9: =ROUND(Inputs!$E$8*F$5,0) -> 27 | G9: =ROUND(Inputs!$E$8*G$5,0) -> 27 | H9: =ROUND(Inputs!$E$8*H$5,0) -> 28
A10: SNF census | B10: =ROUND(Inputs!$F$8*B$5,0) -> 39 | C10: =ROUND(Inputs!$F$8*C$5,0) -> 42 | D10: =ROUND(Inputs!$F$8*D$5,0) -> 44 | E10: =ROUND(Inputs!$F$8*E$5,0) -> 47 | F10: =ROUND(Inputs!$F$8*F$5,0) -> 49 | G10: =ROUND(Inputs!$F$8*G$5,0) -> 51 | H10: =ROUND(Inputs!$F$8*H$5,0) -> 52
A11: Total residents | B11: =(ROUND(Inputs!$C$8*B$5,0)+ROUND(Inputs!$D$8*B$5,0)+ROUND(Inputs!$E$8*B$5,0)+ROUND(Inputs!$F$8*B$5,0)) -> 211 | C11: =(ROUND(Inputs!$C$8*C$5,0)+ROUND(Inputs!$D$8*C$5,0)+ROUND(Inputs!$E$8*C$5,0)+ROUND(Inputs!$F$8*C$5,0)) -> 224 | D11: =(ROUND(Inputs!$C$8*D$5,0)+ROUND(Inputs!$D$8*D$5,0)+ROUND(Inputs!$E$8*D$5,0)+ROUND(Inputs!$F$8*D$5,0)) -> 238 | E11: =(ROUND(Inputs!$C$8*E$5,0)+ROUND(Inputs!$D$8*E$5,0)+ROUND(Inputs!$E$8*E$5,0)+ROUND(Inputs!$F$8*E$5,0)) -> 252 | F11: =(ROUND(Inputs!$C$8*F$5,0)+ROUND(Inputs!$D$8*F$5,0)+ROUND(Inputs!$E$8*F$5,0)+ROUND(Inputs!$F$8*F$5,0)) -> 266 | G11: =(ROUND(Inputs!$C$8*G$5,0)+ROUND(Inputs!$D$8*G$5,0)+ROUND(Inputs!$E$8*G$5,0)+ROUND(Inputs!$F$8*G$5,0)) -> 274 | H11: =(ROUND(Inputs!$C$8*H$5,0)+ROUND(Inputs!$D$8*H$5,0)+ROUND(Inputs!$E$8*H$5,0)+ROUND(Inputs!$F$8*H$5,0)) -> 280
A12: Recommended staffing (FTE)
A13: CNA / aide | B13: =IF(ROUND(Inputs!$D$8*B$5,0)=0,0,((ROUND(Inputs!$D$8*B$5,0)/Inputs!$D$38)+(ROUND(Inputs!$D$8*B$5,0)/Inputs!$D$39)+MAX(Inputs!$D$44,ROUND(Inputs!$D$8*B$5,0)/Inputs!$D$40))*8*7/40)+IF(ROUND(Inputs!$E$8*B$5,0)=0,0,((ROUND(Inputs!$E$8*B$5,0)/Inputs!$E$38)+(ROUND(Inputs!$E$8*B$5,0)/Inputs!$E$39)+MAX(Inputs!$E$44,ROUND(Inputs!$E$8*B$5,0)/Inputs!$E$40))*8*7/40)+IF(ROUND(Inputs!$F$8*B$5,0)=0,0,((ROUND(Inputs!$F$8*B$5,0)/Inputs!$F$38)+(ROUND(Inputs!$F$8*B$5,0)/Inputs!$F$39)+MAX(Inputs!$F$44,ROUND(Inputs!$F$8*B$5,0)/Inputs!$F$40))*8*7/40) -> 40.67 | C13: =IF(ROUND(Inputs!$D$8*C$5,0)=0,0,((ROUND(Inputs!$D$8*C$5,0)/Inputs!$D$38)+(ROUND(Inputs!$D$8*C$5,0)/Inputs!$D$39)+MAX(Inputs!$D$44,ROUND(Inputs!$D$8*C$5,0)/Inputs!$D$40))*8*7/40)+IF(ROUND(Inputs!$E$8*C$5,0)=0,0,((ROUND(Inputs!$E$8*C$5,0)/Inputs!$E$38)+(ROUND(Inputs!$E$8*C$5,0)/Inputs!$E$39)+MAX(Inputs!$E$44,ROUND(Inputs!$E$8*C$5,0)/Inputs!$E$40))*8*7/40)+IF(ROUND(Inputs!$F$8*C$5,0)=0,0,((ROUND(Inputs!$F$8*C$5,0)/Inputs!$F$38)+(ROUND(Inputs!$F$8*C$5,0)/Inputs!$F$39)+MAX(Inputs!$F$44,ROUND(Inputs!$F$8*C$5,0)/Inputs!$F$40))*8*7/40) -> 42.98 | D13: =IF(ROUND(Inputs!$D$8*D$5,0)=0,0,((ROUND(Inputs!$D$8*D$5,0)/Inputs!$D$38)+(ROUND(Inputs!$D$8*D$5,0)/Inputs!$D$39)+MAX(Inputs!$D$44,ROUND(Inputs!$D$8*D$5,0)/Inputs!$D$40))*8*7/40)+IF(ROUND(Inputs!$E$8*D$5,0)=0,0,((ROUND(Inputs!$E$8*D$5,0)/Inputs!$E$38)+(ROUND(Inputs!$E$8*D$5,0)/Inputs!$E$39)+MAX(Inputs!$E$44,ROUND(Inputs!$E$8*D$5,0)/Inputs!$E$40))*8*7/40)+IF(ROUND(Inputs!$F$8*D$5,0)=0,0,((ROUND(Inputs!$F$8*D$5,0)/Inputs!$F$38)+(ROUND(Inputs!$F$8*D$5,0)/Inputs!$F$39)+MAX(Inputs!$F$44,ROUND(Inputs!$F$8*D$5,0)/Inputs!$F$40))*8*7/40) -> 45.453333 | E13: =IF(ROUND(Inputs!$D$8*E$5,0)=0,0,((ROUND(Inputs!$D$8*E$5,0)/Inputs!$D$38)+(ROUND(Inputs!$D$8*E$5,0)/Inputs!$D$39)+MAX(Inputs!$D$44,ROUND(Inputs!$D$8*E$5,0)/Inputs!$D$40))*8*7/40)+IF(ROUND(Inputs!$E$8*E$5,0)=0,0,((ROUND(Inputs!$E$8*E$5,0)/Inputs!$E$38)+(ROUND(Inputs!$E$8*E$5,0)/Inputs!$E$39)+MAX(Inputs!$E$44,ROUND(Inputs!$E$8*E$5,0)/Inputs!$E$40))*8*7/40)+IF(ROUND(Inputs!$F$8*E$5,0)=0,0,((ROUND(Inputs!$F$8*E$5,0)/Inputs!$F$38)+(ROUND(Inputs!$F$8*E$5,0)/Inputs!$F$39)+MAX(Inputs!$F$44,ROUND(Inputs!$F$8*E$5,0)/Inputs!$F$40))*8*7/40) -> 48.16 | F13: =IF(ROUND(Inputs!$D$8*F$5,0)=0,0,((ROUND(Inputs!$D$8*F$5,0)/Inputs!$D$38)+(ROUND(Inputs!$D$8*F$5,0)/Inputs!$D$39)+MAX(Inputs!$D$44,ROUND(Inputs!$D$8*F$5,0)/Inputs!$D$40))*8*7/40)+IF(ROUND(Inputs!$E$8*F$5,0)=0,0,((ROUND(Inputs!$E$8*F$5,0)/Inputs!$E$38)+(ROUND(Inputs!$E$8*F$5,0)/Inputs!$E$39)+MAX(Inputs!$E$44,ROUND(Inputs!$E$8*F$5,0)/Inputs!$E$40))*8*7/40)+IF(ROUND(Inputs!$F$8*F$5,0)=0,0,((ROUND(Inputs!$F$8*F$5,0)/Inputs!$F$38)+(ROUND(Inputs!$F$8*F$5,0)/Inputs!$F$39)+MAX(Inputs!$F$44,ROUND(Inputs!$F$8*F$5,0)/Inputs!$F$40))*8*7/40) -> 50.866667 | G13: =IF(ROUND(Inputs!$D$8*G$5,0)=0,0,((ROUND(Inputs!$D$8*G$5,0)/Inputs!$D$38)+(ROUND(Inputs!$D$8*G$5,0)/Inputs!$D$39)+MAX(Inputs!$D$44,ROUND(Inputs!$D$8*G$5,0)/Inputs!$D$40))*8*7/40)+IF(ROUND(Inputs!$E$8*G$5,0)=0,0,((ROUND(Inputs!$E$8*G$5,0)/Inputs!$E$38)+(ROUND(Inputs!$E$8*G$5,0)/Inputs!$E$39)+MAX(Inputs!$E$44,ROUND(Inputs!$E$8*G$5,0)/Inputs!$E$40))*8*7/40)+IF(ROUND(Inputs!$F$8*G$5,0)=0,0,((ROUND(Inputs!$F$8*G$5,0)/Inputs!$F$38)+(ROUND(Inputs!$F$8*G$5,0)/Inputs!$F$39)+MAX(Inputs!$F$44,ROUND(Inputs!$F$8*G$5,0)/Inputs!$F$40))*8*7/40) -> 52.36 | H13: =IF(ROUND(Inputs!$D$8*H$5,0)=0,0,((ROUND(Inputs!$D$8*H$5,0)/Inputs!$D$38)+(ROUND(Inputs!$D$8*H$5,0)/Inputs!$D$39)+MAX(Inputs!$D$44,ROUND(Inputs!$D$8*H$5,0)/Inputs!$D$40))*8*7/40)+IF(ROUND(Inputs!$E$8*H$5,0)=0,0,((ROUND(Inputs!$E$8*H$5,0)/Inputs!$E$38)+(ROUND(Inputs!$E$8*H$5,0)/Inputs!$E$39)+MAX(Inputs!$E$44,ROUND(Inputs!$E$8*H$5,0)/Inputs!$E$40))*8*7/40)+IF(ROUND(Inputs!$F$8*H$5,0)=0,0,((ROUND(Inputs!$F$8*H$5,0)/Inputs!$F$38)+(ROUND(Inputs!$F$8*H$5,0)/Inputs!$F$39)+MAX(Inputs!$F$44,ROUND(Inputs!$F$8*H$5,0)/Inputs!$F$40))*8*7/40) -> 53.573333 | I13: Three-shift ratio model
A14: Nurse / med aide | B14: =IF(ROUND(Inputs!$D$8*B$5,0)=0,0,(MAX(1,ROUND(Inputs!$D$8*B$5,0)/Inputs!$D$41)+MAX(1,ROUND(Inputs!$D$8*B$5,0)/Inputs!$D$42)+MAX(1,ROUND(Inputs!$D$8*B$5,0)/Inputs!$D$43))*8*7/40)+IF(ROUND(Inputs!$E$8*B$5,0)=0,0,(MAX(1,ROUND(Inputs!$E$8*B$5,0)/Inputs!$E$41)+MAX(1,ROUND(Inputs!$E$8*B$5,0)/Inputs!$E$42)+MAX(1,ROUND(Inputs!$E$8*B$5,0)/Inputs!$E$43))*8*7/40)+IF(ROUND(Inputs!$F$8*B$5,0)=0,0,(MAX(1,ROUND(Inputs!$F$8*B$5,0)/Inputs!$F$41)+MAX(1,ROUND(Inputs!$F$8*B$5,0)/Inputs!$F$42)+MAX(1,ROUND(Inputs!$F$8*B$5,0)/Inputs!$F$43))*8*7/40) -> 18.55 | C14: =IF(ROUND(Inputs!$D$8*C$5,0)=0,0,(MAX(1,ROUND(Inputs!$D$8*C$5,0)/Inputs!$D$41)+MAX(1,ROUND(Inputs!$D$8*C$5,0)/Inputs!$D$42)+MAX(1,ROUND(Inputs!$D$8*C$5,0)/Inputs!$D$43))*8*7/40)+IF(ROUND(Inputs!$E$8*C$5,0)=0,0,(MAX(1,ROUND(Inputs!$E$8*C$5,0)/Inputs!$E$41)+MAX(1,ROUND(Inputs!$E$8*C$5,0)/Inputs!$E$42)+MAX(1,ROUND(Inputs!$E$8*C$5,0)/Inputs!$E$43))*8*7/40)+IF(ROUND(Inputs!$F$8*C$5,0)=0,0,(MAX(1,ROUND(Inputs!$F$8*C$5,0)/Inputs!$F$41)+MAX(1,ROUND(Inputs!$F$8*C$5,0)/Inputs!$F$42)+MAX(1,ROUND(Inputs!$F$8*C$5,0)/Inputs!$F$43))*8*7/40) -> 19.46 | D14: =IF(ROUND(Inputs!$D$8*D$5,0)=0,0,(MAX(1,ROUND(Inputs!$D$8*D$5,0)/Inputs!$D$41)+MAX(1,ROUND(Inputs!$D$8*D$5,0)/Inputs!$D$42)+MAX(1,ROUND(Inputs!$D$8*D$5,0)/Inputs!$D$43))*8*7/40)+IF(ROUND(Inputs!$E$8*D$5,0)=0,0,(MAX(1,ROUND(Inputs!$E$8*D$5,0)/Inputs!$E$41)+MAX(1,ROUND(Inputs!$E$8*D$5,0)/Inputs!$E$42)+MAX(1,ROUND(Inputs!$E$8*D$5,0)/Inputs!$E$43))*8*7/40)+IF(ROUND(Inputs!$F$8*D$5,0)=0,0,(MAX(1,ROUND(Inputs!$F$8*D$5,0)/Inputs!$F$41)+MAX(1,ROUND(Inputs!$F$8*D$5,0)/Inputs!$F$42)+MAX(1,ROUND(Inputs!$F$8*D$5,0)/Inputs!$F$43))*8*7/40) -> 20.3 | E14: =IF(ROUND(Inputs!$D$8*E$5,0)=0,0,(MAX(1,ROUND(Inputs!$D$8*E$5,0)/Inputs!$D$41)+MAX(1,ROUND(Inputs!$D$8*E$5,0)/Inputs!$D$42)+MAX(1,ROUND(Inputs!$D$8*E$5,0)/Inputs!$D$43))*8*7/40)+IF(ROUND(Inputs!$E$8*E$5,0)=0,0,(MAX(1,ROUND(Inputs!$E$8*E$5,0)/Inputs!$E$41)+MAX(1,ROUND(Inputs!$E$8*E$5,0)/Inputs!$E$42)+MAX(1,ROUND(Inputs!$E$8*E$5,0)/Inputs!$E$43))*8*7/40)+IF(ROUND(Inputs!$F$8*E$5,0)=0,0,(MAX(1,ROUND(Inputs!$F$8*E$5,0)/Inputs!$F$41)+MAX(1,ROUND(Inputs!$F$8*E$5,0)/Inputs!$F$42)+MAX(1,ROUND(Inputs!$F$8*E$5,0)/Inputs!$F$43))*8*7/40) -> 21.35 | F14: =IF(ROUND(Inputs!$D$8*F$5,0)=0,0,(MAX(1,ROUND(Inputs!$D$8*F$5,0)/Inputs!$D$41)+MAX(1,ROUND(Inputs!$D$8*F$5,0)/Inputs!$D$42)+MAX(1,ROUND(Inputs!$D$8*F$5,0)/Inputs!$D$43))*8*7/40)+IF(ROUND(Inputs!$E$8*F$5,0)=0,0,(MAX(1,ROUND(Inputs!$E$8*F$5,0)/Inputs!$E$41)+MAX(1,ROUND(Inputs!$E$8*F$5,0)/Inputs!$E$42)+MAX(1,ROUND(Inputs!$E$8*F$5,0)/Inputs!$E$43))*8*7/40)+IF(ROUND(Inputs!$F$8*F$5,0)=0,0,(MAX(1,ROUND(Inputs!$F$8*F$5,0)/Inputs!$F$41)+MAX(1,ROUND(Inputs!$F$8*F$5,0)/Inputs!$F$42)+MAX(1,ROUND(Inputs!$F$8*F$5,0)/Inputs!$F$43))*8*7/40) -> 22.19 | G14: =IF(ROUND(Inputs!$D$8*G$5,0)=0,0,(MAX(1,ROUND(Inputs!$D$8*G$5,0)/Inputs!$D$41)+MAX(1,ROUND(Inputs!$D$8*G$5,0)/Inputs!$D$42)+MAX(1,ROUND(Inputs!$D$8*G$5,0)/Inputs!$D$43))*8*7/40)+IF(ROUND(Inputs!$E$8*G$5,0)=0,0,(MAX(1,ROUND(Inputs!$E$8*G$5,0)/Inputs!$E$41)+MAX(1,ROUND(Inputs!$E$8*G$5,0)/Inputs!$E$42)+MAX(1,ROUND(Inputs!$E$8*G$5,0)/Inputs!$E$43))*8*7/40)+IF(ROUND(Inputs!$F$8*G$5,0)=0,0,(MAX(1,ROUND(Inputs!$F$8*G$5,0)/Inputs!$F$41)+MAX(1,ROUND(Inputs!$F$8*G$5,0)/Inputs!$F$42)+MAX(1,ROUND(Inputs!$F$8*G$5,0)/Inputs!$F$43))*8*7/40) -> 22.89 | H14: =IF(ROUND(Inputs!$D$8*H$5,0)=0,0,(MAX(1,ROUND(Inputs!$D$8*H$5,0)/Inputs!$D$41)+MAX(1,ROUND(Inputs!$D$8*H$5,0)/Inputs!$D$42)+MAX(1,ROUND(Inputs!$D$8*H$5,0)/Inputs!$D$43))*8*7/40)+IF(ROUND(Inputs!$E$8*H$5,0)=0,0,(MAX(1,ROUND(Inputs!$E$8*H$5,0)/Inputs!$E$41)+MAX(1,ROUND(Inputs!$E$8*H$5,0)/Inputs!$E$42)+MAX(1,ROUND(Inputs!$E$8*H$5,0)/Inputs!$E$43))*8*7/40)+IF(ROUND(Inputs!$F$8*H$5,0)=0,0,(MAX(1,ROUND(Inputs!$F$8*H$5,0)/Inputs!$F$41)+MAX(1,ROUND(Inputs!$F$8*H$5,0)/Inputs!$F$42)+MAX(1,ROUND(Inputs!$F$8*H$5,0)/Inputs!$F$43))*8*7/40) -> 23.24
A15: Dining | B15: =ROUND(Inputs!$C$8*B$5,0)*Inputs!$C$48*365/Inputs!$C$49/Inputs!$C$85+ROUND(Inputs!$D$8*B$5,0)*Inputs!$D$48*365/Inputs!$D$49/Inputs!$C$85+ROUND(Inputs!$E$8*B$5,0)*Inputs!$E$48*365/Inputs!$E$49/Inputs!$C$85+ROUND(Inputs!$F$8*B$5,0)*Inputs!$F$48*365/Inputs!$F$49/Inputs!$C$85 -> 27.351299 | C15: =ROUND(Inputs!$C$8*C$5,0)*Inputs!$C$48*365/Inputs!$C$49/Inputs!$C$85+ROUND(Inputs!$D$8*C$5,0)*Inputs!$D$48*365/Inputs!$D$49/Inputs!$C$85+ROUND(Inputs!$E$8*C$5,0)*Inputs!$E$48*365/Inputs!$E$49/Inputs!$C$85+ROUND(Inputs!$F$8*C$5,0)*Inputs!$F$48*365/Inputs!$F$49/Inputs!$C$85 -> 28.957517 | D15: =ROUND(Inputs!$C$8*D$5,0)*Inputs!$C$48*365/Inputs!$C$49/Inputs!$C$85+ROUND(Inputs!$D$8*D$5,0)*Inputs!$D$48*365/Inputs!$D$49/Inputs!$C$85+ROUND(Inputs!$E$8*D$5,0)*Inputs!$E$48*365/Inputs!$E$49/Inputs!$C$85+ROUND(Inputs!$F$8*D$5,0)*Inputs!$F$48*365/Inputs!$F$49/Inputs!$C$85 -> 30.799382 | E15: =ROUND(Inputs!$C$8*E$5,0)*Inputs!$C$48*365/Inputs!$C$49/Inputs!$C$85+ROUND(Inputs!$D$8*E$5,0)*Inputs!$D$48*365/Inputs!$D$49/Inputs!$C$85+ROUND(Inputs!$E$8*E$5,0)*Inputs!$E$48*365/Inputs!$E$49/Inputs!$C$85+ROUND(Inputs!$F$8*E$5,0)*Inputs!$F$48*365/Inputs!$F$49/Inputs!$C$85 -> 32.616178 | F15: =ROUND(Inputs!$C$8*F$5,0)*Inputs!$C$48*365/Inputs!$C$49/Inputs!$C$85+ROUND(Inputs!$D$8*F$5,0)*Inputs!$D$48*365/Inputs!$D$49/Inputs!$C$85+ROUND(Inputs!$E$8*F$5,0)*Inputs!$E$48*365/Inputs!$E$49/Inputs!$C$85+ROUND(Inputs!$F$8*F$5,0)*Inputs!$F$48*365/Inputs!$F$49/Inputs!$C$85 -> 34.458042 | G15: =ROUND(Inputs!$C$8*G$5,0)*Inputs!$C$48*365/Inputs!$C$49/Inputs!$C$85+ROUND(Inputs!$D$8*G$5,0)*Inputs!$D$48*365/Inputs!$D$49/Inputs!$C$85+ROUND(Inputs!$E$8*G$5,0)*Inputs!$E$48*365/Inputs!$E$49/Inputs!$C$85+ROUND(Inputs!$F$8*G$5,0)*Inputs!$F$48*365/Inputs!$F$49/Inputs!$C$85 -> 35.499076 | H15: =ROUND(Inputs!$C$8*H$5,0)*Inputs!$C$48*365/Inputs!$C$49/Inputs!$C$85+ROUND(Inputs!$D$8*H$5,0)*Inputs!$D$48*365/Inputs!$D$49/Inputs!$C$85+ROUND(Inputs!$E$8*H$5,0)*Inputs!$E$48*365/Inputs!$E$49/Inputs!$C$85+ROUND(Inputs!$F$8*H$5,0)*Inputs!$F$48*365/Inputs!$F$49/Inputs!$C$85 -> 36.274838
A16: Business office | B16: =IF(ROUND(Inputs!$C$8*B$5,0)=0,0,IF(ROUND(Inputs!$C$8*B$5,0)<125,1,ROUND(Inputs!$C$8*B$5,0)*0.005))+IF(ROUND(Inputs!$D$8*B$5,0)>75,1,ROUND(Inputs!$D$8*B$5,0)*0.005)+IF(ROUND(Inputs!$E$8*B$5,0)>75,1,ROUND(Inputs!$E$8*B$5,0)*0.005)+IF(ROUND(Inputs!$F$8*B$5,0)>0,1,0) -> 2.325 | C16: =IF(ROUND(Inputs!$C$8*C$5,0)=0,0,IF(ROUND(Inputs!$C$8*C$5,0)<125,1,ROUND(Inputs!$C$8*C$5,0)*0.005))+IF(ROUND(Inputs!$D$8*C$5,0)>75,1,ROUND(Inputs!$D$8*C$5,0)*0.005)+IF(ROUND(Inputs!$E$8*C$5,0)>75,1,ROUND(Inputs!$E$8*C$5,0)*0.005)+IF(ROUND(Inputs!$F$8*C$5,0)>0,1,0) -> 2.34 | D16: =IF(ROUND(Inputs!$C$8*D$5,0)=0,0,IF(ROUND(Inputs!$C$8*D$5,0)<125,1,ROUND(Inputs!$C$8*D$5,0)*0.005))+IF(ROUND(Inputs!$D$8*D$5,0)>75,1,ROUND(Inputs!$D$8*D$5,0)*0.005)+IF(ROUND(Inputs!$E$8*D$5,0)>75,1,ROUND(Inputs!$E$8*D$5,0)*0.005)+IF(ROUND(Inputs!$F$8*D$5,0)>0,1,0) -> 2.365 | E16: =IF(ROUND(Inputs!$C$8*E$5,0)=0,0,IF(ROUND(Inputs!$C$8*E$5,0)<125,1,ROUND(Inputs!$C$8*E$5,0)*0.005))+IF(ROUND(Inputs!$D$8*E$5,0)>75,1,ROUND(Inputs!$D$8*E$5,0)*0.005)+IF(ROUND(Inputs!$E$8*E$5,0)>75,1,ROUND(Inputs!$E$8*E$5,0)*0.005)+IF(ROUND(Inputs!$F$8*E$5,0)>0,1,0) -> 2.025 | F16: =IF(ROUND(Inputs!$C$8*F$5,0)=0,0,IF(ROUND(Inputs!$C$8*F$5,0)<125,1,ROUND(Inputs!$C$8*F$5,0)*0.005))+IF(ROUND(Inputs!$D$8*F$5,0)>75,1,ROUND(Inputs!$D$8*F$5,0)*0.005)+IF(ROUND(Inputs!$E$8*F$5,0)>75,1,ROUND(Inputs!$E$8*F$5,0)*0.005)+IF(ROUND(Inputs!$F$8*F$5,0)>0,1,0) -> 2.085 | G16: =IF(ROUND(Inputs!$C$8*G$5,0)=0,0,IF(ROUND(Inputs!$C$8*G$5,0)<125,1,ROUND(Inputs!$C$8*G$5,0)*0.005))+IF(ROUND(Inputs!$D$8*G$5,0)>75,1,ROUND(Inputs!$D$8*G$5,0)*0.005)+IF(ROUND(Inputs!$E$8*G$5,0)>75,1,ROUND(Inputs!$E$8*G$5,0)*0.005)+IF(ROUND(Inputs!$F$8*G$5,0)>0,1,0) -> 2.115 | H16: =IF(ROUND(Inputs!$C$8*H$5,0)=0,0,IF(ROUND(Inputs!$C$8*H$5,0)<125,1,ROUND(Inputs!$C$8*H$5,0)*0.005))+IF(ROUND(Inputs!$D$8*H$5,0)>75,1,ROUND(Inputs!$D$8*H$5,0)*0.005)+IF(ROUND(Inputs!$E$8*H$5,0)>75,1,ROUND(Inputs!$E$8*H$5,0)*0.005)+IF(ROUND(Inputs!$F$8*H$5,0)>0,1,0) -> 2.14
A17: Concierge / front desk | B17: =IF(ROUND(Inputs!$C$8*B$5,0)>0,4.2,0)+IF(ROUND(Inputs!$D$8*B$5,0)<45,ROUND(Inputs!$D$8*B$5,0)*0.005,1)+ROUND(Inputs!$E$8*B$5,0)*0.005+IF(ROUND(Inputs!$F$8*B$5,0)>40,2.1,0) -> 4.525 | C17: =IF(ROUND(Inputs!$C$8*C$5,0)>0,4.2,0)+IF(ROUND(Inputs!$D$8*C$5,0)<45,ROUND(Inputs!$D$8*C$5,0)*0.005,1)+ROUND(Inputs!$E$8*C$5,0)*0.005+IF(ROUND(Inputs!$F$8*C$5,0)>40,2.1,0) -> 7.41 | D17: =IF(ROUND(Inputs!$C$8*D$5,0)>0,4.2,0)+IF(ROUND(Inputs!$D$8*D$5,0)<45,ROUND(Inputs!$D$8*D$5,0)*0.005,1)+ROUND(Inputs!$E$8*D$5,0)*0.005+IF(ROUND(Inputs!$F$8*D$5,0)>40,2.1,0) -> 7.42 | E17: =IF(ROUND(Inputs!$C$8*E$5,0)>0,4.2,0)+IF(ROUND(Inputs!$D$8*E$5,0)<45,ROUND(Inputs!$D$8*E$5,0)*0.005,1)+ROUND(Inputs!$E$8*E$5,0)*0.005+IF(ROUND(Inputs!$F$8*E$5,0)>40,2.1,0) -> 7.425 | F17: =IF(ROUND(Inputs!$C$8*F$5,0)>0,4.2,0)+IF(ROUND(Inputs!$D$8*F$5,0)<45,ROUND(Inputs!$D$8*F$5,0)*0.005,1)+ROUND(Inputs!$E$8*F$5,0)*0.005+IF(ROUND(Inputs!$F$8*F$5,0)>40,2.1,0) -> 7.435 | G17: =IF(ROUND(Inputs!$C$8*G$5,0)>0,4.2,0)+IF(ROUND(Inputs!$D$8*G$5,0)<45,ROUND(Inputs!$D$8*G$5,0)*0.005,1)+ROUND(Inputs!$E$8*G$5,0)*0.005+IF(ROUND(Inputs!$F$8*G$5,0)>40,2.1,0) -> 7.435 | H17: =IF(ROUND(Inputs!$C$8*H$5,0)>0,4.2,0)+IF(ROUND(Inputs!$D$8*H$5,0)<45,ROUND(Inputs!$D$8*H$5,0)*0.005,1)+ROUND(Inputs!$E$8*H$5,0)*0.005+IF(ROUND(Inputs!$F$8*H$5,0)>40,2.1,0) -> 7.44
A18: Activities / life enrichment | B18: =ROUND(Inputs!$C$8*B$5,0)/100+IF(ROUND(Inputs!$D$8*B$5,0)=0,0,IF(ROUND(Inputs!$D$8*B$5,0)<60,1.4,ROUND(Inputs!$D$8*B$5,0)*0.05))+IF(ROUND(Inputs!$E$8*B$5,0)=0,0,IF(ROUND(Inputs!$E$8*B$5,0)<30,1.4,ROUND(Inputs!$E$8*B$5,0)*0.035))+IF(ROUND(Inputs!$F$8*B$5,0)=0,0,IF(ROUND(Inputs!$F$8*B$5,0)<30,1.4,ROUND(Inputs!$F$8*B$5,0)*0.035)) -> 5.235 | C18: =ROUND(Inputs!$C$8*C$5,0)/100+IF(ROUND(Inputs!$D$8*C$5,0)=0,0,IF(ROUND(Inputs!$D$8*C$5,0)<60,1.4,ROUND(Inputs!$D$8*C$5,0)*0.05))+IF(ROUND(Inputs!$E$8*C$5,0)=0,0,IF(ROUND(Inputs!$E$8*C$5,0)<30,1.4,ROUND(Inputs!$E$8*C$5,0)*0.035))+IF(ROUND(Inputs!$F$8*C$5,0)=0,0,IF(ROUND(Inputs!$F$8*C$5,0)<30,1.4,ROUND(Inputs!$F$8*C$5,0)*0.035)) -> 5.41 | D18: =ROUND(Inputs!$C$8*D$5,0)/100+IF(ROUND(Inputs!$D$8*D$5,0)=0,0,IF(ROUND(Inputs!$D$8*D$5,0)<60,1.4,ROUND(Inputs!$D$8*D$5,0)*0.05))+IF(ROUND(Inputs!$E$8*D$5,0)=0,0,IF(ROUND(Inputs!$E$8*D$5,0)<30,1.4,ROUND(Inputs!$E$8*D$5,0)*0.035))+IF(ROUND(Inputs!$F$8*D$5,0)=0,0,IF(ROUND(Inputs!$F$8*D$5,0)<30,1.4,ROUND(Inputs!$F$8*D$5,0)*0.035)) -> 5.55 | E18: =ROUND(Inputs!$C$8*E$5,0)/100+IF(ROUND(Inputs!$D$8*E$5,0)=0,0,IF(ROUND(Inputs!$D$8*E$5,0)<60,1.4,ROUND(Inputs!$D$8*E$5,0)*0.05))+IF(ROUND(Inputs!$E$8*E$5,0)=0,0,IF(ROUND(Inputs!$E$8*E$5,0)<30,1.4,ROUND(Inputs!$E$8*E$5,0)*0.035))+IF(ROUND(Inputs!$F$8*E$5,0)=0,0,IF(ROUND(Inputs!$F$8*E$5,0)<30,1.4,ROUND(Inputs!$F$8*E$5,0)*0.035)) -> 5.725 | F18: =ROUND(Inputs!$C$8*F$5,0)/100+IF(ROUND(Inputs!$D$8*F$5,0)=0,0,IF(ROUND(Inputs!$D$8*F$5,0)<60,1.4,ROUND(Inputs!$D$8*F$5,0)*0.05))+IF(ROUND(Inputs!$E$8*F$5,0)=0,0,IF(ROUND(Inputs!$E$8*F$5,0)<30,1.4,ROUND(Inputs!$E$8*F$5,0)*0.035))+IF(ROUND(Inputs!$F$8*F$5,0)=0,0,IF(ROUND(Inputs!$F$8*F$5,0)<30,1.4,ROUND(Inputs!$F$8*F$5,0)*0.035)) -> 5.865 | G18: =ROUND(Inputs!$C$8*G$5,0)/100+IF(ROUND(Inputs!$D$8*G$5,0)=0,0,IF(ROUND(Inputs!$D$8*G$5,0)<60,1.4,ROUND(Inputs!$D$8*G$5,0)*0.05))+IF(ROUND(Inputs!$E$8*G$5,0)=0,0,IF(ROUND(Inputs!$E$8*G$5,0)<30,1.4,ROUND(Inputs!$E$8*G$5,0)*0.035))+IF(ROUND(Inputs!$F$8*G$5,0)=0,0,IF(ROUND(Inputs!$F$8*G$5,0)<30,1.4,ROUND(Inputs!$F$8*G$5,0)*0.035)) -> 5.975 | H18: =ROUND(Inputs!$C$8*H$5,0)/100+IF(ROUND(Inputs!$D$8*H$5,0)=0,0,IF(ROUND(Inputs!$D$8*H$5,0)<60,1.4,ROUND(Inputs!$D$8*H$5,0)*0.05))+IF(ROUND(Inputs!$E$8*H$5,0)=0,0,IF(ROUND(Inputs!$E$8*H$5,0)<30,1.4,ROUND(Inputs!$E$8*H$5,0)*0.035))+IF(ROUND(Inputs!$F$8*H$5,0)=0,0,IF(ROUND(Inputs!$F$8*H$5,0)<30,1.4,ROUND(Inputs!$F$8*H$5,0)*0.035)) -> 6.04
A19: Social services | B19: =IF(ROUND(Inputs!$D$8*B$5,0)=0,0,ROUND(Inputs!$D$8*B$5,0)/120)+IF(ROUND(Inputs!$E$8*B$5,0)=0,0,ROUND(Inputs!$E$8*B$5,0)/80)+ROUND(ROUND(Inputs!$F$8*B$5,0)*Inputs!$F$15,0)/25+(ROUND(Inputs!$F$8*B$5,0)-ROUND(ROUND(Inputs!$F$8*B$5,0)*Inputs!$F$15,0))/50 -> 1.6491667 | C19: =IF(ROUND(Inputs!$D$8*C$5,0)=0,0,ROUND(Inputs!$D$8*C$5,0)/120)+IF(ROUND(Inputs!$E$8*C$5,0)=0,0,ROUND(Inputs!$E$8*C$5,0)/80)+ROUND(ROUND(Inputs!$F$8*C$5,0)*Inputs!$F$15,0)/25+(ROUND(Inputs!$F$8*C$5,0)-ROUND(ROUND(Inputs!$F$8*C$5,0)*Inputs!$F$15,0))/50 -> 1.7583333 | D19: =IF(ROUND(Inputs!$D$8*D$5,0)=0,0,ROUND(Inputs!$D$8*D$5,0)/120)+IF(ROUND(Inputs!$E$8*D$5,0)=0,0,ROUND(Inputs!$E$8*D$5,0)/80)+ROUND(ROUND(Inputs!$F$8*D$5,0)*Inputs!$F$15,0)/25+(ROUND(Inputs!$F$8*D$5,0)-ROUND(ROUND(Inputs!$F$8*D$5,0)*Inputs!$F$15,0))/50 -> 1.8483333 | E19: =IF(ROUND(Inputs!$D$8*E$5,0)=0,0,ROUND(Inputs!$D$8*E$5,0)/120)+IF(ROUND(Inputs!$E$8*E$5,0)=0,0,ROUND(Inputs!$E$8*E$5,0)/80)+ROUND(ROUND(Inputs!$F$8*E$5,0)*Inputs!$F$15,0)/25+(ROUND(Inputs!$F$8*E$5,0)-ROUND(ROUND(Inputs!$F$8*E$5,0)*Inputs!$F$15,0))/50 -> 1.9658333 | F19: =IF(ROUND(Inputs!$D$8*F$5,0)=0,0,ROUND(Inputs!$D$8*F$5,0)/120)+IF(ROUND(Inputs!$E$8*F$5,0)=0,0,ROUND(Inputs!$E$8*F$5,0)/80)+ROUND(ROUND(Inputs!$F$8*F$5,0)*Inputs!$F$15,0)/25+(ROUND(Inputs!$F$8*F$5,0)-ROUND(ROUND(Inputs!$F$8*F$5,0)*Inputs!$F$15,0))/50 -> 2.0758333 | G19: =IF(ROUND(Inputs!$D$8*G$5,0)=0,0,ROUND(Inputs!$D$8*G$5,0)/120)+IF(ROUND(Inputs!$E$8*G$5,0)=0,0,ROUND(Inputs!$E$8*G$5,0)/80)+ROUND(ROUND(Inputs!$F$8*G$5,0)*Inputs!$F$15,0)/25+(ROUND(Inputs!$F$8*G$5,0)-ROUND(ROUND(Inputs!$F$8*G$5,0)*Inputs!$F$15,0))/50 -> 2.1325 | H19: =IF(ROUND(Inputs!$D$8*H$5,0)=0,0,ROUND(Inputs!$D$8*H$5,0)/120)+IF(ROUND(Inputs!$E$8*H$5,0)=0,0,ROUND(Inputs!$E$8*H$5,0)/80)+ROUND(ROUND(Inputs!$F$8*H$5,0)*Inputs!$F$15,0)/25+(ROUND(Inputs!$F$8*H$5,0)-ROUND(ROUND(Inputs!$F$8*H$5,0)*Inputs!$F$15,0))/50 -> 2.1933333
A20: Laundry | B20: =ROUND(Inputs!$C$8*B$5,0)*Inputs!$C$51/Inputs!$C$52/40+ROUND(Inputs!$D$8*B$5,0)*Inputs!$D$51/Inputs!$C$52/40+ROUND(Inputs!$E$8*B$5,0)*Inputs!$E$51/Inputs!$C$52/40+ROUND(Inputs!$F$8*B$5,0)*Inputs!$F$51/Inputs!$C$52/40 -> 2.24365 | C20: =ROUND(Inputs!$C$8*C$5,0)*Inputs!$C$51/Inputs!$C$52/40+ROUND(Inputs!$D$8*C$5,0)*Inputs!$D$51/Inputs!$C$52/40+ROUND(Inputs!$E$8*C$5,0)*Inputs!$E$51/Inputs!$C$52/40+ROUND(Inputs!$F$8*C$5,0)*Inputs!$F$51/Inputs!$C$52/40 -> 2.3934 | D20: =ROUND(Inputs!$C$8*D$5,0)*Inputs!$C$51/Inputs!$C$52/40+ROUND(Inputs!$D$8*D$5,0)*Inputs!$D$51/Inputs!$C$52/40+ROUND(Inputs!$E$8*D$5,0)*Inputs!$E$51/Inputs!$C$52/40+ROUND(Inputs!$F$8*D$5,0)*Inputs!$F$51/Inputs!$C$52/40 -> 2.52905 | E20: =ROUND(Inputs!$C$8*E$5,0)*Inputs!$C$51/Inputs!$C$52/40+ROUND(Inputs!$D$8*E$5,0)*Inputs!$D$51/Inputs!$C$52/40+ROUND(Inputs!$E$8*E$5,0)*Inputs!$E$51/Inputs!$C$52/40+ROUND(Inputs!$F$8*E$5,0)*Inputs!$F$51/Inputs!$C$52/40 -> 2.68825 | F20: =ROUND(Inputs!$C$8*F$5,0)*Inputs!$C$51/Inputs!$C$52/40+ROUND(Inputs!$D$8*F$5,0)*Inputs!$D$51/Inputs!$C$52/40+ROUND(Inputs!$E$8*F$5,0)*Inputs!$E$51/Inputs!$C$52/40+ROUND(Inputs!$F$8*F$5,0)*Inputs!$F$51/Inputs!$C$52/40 -> 2.8239 | G20: =ROUND(Inputs!$C$8*G$5,0)*Inputs!$C$51/Inputs!$C$52/40+ROUND(Inputs!$D$8*G$5,0)*Inputs!$D$51/Inputs!$C$52/40+ROUND(Inputs!$E$8*G$5,0)*Inputs!$E$51/Inputs!$C$52/40+ROUND(Inputs!$F$8*G$5,0)*Inputs!$F$51/Inputs!$C$52/40 -> 2.9216 | H20: =ROUND(Inputs!$C$8*H$5,0)*Inputs!$C$51/Inputs!$C$52/40+ROUND(Inputs!$D$8*H$5,0)*Inputs!$D$51/Inputs!$C$52/40+ROUND(Inputs!$E$8*H$5,0)*Inputs!$E$51/Inputs!$C$52/40+ROUND(Inputs!$F$8*H$5,0)*Inputs!$F$51/Inputs!$C$52/40 -> 2.9831
A21: Transport | B21: =IF(ROUND(Inputs!$C$8*B$5,0)=0,0,ROUND(Inputs!$C$8*B$5,0)*0.006) -> 0.642 | C21: =IF(ROUND(Inputs!$C$8*C$5,0)=0,0,ROUND(Inputs!$C$8*C$5,0)*0.006) -> 0.684 | D21: =IF(ROUND(Inputs!$C$8*D$5,0)=0,0,ROUND(Inputs!$C$8*D$5,0)*0.006) -> 0.726 | E21: =IF(ROUND(Inputs!$C$8*E$5,0)=0,0,ROUND(Inputs!$C$8*E$5,0)*0.006) -> 0.768 | F21: =IF(ROUND(Inputs!$C$8*F$5,0)=0,0,ROUND(Inputs!$C$8*F$5,0)*0.006) -> 0.81 | G21: =IF(ROUND(Inputs!$C$8*G$5,0)=0,0,ROUND(Inputs!$C$8*G$5,0)*0.006) -> 0.834 | H21: =IF(ROUND(Inputs!$C$8*H$5,0)=0,0,ROUND(Inputs!$C$8*H$5,0)*0.006) -> 0.852
A22: MDS coordinator | B22: =IF(ROUND(Inputs!$F$8*B$5,0)=0,0,(ROUND(Inputs!$F$8*B$5,0)-ROUND(ROUND(Inputs!$F$8*B$5,0)*Inputs!$F$15,0))/45+ROUND(ROUND(Inputs!$F$8*B$5,0)*Inputs!$F$15,0)/30) -> 1 | C22: =IF(ROUND(Inputs!$F$8*C$5,0)=0,0,(ROUND(Inputs!$F$8*C$5,0)-ROUND(ROUND(Inputs!$F$8*C$5,0)*Inputs!$F$15,0))/45+ROUND(ROUND(Inputs!$F$8*C$5,0)*Inputs!$F$15,0)/30) -> 1.0777778 | D22: =IF(ROUND(Inputs!$F$8*D$5,0)=0,0,(ROUND(Inputs!$F$8*D$5,0)-ROUND(ROUND(Inputs!$F$8*D$5,0)*Inputs!$F$15,0))/45+ROUND(ROUND(Inputs!$F$8*D$5,0)*Inputs!$F$15,0)/30) -> 1.1222222 | E22: =IF(ROUND(Inputs!$F$8*E$5,0)=0,0,(ROUND(Inputs!$F$8*E$5,0)-ROUND(ROUND(Inputs!$F$8*E$5,0)*Inputs!$F$15,0))/45+ROUND(ROUND(Inputs!$F$8*E$5,0)*Inputs!$F$15,0)/30) -> 1.2 | F22: =IF(ROUND(Inputs!$F$8*F$5,0)=0,0,(ROUND(Inputs!$F$8*F$5,0)-ROUND(ROUND(Inputs!$F$8*F$5,0)*Inputs!$F$15,0))/45+ROUND(ROUND(Inputs!$F$8*F$5,0)*Inputs!$F$15,0)/30) -> 1.2555556 | G22: =IF(ROUND(Inputs!$F$8*G$5,0)=0,0,(ROUND(Inputs!$F$8*G$5,0)-ROUND(ROUND(Inputs!$F$8*G$5,0)*Inputs!$F$15,0))/45+ROUND(ROUND(Inputs!$F$8*G$5,0)*Inputs!$F$15,0)/30) -> 1.3 | H22: =IF(ROUND(Inputs!$F$8*H$5,0)=0,0,(ROUND(Inputs!$F$8*H$5,0)-ROUND(ROUND(Inputs!$F$8*H$5,0)*Inputs!$F$15,0))/45+ROUND(ROUND(Inputs!$F$8*H$5,0)*Inputs!$F$15,0)/30) -> 1.3333333
A23: Associate ED | B23: =IF((ROUND(Inputs!$C$8*B$5,0)+ROUND(Inputs!$D$8*B$5,0)+ROUND(Inputs!$E$8*B$5,0)+ROUND(Inputs!$F$8*B$5,0))>200,1,0) -> 1 | C23: =IF((ROUND(Inputs!$C$8*C$5,0)+ROUND(Inputs!$D$8*C$5,0)+ROUND(Inputs!$E$8*C$5,0)+ROUND(Inputs!$F$8*C$5,0))>200,1,0) -> 1 | D23: =IF((ROUND(Inputs!$C$8*D$5,0)+ROUND(Inputs!$D$8*D$5,0)+ROUND(Inputs!$E$8*D$5,0)+ROUND(Inputs!$F$8*D$5,0))>200,1,0) -> 1 | E23: =IF((ROUND(Inputs!$C$8*E$5,0)+ROUND(Inputs!$D$8*E$5,0)+ROUND(Inputs!$E$8*E$5,0)+ROUND(Inputs!$F$8*E$5,0))>200,1,0) -> 1 | F23: =IF((ROUND(Inputs!$C$8*F$5,0)+ROUND(Inputs!$D$8*F$5,0)+ROUND(Inputs!$E$8*F$5,0)+ROUND(Inputs!$F$8*F$5,0))>200,1,0) -> 1 | G23: =IF((ROUND(Inputs!$C$8*G$5,0)+ROUND(Inputs!$D$8*G$5,0)+ROUND(Inputs!$E$8*G$5,0)+ROUND(Inputs!$F$8*G$5,0))>200,1,0) -> 1 | H23: =IF((ROUND(Inputs!$C$8*H$5,0)+ROUND(Inputs!$D$8*H$5,0)+ROUND(Inputs!$E$8*H$5,0)+ROUND(Inputs!$F$8*H$5,0))>200,1,0) -> 1
A24: Occupancy-invariant roles | B24: ='Staffing Model'!G6+'Staffing Model'!G10+'Staffing Model'!G11+'Staffing Model'!G13+'Staffing Model'!G14+'Staffing Model'!G18+'Staffing Model'!G21+'Staffing Model'!G22+'Staffing Model'!G23+'Staffing Model'!G30+'Staffing Model'!G31 -> 44.358186 | C24: ='Staffing Model'!G6+'Staffing Model'!G10+'Staffing Model'!G11+'Staffing Model'!G13+'Staffing Model'!G14+'Staffing Model'!G18+'Staffing Model'!G21+'Staffing Model'!G22+'Staffing Model'!G23+'Staffing Model'!G30+'Staffing Model'!G31 -> 44.358186 | D24: ='Staffing Model'!G6+'Staffing Model'!G10+'Staffing Model'!G11+'Staffing Model'!G13+'Staffing Model'!G14+'Staffing Model'!G18+'Staffing Model'!G21+'Staffing Model'!G22+'Staffing Model'!G23+'Staffing Model'!G30+'Staffing Model'!G31 -> 44.358186 | E24: ='Staffing Model'!G6+'Staffing Model'!G10+'Staffing Model'!G11+'Staffing Model'!G13+'Staffing Model'!G14+'Staffing Model'!G18+'Staffing Model'!G21+'Staffing Model'!G22+'Staffing Model'!G23+'Staffing Model'!G30+'Staffing Model'!G31 -> 44.358186 | F24: ='Staffing Model'!G6+'Staffing Model'!G10+'Staffing Model'!G11+'Staffing Model'!G13+'Staffing Model'!G14+'Staffing Model'!G18+'Staffing Model'!G21+'Staffing Model'!G22+'Staffing Model'!G23+'Staffing Model'!G30+'Staffing Model'!G31 -> 44.358186 | G24: ='Staffing Model'!G6+'Staffing Model'!G10+'Staffing Model'!G11+'Staffing Model'!G13+'Staffing Model'!G14+'Staffing Model'!G18+'Staffing Model'!G21+'Staffing Model'!G22+'Staffing Model'!G23+'Staffing Model'!G30+'Staffing Model'!G31 -> 44.358186 | H24: ='Staffing Model'!G6+'Staffing Model'!G10+'Staffing Model'!G11+'Staffing Model'!G13+'Staffing Model'!G14+'Staffing Model'!G18+'Staffing Model'!G21+'Staffing Model'!G22+'Staffing Model'!G23+'Staffing Model'!G30+'Staffing Model'!G31 -> 44.358186 | I24: ED, sales, plant, housekeeping, DON, security, foundation, employee dining, shift supervisor
A25: TOTAL recommended FTE | B25: =B13+B14+B15+B16+B17+B18+B19+B20+B21+B22+B23+B24 -> 149.5493 | C25: =C13+C14+C15+C16+C17+C18+C19+C20+C21+C22+C23+C24 -> 157.82921 | D25: =D13+D14+D15+D16+D17+D18+D19+D20+D21+D22+D23+D24 -> 163.47151 | E25: =E13+E14+E15+E16+E17+E18+E19+E20+E21+E22+E23+E24 -> 169.28145 | F25: =F13+F14+F15+F16+F17+F18+F19+F20+F21+F22+F23+F24 -> 175.22318 | G25: =G13+G14+G15+G16+G17+G18+G19+G20+G21+G22+G23+G24 -> 178.82036 | H25: =H13+H14+H15+H16+H17+H18+H19+H20+H21+H22+H23+H24 -> 181.42812
A26: Current FTE (held constant) | B26: =Inputs!C113 -> 159.5 | C26: =Inputs!C113 -> 159.5 | D26: =Inputs!C113 -> 159.5 | E26: =Inputs!C113 -> 159.5 | F26: =Inputs!C113 -> 159.5 | G26: =Inputs!C113 -> 159.5 | H26: =Inputs!C113 -> 159.5 | I26: Today's headcount
A27: Variance to current | B27: =B26-B25 -> 9.9506987 | C27: =C26-C25 -> 1.6707855 | D27: =D26-D25 -> -3.9715067 | E27: =E26-E25 -> -9.7814468 | F27: =F26-F25 -> -15.723183 | G27: =G26-G25 -> -19.320362 | H27: =H26-H25 -> -21.928124 | I27: Negative = understaffed for that occupancy
A28: FTE per occupied unit | B28: =IFERROR(B25/B11,0) -> 0.70876446 | C28: =IFERROR(C25/C11,0) -> 0.70459471 | D28: =IFERROR(D25/D11,0) -> 0.68685507 | E28: =IFERROR(E25/E11,0) -> 0.67175177 | F28: =IFERROR(F25/F11,0) -> 0.65873377 | G28: =IFERROR(G25/G11,0) -> 0.65262906 | H28: =IFERROR(H25/H11,0) -> 0.64795758
A29: Financial result at each occupancy
A30: Revenue | B30: =ROUND(Inputs!$C$8*B$5,0)*Inputs!$C$31*12+ROUND(Inputs!$D$8*B$5,0)*Inputs!$D$31*12+ROUND(Inputs!$E$8*B$5,0)*Inputs!$E$31*12+ROUND(Inputs!$F$8*B$5,0)*Inputs!$F$31*365 -> 16947930 | C30: =ROUND(Inputs!$C$8*C$5,0)*Inputs!$C$31*12+ROUND(Inputs!$D$8*C$5,0)*Inputs!$D$31*12+ROUND(Inputs!$E$8*C$5,0)*Inputs!$E$31*12+ROUND(Inputs!$F$8*C$5,0)*Inputs!$F$31*365 -> 18007740 | D30: =ROUND(Inputs!$C$8*D$5,0)*Inputs!$C$31*12+ROUND(Inputs!$D$8*D$5,0)*Inputs!$D$31*12+ROUND(Inputs!$E$8*D$5,0)*Inputs!$E$31*12+ROUND(Inputs!$F$8*D$5,0)*Inputs!$F$31*365 -> 19112480 | E30: =ROUND(Inputs!$C$8*E$5,0)*Inputs!$C$31*12+ROUND(Inputs!$D$8*E$5,0)*Inputs!$D$31*12+ROUND(Inputs!$E$8*E$5,0)*Inputs!$E$31*12+ROUND(Inputs!$F$8*E$5,0)*Inputs!$F$31*365 -> 20257490 | F30: =ROUND(Inputs!$C$8*F$5,0)*Inputs!$C$31*12+ROUND(Inputs!$D$8*F$5,0)*Inputs!$D$31*12+ROUND(Inputs!$E$8*F$5,0)*Inputs!$E$31*12+ROUND(Inputs!$F$8*F$5,0)*Inputs!$F$31*365 -> 21362230 | G30: =ROUND(Inputs!$C$8*G$5,0)*Inputs!$C$31*12+ROUND(Inputs!$D$8*G$5,0)*Inputs!$D$31*12+ROUND(Inputs!$E$8*G$5,0)*Inputs!$E$31*12+ROUND(Inputs!$F$8*G$5,0)*Inputs!$F$31*365 -> 22022370 | H30: =ROUND(Inputs!$C$8*H$5,0)*Inputs!$C$31*12+ROUND(Inputs!$D$8*H$5,0)*Inputs!$D$31*12+ROUND(Inputs!$E$8*H$5,0)*Inputs!$E$31*12+ROUND(Inputs!$F$8*H$5,0)*Inputs!$F$31*365 -> 22507240
A31: Non-labour variable expense | B31: =ROUND(Inputs!$C$8*B$5,0)*Inputs!$C$32*12+ROUND(Inputs!$D$8*B$5,0)*Inputs!$D$32*12+ROUND(Inputs!$E$8*B$5,0)*Inputs!$E$32*12+ROUND(Inputs!$F$8*B$5,0)*Inputs!$F$32*365 -> 2461920 | C31: =ROUND(Inputs!$C$8*C$5,0)*Inputs!$C$32*12+ROUND(Inputs!$D$8*C$5,0)*Inputs!$D$32*12+ROUND(Inputs!$E$8*C$5,0)*Inputs!$E$32*12+ROUND(Inputs!$F$8*C$5,0)*Inputs!$F$32*365 -> 2626080 | D31: =ROUND(Inputs!$C$8*D$5,0)*Inputs!$C$32*12+ROUND(Inputs!$D$8*D$5,0)*Inputs!$D$32*12+ROUND(Inputs!$E$8*D$5,0)*Inputs!$E$32*12+ROUND(Inputs!$F$8*D$5,0)*Inputs!$F$32*365 -> 2776320 | E31: =ROUND(Inputs!$C$8*E$5,0)*Inputs!$C$32*12+ROUND(Inputs!$D$8*E$5,0)*Inputs!$D$32*12+ROUND(Inputs!$E$8*E$5,0)*Inputs!$E$32*12+ROUND(Inputs!$F$8*E$5,0)*Inputs!$F$32*365 -> 2949840 | F31: =ROUND(Inputs!$C$8*F$5,0)*Inputs!$C$32*12+ROUND(Inputs!$D$8*F$5,0)*Inputs!$D$32*12+ROUND(Inputs!$E$8*F$5,0)*Inputs!$E$32*12+ROUND(Inputs!$F$8*F$5,0)*Inputs!$F$32*365 -> 3100080 | G31: =ROUND(Inputs!$C$8*G$5,0)*Inputs!$C$32*12+ROUND(Inputs!$D$8*G$5,0)*Inputs!$D$32*12+ROUND(Inputs!$E$8*G$5,0)*Inputs!$E$32*12+ROUND(Inputs!$F$8*G$5,0)*Inputs!$F$32*365 -> 3205200 | H31: =ROUND(Inputs!$C$8*H$5,0)*Inputs!$C$32*12+ROUND(Inputs!$D$8*H$5,0)*Inputs!$D$32*12+ROUND(Inputs!$E$8*H$5,0)*Inputs!$E$32*12+ROUND(Inputs!$F$8*H$5,0)*Inputs!$F$32*365 -> 3273600
A32: Fixed campus expense | B32: =Inputs!$C$33 -> 3100000 | C32: =Inputs!$C$33 -> 3100000 | D32: =Inputs!$C$33 -> 3100000 | E32: =Inputs!$C$33 -> 3100000 | F32: =Inputs!$C$33 -> 3100000 | G32: =Inputs!$C$33 -> 3100000 | H32: =Inputs!$C$33 -> 3100000
A33: Labour at recommended staffing | B33: =B25*IFERROR('Staffing Model'!L34/'Staffing Model'!G34,0) -> 8705093.3 | C33: =C25*IFERROR('Staffing Model'!L34/'Staffing Model'!G34,0) -> 9187057.6 | D33: =D25*IFERROR('Staffing Model'!L34/'Staffing Model'!G34,0) -> 9515488.9 | E33: =E25*IFERROR('Staffing Model'!L34/'Staffing Model'!G34,0) -> 9853678.9 | F33: =F25*IFERROR('Staffing Model'!L34/'Staffing Model'!G34,0) -> 10199541 | G33: =G25*IFERROR('Staffing Model'!L34/'Staffing Model'!G34,0) -> 10408928 | H33: =H25*IFERROR('Staffing Model'!L34/'Staffing Model'!G34,0) -> 10560723 | I33: Recommended FTE at the blended loaded cost per FTE
A34: Net operating income | B34: =B30-B31-B32-B33 -> 2680916.7 | C34: =C30-C31-C32-C33 -> 3094602.4 | D34: =D30-D31-D32-D33 -> 3720671.1 | E34: =E30-E31-E32-E33 -> 4353971.1 | F34: =F30-F31-F32-F33 -> 4962609.5 | G34: =G30-G31-G32-G33 -> 5308241.8 | H34: =H30-H31-H32-H33 -> 5572917
A35: Operating margin | B35: =IFERROR(B34/B30,0) -> 0.15818549 | C35: =IFERROR(C34/C30,0) -> 0.17184846 | D35: =IFERROR(D34/D30,0) -> 0.19467233 | E35: =IFERROR(E34/E30,0) -> 0.21493142 | F35: =IFERROR(F34/F30,0) -> 0.23230765 | G35: =IFERROR(G34/G30,0) -> 0.24103863 | H35: =IFERROR(H34/H30,0) -> 0.24760553
A36: Labour as % of revenue | B36: =IFERROR(B33/B30,0) -> 0.51363755 | C36: =IFERROR(C33/C30,0) -> 0.51017271 | D36: =IFERROR(D33/D30,0) -> 0.49786783 | E36: =IFERROR(E33/E30,0) -> 0.48642151 | F36: =IFERROR(F33/F30,0) -> 0.47745673 | G36: =IFERROR(G33/G30,0) -> 0.4726525 | H36: =IFERROR(H33/H30,0) -> 0.46921448
A38: Read across: revenue rises faster than cost because fixed campus expense and the occupancy-invariant roles do not move with census. That spread is the entire economic case for filling units, and it is why the margin line steepens as occupancy climbs.
A39: Labour here is priced at the blended loaded cost per recommended FTE from the Staffing Model sheet, rather than position by position, so it will differ by a small amount from the Financials sheet where every role carries its own wage.

Sheet Staffing Model
A1: Staffing Model
A3: Recommended FTE computed live from the occupancy on the Inputs sheet. Change occupancy there and every figure on this sheet moves. Ratios, meals per labour hour, square feet per FTE and the night-shift floor are all editable on Inputs.
A5: Position | B5: IL | C5: AL | D5: MC | E5: SNF | F5: Campus | G5: Model FTE | H5: Current | I5: Variance | J5: Cost of gap | K5: Driver | L5: Model labour $ | M5: Current labour $
A6: Executive Director / SNF Administrator (NHA) | B6: 0 | C6: 0 | D6: 0 | E6: =IF(Inputs!F8>0,IF(AND(Inputs!$C$22="Yes",OR(Inputs!C14>0,Inputs!D14>0,Inputs!E14>0),Inputs!F8<60,Inputs!$C$25="Single"),0,1),0) -> 0 | F6: =IF(OR(Inputs!C14>0,Inputs!D14>0,Inputs!E14>0),1,0) -> 1 | G6: =SUM(B6:F6) -> 1 | H6: =Inputs!C90 -> 1 | I6: =H6-G6 -> 0 | J6: =IF(I6<0,-I6*Inputs!D57,0) -> 0 | K6: Campus ED plus a dedicated NHA unless CCRC consolidation applies | L6: =G6*Inputs!D57 -> 157331.2 | M6: =H6*Inputs!D57 -> 157331.2
A7: Associate ED | B7: 0 | C7: 0 | D7: 0 | E7: 0 | F7: =IF(Inputs!E19>200,1,0) -> 1 | G7: =SUM(B7:F7) -> 1 | H7: =Inputs!C91 -> 1 | I7: =H7-G7 -> 0 | J7: =IF(I7<0,-I7*Inputs!D58,0) -> 0 | K7: Fires above 200 total census | L7: =G7*Inputs!D58 -> 111654.4 | M7: =H7*Inputs!D58 -> 111654.4
A8: Business office / billing | B8: =IF(Inputs!C14=0,0,IF(Inputs!C14<125,1,Inputs!C14*0.005)) -> 0.655 | C8: =IF(Inputs!D14>75,1,Inputs!D14*0.005) -> 0.265 | D8: =IF(Inputs!E14>75,1,Inputs!E14*0.005) -> 0.13 | E8: =IF(Inputs!F14>0,1,0) -> 1 | F8: 0 | G8: =SUM(B8:F8) -> 2.05 | H8: =Inputs!C92 -> 3 | I8: =H8-G8 -> 0.95 | J8: =IF(I8<0,-I8*Inputs!D59,0) -> 0 | K8: 0.5% of occupancy per level; SNF binary | L8: =G8*Inputs!D59 -> 140456.16 | M8: =H8*Inputs!D59 -> 205545.6
A9: Concierge / front desk | B9: =IF(Inputs!C14>0,4.2,0) -> 4.2 | C9: =IF(Inputs!D14<45,Inputs!D14*0.005,1) -> 1 | D9: =Inputs!E14*0.005 -> 0.13 | E9: =IF(Inputs!F14>40,2.1,0) -> 2.1 | F9: 0 | G9: =SUM(B9:F9) -> 7.43 | H9: =Inputs!C93 -> 7 | I9: =H9-G9 -> -0.43 | J9: =IF(I9<0,-I9*Inputs!D60,0) -> 18549.856 | K9: IL desk is 24/7 cover at 4.2 FTE | L9: =G9*Inputs!D60 -> 320524.26 | M9: =H9*Inputs!D60 -> 301974.4
A10: Sales / marketing / admissions | B10: =IF(Inputs!C8=0,0,IF(Inputs!C8<100,1,Inputs!C8/100)) -> 1.42 | C10: =IF(Inputs!D8=0,0,IF(Inputs!D8<40,1,Inputs!D8/40)) -> 1.45 | D10: =IF(Inputs!E8=0,0,IF(Inputs!E8<30,1,Inputs!E8/30)) -> 1 | E10: =IF(Inputs!F16=0,0,IF(Inputs!F16<30,1,Inputs!F16/30))+IF(Inputs!F17=0,0,IF(Inputs!F17<30,1,Inputs!F17/30)) -> 2.1 | F10: 0 | G10: =SUM(B10:F10) -> 5.97 | H10: =Inputs!C94 -> 5 | I10: =H10-G10 -> -0.97 | J10: =IF(I10<0,-I10*Inputs!D61,0) -> 83690.048 | K10: Driven by CAPACITY not occupancy - sized to build census | L10: =G10*Inputs!D61 -> 515082.05 | M10: =H10*Inputs!D61 -> 431392
A11: Program director | B11: 0 | C11: 0 | D11: 0 | E11: 0 | F11: 0 | G11: =SUM(B11:F11) -> 0 | H11: =Inputs!C95 -> 1 | I11: =H11-G11 -> 1 | J11: =IF(I11<0,-I11*Inputs!D62,0) -> 0 | K11: Model default 0 - manual role | L11: =G11*Inputs!D62 -> 0 | M11: =H11*Inputs!D62 -> 86278.4
A12: Dining | B12: =IFERROR(Inputs!C14*Inputs!C48*365/Inputs!C49/52/Inputs!$C$85*52,0) -> 10.449082 | C12: =IFERROR(Inputs!D14*Inputs!D48*365/Inputs!D49/52/Inputs!$C$85*52,0) -> 11.160577 | D12: =IFERROR(Inputs!E14*Inputs!E48*365/Inputs!E49/52/Inputs!$C$85*52,0) -> 4.5625 | E12: =IFERROR(Inputs!F14*Inputs!F48*365/Inputs!F49/52/Inputs!$C$85*52,0) -> 7.0693681 | F12: 0 | G12: =SUM(B12:F12) -> 33.241527 | H12: =Inputs!C96 -> 30 | I12: =H12-G12 -> -3.2415272 | J12: =IF(I12<0,-I12*Inputs!D63,0) -> 141482.03 | K12: Annual meals / MPLH / hours per FTE | L12: =G12*Inputs!D63 -> 1450883.6 | M12: =H12*Inputs!D63 -> 1309401.6
A13: Plant operations | B13: 0 | C13: 0 | D13: 0 | E13: 0 | F13: =IFERROR(SUM(Inputs!C9,Inputs!D9,Inputs!E9,Inputs!F9)/Inputs!C53,0) -> 5.512 | G13: =SUM(B13:F13) -> 5.512 | H13: =Inputs!C97 -> 5 | I13: =H13-G13 -> -0.512 | J13: =IF(I13<0,-I13*Inputs!D64,0) -> 34430.157 | K13: Campus square feet per FTE; grounds outsourced | L13: =G13*Inputs!D64 -> 370662.16 | M13: =H13*Inputs!D64 -> 336232
A14: DON / head nurse / care manager | B14: 0 | C14: =IF(OR(Inputs!D14>0,Inputs!E14>0),1,0) -> 1 | D14: 0 | E14: =IF(Inputs!F14>0,1,0) -> 1 | F14: 0 | G14: =SUM(B14:F14) -> 2 | H14: =Inputs!C98 -> 2 | I14: =H14-G14 -> 0 | J14: =IF(I14<0,-I14*Inputs!D65,0) -> 0 | K14: One care director covers AL+MC; SNF keeps its own DON | L14: =G14*Inputs!D65 -> 213158.4 | M14: =H14*Inputs!D65 -> 213158.4
A15: Human resources | B15: 0 | C15: 0 | D15: 0 | E15: 0 | F15: =IF(Inputs!$C$23="System",MAX(0.25,(SUM(G6:G14)+SUM(G16:G23)+G33)/70*0.25),IF((SUM(G6:G14)+SUM(G16:G23)+G33)>40,MAX(0.5,(SUM(G6:G14)+SUM(G16:G23)+G33)/70),(SUM(G6:G14)+SUM(G16:G23)+G33)/70)) -> 2.4417257 | G15: =SUM(B15:F15) -> 2.4417257 | H15: =Inputs!C99 -> 2 | I15: =H15-G15 -> -0.44172566 | J15: =IF(I15<0,-I15*Inputs!D66,0) -> 33627.691 | K15: Headcount driven; excludes itself from its own base | L15: =G15*Inputs!D66 -> 185883.69 | M15: =H15*Inputs!D66 -> 152256
A16: Activities / life enrichment | B16: =Inputs!C14/100 -> 1.31 | C16: =IF(Inputs!D14=0,0,IF(Inputs!D14<60,1.4,Inputs!D14*0.05)) -> 1.4 | D16: =IF(Inputs!E14=0,0,IF(Inputs!E14<30,1.4,Inputs!E14*0.035)) -> 1.4 | E16: =IF(Inputs!F14=0,0,IF(Inputs!F14<30,1.4,Inputs!F14*0.035)) -> 1.645 | F16: 0 | G16: =SUM(B16:F16) -> 5.755 | H16: =Inputs!C100 -> 5.4 | I16: =H16-G16 -> -0.355 | J16: =IF(I16<0,-I16*Inputs!D67,0) -> 17116.112 | K16: Floors of 1.4 keep programming alive in small levels | L16: =G16*Inputs!D67 -> 277473.87 | M16: =H16*Inputs!D67 -> 260357.76
A17: Social services | B17: 0 | C17: =IF(Inputs!D14=0,0,Inputs!D14/120) -> 0.44166667 | D17: =IF(Inputs!E14=0,0,Inputs!E14/80) -> 0.325 | E17: =IFERROR(Inputs!F16/25+Inputs!F17/50,0) -> 1.22 | F17: 0 | G17: =SUM(B17:F17) -> 1.9866667 | H17: =Inputs!C101 -> 2 | I17: =H17-G17 -> 0.013333333 | J17: =IF(I17<0,-I17*Inputs!D68,0) -> 0 | K17: Short-stay weighted heavier than long-term care | L17: =G17*Inputs!D68 -> 120992.77 | M17: =H17*Inputs!D68 -> 121804.8
A18: Housekeeping | B18: =IFERROR(Inputs!C9/Inputs!C50,0) -> 6.72 | C18: =IFERROR(Inputs!D9/Inputs!D50,0) -> 2.32 | D18: =IFERROR(Inputs!E9/Inputs!E50,0) -> 2.45 | E18: =IFERROR(Inputs!F9/Inputs!F50,0) -> 5.2 | F18: 0 | G18: =SUM(B18:F18) -> 16.69 | H18: =Inputs!C102 -> 15 | I18: =H18-G18 -> -1.69 | J18: =IF(I18<0,-I18*Inputs!D69,0) -> 70332.122 | K18: Square-foot driven - does not move with occupancy | L18: =G18*Inputs!D69 -> 694581.72 | M18: =H18*Inputs!D69 -> 624249.6
A19: Laundry | B19: =IFERROR(Inputs!C14*Inputs!C51/Inputs!C52/40,0) -> 0.4192 | C19: =IFERROR(Inputs!D14*Inputs!D51/Inputs!C52/40,0) -> 0.50085 | D19: =IFERROR(Inputs!E14*Inputs!E51/Inputs!C52/40,0) -> 0.2457 | E19: =IFERROR(Inputs!F14*Inputs!F51/Inputs!C52/40,0) -> 1.551 | F19: 0 | G19: =SUM(B19:F19) -> 2.71675 | H19: =Inputs!C103 -> 3 | I19: =H19-G19 -> 0.28325 | J19: =IF(I19<0,-I19*Inputs!D70,0) -> 0 | K19: Pounds per resident week at the processing rate | L19: =G19*Inputs!D70 -> 110304.4 | M19: =H19*Inputs!D70 -> 121804.8
A20: Transport | B20: 0 | C20: 0 | D20: 0 | E20: 0 | F20: =IF(Inputs!C14=0,0,Inputs!C14*0.006) -> 0.786 | G20: =SUM(B20:F20) -> 0.786 | H20: =Inputs!C104 -> 0.8 | I20: =H20-G20 -> 0.014 | J20: =IF(I20<0,-I20*Inputs!D71,0) -> 0 | K20: Scales with IL residents | L20: =G20*Inputs!D71 -> 35901.965 | M20: =H20*Inputs!D71 -> 36541.44
A21: Security | B21: 0 | C21: 0 | D21: 0 | E21: 0 | F21: =IF(Inputs!$C$22="Yes",Inputs!C82,IF(AND(Inputs!C8>0,Inputs!$C$26="Yes"),Inputs!C82,0)) -> 5.12 | G21: =SUM(B21:F21) -> 5.12 | H21: =Inputs!C105 -> 4.6 | I21: =H21-G21 -> -0.52 | J21: =IF(I21<0,-I21*Inputs!D72,0) -> 25731.264 | K21: CCRC registration turns the post on | L21: =G21*Inputs!D72 -> 253353.98 | M21: =H21*Inputs!D72 -> 227622.72
A22: Foundation / giving | B22: 0 | C22: 0 | D22: 0 | E22: 0 | F22: =IF(AND(Inputs!$C$22="Yes",Inputs!$C$24="Nonprofit"),1,0) -> 1 | G22: =SUM(B22:F22) -> 1 | H22: =Inputs!C106 -> 1 | I22: =H22-G22 -> 0 | J22: =IF(I22<0,-I22*Inputs!D73,0) -> 0 | K22: Nonprofit CCRC only | L22: =G22*Inputs!D73 -> 91353.6 | M22: =H22*Inputs!D73 -> 91353.6
A23: Dining - employee meals | B23: 0 | C23: 0 | D23: 0 | E23: 0 | F23: =IFERROR(Inputs!$C$27*Inputs!C83*365/Inputs!C84/Inputs!$C$85,0) -> 2.8661859 | G23: =SUM(B23:F23) -> 2.8661859 | H23: =Inputs!C107 -> 2.5 | I23: =H23-G23 -> -0.3661859 | J23: =IF(I23<0,-I23*Inputs!D63,0) -> 15982.813 | K23: Employee meal volume at its own MPLH | L23: =G23*Inputs!D63 -> 125099.61 | M23: =H23*Inputs!D63 -> 109116.8
A24: Non-direct care subtotal | G24: =SUM(G6:G23) -> 97.565855 | H24: =SUM(H6:H23) -> 91.3 | I24: =SUM(I6:I23) -> -6.2658555 | J24: =SUM(J6:J23) -> 440942.09 | L24: =SUM(L6:L23) -> 5174697.9 | M24: =SUM(M6:M23) -> 4898075.5
A26: Direct care
A27: Position | B27: IL | C27: AL | D27: MC | E27: SNF | F27: Campus | G27: Model FTE | H27: Current | I27: Variance | J27: Cost of gap | K27: Driver
A28: CNA / aide | B28: 0 | C28: =IF(Inputs!D14=0,0,((Inputs!D14/Inputs!D38)+(Inputs!D14/Inputs!D39)+MAX(Inputs!D44,Inputs!D14/Inputs!D40))*8*7/40) -> 14.84 | D28: =IF(Inputs!E14=0,0,((Inputs!E14/Inputs!E38)+(Inputs!E14/Inputs!E39)+MAX(Inputs!E44,Inputs!E14/Inputs!E40))*8*7/40) -> 12.133333 | E28: =IF(Inputs!F14=0,0,((Inputs!F14/Inputs!F38)+(Inputs!F14/Inputs!F39)+MAX(Inputs!F44,Inputs!F14/Inputs!F40))*8*7/40) -> 21.933333 | F28: 0 | G28: =SUM(B28:F28) -> 48.906667 | H28: =Inputs!C108 -> 43 | I28: =H28-G28 -> -5.9066667 | J28: =IF(I28<0,-I28*Inputs!D74,0) -> 320759.41 | K28: Three-shift ratio model with the night floor from Inputs | L28: =G28*Inputs!D74 -> 2655858.9 | M28: =H28*Inputs!D74 -> 2335099.5
A29: Nurse / med aide | B29: 0 | C29: =IF(Inputs!D14=0,0,(MAX(1,Inputs!D14/Inputs!D41)+MAX(1,Inputs!D14/Inputs!D42)+MAX(1,Inputs!D14/Inputs!D43))*8*7/40) -> 7.42 | D29: =IF(Inputs!E14=0,0,(MAX(1,Inputs!E14/Inputs!E41)+MAX(1,Inputs!E14/Inputs!E42)+MAX(1,Inputs!E14/Inputs!E43))*8*7/40) -> 4.2 | E29: =IF(Inputs!F14=0,0,(MAX(1,Inputs!F14/Inputs!F41)+MAX(1,Inputs!F14/Inputs!F42)+MAX(1,Inputs!F14/Inputs!F43))*8*7/40) -> 9.87 | F29: 0 | G29: =SUM(B29:F29) -> 21.49 | H29: =Inputs!C109 -> 19.6 | I29: =H29-G29 -> -1.89 | J29: =IF(I29<0,-I29*Inputs!D75,0) -> 157310.9 | K29: Minimum one nurse per shift at any occupied level | L29: =G29*Inputs!D75 -> 1788683.2 | M29: =H29*Inputs!D75 -> 1631372.3
A30: Specialty / GCM | B30: 0 | C30: 0 | D30: 0 | E30: 0 | F30: 0 | G30: =SUM(B30:F30) -> 0 | H30: =Inputs!C110 -> 0 | I30: =H30-G30 -> 0 | J30: =IF(I30<0,-I30*Inputs!D75,0) -> 0 | K30: Model default 0 - manual role | L30: =G30*Inputs!D75 -> 0 | M30: =H30*Inputs!D75 -> 0
A31: Shift supervisor | B31: 0 | C31: 0 | D31: 0 | E31: =IF(Inputs!F14>0,4.2,0) -> 4.2 | F31: 0 | G31: =SUM(B31:F31) -> 4.2 | H31: =Inputs!C111 -> 4.2 | I31: =H31-G31 -> 0 | J31: =IF(I31<0,-I31*Inputs!D76,0) -> 0 | K31: 24/7 SNF shift supervision | L31: =G31*Inputs!D76 -> 362369.28 | M31: =H31*Inputs!D76 -> 362369.28
A32: MDS coordinator | B32: 0 | C32: 0 | D32: 0 | E32: =IF(Inputs!F14=0,0,Inputs!F17/45+Inputs!F16/30) -> 1.2 | F32: 0 | G32: =SUM(B32:F32) -> 1.2 | H32: =Inputs!C112 -> 1.4 | I32: =H32-G32 -> 0.2 | J32: =IF(I32<0,-I32*Inputs!D77,0) -> 0 | K32: Short-stay weighted heavier; gated on any SNF census | L32: =G32*Inputs!D77 -> 109624.32 | M32: =H32*Inputs!D77 -> 127895.04
A33: Direct care subtotal | G33: =SUM(G28:G32) -> 75.796667 | H33: =SUM(H28:H32) -> 68.2 | I33: =SUM(I28:I32) -> -7.5966667 | J33: =SUM(J28:J32) -> 478070.31 | L33: =SUM(L28:L32) -> 4916535.7 | M33: =SUM(M28:M32) -> 4456736.1
A34: TOTAL - all positions | G34: =G24+G33 -> 173.36252 | H34: =H24+H33 -> 159.5 | I34: =I24+I33 -> -13.862522 | J34: =J24+J33 -> 919012.4 | L34: =L24+L33 -> 10091234 | M34: =M24+M33 -> 9354811.6
A36: Model labour is the recommended pattern at the selected occupancy. Current labour holds today's FTE constant at the same wages, so the two diverge as occupancy moves.

Sheet Financials
A1: Financial Model
A3: A pro forma at the occupancy selected on Inputs. Revenue and variable expense move with census; fixed campus expense does not. Labour is shown twice - at the staffing the model recommends for this occupancy, and at today's headcount held constant.
A5: Revenue
A6: Line | B6: IL | C6: AL | D6: MC | E6: SNF | F6: Total | G6: Basis
A7: Resident revenue | B7: =Inputs!C14*Inputs!C31*12 -> 6523800 | C7: =Inputs!D14*Inputs!D31*12 -> 4515600 | D7: =Inputs!E14*Inputs!E31*12 -> 2730000 | E7: =Inputs!F14*Inputs!F31*365 -> 6827690 | F7: =SUM(B7:E7) -> 20597090 | G7: Occupied x rate. SNF is per patient day.
A9: Operating expense
A10: Line | B10: IL | C10: AL | D10: MC | E10: SNF | F10: Total | G10: Basis
A11: Non-labour variable expense | B11: =Inputs!C14*Inputs!C32*12 -> 534480 | C11: =Inputs!D14*Inputs!D32*12 -> 496080 | D11: =Inputs!E14*Inputs!E32*12 -> 305760 | E11: =Inputs!F14*Inputs!F32*365 -> 1646880 | F11: =SUM(B11:E11) -> 2983200 | G11: Food, supplies, variable utilities - moves with census
A12: Fixed campus expense | F12: =Inputs!C33 -> 3100000 | G12: Insurance, property, admin, base utilities
A13: Labour - at model staffing | F13: ='Staffing Model'!L34 -> 10091234 | G13: Recommended FTE at this occupancy x loaded wage
A14: Labour - at current staffing | F14: ='Staffing Model'!M34 -> 9354811.6 | G14: Today's FTE held constant - shown for comparison
A16: Result
A17: Line | E17: At model staffing | F17: At current staffing
A18: Total operating expense | E18: =F11+F12+F13 -> 16174434 | F18: =F11+F12+F14 -> 15438012
A19: Net operating income | E19: =F7-E18 -> 4422656.4 | F19: =F7-F18 -> 5159078.4
A20: Operating margin | E20: =IFERROR(E19/F7,0) -> 0.21472239 | F20: =IFERROR(F19/F7,0) -> 0.25047608
A21: Labour as % of revenue | E21: =IFERROR(F13/F7,0) -> 0.48993492 | F21: =IFERROR(F14/F7,0) -> 0.45418123
A22: Revenue per occupied unit / month | E22: =IFERROR(F7/Inputs!E19/12,0) -> 6678.6933 | F22: =IFERROR(F7/Inputs!E19/12,0) -> 6678.6933
A23: Operating expense per occupied unit / month | E23: =IFERROR(E18/Inputs!E19/12,0) -> 5244.6283 | F23: =IFERROR(F18/Inputs!E19/12,0) -> 5005.8404
A25: Benchmarks: CCRC operating margin 22.8% and labour 40% of revenue (SOSH 2025 / CARF 2024 medians). Revenue and expense per occupied unit benchmark to the SOSH segment tables. The scorecard scores these automatically.

Sheet KPI Scorecard
A1: KPI Scorecard - Operations KPI Catalog v9
A3: All 115 measures, scoped to the care levels selected on Inputs. Model-linked rows recompute when you change occupancy. Reported rows come from the uploaded operating reports and hold still. CMS rows are fetched from Care Compare.
A5: Code | B5: Measure | C5: Scope | D5: Value | E5: Basis | F5: Status | G5: Benchmark / target | H5: Benchmark source | I5: Intake screen | J5: Department
A6: Operations (8)
A7: OPS-01 | B7: Occupancy Rate by Care Level | C7: IL/AL/MC/SNF | D7: ="IL "&TEXT(Inputs!C13,"0.0%")&" | AL "&TEXT(Inputs!D13,"0.0%")&" | MC "&TEXT(Inputs!E13,"0.0%")&" | SNF "&TEXT(Inputs!F13,"0.0%") -> IL 92.3% | AL 91.4% | MC 92.9% | SNF 90.4% | E7: Model-linked | F7: =IF(AND(Inputs!C13>=0.878,Inputs!D13>=0.899,Inputs!E13>=0.86,Inputs!F13>=0.792),"On benchmark",IF(AND(Inputs!C13>=0.85,Inputs!D13>=0.87,Inputs!E13>=0.83),"Watch","Below")) -> On benchmark | G7: IL 87.8% | AL 89.9% | MC 86.0% | CCRC 90.6% | SNF 79.2% (CARF 2024) | H7: SOSH 2025 Table 2.7 (IL/AL/MC/CCRC); CARF 2025 Occupancy Trends (SNF) | I7: Census / occupancy report (Screen 09) | J7: Operations
A8: OPS-02 | B8: Net Census Change | C8: IL/AL/MC/SNF | D8: +9 units over T-12 | E8: Reported | F8: On benchmark | G8: Directional. Sector occupancy has risen ~0.5-0.7 pp/qtr for 17+ quarters; net decline against a rising market is the flag | H8: Rob Clark - internal standard | I8: Census / occupancy report (Screen 09) | J8: Operations
A9: OPS-03 | B9: Annual Resident Turnover by Care Level | C9: IL/AL/MC | D9: IL 21.4% | AL 46.2% | MC 61.5% | E9: Reported | F9: On benchmark | G9: IL 44.3% | AL 48.1% | MC 64.7% | CCRC 15.6% | H9: SOSH 2025 Table 2.15 | I9: Census / occupancy report (Screen 09) | J9: Operations
A10: OPS-04 | B10: Average Length of Stay by Care Level | C10: IL/AL/MC/SNF | D10: IL 4.7 yr | AL 2.2 yr | MC 1.6 yr | SNF 31 d | E10: Reported | F10: On benchmark | G10: Derived from SOSH turnover: IL ~2.3 yr | AL ~2.1 yr | MC ~1.5 yr. SNF Medicare LOS on own trend | H10: SOSH 2025 Table 2.15 (inverse of turnover); CMS MDS (SNF) | I10: Census report + clinical / MDS report (Screen 09) | J10: Operations
A11: OPS-05 | B11: Resident Satisfaction Score | C11: IL/AL/MC/SNF | D11: 88.4% | E11: Reported | F11: Watch | G11: RC 2025 target >= 90%. Reference: J.D. Power 2025 IL 753/1000; Holleran Choice Award > 85th percentile | H11: RC 2025 CCRC Benchmarks | I11: Manual entry (Screen 10) | J11: Operations
A12: OPS-06 | B12: Family Satisfaction Score | C12: IL/AL/MC/SNF | D12: 86.1% | E12: Reported | F12: Watch | G12: RC 2025 target >= 88%. Reference: J.D. Power 2025 AL/MC 867/1000 | H12: RC 2025 CCRC Benchmarks | I12: Manual entry (Screen 10) | J12: Operations
A13: OPS-07 | B13: Reportable Incident Rate | C13: IL/AL/MC/SNF | D13: 4.9 per 1,000 resident days | E13: Reported | F13: Watch | G13: Scored on the community's own trend. Component reference: falls 3.5-4.0 per 1,000 resident days | H13: Rob Clark - internal standard | I13: Incident and grievance log (Screen 09) | J13: Operations
A14: OPS-08 | B14: Grievance Resolution Time | C14: IL/AL/MC/SNF | D14: 11.4 day average close | 4.1 day acknowledgment | E14: Reported | F14: On benchmark | G14: Resolution <= 30 days; acknowledgment <= 5 business days | H14: CMS 42 CFR 483.10(j); CMS Medicare-plan 30-day grievance standard (reference) | I14: Incident and grievance log (Screen 09) | J14: Operations
A16: Sales and Marketing (11)
A17: SAL-01 | B17: Inquiries per 100 Units per Month | C17: IL/AL/MC | D17: IL 31 | AL 42 | MC 38 | E17: Reported | F17: Watch | G17: IL 37 | AL 45 | MC 41 | Life Plan Residential 30. Urban and rural cuts available | H17: Aline Sales and Marketing Benchmark Report Q1 2024 | I17: Sales / CRM report (Screen 09) + months in period (Screen 10) | J17: Sales and Marketing
A18: SAL-02 | B18: Tours per 100 Units per Month | C18: IL/AL/MC | D18: IL 7 | AL 10 | MC 12 | E18: Reported | F18: Watch | G18: IL 8 | AL 11 | MC 13 | Life Plan Residential 7 | H18: Aline Sales and Marketing Benchmark Report Q1 2024 | I18: Sales / CRM report (Screen 09) | J18: Sales and Marketing
A19: SAL-03 | B19: Move-Ins per 100 Units per Month | C19: IL/AL/MC | D19: IL 2.4 | AL 4.1 | MC 6.2 | E19: Reported | F19: Below | G19: IL 3 | AL 5 | MC 7 | Life Plan Residential 2 | H19: Aline Sales and Marketing Benchmark Report Q1 2024 | I19: Sales / CRM report (Screen 09) | J19: Sales and Marketing
A20: SAL-04 | B20: Inquiry-to-Tour Conversion Rate | C20: IL/AL/MC | D20: IL 23% | AL 24% | MC 32% | E20: Reported | F20: Below | G20: IL 28% | AL 29% | MC 36% | Life Plan Residential 29% | H20: Aline Sales and Marketing Benchmark Report Q1 2024 | I20: Sales / CRM report (Screen 09) | J20: Sales and Marketing
A21: SAL-05 | B21: Tour-to-Move-In Conversion Rate | C21: IL/AL/MC | D21: IL 34% | AL 41% | MC 52% | E21: Reported | F21: Watch | G21: IL 34% | AL 45% | MC 58% | Life Plan Residential 31% | H21: Aline Sales and Marketing Benchmark Report Q1 2024 | I21: Sales / CRM report (Screen 09) | J21: Sales and Marketing
A22: SAL-06 | B22: Inquiry Channel Mix | C22: IL/AL/MC | D22: Web 44% | Paid 21% | Call-in 26% | Referral 9% | E22: Reported | F22: Informational | G22: Web IL 40 / AL 43 / MC 35 / LPR 47 | Paid IL 27 / AL 32 / MC 34 / LPR 7 | Call-in IL 24 / AL 14 / MC 14 / LPR 32 | Unpaid IL 9 / AL 11 / MC 17 / LPR 14 (percent) | H22: Aline Sales and Marketing Benchmark Report Q1 2024 | I22: Sales / CRM report (Screen 09) | J22: Sales and Marketing
A23: SAL-07 | B23: Inquiry-to-Tour Conversion by Channel | C23: IL/AL/MC | D23: Unpaid referral 58% | Call-in 47% | Web 31% | E23: Reported | F23: Watch | G23: Unpaid referral IL 61 / AL 59 / MC 61 / LPR 51 | Call-in and other IL 50 / AL 55 / MC 56 / LPR 42 | Web IL 28 / AL 28 / MC 37 / LPR 28 | Paid and aggregator IL 22 / AL 27 / MC 36 / LPR 30 (percent) | H23: Aline Sales and Marketing Benchmark Report Q1 2024 | I23: Sales / CRM report (Screen 09) | J23: Sales and Marketing
A24: SAL-08 | B24: Average Rate Achieved vs Published Rate | C24: IL/AL/MC | D24: 4.6% concessions of gross rent | E24: Reported | F24: Below | G24: Concessions < 3% of gross rent | H24: SOSH 2025; operator rate sheet | I24: Rate sheet (Screen 04) + sales / CRM report (Screen 09) + published ra | J24: Sales and Marketing
A25: SAL-09 | B25: Online Reputation Score | C25: IL/AL/MC/SNF | D25: 4.5 stars, 214 reviews, 71% response | E25: Reported | F25: Watch | G25: RC 2025 target >= 4.3 stars. Practice standard 4.5+ stars, 50+ reviews, 100% response rate | H25: RC 2025 CCRC Benchmarks | I25: Manual entry with source platform (Screen 10) | J25: Sales and Marketing
A26: SAL-10 | B26: Deposit-to-Move-In Conversion Rate | C26: IL/AL/MC/SNF | D26: 86.2% | E26: Reported | F26: On benchmark | G26: 80-90% deposit-to-move-in; target 85% | H26: RC 2025 CCRC Performance Benchmarks; Kushant Shah internal standard | I26: TO BE MAPPED - added from Gap Matrix v9; intake screen not yet assigne | J26: Sales and Marketing
A27: SAL-11 | B27: Cost per Acquired Resident | C27: IL/AL/MC/SNF | D27: $4,180 per acquired resident | E27: Reported | F27: Watch | G27: Community-specific ceiling = (marketing spend at 2-3% of operating expenses) / expected annual move-ins | H27: RC 2025 CCRC Performance Benchmarks - CDS Best Practice Metrics 2025 (advisor material, de | I27: TO BE MAPPED - added from Gap Matrix v9; intake screen not yet assigne | J27: Sales and Marketing
A29: Nursing (12)
A30: NUR-01 | B30: Medication Administration Error Rate | C30: AL/MC/SNF | D30: 1.6% error rate | 98.4% accuracy | E30: Reported | F30: On benchmark | G30: RC 2025: >= 98% administration accuracy, < 2% error rate | H30: RC 2025 CCRC Benchmarks | I30: Clinical / EHR report (Screen 09) | J30: Nursing
A31: NUR-02 | B31: Fall Rate per 1,000 Resident Days | C31: AL/MC | D31: 3.8 per 1,000 resident days | E31: Reported | F31: On benchmark | G31: 3.5-4.0 falls per 1,000 resident days | H31: Rob Clark - internal standard | I31: Clinical / EHR report + incident log (Screen 09) | J31: Nursing
A32: NUR-03 | B32: Unplanned Hospital Transfer Rate | C32: AL/MC | D32: 8.9% readmission | 94% timely transitions | E32: Reported | F32: Watch | G32: RC 2025: >= 95% timely transitions, < 10% readmission | H32: RC 2025 CCRC Benchmarks (care transition efficiency) | I32: Clinical / EHR report (Screen 09) | J32: Nursing
A33: NUR-04 | B33: Service Plan Reassessment Timeliness | C33: AL/MC | D33: 97.2% on time | E33: Reported | F33: Watch | G33: 100% on time. Interval is state-specific and pulled from the state regulatory dataset | H33: State regulation (Advantedge State Regulatory Reference) | I33: Clinical / EHR report (Screen 09) | J33: Nursing
A34: NUR-05 | B34: Resident Acuity and Care Tier Mix | C34: AL/MC | D34: Tier 3+ mix up 6 pts YoY, rate flat | E34: Reported | F34: Below | G34: Directional. Upward acuity migration without a matching rate or staffing response is the flag | H34: Internal trend, read against SOSH 2025 revenue per occupied unit | I34: Clinical / EHR report + census report (Screen 09) | J34: Nursing
A35: NUR-06 | B35: New Pressure Injury Incidence, Stage 2 and Above | C35: AL/MC | D35: 1.9% | E35: Reported | F35: On benchmark | G35: Trend to zero; CMS SNF long-stay rate as the external reference point | H35: CMS long-stay pressure ulcer QM distribution used as reference | I35: Clinical / EHR report (Screen 09) | J35: Nursing
A36: NUR-07 | B36: Elopement and Exit-Seeking Incidents | C36: AL/MC | D36: 2 exit-seeking events, 0 elopements | E36: Reported | F36: Watch | G36: Zero tolerance. Any event triggers review; trend scored on the community's own baseline | H36: State regulation; no published rate benchmark | I36: Incident and grievance log (Screen 09) | J36: Nursing
A37: NUR-08 | B37: Antipsychotic Use Rate | C37: AL/MC | D37: 12.8% | E37: Reported | F37: On benchmark | G37: CMS long-stay QM distribution as the external reference point | H37: CMS long-stay antipsychotic QM distribution used as reference | I37: Clinical / EHR report (Screen 09) | J37: Nursing
A38: NUR-09 | B38: MDS Assessment Completion Timeliness | C38: SNF | D38: 99.1% within window | E38: Reported | F38: Watch | G38: 100% transmitted within the required window | H38: CMS RAI Manual | I38: Clinical / EHR MDS report (Screen 09) | J38: Nursing
A39: NUR-10 | B39: ARD and Late Assessment Rate | C39: SNF | D39: 1.4% late ARD | E39: Reported | F39: Below | G39: Target 0%. Each late ARD defaults the stay to the lowest PDPM rate | H39: CMS RAI Manual; PDPM default rate exposure | I39: Clinical / EHR MDS report (Screen 09) | J39: Nursing
A40: NUR-11 | B40: PDPM Case Mix Index by Component | C40: SNF | D40: PT 1.42 | OT 1.38 | SLP 1.19 | Nursing 1.51 | NTA 1.09 | E40: Reported | F40: Informational | G40: Compare to national and state PDPM CMI distribution | H40: CMS FY2024 SNF PPS Final Rule nursing CMIs (ES3 3.84 down to PA1 0.62) | I40: Clinical / EHR MDS report (Screen 09) | J40: Nursing
A41: NUR-12 | B41: Care Plan Completion and Update Timeliness | C41: SNF | D41: 99.4% | E41: Reported | F41: Watch | G41: 100% | H41: CMS 42 CFR 483.21 (F656) | I41: Clinical / EHR report (Screen 09) | J41: Nursing
A43: Finance (12)
A44: FIN-01 | B44: Community Operating Margin by Care Level | C44: IL/AL/MC | D44: =TEXT(Financials!E20,"0.0%")&" at recommended staffing" -> 21.5% at recommended staffing | E44: Model-linked | F44: =IF(Financials!E20>=0.228,"On benchmark",IF(Financials!E20>=0.205,"Watch","Below")) -> Watch | G44: IL 31.2% | AL 24.5% | MC 21.7% | CCRC 22.8% | H44: SOSH 2025 Table 3.27 (for-profit) | I44: T-12 P&L (Screen 07) + GL (Screen 06) + chart of accounts (Screen 05) | J44: Finance
A45: FIN-02 | B45: Entity Operating Margin and Net Operating Margin | C45: Entity | D45: =TEXT(Financials!E20,"0.0%")&" entity operating margin" -> 21.5% entity operating margin | E45: Model-linked | F45: =IF(Financials!E20>=0.228,"On benchmark",IF(Financials!E20>=0.205,"Watch","Below")) -> Watch | G45: CARF 2024 medians: OM 0.29% single-site / 1.00% multi-site; NOM 6.19% / 5.77%. RC 2025 target >= 3% | H45: CARF 2025 Financial Ratios and Trend Analysis; RC 2025 | I45: Trial balance or balance sheet (Screen 07) + T-12 P&L | J45: Finance
A46: FIN-03 | B46: Revenue per Occupied Unit by Care Level | C46: IL/AL/MC/SNF | D46: =TEXT(Financials!E22,"$#,##0")&" per occupied unit per month" -> $6,679 per occupied unit per month | E46: Model-linked | F46: Informational | G46: SOSH segment median by care level. CPI toggle applies to all dollar measures | H46: SOSH 2025 revenue per occupied unit (CPI-adjusted); CLA 40th Annual SNF (per patient day) | I46: T-12 P&L (Screen 07) + census report (Screen 09) | J46: Finance
A47: FIN-04 | B47: Operating Expense per Occupied Unit by Care Level | C47: IL/AL/MC/SNF | D47: =TEXT(Financials!E23,"$#,##0")&" per occupied unit per month" -> $5,245 per occupied unit per month | E47: Model-linked | F47: Informational | G47: SOSH segment median by care level. CPI toggle applies | H47: SOSH 2025 expense per occupied unit (CPI-adjusted); CLA 40th Annual SNF | I47: GL (Screen 06) + chart of accounts (Screen 05) + census report | J47: Finance
A48: FIN-05 | B48: Labor Cost as Percent of Revenue | C48: IL/AL/MC/SNF | D48: =TEXT(Financials!E21,"0.0%")&" at recommended staffing" -> 49.0% at recommended staffing | E48: Model-linked | F48: =IF(Financials!E21<=0.4,"On benchmark",IF(Financials!E21<=0.44,"Watch","Below")) -> Below | G48: IL 28% | AL 39% | AL/MC 46% | CCRC 40% | H48: SOSH 2025 Tables 3.1-3.7 | I48: GL (Screen 06) + T-12 P&L (Screen 07) | J48: Finance
A49: FIN-06 | B49: Payer Mix by Care Level | C49: IL/AL/MC/SNF | D49: SNF: Medicaid 54% | Medicare A 18% | MA 14% | Private 14% | E49: Reported | F49: Informational | G49: SNF: Medicaid ~62.2%, Medicare FFS ~7.8%, other including Medicare Advantage ~30%. IL and AL predominantly private pay, with state Medicaid waiver share where applicable | H49: CLA 40th Annual SNF (approx 11,700 Medicare cost reports); SOSH 2025 | I49: Census report (Screen 09) + billing / AR detail | J49: Finance
A50: FIN-07 | B50: Days in Accounts Receivable | C50: Entity | D50: 38.4 days | E50: Reported | F50: Watch | G50: CARF 2024 medians: 14 days single-site, 18 days multi-site. Under 30 days desired | H50: CARF 2025 Financial Ratios and Trend Analysis | I50: Trial balance or balance sheet (Screen 07) + T-12 P&L | J50: Finance
A51: FIN-08 | B51: Days Cash on Hand | C51: Entity | D51: 168 days | E51: Reported | F51: Watch | G51: CARF 2024 medians: 437 days single-site, 291 days multi-site. RC 2025 target >= 180 days, 120 minimum | H51: CARF 2025; RC 2025 | I51: Trial balance or balance sheet (Screen 07) | J51: Finance
A52: FIN-09 | B52: Debt Service Coverage Ratio | C52: Entity | D52: 1.41x | E52: Reported | F52: On benchmark | G52: CARF 2024 medians: 3.00x single-site, 2.77x multi-site. RC 2025 target >= 1.25x. Typical bond covenant minimum 1.20x | H52: CARF 2025; RC 2025 | I52: Debt schedule (Screen 08) + trial balance (Screen 07) | J52: Finance
A53: FIN-10 | B53: Entrance Fee Refund Liability Funding | C53: Entity | D53: Refund liability $6.1M | funded 78% | E53: Reported | F53: Watch | G53: RC 2025: >= 90% funded on an actuarial basis, or 100% funded | H53: RC 2025 CCRC Benchmarks | I53: Trial balance (Screen 07) + residency agreements (Screen 04) | J53: Finance
A54: FIN-11 | B54: Accounts Receivable Aging (Percent Over 90 Days) | C54: IL/AL/MC/SNF | D54: 14.1% over 90 days | E54: Reported | F54: On benchmark | G54: No more than 15% of total A/R aged over 90 days | H54: Kushant Shah internal standard | I54: TO BE MAPPED - added from Gap Matrix v9; intake screen not yet assigne | J54: Finance
A55: FIN-12 | B55: Bad Debt and Write-Off Rate | C55: IL/AL/MC/SNF | D55: 0.9% | E55: Reported | F55: On benchmark | G55: Write-offs below 1.5% of total operating revenue | H55: RC 2025 CCRC Performance Benchmarks; Kushant Shah internal standard | I55: TO BE MAPPED - added from Gap Matrix v9; intake screen not yet assigne | J55: Finance
A57: Human Resources (11)
A58: HR-01 | B58: Total Staff Turnover Rate | C58: IL/AL/MC/SNF | D58: 51.4% | E58: Reported | F58: Below | G58: RC 2025 target < 20% overall. Market reference: HCS 2024 SNF ~53.9% | H58: RC 2025 CCRC Benchmarks | I58: Payroll / turnover report (Screen 09) | J58: Human Resources
A59: HR-02 | B59: Frontline and Direct Care Turnover Rate | C59: IL/AL/MC/SNF | D59: 58.9% frontline | E59: Reported | F59: Below | G59: RC 2025 target < 35% frontline. Market reference: HCS 2024 CNA ~40%, AL resident assistant ~44% | H59: RC 2025 CCRC Benchmarks | I59: Payroll / turnover report (Screen 09) | J59: Human Resources
A60: HR-03 | B60: 90-Day New Hire Retention Rate | C60: IL/AL/MC/SNF | D60: 71.8% | E60: Reported | F60: Below | G60: > 80% | H60: Rob Clark - internal standard | I60: Payroll / turnover report (Screen 09) | J60: Human Resources
A61: HR-04 | B61: Position Vacancy Rate | C61: IL/AL/MC/SNF | D61: 8.9% | 17 open positions | E61: Reported | F61: Below | G61: < 5% of approved positions | H61: Rob Clark - internal standard | I61: Payroll report (Screen 09) + org chart (Screen 04) | J61: Human Resources
A62: HR-05 | B62: Agency and Contract Labor as Percent of Labor | C62: IL/AL/MC/SNF | D62: 9.4% of labour | E62: Reported | F62: Below | G62: < 5% of hours and < 5% of labor cost | H62: SOSH 2025 | I62: Payroll report (Screen 09) + GL (Screen 06) | J62: Human Resources
A63: HR-06 | B63: Overtime Rate | C63: IL/AL/MC/SNF | D63: 7.2% | E63: Reported | F63: Below | G63: < 5% of total hours | H63: Rob Clark - internal standard | I63: Payroll report (Screen 09) | J63: Human Resources
A64: HR-07 | B64: Absenteeism and Call-Off Rate | C64: IL/AL/MC/SNF | D64: 4.2% | E64: Reported | F64: Watch | G64: < 3-4% unscheduled absence | H64: Rob Clark - internal standard | I64: Payroll report (Screen 09) | J64: Human Resources
A65: HR-08 | B65: Employee Engagement and Satisfaction Score | C65: IL/AL/MC/SNF | D65: 3.6 / 5.0 | E65: Reported | F65: Watch | G65: RC 2025 target >= 85%. Reference: Holleran Choice Award > 85th percentile | H65: RC 2025 CCRC Benchmarks | I65: Manual entry (Screen 10) | J65: Human Resources
A66: HR-09 | B66: Mandatory Training Completion Rate and Hours | C66: IL/AL/MC/SNF | D66: 98.6% | 14.2 hrs per FTE | E66: Reported | F66: Watch | G66: 100% on-time completion. RC 2025: >= 24 hours clinical, >= 16 hours non-clinical per year | H66: RC 2025 CCRC Benchmarks; state and federal regulation | I66: Payroll / LMS report (Screen 09) | J66: Human Resources
A67: HR-10 | B67: Workers Compensation Cost as Percent of Wages | C67: IL/AL/MC/SNF | D67: 2.4% of wages | E67: Reported | F67: Watch | G67: Average 2.2% of wages (published range 0.1-13.1%) | H67: SOSH 2025 Tables 3.20-3.21 | I67: GL (Screen 06) + payroll report (Screen 09) | J67: Human Resources
A68: HR-11 | B68: Time to Fill | C68: IL/AL/MC/SNF | D68: 58 days | E68: Reported | F68: Below | G68: 30-45 days to fill clinical roles; target 45; flag above 60 | H68: RC 2025 CCRC Performance Benchmarks (advisor internal standard) | I68: TO BE MAPPED - added from Gap Matrix v9; intake screen not yet assigne | J68: Human Resources
A70: Plant and Maintenance (10)
A71: PLT-01 | B71: Work Orders per Resident Unit | C71: IL/AL/MC/SNF | D71: 0.71 work orders per unit per month | E71: Reported | F71: On benchmark | G71: 18 total per resident unit: 13 ad hoc, 5 preventive | H71: Siemens / Brightly Senior Living Maintenance Benchmarks (1,000+ organizations) | I71: Plant / maintenance report (Screen 09) | J71: Plant and Maintenance
A72: PLT-02 | B72: Work Order On-Time Completion Rate | C72: IL/AL/MC/SNF | D72: 86.4% on time | E72: Reported | F72: Watch | G72: 76% completed on time | H72: Siemens / Brightly Senior Living Maintenance Benchmarks | I72: Plant / maintenance report (Screen 09) | J72: Plant and Maintenance
A73: PLT-03 | B73: Maintenance Labor Hours per Resident Unit | C73: IL/AL/MC/SNF | D73: 0.42 labour hours per unit per month | E73: Reported | F73: On benchmark | G73: 14 hours per resident unit: 9 ad hoc, 5 preventive | H73: Siemens / Brightly Senior Living Maintenance Benchmarks | I73: Plant / maintenance report (Screen 09) | J73: Plant and Maintenance
A74: PLT-04 | B74: Average Days Overdue | C74: IL/AL/MC/SNF | D74: 19 days average overdue | E74: Reported | F74: Below | G74: 3.4 days overall: PM 5.6 days, ad hoc 2.4 days | H74: Siemens / Brightly Senior Living Maintenance Benchmarks | I74: Plant / maintenance report (Screen 09) | J74: Plant and Maintenance
A75: PLT-05 | B75: Average Days Open per Work Order | C75: IL/AL/MC/SNF | D75: 9.4 days average open | E75: Reported | F75: Watch | G75: 3.8 days open | H75: Siemens / Brightly Senior Living Maintenance Benchmarks | I75: Plant / maintenance report (Screen 09) | J75: Plant and Maintenance
A76: PLT-06 | B76: Resident Billings per Resident Unit | C76: IL/AL/MC/SNF | D76: $14.20 per unit per month | E76: Reported | F76: Informational | G76: $18 per resident unit | H76: Siemens / Brightly Senior Living Maintenance Benchmarks | I76: Plant / maintenance report (Screen 09) + GL (Screen 06) | J76: Plant and Maintenance
A77: PLT-07 | B77: Preventive Maintenance Completion Rate | C77: IL/AL/MC/SNF | D77: 81.2% | E77: Reported | F77: Below | G77: > 90% on-time. PM should hold about 28% of total work order volume | H77: Siemens / Brightly (PM = 5 of 18 work orders, about 28% of volume) | I77: Plant / maintenance report (Screen 09) | J77: Plant and Maintenance
A78: PLT-08 | B78: Life Safety and Fire Inspection Deficiencies | C78: IL/AL/MC/SNF | D78: 0 open life-safety deficiencies | E78: Reported | F78: On benchmark | G78: Zero open deficiencies; 100% cleared within the required window | H78: CMS Life Safety Code survey (SNF, from the PDC Survey Summary file); state fire marshal in | I78: Fire marshal reports (Screen 11, always manual); CMS LSC data for SNF | J78: Plant and Maintenance
A79: PLT-09 | B79: Average Age of Plant | C79: Entity | D79: 14.8 years | E79: Reported | F79: Watch | G79: CARF 2024 medians: 11.77 years single-site, 11.87 years multi-site. Rising age signals underinvestment | H79: CARF 2025 Financial Ratios and Trend Analysis | I79: Trial balance or balance sheet (Screen 07) | J79: Plant and Maintenance
A80: PLT-10 | B80: Energy Use Intensity | C80: IL/AL/MC/SNF | D80: 198 kBtu per square foot | E80: Reported | F80: On benchmark | G80: Median site EUI approximately 214 kBtu per square foot. ENERGY STAR score >= 75 is top quartile | H80: EPA ENERGY STAR Portfolio Manager, Senior Care Communities DataTrends | I80: GL utility accounts (Screen 06) + gross building area (Screen 10) | J80: Plant and Maintenance
A82: Life Enrichment (6)
A83: LE-01 | B83: Weekly Resident Participation Rate | C83: IL/AL/MC/SNF | D83: 78.9% | E83: Reported | F83: Watch | G83: > 80% weekly participation | H83: Rob Clark - internal standard | I83: Life enrichment / activity participation report (Screen 09) | J83: Life Enrichment
A84: LE-02 | B84: Programs Offered per Resident per Week | C84: IL/AL/MC/SNF | D84: 11.4 programs per resident per week | E84: Reported | F84: Watch | G84: Directional. Offering volume read against LE-01 participation is what identifies programming fit rather than programming quantity | H84: Rob Clark - internal standard | I84: Activity calendar (Screen 04) + activity participation report (Screen | J84: Life Enrichment
A85: LE-03 | B85: Programming Satisfaction Score | C85: IL/AL/MC/SNF | D85: 86.2% | E85: Reported | F85: On benchmark | G85: > 85% favorable. RC 2025 resident satisfaction target >= 90% | H85: RC 2025 resident experience; industry surveys | I85: Manual entry (Screen 10) | J85: Life Enrichment
A86: LE-04 | B86: Resident Technology Engagement Rate | C86: IL/AL/MC | D86: 64.1% of occupied units | E86: Reported | F86: Below | G86: >= 90% resident technology use | H86: RC 2025 CCRC Benchmarks | I86: Resident engagement system report (Screen 02 system inventory drives t | J86: Life Enrichment
A87: LE-05 | B87: Participation Mix by Wellness Dimension | C87: IL/AL/MC/SNF | D87: Physical 26% | Social 31% | Cognitive 18% | Spiritual 12% | Creative 13% | E87: Reported | F87: Informational | G87: Balanced coverage across dimensions; no dimension at zero | H87: Rob Clark - internal standard | I87: Activity calendar (Screen 04) + activity participation report (Screen | J87: Life Enrichment
A88: LE-06 | B88: Life Enrichment Programming Coverage | C88: IL/AL/MC/SNF | D88: 7-day coverage | 2 of 7 evenings | MC weekend 1.5 hrs/day | E88: Reported | F88: Below | G88: Minimum 8 hours per day, 7 days per week | H88: Rob Clark - internal standard | I88: TO BE MAPPED - added from an owner ruling 22 Sep 2026; intake screen n | J88: Life Enrichment
A90: Dining Services (9)
A91: DIN-01 | B91: Raw Food Cost per Resident Day | C91: IL/AL/MC/SNF | D91: =TEXT(IFERROR((Financials!F11*Inputs!C86)/(Inputs!E19*365),0),"$#,##0.00")&" per resident day" -> $5.72 per resident day | E91: Model-linked | F91: =IF(AND(IFERROR((Financials!F11*Inputs!C86)/(Inputs!E19*365),0)>=4.5,IFERROR((Financials!F11*Inputs!C86)/(Inputs!E19*365),0)<=6.5),"On benchmark","Watch") -> On benchmark | G91: SOSH segment median. Practitioner range approximately $4.50-$6.50 per resident day | H91: SOSH 2025 dietary cost per resident day, by care level (CPI-adjusted) | I91: GL (Screen 06) + chart of accounts (Screen 05) + census report (Screen | J91: Dining Services
A92: DIN-02 | B92: Total Dining Cost per Resident Day | C92: IL/AL/MC/SNF | D92: =TEXT(IFERROR(((Financials!F11*Inputs!C86)+'Staffing Model'!L12)/(Inputs!E19*365),0),"$#,##0.00")&" per resident day" -> $21.19 per resident day | E92: Model-linked | F92: Informational | G92: SOSH segment median by care level | H92: SOSH 2025 dietary expense per resident day (CPI-adjusted) | I92: GL (Screen 06) + census report (Screen 09) | J92: Dining Services
A93: DIN-03 | B93: Meal Participation Rate | C93: IL/AL/MC | D93: IL 88% | AL 79% | MC 64% | E93: Reported | F93: Watch | G93: IL > 90% | AL 75-85% | MC 60-75% | H93: Rob Clark - internal standard | I93: Dining / food service report (Screen 09) + census report | J93: Dining Services
A94: DIN-04 | B94: Resident Meal Satisfaction Score | C94: IL/AL/MC/SNF | D94: 79.2% | E94: Reported | F94: Below | G94: > 85% favorable; top quartile > 90% | H94: RC 2025 resident experience (Rob Clark) | I94: Manual entry (Screen 10) | J94: Dining Services
A95: DIN-05 | B95: Therapeutic and Modified Diet Accuracy Rate | C95: AL/MC/SNF | D95: 98.4% | E95: Reported | F95: On benchmark | G95: > 98% accuracy; zero allergen errors | H95: CMS F-tag F812 (therapeutic and modified diet accuracy) | I95: Dining / food service report (Screen 09) | J95: Dining Services
A96: DIN-06 | B96: Unplanned Weight Loss Incidence | C96: AL/MC/SNF | D96: 4.4% quarterly | E96: Reported | F96: On benchmark | G96: < 5% of residents per quarter | H96: CMS F-tag F692; MDS Section K | I96: Dining / food service report + clinical / EHR report (Screen 09) | J96: Dining Services
A97: DIN-07 | B97: Food Safety Inspection Score | C97: IL/AL/MC/SNF | D97: 97.0 Kent County inspection | E97: Reported | F97: On benchmark | G97: > 95% score; zero critical violations | H97: State health department food service inspection; CMS F-tag F812 | I97: Dining / food service report (Screen 09) + inspection upload (Screen 1 | J97: Dining Services
A98: DIN-08 | B98: Nutritional Assessment Completion Rate | C98: SNF | D98: 99.1% on time | E98: Reported | F98: Watch | G98: 100% of nutritional assessments completed on time | H98: RC 2025 CCRC Performance Benchmarks (advisor internal standard) | I98: TO BE MAPPED - added from Gap Matrix v9; intake screen not yet assigne | J98: Dining Services
A99: DIN-09 | B99: Food Waste Rate | C99: IL/AL/MC/SNF | D99: 6.8% of food purchased | E99: Reported | F99: Watch | G99: Food waste below 6% of food purchases | H99: Kushant Shah internal standard | I99: TO BE MAPPED - added from Gap Matrix v9; intake screen not yet assigne | J99: Dining Services
A101: Skilled Nursing (36)
A102: SNF-00 | B102: Overall Five-Star Rating | C102: SNF | D102: 3 stars overall | E102: CMS fetch | F102: CMS-fetched | G102: Caps: if health inspection = 1 star the overall cannot rise more than one star (max 2). Abuse icon caps health inspection at 2, so overall maxes at 4. Current SFF participants receive no ratings in any domain | H102: CMS Five-Star Technical Users Guide, September 2026 | I102: Tool-fetched from CMS. No operator upload | J102: Skilled Nursing
A103: SNF-01 | B103: Health Inspection Star Rating | C103: SNF | D103: 2 stars | E103: CMS fetch | F103: CMS-fetched | G103: Top 10% of the state = 5 stars; middle 70% split into three bands of 23.33% = 4, 3, 2 stars; bottom 20% = 1 star. Recalibrated monthly | H103: CMS TUG September 2026; state cut-point tables (August 2026) | I103: Tool-fetched from CMS | J103: Skilled Nursing
A104: SNF-02 | B104: Staffing Star Rating | C104: SNF | D104: 3 stars | E104: CMS fetch | F104: CMS-fetched | G104: 1 star < 155 | 2 stars 155-204 | 3 stars 205-254 | 4 stars 255-319 | 5 stars 320-380 | H104: CMS TUG September 2026 Table 3 | I104: Tool-fetched from CMS PBJ | J104: Skilled Nursing
A105: SNF-03 | B105: Quality Measure Star Rating | C105: SNF | D105: 4 stars | E105: CMS fetch | F105: CMS-fetched | G105: Overall QM: 1 star 299-927 | 2 stars 928-1120 | 3 stars 1121-1299 | 4 stars 1300-1493 | 5 stars 1494-2300. Thresholds rise every six months by half the observed score gain; next increase expected January 2027 | H105: CMS TUG September 2026 Table 5 (thresholds raised July 2026) | I105: Tool-fetched from CMS | J105: Skilled Nursing
A106: SNF-H1 | B106: Weighted Health Inspection Score | C106: SNF | D106: 68.7 weighted points | E106: CMS fetch | F106: CMS-fetched | G106: Two standard survey cycles only, weighted 3/4 and 1/4. Cycle 3 is still displayed on Care Compare but is no longer scored (changed July 2025 from three cycles at 1/2, 1/3, 1/6) | H106: CMS TUG September 2026 | I106: Tool-fetched from CMS | J106: Skilled Nursing
A107: SNF-H2 | B107: Standard Survey Deficiency Points by Scope and Severity | C107: SNF | D107: 7 deficiencies, highest G, 44 points | E107: CMS fetch | F107: CMS-fetched | G107: A/B/C 0 | D 4 | E 8 | F 16 (20 if SQC) | G 20 | H 35 (40) | I 45 (50) | J 50 (75) | K 100 (125) | L 150 (175). Past non-compliance at J/K/L scores at the G value of 20 | H107: CMS TUG September 2026 Table 1 | I107: Tool-fetched from CMS | J107: Skilled Nursing
A108: SNF-H3 | B108: Complaint Survey Deficiency Points | C108: SNF | D108: 2 complaint deficiencies, 12 points | E108: CMS fetch | F108: CMS-fetched | G108: Months 0-12 weighted 3/4; months 13-36 weighted 1/4 as a single band. Complaint deficiencies within 15 days of a recertification survey are counted once at the higher scope and severity | H108: CMS TUG September 2026 | I108: Tool-fetched from CMS | J108: Skilled Nursing
A109: SNF-H4 | B109: Focused Infection Control Survey Deficiency Points | C109: SNF | D109: 1 ICS deficiency, 4 points | E109: CMS fetch | F109: CMS-fetched | G109: Same 3/4 and 1/4 weighting as complaint surveys. Where an ICS citation overlaps a recertification or complaint citation within 15 days, only the ICS citation is counted | H109: CMS TUG September 2026 | I109: Tool-fetched from CMS | J109: Skilled Nursing
A110: SNF-H5 | B110: Revisit Points | C110: SNF | D110: 1 revisit, 0 points | E110: CMS fetch | F110: CMS-fetched | G110: First revisit 0 | second 50% of the cycle score | third 70% | fourth 85% | H110: CMS TUG September 2026 Table 2 | I110: Tool-fetched from CMS | J110: Skilled Nursing
...

Sheet Department Rollup
A1: Department Rollup
A3: Live counts from the scorecard. Change occupancy and the model-linked measures move between bands here too.
A5: Department | B5: Measures | C5: On benchmark | D5: Watch | E5: Below | F5: Informational | G5: CMS-fetched
A6: Operations | B6: =COUNTIF('KPI Scorecard'!$J$7:$J$140,"Operations") -> 8 | C6: =COUNTIFS('KPI Scorecard'!$J$7:$J$140,"Operations",'KPI Scorecard'!$F$7:$F$140,"On benchmark") -> 5 | D6: =COUNTIFS('KPI Scorecard'!$J$7:$J$140,"Operations",'KPI Scorecard'!$F$7:$F$140,"Watch") -> 3 | E6: =COUNTIFS('KPI Scorecard'!$J$7:$J$140,"Operations",'KPI Scorecard'!$F$7:$F$140,"Below") -> 0 | F6: =COUNTIFS('KPI Scorecard'!$J$7:$J$140,"Operations",'KPI Scorecard'!$F$7:$F$140,"Informational") -> 0 | G6: =COUNTIFS('KPI Scorecard'!$J$7:$J$140,"Operations",'KPI Scorecard'!$F$7:$F$140,"CMS-fetched") -> 0
A7: Sales and Marketing | B7: =COUNTIF('KPI Scorecard'!$J$7:$J$140,"Sales and Marketing") -> 11 | C7: =COUNTIFS('KPI Scorecard'!$J$7:$J$140,"Sales and Marketing",'KPI Scorecard'!$F$7:$F$140,"On benchmark") -> 1 | D7: =COUNTIFS('KPI Scorecard'!$J$7:$J$140,"Sales and Marketing",'KPI Scorecard'!$F$7:$F$140,"Watch") -> 6 | E7: =COUNTIFS('KPI Scorecard'!$J$7:$J$140,"Sales and Marketing",'KPI Scorecard'!$F$7:$F$140,"Below") -> 3 | F7: =COUNTIFS('KPI Scorecard'!$J$7:$J$140,"Sales and Marketing",'KPI Scorecard'!$F$7:$F$140,"Informational") -> 1 | G7: =COUNTIFS('KPI Scorecard'!$J$7:$J$140,"Sales and Marketing",'KPI Scorecard'!$F$7:$F$140,"CMS-fetched") -> 0
A8: Nursing | B8: =COUNTIF('KPI Scorecard'!$J$7:$J$140,"Nursing") -> 12 | C8: =COUNTIFS('KPI Scorecard'!$J$7:$J$140,"Nursing",'KPI Scorecard'!$F$7:$F$140,"On benchmark") -> 4 | D8: =COUNTIFS('KPI Scorecard'!$J$7:$J$140,"Nursing",'KPI Scorecard'!$F$7:$F$140,"Watch") -> 5 | E8: =COUNTIFS('KPI Scorecard'!$J$7:$J$140,"Nursing",'KPI Scorecard'!$F$7:$F$140,"Below") -> 2 | F8: =COUNTIFS('KPI Scorecard'!$J$7:$J$140,"Nursing",'KPI Scorecard'!$F$7:$F$140,"Informational") -> 1 | G8: =COUNTIFS('KPI Scorecard'!$J$7:$J$140,"Nursing",'KPI Scorecard'!$F$7:$F$140,"CMS-fetched") -> 0
A9: Finance | B9: =COUNTIF('KPI Scorecard'!$J$7:$J$140,"Finance") -> 12 | C9: =COUNTIFS('KPI Scorecard'!$J$7:$J$140,"Finance",'KPI Scorecard'!$F$7:$F$140,"On benchmark") -> 3 | D9: =COUNTIFS('KPI Scorecard'!$J$7:$J$140,"Finance",'KPI Scorecard'!$F$7:$F$140,"Watch") -> 5 | E9: =COUNTIFS('KPI Scorecard'!$J$7:$J$140,"Finance",'KPI Scorecard'!$F$7:$F$140,"Below") -> 1 | F9: =COUNTIFS('KPI Scorecard'!$J$7:$J$140,"Finance",'KPI Scorecard'!$F$7:$F$140,"Informational") -> 3 | G9: =COUNTIFS('KPI Scorecard'!$J$7:$J$140,"Finance",'KPI Scorecard'!$F$7:$F$140,"CMS-fetched") -> 0
A10: Human Resources | B10: =COUNTIF('KPI Scorecard'!$J$7:$J$140,"Human Resources") -> 11 | C10: =COUNTIFS('KPI Scorecard'!$J$7:$J$140,"Human Resources",'KPI Scorecard'!$F$7:$F$140,"On benchmark") -> 0 | D10: =COUNTIFS('KPI Scorecard'!$J$7:$J$140,"Human Resources",'KPI Scorecard'!$F$7:$F$140,"Watch") -> 4 | E10: =COUNTIFS('KPI Scorecard'!$J$7:$J$140,"Human Resources",'KPI Scorecard'!$F$7:$F$140,"Below") -> 7 | F10: =COUNTIFS('KPI Scorecard'!$J$7:$J$140,"Human Resources",'KPI Scorecard'!$F$7:$F$140,"Informational") -> 0 | G10: =COUNTIFS('KPI Scorecard'!$J$7:$J$140,"Human Resources",'KPI Scorecard'!$F$7:$F$140,"CMS-fetched") -> 0
A11: Plant and Maintenance | B11: =COUNTIF('KPI Scorecard'!$J$7:$J$140,"Plant and Maintenance") -> 10 | C11: =COUNTIFS('KPI Scorecard'!$J$7:$J$140,"Plant and Maintenance",'KPI Scorecard'!$F$7:$F$140,"On benchmark") -> 4 | D11: =COUNTIFS('KPI Scorecard'!$J$7:$J$140,"Plant and Maintenance",'KPI Scorecard'!$F$7:$F$140,"Watch") -> 3 | E11: =COUNTIFS('KPI Scorecard'!$J$7:$J$140,"Plant and Maintenance",'KPI Scorecard'!$F$7:$F$140,"Below") -> 2 | F11: =COUNTIFS('KPI Scorecard'!$J$7:$J$140,"Plant and Maintenance",'KPI Scorecard'!$F$7:$F$140,"Informational") -> 1 | G11: =COUNTIFS('KPI Scorecard'!$J$7:$J$140,"Plant and Maintenance",'KPI Scorecard'!$F$7:$F$140,"CMS-fetched") -> 0
A12: Life Enrichment | B12: =COUNTIF('KPI Scorecard'!$J$7:$J$140,"Life Enrichment") -> 6 | C12: =COUNTIFS('KPI Scorecard'!$J$7:$J$140,"Life Enrichment",'KPI Scorecard'!$F$7:$F$140,"On benchmark") -> 1 | D12: =COUNTIFS('KPI Scorecard'!$J$7:$J$140,"Life Enrichment",'KPI Scorecard'!$F$7:$F$140,"Watch") -> 2 | E12: =COUNTIFS('KPI Scorecard'!$J$7:$J$140,"Life Enrichment",'KPI Scorecard'!$F$7:$F$140,"Below") -> 2 | F12: =COUNTIFS('KPI Scorecard'!$J$7:$J$140,"Life Enrichment",'KPI Scorecard'!$F$7:$F$140,"Informational") -> 1 | G12: =COUNTIFS('KPI Scorecard'!$J$7:$J$140,"Life Enrichment",'KPI Scorecard'!$F$7:$F$140,"CMS-fetched") -> 0
A13: Dining Services | B13: =COUNTIF('KPI Scorecard'!$J$7:$J$140,"Dining Services") -> 9 | C13: =COUNTIFS('KPI Scorecard'!$J$7:$J$140,"Dining Services",'KPI Scorecard'!$F$7:$F$140,"On benchmark") -> 4 | D13: =COUNTIFS('KPI Scorecard'!$J$7:$J$140,"Dining Services",'KPI Scorecard'!$F$7:$F$140,"Watch") -> 3 | E13: =COUNTIFS('KPI Scorecard'!$J$7:$J$140,"Dining Services",'KPI Scorecard'!$F$7:$F$140,"Below") -> 1 | F13: =COUNTIFS('KPI Scorecard'!$J$7:$J$140,"Dining Services",'KPI Scorecard'!$F$7:$F$140,"Informational") -> 1 | G13: =COUNTIFS('KPI Scorecard'!$J$7:$J$140,"Dining Services",'KPI Scorecard'!$F$7:$F$140,"CMS-fetched") -> 0
A14: Skilled Nursing | B14: =COUNTIF('KPI Scorecard'!$J$7:$J$140,"Skilled Nursing") -> 36 | C14: =COUNTIFS('KPI Scorecard'!$J$7:$J$140,"Skilled Nursing",'KPI Scorecard'!$F$7:$F$140,"On benchmark") -> 0 | D14: =COUNTIFS('KPI Scorecard'!$J$7:$J$140,"Skilled Nursing",'KPI Scorecard'!$F$7:$F$140,"Watch") -> 0 | E14: =COUNTIFS('KPI Scorecard'!$J$7:$J$140,"Skilled Nursing",'KPI Scorecard'!$F$7:$F$140,"Below") -> 0 | F14: =COUNTIFS('KPI Scorecard'!$J$7:$J$140,"Skilled Nursing",'KPI Scorecard'!$F$7:$F$140,"Informational") -> 0 | G14: =COUNTIFS('KPI Scorecard'!$J$7:$J$140,"Skilled Nursing",'KPI Scorecard'!$F$7:$F$140,"CMS-fetched") -> 36
A15: TOTAL | B15: =SUM(B6:B14) -> 115 | C15: =SUM(C6:C14) -> 22 | D15: =SUM(D6:D14) -> 31 | E15: =SUM(E6:E14) -> 18 | F15: =SUM(F6:F14) -> 8 | G15: =SUM(G6:G14) -> 36
A17: Nursing splits across care levels: NUR-01 to NUR-08 apply to assisted living and memory care, NUR-09 to NUR-12 are skilled-nursing MDS and PDPM measures that are not Five-Star contributors. The 36 Skilled Nursing measures are the CMS Five-Star set and are fetched, not entered.

Sheet Action Plan
A1: Consolidated Action Plan
A3: Every finding in this workbook on the VMP horizons, in SMART form. KPI codes are stripped by design. Ordered so the work that moves the most measures comes first.
A5: Tactical (30 days)
A6: Tactical | B6: Human Resources Open positions | C6: Move the 17 open positions to continuous posting with same-week interview scheduling, starting with CNA and the AL med-tech line.
B7: Measurable | C7: Vacancy 8.9% to under 6.0%. Time to fill 58 days to under 50. Agency 9.4% to under 8.0%.
B8: Achievable | C8: HR director with the two care-level leaders. No new headcount required.
B9: Relevant | C9: This single gap drives the labour percentage, the CMS staffing domain, frontline turnover and the direct-care variance in the staffing model.
B10: Time-bound | C10: Postings live and interview blocks calendared within 30 days.
A12: Tactical | B12: Skilled Nursing Weekend coverage | C12: Level the weekend nursing pattern against weekday. The hours already exist mid-week.
B13: Measurable | C13: Weekend HPRD 2.714 toward the weekday 3.452, closing the 27% gap.
B14: Achievable | C14: DON and scheduler. A scheduling change, not a hiring one.
B15: Relevant | C15: Weekend HPRD is a direct CMS Five-Star staffing input and the largest recoverable point gap in the domain.
B16: Time-bound | C16: New pattern live within 30 days; PBJ reflects it the following quarter.
A18: Tactical | B18: Plant and Maintenance Overdue backlog | C18: Clear every work order more than 30 days overdue and put the preventive-maintenance schedule on a tracked list with an owner per item.
B19: Measurable | C19: Average days overdue 19 to under 14. PM completion 81.2% to above 90%.
B20: Achievable | C20: Plant director at 5.0 FTE against a 5.51 model requirement.
B21: Relevant | C21: PM completion on a 1994 campus is how deferred maintenance becomes capital expense.
B22: Time-bound | C22: Backlog listed within 14 days, aged items cleared within 30.
A24: Strategic (90 days)
A25: Strategic | B25: Sales and Marketing Funnel and occupancy | C25: Rebuild the inquiry-to-tour step and work the unpaid referral channel that already converts at 58%.
B26: Measurable | C26: Inquiry-to-tour from IL 23% / AL 24% toward the Aline medians of 28% and 29%. Move-ins per 100 units from 2.4 / 4.1 toward 3 and 5.
B27: Achievable | C27: Sales director at 5.0 FTE against a 5.97 model requirement - one open position.
B28: Relevant | C28: Occupancy is the highest-value lever in this model: the Sensitivity sheet shows roughly nine points of margin between 75% and 100%.
B29: Time-bound | C29: Channel plan set in 30 days, funnel measured at 90.
A31: Strategic | B31: Dining Services Meal satisfaction | C31: Seat a resident dining council and run a menu refresh in assisted living and memory care, then re-survey.
B32: Measurable | C32: Meal satisfaction 79.2% toward 85%. Memory care meal participation 64% toward the 60-75% band's upper half.
B33: Achievable | C33: Dining director. The model shows dining 3.2 FTE short, not over - this is not a cost-cutting exercise.
B34: Relevant | C34: Meal satisfaction is the lowest resident-facing score and the one prospects hear about on tour.
B35: Time-bound | C35: Council seated in 30 days, menu changed by 60, re-survey at 90.
A37: Strategic | B37: Finance Budget on the model | C37: Build the FY27 budget off the staffing model at the planned occupancy rather than off prior-year actuals.
B38: Measurable | C38: Labour toward 45% of revenue at planned occupancy. Operating margin toward the 22.8% CCRC benchmark.
B39: Achievable | C39: CFO with the department heads. The model is the input.
B40: Relevant | C40: Budgeting from last year's actuals bakes in the current vacancy and agency pattern as if it were normal.
B41: Time-bound | C41: Budget built by the 90-day mark for board adoption.
A43: Strategic | B43: Nursing Acuity and rate | C43: Reconcile the assisted-living acuity migration to the care-tier rate schedule and the staffing ratios.
B44: Measurable | C44: Tier 3+ mix rose 6 points year over year with no rate or staffing response. Close that gap.
B45: Achievable | C45: DON and business office. The rate schedule already has five tiers.
B46: Relevant | C46: Rising acuity without a rate response is revenue left on the table and a staffing risk at the same time.
B47: Time-bound | C47: Reassessment sweep complete and repriced within 90 days.
A49: Horizon (6-12 months)
A50: Horizon | B50: Life Enrichment Evening and weekend programming | C50: Extend evening and weekend programming, prioritising memory care where structured engagement is measurably short.
B51: Measurable | C51: Participation 78.9% above 80%. Evening coverage from 2 of 7 nights. Memory care weekend from 1.5 hours per day.
B52: Achievable | C52: Life enrichment director at 5.4 FTE against a 5.75 model requirement.
B53: Relevant | C53: Thin weekend memory-care programming is both a quality finding and a survey exposure in a secured unit.
B54: Time-bound | C54: Calendar rebuilt within 6 months, measured over the following two quarters.
A56: Horizon | B56: Technology Close the measurement gaps | C56: Put dining, maintenance and resident engagement on systems that produce reports, and activate the scheduling module already licensed.
B57: Measurable | C57: Six measures move from hand-compiled to system-reported, including PM completion, food cost and technology engagement.
B58: Achievable | C58: Plant, dining and HR directors. Scheduling carries no incremental licence cost.
B59: Relevant | C59: The measures with the widest error bars in this scorecard are the ones no system produces.
B60: Time-bound | C60: Scheduling activated in 90 days; dining and CMMS live within 12 months.
A62: Horizon | B62: Finance Capital and the 2028 call | C62: Build a multi-year capital renewal plan and position for the 2028 optional call on the Series 2018 bonds.
B63: Measurable | C63: Average age of plant 14.8 years held or improved. Refunding analysis complete with covenant headroom verified.
B64: Achievable | C64: CFO, plant director and bond counsel.
B65: Relevant | C65: Days cash at 168 clears the 120 covenant but sits below the 180 standard. Liquidity has to be established before the call window.
B66: Time-bound | C66: Capital plan adopted within 12 months; refunding analysis six months before the call.
A68: Sequencing note: the recruiting sprint and the weekend scheduling change are first because between them they move the labour percentage, the CMS staffing domain, frontline turnover, the direct-care variance and the operating margin. Nothing else in this plan moves five measures at once.

Sheet Benchmark Sources
A1: Benchmark Sources
A3: Copied from the Benchmark Source Map in Operations KPI Catalog v9. Every target scored in this workbook traces to one of these published sources.
A5: Source | B5: Applies To | C5: Supplies | D5: Vintage / Note | E5: Match Key | F5: Alt Match Key | G5: KPIs Mapped | H5: KPI Codes | I5: Where the Data Is Found (Gap Matrix v9)
A6: State of Seniors Housing (SOSH) 2025 | B6: IL, AL, MC, CCRC | C6: Occupancy, annual turnover, revenue and expense per occupied unit, labor percent of revenue, community operating margin, dietary cost per resident day, workers compensation percent of wages | D6: 2025 edition. All dollar measures pass through the CPI toggle. | E6: SOSH | F6: State of Seniors | G6: 14 | H6: OPS-01, OPS-03, OPS-04, SAL-08, NUR-05, FIN-01, FIN-03, FIN-04, FIN-05, FIN-06, HR-05, HR-10, DIN-01, DIN-02 | I6: Gap Matrix v9: 'Benchmark Sources' row 6 (name A6, link I6). Link: https://ashaliving.org/research-and-analytics/ - publisher landing page, NOT a deep link; report is purchasable (ASHA member or paid). Locations cited: Tables 2.7, 2.15, 2.18-2.19, 3.1-3.7, 3.20-3.21, 3.22-3.24, 3.27, 4.1. URL verified 22 Sep 2026. Matrix does not hold the PDF.
A7: CMS and regulatory requirements (Five-Star Technical Users' Guide, RAI Manual, 42 CFR, Life Safety Code, state regulation) | B7: SNF only | C7: All 36 SNF Five-Star measures and their cut-points, plus the regulatory requirements behind assessment timeliness, care plan timeliness, grievance response, life safety, food safety, therapeutic diets and unplanned weight loss | D7: September 2026 for the Five-Star Technical Users' Guide (decision recorded below). Regulatory citations carry no edition - 42 CFR, F-tags, RAI Manual and state regulation are requirements, not benchmark vintages. | E7: CMS | F7: State regulat | G7: 50 | H7: OPS-04, OPS-08, NUR-04, NUR-06, NUR-07, NUR-08, NUR-09, NUR-10, NUR-11, NUR-12, SNF-00, SNF-01, SNF-02, SNF-03, SNF-H1, SNF-H2, SNF-H3, SNF-H4, SNF-H5, SNF-H6, SNF-H7, SNF-H8, SNF-H9, SNF-S1, SNF-S2, SNF-S3, SNF-S4, SNF-S5, SNF-S6, SNF-S7, SNF-Q1, SNF-Q2, SNF-Q3, SNF-Q4, SNF-Q5, SNF-Q6, SNF-Q7, SNF-Q8, SNF-Q9, SNF-Q10, SNF-Q11, SNF-Q12, SNF-Q13, SNF-Q14, SNF-Q15, SNF-Q16, PLT-08, DIN-05, DIN-06, DIN-07 | I7: Gap Matrix v9: 'Benchmark Sources' row 5 (name A5, link I5, which also holds 4 sub-URLs). Link: https://www.cms.gov/medicare/health-safety-standards/certification-compliance/five-star-quality-rating-system - URL pre-existing and not independently verified, though it matches the official CMS page. Locations cited: Table 3 (staffing cut-points), Table A2 (staffing point ranges), Table 5 (QM points). EDITION UNSETTLED - see note in row 22.
A8: CARF 2025 Financial Ratios and Trend Analysis | B8: CCRC and Life Plan, entity level | C8: Days Cash on Hand, Debt Service Coverage, Days in AR, Net Operating Margin, Operating Margin, Average Age of Plant, occupancy trend by care level | D8: CARF / Ziegler / Baker Tilly, 33rd edition. 2024 medians, single-site and multi-site, with Type A/B/C contract cuts available. | E8: CARF | F8: CARF 2025 | G8: 6 | H8: OPS-01, FIN-02, FIN-07, FIN-08, FIN-09, PLT-09 | I8: Gap Matrix v9: 'Benchmark Sources' row 8 (name A8, access note E8, link I8). Link: https://carf.org/wp-content/uploads/2025/10/2025FinancialRatiosTrendAnalysis.pdf - free, no login or payment gate, downloaded and verified 22 Sep 2026 (90pp). Locations: Ratio Summary p.10 (2024 medians, single-site n=71 / multi-site n=26); Section 3 Liquidity pp.41-44 with the Days Cash quartile table p.44; Appendices A and B for account-level inclusions.
A9: Rob Clark - 2025 CCRC Performance Benchmarks and advisor internal standards | B9: CCRC, and universal people measures at every care level | C9: Resident and family satisfaction, online review rating, staff turnover (overall and frontline), employee satisfaction, training hours, medication accuracy, care transition, days cash, DSC, entrance fee refund funding, resident technology use | D9: 2025 for the CCRC Performance Benchmarks; advisor internal standards carry no publication date. Row covers both because neither is externally published - the LE-06 programming coverage floor was set by owner ruling on 22 Sep 2026. | E9: RC 2025 | F9: Rob Clark | G9: 33 | H9: OPS-02, OPS-05, OPS-06, OPS-07, SAL-09, SAL-10, SAL-11, NUR-01, NUR-02, NUR-03, FIN-02, FIN-08, FIN-09, FIN-10, FIN-12, HR-01, HR-02, HR-03, HR-04, HR-06, HR-07, HR-08, HR-09, HR-11, LE-01, LE-02, LE-03, LE-04, LE-05, LE-06, DIN-03, DIN-04, DIN-08 | I9: Gap Matrix v9: 'Benchmark Sources' row 7 (name A7, I7 states no public link). No URL exists - advisor material, not published. Not documented at table or page level in either workbook, so these targets cannot be externally verified by a third party.
A10: Aline Sales and Marketing Benchmark Report | B10: IL, AL, MC, Life Plan Residential | C10: Inquiries, tours and move-ins per 100 units per month; inquiry-to-tour and tour-to-move-in conversion; inquiry channel mix; conversion by channel | D10: Q1 2024 edition as held. The 2026 Senior Living Sales and Marketing Benchmark Report is the current publication but is registration-gated and its figures could not be obtained, so the catalog cites Q1 2024 to match its own numbers. | E10: Aline | F10: Aline Benchmark | G10: 7 | H10: SAL-01, SAL-02, SAL-03, SAL-04, SAL-05, SAL-06, SAL-07 | I10: Gap Matrix v9: 'Benchmark Sources' row 15 (name A15, link I15). Link: https://alineops.com/senior-living-sales-marketing-benchmark-report-2026/ - verified 22 Sep 2026. EDITION MISMATCH: the matrix holds the 2026 Senior Living Sales & Marketing Benchmark Report, not the Q1 2024 edition recorded in column D of this row. Not recorded at table or exhibit level.
A11: Siemens / Brightly Senior Living Maintenance Benchmarks | B11: All care levels, campus wide | C11: Work orders per resident unit, on-time completion, labor hours per resident unit, average days overdue, average days open, resident billings per resident unit | D11: Drawn from 1,000+ senior living organizations. Entire Plant block except Average Age of Plant and Energy Use Intensity. | E11: Brightly | F11: Siemens | G11: 7 | H11: PLT-01, PLT-02, PLT-03, PLT-04, PLT-05, PLT-06, PLT-07 | I11: Gap Matrix v9: 'Benchmark Sources' row 9 (name A9, basis H9, link I9). Link: https://www.assetmanagement.siemens.com/use-cases/senior-living - verified 22 Sep 2026. 2026 edition, (c) Brightly Software Inc 2026, 1,000+ senior living organisations. Locations: KPI #2 on-time (76%), KPI #4 overdue severity (3.4 days avg; PM 5.6, ad hoc 2.4). NAMING: the matrix records this source as Siemens throughout (Brightly was acquired by Siemens).
A12: CLA 40th Annual SNF Report | B12: SNF, financial only | C12: SNF payer mix, revenue and expense per patient day | D12: Approximately 11,700 CMS cost reports. Used for SNF financial comparison, which sits in Finance, not in the SNF Five-Star block. | E12: CLA 40th | F12: CLA | G12: 3 | H12: FIN-03, FIN-04, FIN-06 | I12: Gap Matrix v9: 'Benchmark Sources' row 13 (name A13, link I13). Link: https://www.claconnect.com/en/resources/white-papers/snf-cost-comparison-industry-trends-report - verified 22 Sep 2026. 40th edition, 2025 release on FY2024 data. Locations: skilled revenue per patient day by payer; payer mix derived from approximately 11,700 CMS SNF cost reports.
A13: EPA ENERGY STAR Portfolio Manager | B13: All care levels | C13: Energy Use Intensity for senior care communities | D13: Senior Care Communities DataTrends. Median site EUI approximately 214 kBtu per square foot. | E13: ENERGY STAR | F13: Portfolio Manager | G13: 1 | H13: PLT-10 | I13: NOT HELD - DO NOT WRITE A LINK. The Gap Matrix v9 workbook has no row, no link and no KPI citing ENERGY STAR. Its utility benchmark comes from SOSH 2025 Tables 3.22-3.24 instead. PLT-10 in this catalog is therefore the only place ENERGY STAR is used across the two workbooks and must be sourced independently.
A14: Kushant Shah - internal standard | B14: IL, AL, MC, SNF | C14: A/R aged over 90 days, bad debt and write-off rate, food waste rate, deposit-to-move-in conversion (joint with Rob Clark) | D14: No published edition or date - advisor internal standard, no external benchmark exists. Added 22 Sep 2026 with the Gap Matrix v9 measures. | E14: Kushant Shah | F14: KS internal | G14: 4 | H14: SAL-10, FIN-11, FIN-12, DIN-09 | I14: Gap Matrix v9: no dedicated 'Benchmark Sources' row - recorded there as 'Internal standard (Kushant Shah)' on the KPI rows themselves. No URL exists; advisor material, not published.
A15: Other named sources - RETIRED 22 Sep 2026, should read zero | B15: Varies | C15: Emptied by owner instruction: third-party named sources are no longer carried in the Benchmark Source column. Benchmarks that lost their attribution were re-recorded as Rob Clark internal standards; CMS and state regulatory citations were folded into the CMS and regulatory row above rather than re-attributed, because a regulatory requirement is not an advisor standard. | D15: If this count is ever above zero, a new unapproved source has entered the catalog - investigate rather than add a row. | E15: (no key - catch-all) | F15: (no key - catch-all) | G15: 0 | I15: Not applicable - no source. This row is a control check, not a source.
A16: How these counts are built
A17: Counts and codes are formulas over the Benchmark Source column on the KPI Catalog tab, matched on the Match Key and Alt Match Key in columns E and F. Edit a key and the count and code list update. Nothing is typed in.
A18: Other named sources' is the exclusive remainder - KPIs matching none of the nine keys - taken from the Primary Benchmark Source Group helper in column Q of the KPI Catalog. Matching elsewhere is non-exclusive, so a KPI citing two sources is counted under both.
A19: Sum of rows 5-13 (with overlap): | D19: 125
A20: Distinct KPIs in the catalog: | D20: 115
A21: Dual-source KPIs (the difference): | D21: 10
A22: Source discrepancies raised by the Gap Matrix v9 workbook (22 Sep 2026)
A23: CMS Five-Star Technical Users' Guide edition - DECIDED 22 Sep 2026: this catalog keeps September 2026. The Gap Matrix holds April 2026 on some SNF rows and July 2026 on others and is internally inconsistent by its own account; ours is the later edition and stands. The 36 SNF measures and their QM cut-points remain on the September 2026 basis. If the Gap Matrix re-bases to September 2026 the two will align; until then expect its SNF cut-points to differ from ours.
A24: Aline edition - CLOSED 22 Sep 2026: the catalog stays on the Q1 2024 edition, which is the vintage the SAL-01 to SAL-07 target figures actually come from. The 2026 report is the newer publication but is registration-gated and neither workbook can obtain its figures, so citing 2026 would put a label on numbers that did not come from it. Citing the edition we hold is the defensible position. Yellow flags on the target cells have been cleared - the source and the figures now agree. Revisit only if someone with Aline report access supplies the 2026 values.
A25: Siemens / Brightly naming: the Gap Matrix records this source as Siemens throughout, since Siemens acquired Brightly, and asks that the catalog do the same. The seven Plant rows here cite Brightly. The match keys in columns E and F accept both spellings, so counts are unaffected either way - renaming the citations is a one-line change on request.
A26: EPA ENERGY STAR Portfolio Manager: not held by the Gap Matrix at all. PLT-10 is the only measure across both workbooks using it, and the matrix benchmarks utilities from SOSH 2025 instead. PLT-10's 214 kBtu target needs an independent source or should move to SOSH.
A27: Alzheimer's Association attribution - CLOSED 22 Sep 2026 by deletion. The former LE-03 memory care structured engagement hours cited the Alzheimer's Association for 4-6 hours per resident per day with no title, year or page, and no link existed in either workbook. The Gap Matrix recorded the same measure as 4-6 hours per WEEK on a Rob Clark internal standard and noted that the Alzheimer's Association publishes dementia care practice recommendations, not an hours-per-resident benchmark. Rather than carry an unsourceable 7x ambiguity, the owner deleted the measure on 22 Sep 2026 and the LE codes were renumbered. The Alzheimer's Association is no longer cited anywhere in this catalog. The remaining life enrichment coverage expectation is LE-06, attributed to Rob Clark.
A28: Sources held by the Gap Matrix v9 workbook but not cited in this catalog
A29: Third-party named sources removed from the catalog - 22 Sep 2026, owner instruction
A30: The Benchmark Source column no longer names any third-party organisation outside the approved list. Eleven rows kept a valid source and simply had the extra names trimmed: OPS-05, OPS-06, SAL-09, FIN-06, HR-01, HR-02, HR-05, HR-08, PLT-07, DIN-04, DIN-05. Eleven rows were left with no source and are now Rob Clark internal standards: OPS-02, OPS-07, NUR-02, HR-03, HR-04, HR-06, HR-07, LE-01, LE-02, LE-05, DIN-03. Removed names included NIC MAP, LeadingAge, Argentum, ICAA, Activated Insights, ANFP, Holleran, J.D. Power, Caring.com, Senior Housing News, Pinnacle Quality Insight, HCS Annual Report 2024 and unattributed 'industry practice'. Every original attribution is preserved verbatim in that row's Boundary and Notes column - nothing was silently discarded.
A31: EXCEPTION applied deliberately: CMS and state regulatory citations were NOT re-attributed to Rob Clark. 42 CFR, F-tags, the RAI Manual, the Life Safety Code, MDS Section K and state regulation are legal requirements, not advisor benchmarks, and re-labelling them would have destroyed survey-relevant traceability on 13 measures (OPS-08, NUR-04, NUR-06 to NUR-12, PLT-08, DIN-05, DIN-06, DIN-07). They were folded into the CMS and regulatory row instead, which is why its count rose from 36 to 50. Raise this if the intent was to strip them too.
A32: Creating Results - https://creatingresults.com/marketing-research-strategy/ (verified 22 Sep 2026)
A33: State health department / fire marshal inspections - no single national link, varies by state
... A37: Data vintage: Aline figures are Q1 2024. CARF figures are 2024 medians from the 2025 edition. SOSH figures are 2025. CMS cut-points are the September 2026 Five-Star Technical Users Guide.

Sheet Method & Notes
A1: Method, Scope and Caveats
A4: What drives what
A5: The single driver | B5: Occupancy on the Inputs sheet. Changing it re-runs the staffing model, the financial model, the model-linked measures on the scorecard and every live count on the summary and rollup sheets.
A6: Occupancy-elastic staffing | B6: Direct care, dining, laundry, activities, social services, business office, concierge, transport, MDS and the associate ED all scale with census.
A7: Occupancy-invariant staffing | B7: Executive director, sales, plant operations, housekeeping, the care director, security, foundation, employee dining and the SNF shift supervisor do not. Sales is driven by capacity because it is sized to build census, and housekeeping and plant are square-foot driven.
A8: Why margin steepens | B8: Fixed campus expense and the invariant roles do not follow census, so each additional occupied unit carries a much higher contribution margin than the average unit. That spread is the whole economic case for filling units.
A9: Labour in the model | B9: Priced position by position at the wages on Inputs, loaded with the benefit and tax burden. The Sensitivity sheet uses a blended cost per FTE instead, so its labour line differs slightly from the Financials sheet by design.
A11: Scope and filtering
A12: KPI set | B12: Operations KPI Catalog v9, 2026-09-22. 115 measures. The care-level applicability columns in that workbook decide what is in scope; a full CCRC continuum scores all 115.
A13: A note on the count | B13: The v9 title reads 108 measures and the Care Level Filter sheet totals 108 for a CCRC. Appendix B of the Screen Analysis Catalog records that those counts predate the eight additions made on 22 September, so 115 is current. This workbook scopes by the applicability columns, not the filter table.
A14: Staffing boundary | B14: Per the SBC Boundary sheet in v9, no KPI duplicates a staffing model output. FTE per occupied unit, AL and MC hours per patient day, meals per labour hour, housekeeping square feet per FTE and laundry pounds per hour are model outputs and are deliberately absent from the scorecard. The three CMS hours-per-resident-day measures are the documented exception and stay in the SNF block because they are rating inputs.
A15: Screen grounding | B15: Every measure traces to an onboarding screen through the Screen Analysis Catalog. 71 are scored from screens, 36 are fetched from CMS, and 8 were not yet assigned to a screen when that catalog was written.
A17: Caveats
A18: MOCKUP | B18: Whitefield Commons is fictional. Every community-specific value here is fabricated sample data. The KPI set, the benchmark targets and their sources, the Michigan LARA and CMS regulatory references, the staffing rules and the structure are real.
A19: Reported measures do not move | B19: About 70 measures are trailing-twelve-month results from the uploaded reports. They describe what happened at the occupancy the community actually ran. When you raise occupancy on Inputs they hold still, because a hypothetical census cannot restate a historical result. Only the model-linked rows follow.
A20: Model-linked financials | B20: Stated at recommended staffing rather than today's headcount, because current FTE is a fixed historical fact that stops being meaningful at a different occupancy. The Financials sheet shows both side by side.
A21: Rounding | B21: Occupied units are rounded to whole residents at each level, so total census can move by a unit or two between adjacent occupancy scenarios.
A22: Wages | B22: BLS OEWS medians for the Grand Rapids-Kentwood MSA. Replace them with the community's own average hourly rate by role from the payroll report for a precise cost read.
A23: Raw food share | B23: Dining cost per resident day splits raw food out of non-labour variable expense at the share set on Inputs. Replace it with the actual food line from the general ledger when available.
A24: Not modelled | B24: Policy and procedure alignment, contract analysis, document review, market radius, cultural health and the technology gap are analyses rather than KPIs. They are deliberately outside this workbook and outside the v9 catalog.
A26: Advantedge Operations - A VMP Systems product - Prepared by Rob Clark - Confidential to the operator and the advisory team.
